final class ca {
   private int f;
   private int ec;
   private int[] Eb;
   static int q;
   int[] H;
   private int[] jc;
   private int xb;
   static byte[][] tb = new byte[50][];
   private boolean c;
   static int W;
   private boolean v;
   int[] Hb;
   int[] Ob;
   private int Ib;
   int[] M;
   byte[] zb;
   boolean cb;
   int[] a;
   private int Bb = 155;
   private int C;
   static int wb;
   private int[] Pb;
   private int[] Gb;
   private int sb;
   private int z;
   static int ac;
   private int[] Cb;
   int[] bb;
   static int Rb;
   int[] E;
   static int p;
   private int eb;
   int[] pb;
   private boolean b;
   private int P;
   boolean Kb;
   private int Sb;
   private int[] Lb;
   private int jb;
   static int d;
   private int r;
   private int g;
   int Yb;
   private int Tb;
   static int m;
   private int e;
   static int S;
   int[] qb;
   static int mb;
   static int ab;
   private int x;
   private int hb;
   static int R;
   private int K;
   int t;
   static int ub;
   private int Mb;
   private int[] w;
   private boolean Nb;
   private int T;
   static int h;
   private int[] n;
   private int[] Q;
   private int i;
   private int G;
   static int s;
   private int[] ic;
   static int D;
   int[] gb;
   static int N;
   private int yb;
   static int A;
   static int Xb;
   static int[] B;
   int[] cc;
   static int Ub;
   boolean dc;
   static int Wb;
   int[][] o;
   static int u;
   int hc;
   static int kb;
   private int U;
   int rb;
   int[] bc;
   private int j;
   static int I;
   static int nb;
   private int Vb;
   int Db;
   static int ib;
   static int Qb;
   byte[] Ab;
   private int gc;
   private int Y;
   boolean db;
   private int[] Zb;
   int[] V;
   static int L;
   static int O;
   private int[] fb;
   private int F;
   private int Fb;
   private int[] ob;
   static int y;
   static int Z;
   int Jb;
   private int X;
   int[] lb;
   static int J;
   private int[][] fc;
   static int l;
   int[] k;
   static int vb;
   private static final String[] kc = new String[]{
      z(z("x\u0016$p\r")),
      z(z("`Y$\u0013X")),
      z(z("x\u0016$m\r")),
      z(z("u\u0002fQ")),
      z(z("x\u0016$~d3")),
      z(z("u\u0016")),
      z(z("x\u0016$\u0001Lu\u001e~\u0003\r")),
      z(z("x\u0016$zd3")),
      z(z("x\u0016$ud3")),
      z(z("x\u0016${d3")),
      z(z("x\u0016$td3")),
      z(z("x\u0016$l\r")),
      z(z("x\u0016$h\r")),
      z(z("x\u0016$t\r")),
      z(z("x\u0016$z\r")),
      z(z("x\u0016$yd3")),
      z(z("x\u0016$x\r")),
      z(z("x\u0016$j\r")),
      z(z("x\u0016${\r")),
      z(z("x\u0016$~\r")),
      z(z("x\u0016$wd3")),
      z(z("x\u0016$q\r")),
      z(z("x\u0016$\u007fd3")),
      z(z("x\u0016$w\r")),
      z(z("x\u0016$\u007f\r")),
      z(z("x\u0016$k\r")),
      z(z("x\u0016$|d3")),
      z(z("x\u0016$o\r")),
      z(z("x\u0016$s\r")),
      z(z("x\u0016$i\r")),
      z(z("x\u0016$u\r")),
      z(z("x\u0016$r\r")),
      z(z("x\u0016$n\r")),
      z(z("x\u0016$y\r")),
      z(z("x\u0016$|\r")),
      z(z("x\u0016$vd3")),
      z(z("x\u0016$v\r")),
      z(z("x\u0016$xd3"))
   };

   private final void a(int param1) {
      // $VF: Couldn't be decompiled
      // Please report this to the Vineflower issue tracker, at https://github.com/Vineflower/vineflower/issues with a copy of the class file (if you have the rights to distribute it!)
      // java.lang.RuntimeException: parsing failure!
      //   at org.jetbrains.java.decompiler.modules.decompiler.decompose.DomHelper.parseGraph(DomHelper.java:211)
      //   at org.jetbrains.java.decompiler.main.rels.MethodProcessor.codeToJava(MethodProcessor.java:166)
      //
      // Bytecode:
      // 000: getstatic client.vh Z
      // 003: istore 13
      // 005: getstatic ca.h I
      // 008: bipush 1
      // 009: iadd
      // 00a: putstatic ca.h I
      // 00d: aload 0
      // 00e: ldc 999999
      // 010: putfield ca.x I
      // 013: aload 0
      // 014: ldc 999999
      // 016: putfield ca.ec I
      // 019: aload 0
      // 01a: ldc -999999
      // 01c: putfield ca.gc I
      // 01f: aload 0
      // 020: iload 1
      // 021: putfield ca.P I
      // 024: aload 0
      // 025: ldc -999999
      // 027: putfield ca.j I
      // 02a: aload 0
      // 02b: ldc -999999
      // 02d: putfield ca.e I
      // 030: aload 0
      // 031: ldc -999999
      // 033: putfield ca.sb I
      // 036: bipush 0
      // 037: istore 3
      // 038: aload 0
      // 039: getfield ca.t I
      // 03c: bipush -1
      // 03d: ixor
      // 03e: iload 3
      // 03f: bipush -1
      // 040: ixor
      // 041: if_icmpge 265
      // 044: aload 0
      // 045: getfield ca.o [[I
      // 048: iload 3
      // 049: aaload
      // 04a: astore 2
      // 04b: aload 0
      // 04c: getfield ca.lb [I
      // 04f: iload 3
      // 050: iaload
      // 051: istore 6
      // 053: aload 2
      // 054: bipush 0
      // 055: iaload
      // 056: istore 5
      // 058: aload 0
      // 059: getfield ca.jc [I
      // 05c: iload 5
      // 05e: iaload
      // 05f: dup
      // 060: istore 11
      // 062: istore 12
      // 064: aload 0
      // 065: getfield ca.ic [I
      // 068: iload 5
      // 06a: iaload
      // 06b: dup
      // 06c: istore 9
      // 06e: istore 10
      // 070: aload 0
      // 071: getfield ca.Gb [I
      // 074: iload 5
      // 076: iaload
      // 077: dup
      // 078: istore 7
      // 07a: istore 8
      // 07c: iload 13
      // 07e: ifne 28a
      // 081: bipush 0
      // 082: istore 4
      // 084: iload 6
      // 086: iload 4
      // 088: if_icmple 14f
      // 08b: aload 2
      // 08c: iload 4
      // 08e: iaload
      // 08f: istore 5
      // 091: iload 11
      // 093: bipush -1
      // 094: ixor
      // 095: aload 0
      // 096: getfield ca.jc [I
      // 099: iload 5
      // 09b: iaload
      // 09c: bipush -1
      // 09d: ixor
      // 09e: iload 13
      // 0a0: ifne 194
      // 0a3: if_icmplt 0cc
      // 0a6: goto 0aa
      // 0a9: athrow
      // 0aa: iload 12
      // 0ac: bipush -1
      // 0ad: ixor
      // 0ae: aload 0
      // 0af: getfield ca.jc [I
      // 0b2: iload 5
      // 0b4: iaload
      // 0b5: bipush -1
      // 0b6: ixor
      // 0b7: if_icmple 0d5
      // 0ba: goto 0be
      // 0bd: athrow
      // 0be: aload 0
      // 0bf: getfield ca.jc [I
      // 0c2: iload 5
      // 0c4: iaload
      // 0c5: istore 12
      // 0c7: iload 13
      // 0c9: ifeq 0d5
      // 0cc: aload 0
      // 0cd: getfield ca.jc [I
      // 0d0: iload 5
      // 0d2: iaload
      // 0d3: istore 11
      // 0d5: aload 0
      // 0d6: getfield ca.ic [I
      // 0d9: iload 5
      // 0db: iaload
      // 0dc: iload 9
      // 0de: if_icmpge 0ef
      // 0e1: aload 0
      // 0e2: getfield ca.ic [I
      // 0e5: iload 5
      // 0e7: iaload
      // 0e8: istore 9
      // 0ea: iload 13
      // 0ec: ifeq 108
      // 0ef: aload 0
      // 0f0: getfield ca.ic [I
      // 0f3: iload 5
      // 0f5: iaload
      // 0f6: iload 10
      // 0f8: if_icmple 108
      // 0fb: goto 0ff
      // 0fe: athrow
      // 0ff: aload 0
      // 100: getfield ca.ic [I
      // 103: iload 5
      // 105: iaload
      // 106: istore 10
      // 108: aload 0
      // 109: getfield ca.Gb [I
      // 10c: iload 5
      // 10e: iaload
      // 10f: bipush -1
      // 110: ixor
      // 111: iload 7
      // 113: bipush -1
      // 114: ixor
      // 115: if_icmpgt 13e
      // 118: iload 8
      // 11a: bipush -1
      // 11b: ixor
      // 11c: aload 0
      // 11d: getfield ca.Gb [I
      // 120: iload 5
      // 122: iaload
      // 123: bipush -1
      // 124: ixor
      // 125: if_icmpgt 130
      // 128: goto 12c
      // 12b: athrow
      // 12c: goto 147
      // 12f: athrow
      // 130: aload 0
      // 131: getfield ca.Gb [I
      // 134: iload 5
      // 136: iaload
      // 137: istore 8
      // 139: iload 13
      // 13b: ifeq 147
      // 13e: aload 0
      // 13f: getfield ca.Gb [I
      // 142: iload 5
      // 144: iaload
      // 145: istore 7
      // 147: iinc 4 1
      // 14a: iload 13
      // 14c: ifeq 084
      // 14f: aload 0
      // 150: getfield ca.c Z
      // 153: ifeq 15a
      // 156: goto 18a
      // 159: athrow
      // 15a: aload 0
      // 15b: getfield ca.w [I
      // 15e: iload 3
      // 15f: iload 7
      // 161: iastore
      // 162: aload 0
      // 163: getfield ca.n [I
      // 166: iload 3
      // 167: iload 8
      // 169: iastore
      // 16a: aload 0
      // 16b: getfield ca.Q [I
      // 16e: iload 3
      // 16f: iload 9
      // 171: iastore
      // 172: aload 0
      // 173: getfield ca.Lb [I
      // 176: iload 3
      // 177: iload 10
      // 179: iastore
      // 17a: aload 0
      // 17b: getfield ca.Zb [I
      // 17e: iload 3
      // 17f: iload 11
      // 181: iastore
      // 182: aload 0
      // 183: getfield ca.Eb [I
      // 186: iload 3
      // 187: iload 12
      // 189: iastore
      // 18a: iload 7
      // 18c: ineg
      // 18d: iload 8
      // 18f: iadd
      // 190: aload 0
      // 191: getfield ca.sb I
      // 194: if_icmple 1a5
      // 197: aload 0
      // 198: iload 7
      // 19a: ineg
      // 19b: iload 8
      // 19d: iadd
      // 19e: putfield ca.sb I
      // 1a1: goto 1a5
      // 1a4: athrow
      // 1a5: iload 10
      // 1a7: iload 9
      // 1a9: ineg
      // 1aa: iadd
      // 1ab: aload 0
      // 1ac: getfield ca.sb I
      // 1af: if_icmpgt 1b6
      // 1b2: goto 1c0
      // 1b5: athrow
      // 1b6: aload 0
      // 1b7: iload 9
      // 1b9: ineg
      // 1ba: iload 10
      // 1bc: iadd
      // 1bd: putfield ca.sb I
      // 1c0: aload 0
      // 1c1: getfield ca.j I
      // 1c4: iload 8
      // 1c6: if_icmplt 1cd
      // 1c9: goto 1d3
      // 1cc: athrow
      // 1cd: aload 0
      // 1ce: iload 8
      // 1d0: putfield ca.j I
      // 1d3: aload 0
      // 1d4: getfield ca.gc I
      // 1d7: bipush -1
      // 1d8: ixor
      // 1d9: iload 12
      // 1db: bipush -1
      // 1dc: ixor
      // 1dd: if_icmple 1ea
      // 1e0: aload 0
      // 1e1: iload 12
      // 1e3: putfield ca.gc I
      // 1e6: goto 1ea
      // 1e9: athrow
      // 1ea: iload 11
      // 1ec: ineg
      // 1ed: iload 12
      // 1ef: iadd
      // 1f0: aload 0
      // 1f1: getfield ca.sb I
      // 1f4: if_icmple 205
      // 1f7: aload 0
      // 1f8: iload 11
      // 1fa: ineg
      // 1fb: iload 12
      // 1fd: iadd
      // 1fe: putfield ca.sb I
      // 201: goto 205
      // 204: athrow
      // 205: iload 10
      // 207: bipush -1
      // 208: ixor
      // 209: aload 0
      // 20a: getfield ca.e I
      // 20d: bipush -1
      // 20e: ixor
      // 20f: if_icmplt 216
      // 212: goto 21c
      // 215: athrow
      // 216: aload 0
      // 217: iload 10
      // 219: putfield ca.e I
      // 21c: aload 0
      // 21d: getfield ca.x I
      // 220: bipush -1
      // 221: ixor
      // 222: iload 7
      // 224: bipush -1
      // 225: ixor
      // 226: if_icmpge 233
      // 229: aload 0
      // 22a: iload 7
      // 22c: putfield ca.x I
      // 22f: goto 233
      // 232: athrow
      // 233: aload 0
      // 234: getfield ca.P I
      // 237: bipush -1
      // 238: ixor
      // 239: iload 9
      // 23b: bipush -1
      // 23c: ixor
      // 23d: if_icmplt 244
      // 240: goto 24a
      // 243: athrow
      // 244: aload 0
      // 245: iload 9
      // 247: putfield ca.P I
      // 24a: aload 0
      // 24b: getfield ca.ec I
      // 24e: iload 11
      // 250: if_icmpgt 257
      // 253: goto 25d
      // 256: athrow
      // 257: aload 0
      // 258: iload 11
      // 25a: putfield ca.ec I
      // 25d: iinc 3 1
      // 260: iload 13
      // 262: ifeq 038
      // 265: goto 28a
      // 268: astore 2
      // 269: aload 2
      // 26a: new java/lang/StringBuilder
      // 26d: dup
      // 26e: invokespecial java/lang/StringBuilder.<init> ()V
      // 271: getstatic ca.kc [Ljava/lang/String;
      // 274: bipush 19
      // 276: aaload
      // 277: invokevirtual java/lang/StringBuilder.append (Ljava/lang/String;)Ljava/lang/StringBuilder;
      // 27a: iload 1
      // 27b: invokevirtual java/lang/StringBuilder.append (I)Ljava/lang/StringBuilder;
      // 27e: bipush 41
      // 280: invokevirtual java/lang/StringBuilder.append (C)Ljava/lang/StringBuilder;
      // 283: invokevirtual java/lang/StringBuilder.toString ()Ljava/lang/String;
      // 286: invokestatic i.a (Ljava/lang/Throwable;Ljava/lang/String;)Lla;
      // 289: athrow
      // 28a: return
   }

   final void g(int var1, int var2, int var3, int var4) {
      try {
         try {
            this.C = var1 & 0xFF;
            m++;
            if (var2 != -999999) {
               this.a(115, -103, 21, -85, -116, -56);
            }
         } catch (RuntimeException var6) {
            throw var6;
         }

         this.F = var3 & 0xFF;
         this.X = var4 & 0xFF;
         this.b((byte)-117);
         this.Yb = 1;
      } catch (RuntimeException var7) {
         throw i.a(var7, kc[37] + var1 + ',' + var2 + ',' + var3 + ',' + var4 + ')');
      }
   }

   private final void a(int var1, ca[] var2, boolean var3, int var4) {
      boolean var14 = client.vh;

      try {
         kb++;
         int var23 = 0;
         int var6 = 0;
         int var7 = 0;

         while (true) {
            if (~var4 < ~var7) {
               var23 += var2[var7].t;
               var6 += var2[var7].Db;

               try {
                  var7++;
                  if (var14) {
                     break;
                  }

                  if (!var14) {
                     continue;
                  }
               } catch (RuntimeException var21) {
                  throw var21;
               }
            }

            this.a(var23, var6, 88);
            break;
         }

         try {
            if (var3) {
               this.fc = new int[var23][];
            }
         } catch (RuntimeException var20) {
            throw var20;
         }

         var7 = var1;

         label136:
         while (true) {
            int var26 = var7;

            label133:
            while (var26 < var4) {
               ca var8 = var2[var7];
               var8.a((byte)-28);
               this.Ib = var8.Ib;
               this.g = var8.g;
               this.Bb = var8.Bb;
               this.Mb = var8.Mb;
               this.Fb = var8.Fb;
               this.Jb = var8.Jb;
               if (var14) {
                  return;
               }

               int var9 = 0;

               while (~var9 > ~var8.t) {
                  int[] var10 = new int[var8.lb[var9]];
                  int[] var11 = var8.o[var9];
                  var26 = 0;
                  if (var14) {
                     continue label133;
                  }

                  int var12 = 0;

                  while (true) {
                     if (~var12 > ~var8.lb[var9]) {
                        try {
                           var10[var12] = this.e(var8.a[var11[var12]], var8.bc[var11[var12]], var8.ob[var11[var12]], -122);
                           var12++;
                           if (var14) {
                              break;
                           }

                           if (!var14) {
                              continue;
                           }
                        } catch (RuntimeException var19) {
                           throw var19;
                        }
                     }

                     var12 = this.a(var8.lb[var9], var10, var8.V[var9], var8.qb[var9], false);
                     this.Hb[var12] = var8.Hb[var9];
                     this.M[var12] = var8.M[var9];
                     this.k[var12] = var8.k[var9];
                     break;
                  }

                  label118: {
                     label161: {
                        try {
                           if (!var3) {
                              break label161;
                           }
                        } catch (RuntimeException var18) {
                           throw var18;
                        }

                        if (1 >= var4) {
                           this.fc[var12] = new int[var8.fc[var9].length];
                           int var13 = 0;

                           while (~var8.fc[var9].length < ~var13) {
                              try {
                                 this.fc[var12][var13] = var8.fc[var9][var13];
                                 var13++;
                                 if (var14) {
                                    break label118;
                                 }

                                 if (var14) {
                                    break;
                                 }
                              } catch (RuntimeException var17) {
                                 throw var17;
                              }
                           }

                           if (!var14) {
                              break label161;
                           }
                        }

                        this.fc[var12] = new int[var8.fc[var9].length - -1];
                        this.fc[var12][0] = var7;
                        int var25 = 0;

                        while (var25 < var8.fc[var9].length) {
                           try {
                              this.fc[var12][1 + var25] = var8.fc[var9][var25];
                              var25++;
                              if (var14) {
                                 break label118;
                              }

                              if (var14) {
                                 break;
                              }
                           } catch (RuntimeException var16) {
                              throw var16;
                           }
                        }
                     }

                     var9++;
                  }

                  if (var14) {
                     break;
                  }
               }

               var7++;
               if (!var14) {
                  continue label136;
               }
               break;
            }

            this.Yb = 1;
            return;
         }
      } catch (RuntimeException var22) {
         RuntimeException var5 = var22;

         RuntimeException var10000;
         StringBuilder var10001;
         try {
            var10000 = var5;
            var10001 = new StringBuilder().append(kc[35]).append(var1).append(',');
            if (var2 != null) {
               throw i.a(var5, var10001.append(kc[1]).append(',').append(var3).append(',').append(var4).append(')').toString());
            }
         } catch (RuntimeException var15) {
            throw var15;
         }

         throw i.a(var10000, var10001.append(kc[3]).append(',').append(var3).append(',').append(var4).append(')').toString());
      }
   }

   private final void a(int param1, int param2, int param3) {
      // $VF: Couldn't be decompiled
      // Please report this to the Vineflower issue tracker, at https://github.com/Vineflower/vineflower/issues with a copy of the class file (if you have the rights to distribute it!)
      // java.lang.RuntimeException: parsing failure!
      //   at org.jetbrains.java.decompiler.modules.decompiler.decompose.DomHelper.parseGraph(DomHelper.java:211)
      //   at org.jetbrains.java.decompiler.main.rels.MethodProcessor.codeToJava(MethodProcessor.java:166)
      //
      // Bytecode:
      // 000: aload 0
      // 001: getfield ca.db Z
      // 004: ifne 00c
      // 007: bipush 1
      // 008: goto 00d
      // 00b: athrow
      // 00c: bipush 0
      // 00d: ifne 013
      // 010: goto 021
      // 013: aload 0
      // 014: iload 1
      // 015: newarray 8
      // 017: putfield ca.zb [B
      // 01a: aload 0
      // 01b: iload 1
      // 01c: newarray 10
      // 01e: putfield ca.E [I
      // 021: aload 0
      // 022: iload 1
      // 023: newarray 10
      // 025: putfield ca.k [I
      // 028: aload 0
      // 029: iload 2
      // 02a: newarray 10
      // 02c: putfield ca.ob [I
      // 02f: aload 0
      // 030: iload 2
      // 031: newarray 8
      // 033: putfield ca.Ab [B
      // 036: aload 0
      // 037: iload 2
      // 038: newarray 10
      // 03a: putfield ca.a [I
      // 03d: aload 0
      // 03e: iload 1
      // 03f: newarray 10
      // 041: putfield ca.M [I
      // 044: aload 0
      // 045: iload 2
      // 046: newarray 10
      // 048: putfield ca.bc [I
      // 04b: aload 0
      // 04c: iload 1
      // 04d: newarray 10
      // 04f: putfield ca.qb [I
      // 052: aload 0
      // 053: iload 2
      // 054: newarray 10
      // 056: putfield ca.gb [I
      // 059: aload 0
      // 05a: iload 1
      // 05b: newarray 10
      // 05d: putfield ca.V [I
      // 060: aload 0
      // 061: iload 1
      // 062: anewarray 285
      // 065: putfield ca.o [[I
      // 068: aload 0
      // 069: iload 1
      // 06a: newarray 10
      // 06c: putfield ca.lb [I
      // 06f: bipush 0
      // 070: aload 0
      // 071: getfield ca.b Z
      // 074: if_icmpne 09e
      // 077: aload 0
      // 078: iload 2
      // 079: newarray 10
      // 07b: putfield ca.Ob [I
      // 07e: aload 0
      // 07f: iload 2
      // 080: newarray 10
      // 082: putfield ca.H [I
      // 085: aload 0
      // 086: iload 2
      // 087: newarray 10
      // 089: putfield ca.cc [I
      // 08c: aload 0
      // 08d: iload 2
      // 08e: newarray 10
      // 090: putfield ca.bb [I
      // 093: aload 0
      // 094: iload 2
      // 095: newarray 10
      // 097: putfield ca.pb [I
      // 09a: goto 09e
      // 09d: athrow
      // 09e: getstatic ca.nb I
      // 0a1: bipush 1
      // 0a2: iadd
      // 0a3: putstatic ca.nb I
      // 0a6: aload 0
      // 0a7: iload 1
      // 0a8: newarray 10
      // 0aa: putfield ca.Hb [I
      // 0ad: aload 0
      // 0ae: sipush 256
      // 0b1: putfield ca.Y I
      // 0b4: aload 0
      // 0b5: bipush 0
      // 0b6: putfield ca.X I
      // 0b9: aload 0
      // 0ba: sipush 256
      // 0bd: putfield ca.U I
      // 0c0: aload 0
      // 0c1: sipush 256
      // 0c4: putfield ca.Tb I
      // 0c7: aload 0
      // 0c8: sipush 256
      // 0cb: putfield ca.T I
      // 0ce: aload 0
      // 0cf: getfield ca.c Z
      // 0d2: ifne 0da
      // 0d5: bipush 1
      // 0d6: goto 0db
      // 0d9: athrow
      // 0da: bipush 0
      // 0db: bipush 1
      // 0dc: if_icmpne 10d
      // 0df: aload 0
      // 0e0: iload 1
      // 0e1: newarray 10
      // 0e3: putfield ca.n [I
      // 0e6: aload 0
      // 0e7: iload 1
      // 0e8: newarray 10
      // 0ea: putfield ca.Q [I
      // 0ed: aload 0
      // 0ee: iload 1
      // 0ef: newarray 10
      // 0f1: putfield ca.Zb [I
      // 0f4: aload 0
      // 0f5: iload 1
      // 0f6: newarray 10
      // 0f8: putfield ca.Lb [I
      // 0fb: aload 0
      // 0fc: iload 1
      // 0fd: newarray 10
      // 0ff: putfield ca.Eb [I
      // 102: aload 0
      // 103: iload 1
      // 104: newarray 10
      // 106: putfield ca.w [I
      // 109: goto 10d
      // 10c: athrow
      // 10d: aload 0
      // 10e: getfield ca.Nb Z
      // 111: ifeq 12c
      // 114: bipush 0
      // 115: aload 0
      // 116: getfield ca.c Z
      // 119: ifne 125
      // 11c: goto 120
      // 11f: athrow
      // 120: bipush 1
      // 121: goto 126
      // 124: athrow
      // 125: bipush 0
      // 126: if_icmpne 12c
      // 129: goto 141
      // 12c: aload 0
      // 12d: iload 1
      // 12e: newarray 10
      // 130: putfield ca.Cb [I
      // 133: aload 0
      // 134: iload 1
      // 135: newarray 10
      // 137: putfield ca.Pb [I
      // 13a: aload 0
      // 13b: iload 1
      // 13c: newarray 10
      // 13e: putfield ca.fb [I
      // 141: aload 0
      // 142: sipush 256
      // 145: putfield ca.G I
      // 148: aload 0
      // 149: bipush 0
      // 14a: putfield ca.t I
      // 14d: aload 0
      // 14e: bipush 0
      // 14f: putfield ca.F I
      // 152: aload 0
      // 153: bipush 0
      // 154: putfield ca.Sb I
      // 157: aload 0
      // 158: sipush 256
      // 15b: putfield ca.yb I
      // 15e: bipush 1
      // 15f: aload 0
      // 160: getfield ca.v Z
      // 163: if_icmpeq 185
      // 166: aload 0
      // 167: iload 2
      // 168: newarray 10
      // 16a: putfield ca.Gb [I
      // 16d: aload 0
      // 16e: iload 2
      // 16f: newarray 10
      // 171: putfield ca.jc [I
      // 174: aload 0
      // 175: iload 2
      // 176: newarray 10
      // 178: putfield ca.ic [I
      // 17b: getstatic client.vh Z
      // 17e: ifeq 1a1
      // 181: goto 185
      // 184: athrow
      // 185: aload 0
      // 186: aload 0
      // 187: getfield ca.a [I
      // 18a: putfield ca.Gb [I
      // 18d: aload 0
      // 18e: aload 0
      // 18f: getfield ca.bc [I
      // 192: putfield ca.jc [I
      // 195: aload 0
      // 196: aload 0
      // 197: getfield ca.ob [I
      // 19a: putfield ca.ic [I
      // 19d: goto 1a1
      // 1a0: athrow
      // 1a1: aload 0
      // 1a2: bipush 0
      // 1a3: putfield ca.r I
      // 1a6: aload 0
      // 1a7: iload 2
      // 1a8: putfield ca.K I
      // 1ab: aload 0
      // 1ac: sipush 256
      // 1af: putfield ca.eb I
      // 1b2: aload 0
      // 1b3: sipush 256
      // 1b6: putfield ca.f I
      // 1b9: aload 0
      // 1ba: bipush 0
      // 1bb: putfield ca.xb I
      // 1be: aload 0
      // 1bf: bipush 0
      // 1c0: putfield ca.jb I
      // 1c3: aload 0
      // 1c4: bipush 0
      // 1c5: putfield ca.Db I
      // 1c8: aload 0
      // 1c9: sipush 256
      // 1cc: putfield ca.i I
      // 1cf: iload 3
      // 1d0: bipush 68
      // 1d2: if_icmpgt 1e1
      // 1d5: aload 0
      // 1d6: aconst_null
      // 1d7: checkcast [I
      // 1da: putfield ca.lb [I
      // 1dd: goto 1e1
      // 1e0: athrow
      // 1e1: aload 0
      // 1e2: iload 1
      // 1e3: putfield ca.z I
      // 1e6: aload 0
      // 1e7: bipush 0
      // 1e8: putfield ca.C I
      // 1eb: goto 224
      // 1ee: astore 4
      // 1f0: aload 4
      // 1f2: new java/lang/StringBuilder
      // 1f5: dup
      // 1f6: invokespecial java/lang/StringBuilder.<init> ()V
      // 1f9: getstatic ca.kc [Ljava/lang/String;
      // 1fc: bipush 29
      // 1fe: aaload
      // 1ff: invokevirtual java/lang/StringBuilder.append (Ljava/lang/String;)Ljava/lang/StringBuilder;
      // 202: iload 1
      // 203: invokevirtual java/lang/StringBuilder.append (I)Ljava/lang/StringBuilder;
      // 206: bipush 44
      // 208: invokevirtual java/lang/StringBuilder.append (C)Ljava/lang/StringBuilder;
      // 20b: iload 2
      // 20c: invokevirtual java/lang/StringBuilder.append (I)Ljava/lang/StringBuilder;
      // 20f: bipush 44
      // 211: invokevirtual java/lang/StringBuilder.append (C)Ljava/lang/StringBuilder;
      // 214: iload 3
      // 215: invokevirtual java/lang/StringBuilder.append (I)Ljava/lang/StringBuilder;
      // 218: bipush 41
      // 21a: invokevirtual java/lang/StringBuilder.append (C)Ljava/lang/StringBuilder;
      // 21d: invokevirtual java/lang/StringBuilder.toString ()Ljava/lang/String;
      // 220: invokestatic i.a (Ljava/lang/Throwable;Ljava/lang/String;)Lla;
      // 223: athrow
      // 224: return
   }

   final void a(int var1, int var2, int var3, int var4, int var5, int var6) {
      try {
         try {
            Ub++;
            this.Jb = -(4 * var2) + 256;
            this.Mb = (64 - var1) * 16 + 128;
            if (var4 > -110) {
               this.Bb = -67;
            }
         } catch (RuntimeException var8) {
            throw var8;
         }

         if (!this.Nb) {
            this.g = var5;
            this.Fb = var6;
            this.Bb = var3;
            this.Ib = (int)Math.sqrt((double)(var6 * var6 + var3 * var3 + var5 * var5));
            this.e(-102);
         }
      } catch (RuntimeException var9) {
         throw i.a(var9, kc[14] + var1 + ',' + var2 + ',' + var3 + ',' + var4 + ',' + var5 + ',' + var6 + ')');
      }
   }

   final ca[] a(int param1, int param2, int param3, int param4, int param5, int param6, int param7, boolean param8, int param9) {
      // $VF: Couldn't be decompiled
      // Please report this to the Vineflower issue tracker, at https://github.com/Vineflower/vineflower/issues with a copy of the class file (if you have the rights to distribute it!)
      // java.lang.RuntimeException: parsing failure!
      //   at org.jetbrains.java.decompiler.modules.decompiler.decompose.DomHelper.parseGraph(DomHelper.java:211)
      //   at org.jetbrains.java.decompiler.main.rels.MethodProcessor.codeToJava(MethodProcessor.java:166)
      //
      // Bytecode:
      // 000: getstatic client.vh Z
      // 003: istore 19
      // 005: getstatic ca.Rb I
      // 008: bipush 1
      // 009: iadd
      // 00a: putstatic ca.Rb I
      // 00d: aload 0
      // 00e: bipush -28
      // 010: invokespecial ca.a (B)V
      // 013: iload 5
      // 015: newarray 10
      // 017: astore 10
      // 019: iload 5
      // 01b: newarray 10
      // 01d: astore 11
      // 01f: bipush 0
      // 020: istore 12
      // 022: iload 12
      // 024: bipush -1
      // 025: ixor
      // 026: iload 5
      // 028: bipush -1
      // 029: ixor
      // 02a: if_icmple 04a
      // 02d: aload 10
      // 02f: iload 12
      // 031: bipush 0
      // 032: iastore
      // 033: aload 11
      // 035: iload 12
      // 037: bipush 0
      // 038: iastore
      // 039: iinc 12 1
      // 03c: iload 19
      // 03e: ifne 04d
      // 041: iload 19
      // 043: ifeq 022
      // 046: goto 04a
      // 049: athrow
      // 04a: bipush 0
      // 04b: istore 12
      // 04d: iload 12
      // 04f: aload 0
      // 050: getfield ca.t I
      // 053: if_icmpge 0df
      // 056: bipush 0
      // 057: istore 13
      // 059: bipush 0
      // 05a: istore 14
      // 05c: aload 0
      // 05d: getfield ca.lb [I
      // 060: iload 12
      // 062: iaload
      // 063: istore 15
      // 065: aload 0
      // 066: getfield ca.o [[I
      // 069: iload 12
      // 06b: aaload
      // 06c: astore 16
      // 06e: bipush 0
      // 06f: iload 19
      // 071: ifne 0e1
      // 074: istore 17
      // 076: iload 17
      // 078: bipush -1
      // 079: ixor
      // 07a: iload 15
      // 07c: bipush -1
      // 07d: ixor
      // 07e: if_icmple 0b0
      // 081: iload 13
      // 083: aload 0
      // 084: getfield ca.a [I
      // 087: aload 16
      // 089: iload 17
      // 08b: iaload
      // 08c: iaload
      // 08d: iadd
      // 08e: istore 13
      // 090: iload 14
      // 092: aload 0
      // 093: getfield ca.bc [I
      // 096: aload 16
      // 098: iload 17
      // 09a: iaload
      // 09b: iaload
      // 09c: iadd
      // 09d: istore 14
      // 09f: iinc 17 1
      // 0a2: iload 19
      // 0a4: ifne 0da
      // 0a7: iload 19
      // 0a9: ifeq 076
      // 0ac: goto 0b0
      // 0af: athrow
      // 0b0: iload 13
      // 0b2: iload 15
      // 0b4: iload 7
      // 0b6: imul
      // 0b7: idiv
      // 0b8: iload 14
      // 0ba: iload 3
      // 0bb: iload 15
      // 0bd: imul
      // 0be: idiv
      // 0bf: iload 2
      // 0c0: imul
      // 0c1: iadd
      // 0c2: istore 17
      // 0c4: aload 10
      // 0c6: iload 17
      // 0c8: dup2
      // 0c9: iaload
      // 0ca: iload 15
      // 0cc: iadd
      // 0cd: iastore
      // 0ce: aload 11
      // 0d0: iload 17
      // 0d2: dup2
      // 0d3: iaload
      // 0d4: bipush 1
      // 0d5: iadd
      // 0d6: iastore
      // 0d7: iinc 12 1
      // 0da: iload 19
      // 0dc: ifeq 04d
      // 0df: iload 5
      // 0e1: anewarray 289
      // 0e4: astore 12
      // 0e6: bipush 0
      // 0e7: istore 13
      // 0e9: iload 13
      // 0eb: bipush -1
      // 0ec: ixor
      // 0ed: iload 5
      // 0ef: bipush -1
      // 0f0: ixor
      // 0f1: if_icmple 14d
      // 0f4: iload 6
      // 0f6: aload 10
      // 0f8: iload 13
      // 0fa: iaload
      // 0fb: iload 19
      // 0fd: ifne 156
      // 100: if_icmplt 10a
      // 103: goto 107
      // 106: athrow
      // 107: goto 111
      // 10a: aload 10
      // 10c: iload 13
      // 10e: iload 6
      // 110: iastore
      // 111: aload 12
      // 113: iload 13
      // 115: new ca
      // 118: dup
      // 119: aload 10
      // 11b: iload 13
      // 11d: iaload
      // 11e: aload 11
      // 120: iload 13
      // 122: iaload
      // 123: bipush 1
      // 124: bipush 1
      // 125: bipush 1
      // 126: iload 8
      // 128: bipush 1
      // 129: invokespecial ca.<init> (IIZZZZZ)V
      // 12c: aastore
      // 12d: aload 12
      // 12f: iload 13
      // 131: aaload
      // 132: aload 0
      // 133: getfield ca.Mb I
      // 136: putfield ca.Mb I
      // 139: aload 12
      // 13b: iload 13
      // 13d: aaload
      // 13e: aload 0
      // 13f: getfield ca.Jb I
      // 142: putfield ca.Jb I
      // 145: iinc 13 1
      // 148: iload 19
      // 14a: ifeq 0e9
      // 14d: bipush 0
      // 14e: istore 13
      // 150: aload 0
      // 151: getfield ca.t I
      // 154: iload 13
      // 156: if_icmple 1e1
      // 159: bipush 0
      // 15a: istore 14
      // 15c: bipush 0
      // 15d: istore 15
      // 15f: aload 0
      // 160: getfield ca.lb [I
      // 163: iload 13
      // 165: iaload
      // 166: istore 16
      // 168: aload 0
      // 169: getfield ca.o [[I
      // 16c: iload 13
      // 16e: aaload
      // 16f: astore 17
      // 171: bipush 0
      // 172: iload 19
      // 174: ifne 1ef
      // 177: istore 18
      // 179: iload 16
      // 17b: bipush -1
      // 17c: ixor
      // 17d: iload 18
      // 17f: bipush -1
      // 180: ixor
      // 181: if_icmpge 1b3
      // 184: iload 14
      // 186: aload 0
      // 187: getfield ca.a [I
      // 18a: aload 17
      // 18c: iload 18
      // 18e: iaload
      // 18f: iaload
      // 190: iadd
      // 191: istore 14
      // 193: iload 15
      // 195: aload 0
      // 196: getfield ca.bc [I
      // 199: aload 17
      // 19b: iload 18
      // 19d: iaload
      // 19e: iaload
      // 19f: iadd
      // 1a0: istore 15
      // 1a2: iinc 18 1
      // 1a5: iload 19
      // 1a7: ifne 1dc
      // 1aa: iload 19
      // 1ac: ifeq 179
      // 1af: goto 1b3
      // 1b2: athrow
      // 1b3: iload 14
      // 1b5: iload 16
      // 1b7: iload 7
      // 1b9: imul
      // 1ba: idiv
      // 1bb: iload 2
      // 1bc: iload 15
      // 1be: iload 3
      // 1bf: iload 16
      // 1c1: imul
      // 1c2: idiv
      // 1c3: imul
      // 1c4: iadd
      // 1c5: istore 18
      // 1c7: aload 0
      // 1c8: aload 17
      // 1ca: aload 12
      // 1cc: iload 18
      // 1ce: aaload
      // 1cf: iload 16
      // 1d1: iload 13
      // 1d3: sipush 5916
      // 1d6: invokespecial ca.a ([ILca;III)V
      // 1d9: iinc 13 1
      // 1dc: iload 19
      // 1de: ifeq 150
      // 1e1: bipush 0
      // 1e2: istore 13
      // 1e4: bipush -50
      // 1e6: iload 4
      // 1e8: bipush -33
      // 1ea: isub
      // 1eb: bipush 60
      // 1ed: idiv
      // 1ee: idiv
      // 1ef: istore 14
      // 1f1: iload 13
      // 1f3: bipush -1
      // 1f4: ixor
      // 1f5: iload 5
      // 1f7: bipush -1
      // 1f8: ixor
      // 1f9: if_icmple 217
      // 1fc: aload 12
      // 1fe: iload 19
      // 200: ifne 219
      // 203: iload 13
      // 205: aaload
      // 206: bipush 71
      // 208: invokespecial ca.c (B)V
      // 20b: iinc 13 1
      // 20e: iload 19
      // 210: ifeq 1f1
      // 213: goto 217
      // 216: athrow
      // 217: aload 12
      // 219: areturn
      // 21a: astore 10
      // 21c: aload 10
      // 21e: new java/lang/StringBuilder
      // 221: dup
      // 222: invokespecial java/lang/StringBuilder.<init> ()V
      // 225: getstatic ca.kc [Ljava/lang/String;
      // 228: bipush 23
      // 22a: aaload
      // 22b: invokevirtual java/lang/StringBuilder.append (Ljava/lang/String;)Ljava/lang/StringBuilder;
      // 22e: iload 1
      // 22f: invokevirtual java/lang/StringBuilder.append (I)Ljava/lang/StringBuilder;
      // 232: bipush 44
      // 234: invokevirtual java/lang/StringBuilder.append (C)Ljava/lang/StringBuilder;
      // 237: iload 2
      // 238: invokevirtual java/lang/StringBuilder.append (I)Ljava/lang/StringBuilder;
      // 23b: bipush 44
      // 23d: invokevirtual java/lang/StringBuilder.append (C)Ljava/lang/StringBuilder;
      // 240: iload 3
      // 241: invokevirtual java/lang/StringBuilder.append (I)Ljava/lang/StringBuilder;
      // 244: bipush 44
      // 246: invokevirtual java/lang/StringBuilder.append (C)Ljava/lang/StringBuilder;
      // 249: iload 4
      // 24b: invokevirtual java/lang/StringBuilder.append (I)Ljava/lang/StringBuilder;
      // 24e: bipush 44
      // 250: invokevirtual java/lang/StringBuilder.append (C)Ljava/lang/StringBuilder;
      // 253: iload 5
      // 255: invokevirtual java/lang/StringBuilder.append (I)Ljava/lang/StringBuilder;
      // 258: bipush 44
      // 25a: invokevirtual java/lang/StringBuilder.append (C)Ljava/lang/StringBuilder;
      // 25d: iload 6
      // 25f: invokevirtual java/lang/StringBuilder.append (I)Ljava/lang/StringBuilder;
      // 262: bipush 44
      // 264: invokevirtual java/lang/StringBuilder.append (C)Ljava/lang/StringBuilder;
      // 267: iload 7
      // 269: invokevirtual java/lang/StringBuilder.append (I)Ljava/lang/StringBuilder;
      // 26c: bipush 44
      // 26e: invokevirtual java/lang/StringBuilder.append (C)Ljava/lang/StringBuilder;
      // 271: iload 8
      // 273: invokevirtual java/lang/StringBuilder.append (Z)Ljava/lang/StringBuilder;
      // 276: bipush 44
      // 278: invokevirtual java/lang/StringBuilder.append (C)Ljava/lang/StringBuilder;
      // 27b: iload 9
      // 27d: invokevirtual java/lang/StringBuilder.append (I)Ljava/lang/StringBuilder;
      // 280: bipush 41
      // 282: invokevirtual java/lang/StringBuilder.append (C)Ljava/lang/StringBuilder;
      // 285: invokevirtual java/lang/StringBuilder.toString ()Ljava/lang/String;
      // 288: invokestatic i.a (Ljava/lang/Throwable;Ljava/lang/String;)Lla;
      // 28b: athrow
   }

   final int a(int var1, int[] var2, int var3, int var4, boolean var5) {
      try {
         try {
            u++;
            if (var5) {
               this.f(30, -84, 10, 23);
            }
         } catch (RuntimeException var7) {
            throw var7;
         }

         try {
            if (~this.t <= ~this.z) {
               return -1;
            }
         } catch (RuntimeException var9) {
            throw var9;
         }

         this.lb[this.t] = var1;
         this.o[this.t] = var2;
         this.V[this.t] = var3;
         this.qb[this.t] = var4;
         this.Yb = 1;
         return this.t++;
      } catch (RuntimeException var10) {
         RuntimeException var6 = var10;

         RuntimeException var10000;
         StringBuilder var10001;
         try {
            var10000 = var6;
            var10001 = new StringBuilder().append(kc[2]).append(var1).append(',');
            if (var2 != null) {
               throw i.a(
                  var6,
                  var10001.append(kc[1]).append((char)44).append(var3).append((char)44).append(var4).append((char)44).append(var5).append((char)41).toString()
               );
            }
         } catch (RuntimeException var8) {
            throw var8;
         }

         throw i.a(
            var10000,
            var10001.append(kc[3]).append((char)44).append(var3).append((char)44).append(var4).append((char)44).append(var5).append((char)41).toString()
         );
      }
   }

   final void a(int var1, int var2, int var3, boolean var4) {
      try {
         try {
            this.xb += var3;
            this.Sb += var2;
            if (!var4) {
               this.jc = (int[])null;
            }
         } catch (RuntimeException var6) {
            throw var6;
         }

         this.r += var1;
         L++;
         this.b((byte)-127);
         this.Yb = 1;
      } catch (RuntimeException var7) {
         throw i.a(var7, kc[31] + var1 + ',' + var2 + ',' + var3 + ',' + var4 + ')');
      }
   }

   private final void a(int param1, int param2, int param3, int param4, int param5, int param6, byte param7) {
      // $VF: Couldn't be decompiled
      // Please report this to the Vineflower issue tracker, at https://github.com/Vineflower/vineflower/issues with a copy of the class file (if you have the rights to distribute it!)
      // java.lang.RuntimeException: parsing failure!
      //   at org.jetbrains.java.decompiler.modules.decompiler.decompose.DomHelper.parseGraph(DomHelper.java:211)
      //   at org.jetbrains.java.decompiler.main.rels.MethodProcessor.codeToJava(MethodProcessor.java:166)
      //
      // Bytecode:
      // 000: getstatic client.vh Z
      // 003: istore 10
      // 005: getstatic ca.S I
      // 008: bipush 1
      // 009: iadd
      // 00a: putstatic ca.S I
      // 00d: bipush 118
      // 00f: bipush -80
      // 011: iload 7
      // 013: isub
      // 014: bipush 46
      // 016: idiv
      // 017: idiv
      // 018: istore 8
      // 01a: bipush 0
      // 01b: istore 9
      // 01d: iload 9
      // 01f: aload 0
      // 020: getfield ca.Db I
      // 023: if_icmpge 101
      // 026: iload 10
      // 028: ifne 162
      // 02b: bipush -1
      // 02c: iload 3
      // 02d: bipush -1
      // 02e: ixor
      // 02f: if_icmpeq 050
      // 032: goto 036
      // 035: athrow
      // 036: aload 0
      // 037: getfield ca.Gb [I
      // 03a: iload 9
      // 03c: dup2
      // 03d: iaload
      // 03e: aload 0
      // 03f: getfield ca.ic [I
      // 042: iload 9
      // 044: iaload
      // 045: iload 3
      // 046: imul
      // 047: ldc 1095852296
      // 049: ishr
      // 04a: iadd
      // 04b: iastore
      // 04c: goto 050
      // 04f: athrow
      // 050: bipush 0
      // 051: iload 4
      // 053: if_icmpne 05a
      // 056: goto 071
      // 059: athrow
      // 05a: aload 0
      // 05b: getfield ca.jc [I
      // 05e: iload 9
      // 060: dup2
      // 061: iaload
      // 062: iload 4
      // 064: aload 0
      // 065: getfield ca.ic [I
      // 068: iload 9
      // 06a: iaload
      // 06b: imul
      // 06c: ldc -706532120
      // 06e: ishr
      // 06f: iadd
      // 070: iastore
      // 071: bipush -1
      // 072: iload 5
      // 074: bipush -1
      // 075: ixor
      // 076: if_icmpeq 094
      // 079: aload 0
      // 07a: getfield ca.Gb [I
      // 07d: iload 9
      // 07f: dup2
      // 080: iaload
      // 081: iload 5
      // 083: aload 0
      // 084: getfield ca.jc [I
      // 087: iload 9
      // 089: iaload
      // 08a: imul
      // 08b: ldc -324256440
      // 08d: ishr
      // 08e: iadd
      // 08f: iastore
      // 090: goto 094
      // 093: athrow
      // 094: bipush -1
      // 095: iload 2
      // 096: bipush -1
      // 097: ixor
      // 098: if_icmpeq 0b5
      // 09b: aload 0
      // 09c: getfield ca.ic [I
      // 09f: iload 9
      // 0a1: dup2
      // 0a2: iaload
      // 0a3: iload 2
      // 0a4: aload 0
      // 0a5: getfield ca.jc [I
      // 0a8: iload 9
      // 0aa: iaload
      // 0ab: imul
      // 0ac: ldc 423792200
      // 0ae: ishr
      // 0af: iadd
      // 0b0: iastore
      // 0b1: goto 0b5
      // 0b4: athrow
      // 0b5: bipush -1
      // 0b6: iload 1
      // 0b7: bipush -1
      // 0b8: ixor
      // 0b9: if_icmpne 0c0
      // 0bc: goto 0d6
      // 0bf: athrow
      // 0c0: aload 0
      // 0c1: getfield ca.jc [I
      // 0c4: iload 9
      // 0c6: dup2
      // 0c7: iaload
      // 0c8: iload 1
      // 0c9: aload 0
      // 0ca: getfield ca.Gb [I
      // 0cd: iload 9
      // 0cf: iaload
      // 0d0: imul
      // 0d1: ldc -1731094840
      // 0d3: ishr
      // 0d4: iadd
      // 0d5: iastore
      // 0d6: bipush -1
      // 0d7: iload 6
      // 0d9: bipush -1
      // 0da: ixor
      // 0db: if_icmpeq 0f9
      // 0de: aload 0
      // 0df: getfield ca.ic [I
      // 0e2: iload 9
      // 0e4: dup2
      // 0e5: iaload
      // 0e6: aload 0
      // 0e7: getfield ca.Gb [I
      // 0ea: iload 9
      // 0ec: iaload
      // 0ed: iload 6
      // 0ef: imul
      // 0f0: ldc 1779723400
      // 0f2: ishr
      // 0f3: iadd
      // 0f4: iastore
      // 0f5: goto 0f9
      // 0f8: athrow
      // 0f9: iinc 9 1
      // 0fc: iload 10
      // 0fe: ifeq 01d
      // 101: goto 162
      // 104: astore 8
      // 106: aload 8
      // 108: new java/lang/StringBuilder
      // 10b: dup
      // 10c: invokespecial java/lang/StringBuilder.<init> ()V
      // 10f: getstatic ca.kc [Ljava/lang/String;
      // 112: bipush 16
      // 114: aaload
      // 115: invokevirtual java/lang/StringBuilder.append (Ljava/lang/String;)Ljava/lang/StringBuilder;
      // 118: iload 1
      // 119: invokevirtual java/lang/StringBuilder.append (I)Ljava/lang/StringBuilder;
      // 11c: bipush 44
      // 11e: invokevirtual java/lang/StringBuilder.append (C)Ljava/lang/StringBuilder;
      // 121: iload 2
      // 122: invokevirtual java/lang/StringBuilder.append (I)Ljava/lang/StringBuilder;
      // 125: bipush 44
      // 127: invokevirtual java/lang/StringBuilder.append (C)Ljava/lang/StringBuilder;
      // 12a: iload 3
      // 12b: invokevirtual java/lang/StringBuilder.append (I)Ljava/lang/StringBuilder;
      // 12e: bipush 44
      // 130: invokevirtual java/lang/StringBuilder.append (C)Ljava/lang/StringBuilder;
      // 133: iload 4
      // 135: invokevirtual java/lang/StringBuilder.append (I)Ljava/lang/StringBuilder;
      // 138: bipush 44
      // 13a: invokevirtual java/lang/StringBuilder.append (C)Ljava/lang/StringBuilder;
      // 13d: iload 5
      // 13f: invokevirtual java/lang/StringBuilder.append (I)Ljava/lang/StringBuilder;
      // 142: bipush 44
      // 144: invokevirtual java/lang/StringBuilder.append (C)Ljava/lang/StringBuilder;
      // 147: iload 6
      // 149: invokevirtual java/lang/StringBuilder.append (I)Ljava/lang/StringBuilder;
      // 14c: bipush 44
      // 14e: invokevirtual java/lang/StringBuilder.append (C)Ljava/lang/StringBuilder;
      // 151: iload 7
      // 153: invokevirtual java/lang/StringBuilder.append (I)Ljava/lang/StringBuilder;
      // 156: bipush 41
      // 158: invokevirtual java/lang/StringBuilder.append (C)Ljava/lang/StringBuilder;
      // 15b: invokevirtual java/lang/StringBuilder.toString ()Ljava/lang/String;
      // 15e: invokestatic i.a (Ljava/lang/Throwable;Ljava/lang/String;)Lla;
      // 161: athrow
      // 162: return
   }

   final void b(int var1, int var2, int var3) {
      try {
         try {
            ub++;
            this.t -= var3;
            if (var2 > -110) {
               a((byte)-3, (String)null);
            }
         } catch (RuntimeException var6) {
            throw var6;
         }

         try {
            if (~this.t > -1) {
               this.t = 0;
            }
         } catch (RuntimeException var7) {
            throw var7;
         }

         try {
            this.Db -= var1;
            if (this.Db < 0) {
               this.Db = 0;
            }
         } catch (RuntimeException var5) {
            throw var5;
         }
      } catch (RuntimeException var8) {
         throw i.a(var8, kc[18] + var1 + ',' + var2 + ',' + var3 + ')');
      }
   }

   final void c(int var1, int var2, int var3, int var4) {
      try {
         try {
            this.xb = var1;
            this.r = var4;
            this.Sb = var3;
            if (var2 > -112) {
               this.a(-96, (int[])null, -8, 42, true);
            }
         } catch (RuntimeException var6) {
            throw var6;
         }

         q++;
         this.b((byte)-114);
         this.Yb = 1;
      } catch (RuntimeException var7) {
         throw i.a(var7, kc[21] + var1 + ',' + var2 + ',' + var3 + ',' + var4 + ')');
      }
   }

   final void a(int param1, int param2, int param3, byte param4, int param5, int param6, int param7, int param8, int param9) {
      // $VF: Couldn't be decompiled
      // Please report this to the Vineflower issue tracker, at https://github.com/Vineflower/vineflower/issues with a copy of the class file (if you have the rights to distribute it!)
      // java.lang.RuntimeException: parsing failure!
      //   at org.jetbrains.java.decompiler.modules.decompiler.decompose.DomHelper.parseGraph(DomHelper.java:211)
      //   at org.jetbrains.java.decompiler.main.rels.MethodProcessor.codeToJava(MethodProcessor.java:166)
      //
      // Bytecode:
      // 000: getstatic client.vh Z
      // 003: istore 21
      // 005: getstatic ca.ac I
      // 008: bipush 1
      // 009: iadd
      // 00a: putstatic ca.ac I
      // 00d: aload 0
      // 00e: sipush 7972
      // 011: invokespecial ca.d (I)V
      // 014: getstatic da.K I
      // 017: bipush -1
      // 018: ixor
      // 019: aload 0
      // 01a: getfield ca.ec I
      // 01d: bipush -1
      // 01e: ixor
      // 01f: if_icmpgt 07a
      // 022: getstatic m.j I
      // 025: aload 0
      // 026: getfield ca.gc I
      // 029: if_icmpgt 07a
      // 02c: goto 030
      // 02f: athrow
      // 030: aload 0
      // 031: getfield ca.x I
      // 034: bipush -1
      // 035: ixor
      // 036: getstatic oa.b I
      // 039: bipush -1
      // 03a: ixor
      // 03b: if_icmplt 07a
      // 03e: goto 042
      // 041: athrow
      // 042: getstatic aa.f I
      // 045: aload 0
      // 046: getfield ca.j I
      // 049: if_icmpgt 07a
      // 04c: goto 050
      // 04f: athrow
      // 050: aload 0
      // 051: getfield ca.P I
      // 054: getstatic nb.y I
      // 057: if_icmpgt 07a
      // 05a: goto 05e
      // 05d: athrow
      // 05e: aload 0
      // 05f: getfield ca.e I
      // 062: getstatic aa.b I
      // 065: if_icmplt 07a
      // 068: goto 06c
      // 06b: athrow
      // 06c: aload 0
      // 06d: bipush 1
      // 06e: putfield ca.dc Z
      // 071: iload 21
      // 073: ifeq 080
      // 076: goto 07a
      // 079: athrow
      // 07a: aload 0
      // 07b: bipush 0
      // 07c: putfield ca.dc Z
      // 07f: return
      // 080: bipush 0
      // 081: istore 11
      // 083: iload 4
      // 085: bipush -105
      // 087: if_icmple 094
      // 08a: aload 0
      // 08b: bipush -103
      // 08d: invokespecial ca.c (B)V
      // 090: goto 094
      // 093: athrow
      // 094: bipush 0
      // 095: istore 12
      // 097: bipush 0
      // 098: istore 13
      // 09a: bipush 0
      // 09b: istore 14
      // 09d: bipush 0
      // 09e: istore 15
      // 0a0: iload 7
      // 0a2: ifeq 0b9
      // 0a5: getstatic pa.j [I
      // 0a8: sipush 1024
      // 0ab: iload 7
      // 0ad: iadd
      // 0ae: iaload
      // 0af: istore 12
      // 0b1: getstatic pa.j [I
      // 0b4: iload 7
      // 0b6: iaload
      // 0b7: istore 11
      // 0b9: bipush 0
      // 0ba: istore 16
      // 0bc: bipush 0
      // 0bd: iload 8
      // 0bf: if_icmpne 0c6
      // 0c2: goto 0da
      // 0c5: athrow
      // 0c6: getstatic pa.j [I
      // 0c9: iload 8
      // 0cb: iaload
      // 0cc: istore 13
      // 0ce: getstatic pa.j [I
      // 0d1: iload 8
      // 0d3: sipush -1024
      // 0d6: isub
      // 0d7: iaload
      // 0d8: istore 14
      // 0da: iload 6
      // 0dc: ifne 0e3
      // 0df: goto 0f7
      // 0e2: athrow
      // 0e3: getstatic pa.j [I
      // 0e6: iload 6
      // 0e8: iaload
      // 0e9: istore 15
      // 0eb: getstatic pa.j [I
      // 0ee: iload 6
      // 0f0: sipush -1024
      // 0f3: isub
      // 0f4: iaload
      // 0f5: istore 16
      // 0f7: bipush 0
      // 0f8: istore 17
      // 0fa: aload 0
      // 0fb: getfield ca.Db I
      // 0fe: iload 17
      // 100: if_icmple 237
      // 103: aload 0
      // 104: getfield ca.Gb [I
      // 107: iload 17
      // 109: iaload
      // 10a: iload 3
      // 10b: ineg
      // 10c: iadd
      // 10d: istore 18
      // 10f: iload 1
      // 110: ineg
      // 111: aload 0
      // 112: getfield ca.ic [I
      // 115: iload 17
      // 117: iaload
      // 118: iadd
      // 119: istore 19
      // 11b: iload 21
      // 11d: ifne 2ac
      // 120: iload 7
      // 122: ifeq 14f
      // 125: goto 129
      // 128: athrow
      // 129: iload 19
      // 12b: iload 11
      // 12d: imul
      // 12e: iload 12
      // 130: iload 18
      // 132: imul
      // 133: ineg
      // 134: isub
      // 135: ldc 1285023887
      // 137: ishr
      // 138: istore 10
      // 13a: iload 18
      // 13c: iload 11
      // 13e: imul
      // 13f: ineg
      // 140: iload 19
      // 142: iload 12
      // 144: imul
      // 145: iadd
      // 146: ldc 1814361327
      // 148: ishr
      // 149: istore 19
      // 14b: iload 10
      // 14d: istore 18
      // 14f: aload 0
      // 150: getfield ca.jc [I
      // 153: iload 17
      // 155: iaload
      // 156: iload 5
      // 158: isub
      // 159: istore 20
      // 15b: iload 6
      // 15d: bipush -1
      // 15e: ixor
      // 15f: bipush -1
      // 160: if_icmpeq 188
      // 163: iload 16
      // 165: iload 18
      // 167: imul
      // 168: iload 20
      // 16a: iload 15
      // 16c: imul
      // 16d: iadd
      // 16e: ldc 1043773743
      // 170: ishr
      // 171: istore 10
      // 173: iload 18
      // 175: iload 15
      // 177: imul
      // 178: ineg
      // 179: iload 16
      // 17b: iload 20
      // 17d: imul
      // 17e: iadd
      // 17f: ldc -1543110961
      // 181: ishr
      // 182: istore 20
      // 184: iload 10
      // 186: istore 18
      // 188: iload 8
      // 18a: bipush -1
      // 18b: ixor
      // 18c: bipush -1
      // 18d: if_icmpne 194
      // 190: goto 1ba
      // 193: athrow
      // 194: iload 19
      // 196: iload 14
      // 198: imul
      // 199: iload 13
      // 19b: iload 20
      // 19d: imul
      // 19e: ineg
      // 19f: iadd
      // 1a0: ldc 2015943439
      // 1a2: ishr
      // 1a3: istore 10
      // 1a5: iload 13
      // 1a7: iload 19
      // 1a9: imul
      // 1aa: iload 14
      // 1ac: iload 20
      // 1ae: imul
      // 1af: ineg
      // 1b0: isub
      // 1b1: ldc -446444369
      // 1b3: ishr
      // 1b4: istore 20
      // 1b6: iload 10
      // 1b8: istore 19
      // 1ba: iload 20
      // 1bc: iload 9
      // 1be: if_icmpge 1d5
      // 1c1: aload 0
      // 1c2: getfield ca.pb [I
      // 1c5: iload 17
      // 1c7: iload 18
      // 1c9: iload 2
      // 1ca: ishl
      // 1cb: iastore
      // 1cc: iload 21
      // 1ce: ifeq 1e7
      // 1d1: goto 1d5
      // 1d4: athrow
      // 1d5: aload 0
      // 1d6: getfield ca.pb [I
      // 1d9: iload 17
      // 1db: iload 18
      // 1dd: iload 2
      // 1de: ishl
      // 1df: iload 20
      // 1e1: idiv
      // 1e2: iastore
      // 1e3: goto 1e7
      // 1e6: athrow
      // 1e7: iload 20
      // 1e9: iload 9
      // 1eb: if_icmpge 202
      // 1ee: aload 0
      // 1ef: getfield ca.Ob [I
      // 1f2: iload 17
      // 1f4: iload 19
      // 1f6: iload 2
      // 1f7: ishl
      // 1f8: iastore
      // 1f9: iload 21
      // 1fb: ifeq 214
      // 1fe: goto 202
      // 201: athrow
      // 202: aload 0
      // 203: getfield ca.Ob [I
      // 206: iload 17
      // 208: iload 19
      // 20a: iload 2
      // 20b: ishl
      // 20c: iload 20
      // 20e: idiv
      // 20f: iastore
      // 210: goto 214
      // 213: athrow
      // 214: aload 0
      // 215: getfield ca.cc [I
      // 218: iload 17
      // 21a: iload 18
      // 21c: iastore
      // 21d: aload 0
      // 21e: getfield ca.H [I
      // 221: iload 17
      // 223: iload 19
      // 225: iastore
      // 226: aload 0
      // 227: getfield ca.bb [I
      // 22a: iload 17
      // 22c: iload 20
      // 22e: iastore
      // 22f: iinc 17 1
      // 232: iload 21
      // 234: ifeq 0fa
      // 237: goto 2ac
      // 23a: astore 10
      // 23c: aload 10
      // 23e: new java/lang/StringBuilder
      // 241: dup
      // 242: invokespecial java/lang/StringBuilder.<init> ()V
      // 245: getstatic ca.kc [Ljava/lang/String;
      // 248: bipush 12
      // 24a: aaload
      // 24b: invokevirtual java/lang/StringBuilder.append (Ljava/lang/String;)Ljava/lang/StringBuilder;
      // 24e: iload 1
      // 24f: invokevirtual java/lang/StringBuilder.append (I)Ljava/lang/StringBuilder;
      // 252: bipush 44
      // 254: invokevirtual java/lang/StringBuilder.append (C)Ljava/lang/StringBuilder;
      // 257: iload 2
      // 258: invokevirtual java/lang/StringBuilder.append (I)Ljava/lang/StringBuilder;
      // 25b: bipush 44
      // 25d: invokevirtual java/lang/StringBuilder.append (C)Ljava/lang/StringBuilder;
      // 260: iload 3
      // 261: invokevirtual java/lang/StringBuilder.append (I)Ljava/lang/StringBuilder;
      // 264: bipush 44
      // 266: invokevirtual java/lang/StringBuilder.append (C)Ljava/lang/StringBuilder;
      // 269: iload 4
      // 26b: invokevirtual java/lang/StringBuilder.append (I)Ljava/lang/StringBuilder;
      // 26e: bipush 44
      // 270: invokevirtual java/lang/StringBuilder.append (C)Ljava/lang/StringBuilder;
      // 273: iload 5
      // 275: invokevirtual java/lang/StringBuilder.append (I)Ljava/lang/StringBuilder;
      // 278: bipush 44
      // 27a: invokevirtual java/lang/StringBuilder.append (C)Ljava/lang/StringBuilder;
      // 27d: iload 6
      // 27f: invokevirtual java/lang/StringBuilder.append (I)Ljava/lang/StringBuilder;
      // 282: bipush 44
      // 284: invokevirtual java/lang/StringBuilder.append (C)Ljava/lang/StringBuilder;
      // 287: iload 7
      // 289: invokevirtual java/lang/StringBuilder.append (I)Ljava/lang/StringBuilder;
      // 28c: bipush 44
      // 28e: invokevirtual java/lang/StringBuilder.append (C)Ljava/lang/StringBuilder;
      // 291: iload 8
      // 293: invokevirtual java/lang/StringBuilder.append (I)Ljava/lang/StringBuilder;
      // 296: bipush 44
      // 298: invokevirtual java/lang/StringBuilder.append (C)Ljava/lang/StringBuilder;
      // 29b: iload 9
      // 29d: invokevirtual java/lang/StringBuilder.append (I)Ljava/lang/StringBuilder;
      // 2a0: bipush 41
      // 2a2: invokevirtual java/lang/StringBuilder.append (C)Ljava/lang/StringBuilder;
      // 2a5: invokevirtual java/lang/StringBuilder.toString ()Ljava/lang/String;
      // 2a8: invokestatic i.a (Ljava/lang/Throwable;Ljava/lang/String;)Lla;
      // 2ab: athrow
      // 2ac: return
   }

   private final void b(byte param1) {
      // $VF: Couldn't be decompiled
      // Please report this to the Vineflower issue tracker, at https://github.com/Vineflower/vineflower/issues with a copy of the class file (if you have the rights to distribute it!)
      // java.lang.RuntimeException: parsing failure!
      //   at org.jetbrains.java.decompiler.modules.decompiler.decompose.DomHelper.parseGraph(DomHelper.java:211)
      //   at org.jetbrains.java.decompiler.main.rels.MethodProcessor.codeToJava(MethodProcessor.java:166)
      //
      // Bytecode:
      // 000: getstatic ca.vb I
      // 003: bipush 1
      // 004: iadd
      // 005: putstatic ca.vb I
      // 008: iload 1
      // 009: bipush -103
      // 00b: if_icmplt 01d
      // 00e: aload 0
      // 00f: bipush 1
      // 010: bipush -115
      // 012: bipush 1
      // 013: bipush 1
      // 014: bipush 0
      // 015: invokevirtual ca.a (ZIZZZ)Lca;
      // 018: pop
      // 019: goto 01d
      // 01c: athrow
      // 01d: sipush 256
      // 020: aload 0
      // 021: getfield ca.Tb I
      // 024: if_icmpne 077
      // 027: aload 0
      // 028: getfield ca.G I
      // 02b: sipush 256
      // 02e: if_icmpne 077
      // 031: goto 035
      // 034: athrow
      // 035: aload 0
      // 036: getfield ca.Y I
      // 039: bipush -1
      // 03a: ixor
      // 03b: sipush -257
      // 03e: if_icmpne 077
      // 041: goto 045
      // 044: athrow
      // 045: aload 0
      // 046: getfield ca.f I
      // 049: sipush 256
      // 04c: if_icmpne 077
      // 04f: goto 053
      // 052: athrow
      // 053: sipush -257
      // 056: aload 0
      // 057: getfield ca.U I
      // 05a: bipush -1
      // 05b: ixor
      // 05c: if_icmpne 077
      // 05f: goto 063
      // 062: athrow
      // 063: sipush -257
      // 066: aload 0
      // 067: getfield ca.eb I
      // 06a: bipush -1
      // 06b: ixor
      // 06c: if_icmpne 077
      // 06f: goto 073
      // 072: athrow
      // 073: goto 07d
      // 076: athrow
      // 077: aload 0
      // 078: bipush 4
      // 079: putfield ca.jb I
      // 07c: return
      // 07d: sipush -257
      // 080: aload 0
      // 081: getfield ca.yb I
      // 084: bipush -1
      // 085: ixor
      // 086: if_icmpne 0a7
      // 089: aload 0
      // 08a: getfield ca.i I
      // 08d: sipush 256
      // 090: if_icmpne 0a7
      // 093: goto 097
      // 096: athrow
      // 097: sipush -257
      // 09a: aload 0
      // 09b: getfield ca.T I
      // 09e: bipush -1
      // 09f: ixor
      // 0a0: if_icmpeq 0ad
      // 0a3: goto 0a7
      // 0a6: athrow
      // 0a7: aload 0
      // 0a8: bipush 3
      // 0a9: putfield ca.jb I
      // 0ac: return
      // 0ad: bipush 0
      // 0ae: aload 0
      // 0af: getfield ca.F I
      // 0b2: if_icmpne 0d1
      // 0b5: bipush 0
      // 0b6: aload 0
      // 0b7: getfield ca.X I
      // 0ba: if_icmpne 0d1
      // 0bd: goto 0c1
      // 0c0: athrow
      // 0c1: bipush 0
      // 0c2: aload 0
      // 0c3: getfield ca.C I
      // 0c6: if_icmpne 0d1
      // 0c9: goto 0cd
      // 0cc: athrow
      // 0cd: goto 0d7
      // 0d0: athrow
      // 0d1: aload 0
      // 0d2: bipush 2
      // 0d3: putfield ca.jb I
      // 0d6: return
      // 0d7: aload 0
      // 0d8: getfield ca.r I
      // 0db: ifne 0fb
      // 0de: aload 0
      // 0df: getfield ca.xb I
      // 0e2: ifne 0fb
      // 0e5: goto 0e9
      // 0e8: athrow
      // 0e9: bipush -1
      // 0ea: aload 0
      // 0eb: getfield ca.Sb I
      // 0ee: bipush -1
      // 0ef: ixor
      // 0f0: if_icmpne 0fb
      // 0f3: goto 0f7
      // 0f6: athrow
      // 0f7: goto 101
      // 0fa: athrow
      // 0fb: aload 0
      // 0fc: bipush 1
      // 0fd: putfield ca.jb I
      // 100: return
      // 101: aload 0
      // 102: bipush 0
      // 103: putfield ca.jb I
      // 106: return
      // 107: astore 2
      // 108: aload 2
      // 109: new java/lang/StringBuilder
      // 10c: dup
      // 10d: invokespecial java/lang/StringBuilder.<init> ()V
      // 110: getstatic ca.kc [Ljava/lang/String;
      // 113: bipush 34
      // 115: aaload
      // 116: invokevirtual java/lang/StringBuilder.append (Ljava/lang/String;)Ljava/lang/StringBuilder;
      // 119: iload 1
      // 11a: invokevirtual java/lang/StringBuilder.append (I)Ljava/lang/StringBuilder;
      // 11d: bipush 41
      // 11f: invokevirtual java/lang/StringBuilder.append (C)Ljava/lang/StringBuilder;
      // 122: invokevirtual java/lang/StringBuilder.toString ()Ljava/lang/String;
      // 125: invokestatic i.a (Ljava/lang/Throwable;Ljava/lang/String;)Lla;
      // 128: athrow
   }

   private final void a(byte var1) {
      boolean var3 = client.vh;

      try {
         this.d(7972);
         D++;
         int var2 = 0;

         while (true) {
            if (~this.Db < ~var2) {
               try {
                  this.a[var2] = this.Gb[var2];
                  this.ob[var2] = this.ic[var2];
                  this.bc[var2] = this.jc[var2];
                  var2++;
                  if (var3) {
                     break;
                  }

                  if (!var3) {
                     continue;
                  }
               } catch (RuntimeException var5) {
                  throw var5;
               }
            }

            try {
               if (var1 != -28) {
                  this.d(4);
               }
            } catch (RuntimeException var4) {
               throw var4;
            }

            this.C = 0;
            this.F = 0;
            this.U = 256;
            this.f = 256;
            this.xb = 0;
            this.X = 0;
            this.eb = 256;
            this.Y = 256;
            this.yb = 256;
            this.jb = 0;
            this.r = 0;
            this.i = 256;
            this.Tb = 256;
            this.T = 256;
            this.Sb = 0;
            this.G = 256;
            break;
         }
      } catch (RuntimeException var6) {
         throw i.a(var6, kc[27] + var1 + ')');
      }
   }

   final void a(int param1, int param2, int param3, int param4, boolean param5, int param6, int param7) {
      // $VF: Couldn't be decompiled
      // Please report this to the Vineflower issue tracker, at https://github.com/Vineflower/vineflower/issues with a copy of the class file (if you have the rights to distribute it!)
      // java.lang.RuntimeException: parsing failure!
      //   at org.jetbrains.java.decompiler.modules.decompiler.decompose.DomHelper.parseGraph(DomHelper.java:211)
      //   at org.jetbrains.java.decompiler.main.rels.MethodProcessor.codeToJava(MethodProcessor.java:166)
      //
      // Bytecode:
      // 000: getstatic client.vh Z
      // 003: istore 10
      // 005: aload 0
      // 006: iload 6
      // 008: ineg
      // 009: bipush 64
      // 00b: iadd
      // 00c: bipush 16
      // 00e: imul
      // 00f: sipush 128
      // 012: iadd
      // 013: putfield ca.Mb I
      // 016: bipush 76
      // 018: bipush -8
      // 01a: iload 7
      // 01c: isub
      // 01d: bipush 49
      // 01f: idiv
      // 020: idiv
      // 021: istore 8
      // 023: aload 0
      // 024: sipush 256
      // 027: iload 2
      // 028: bipush 4
      // 029: imul
      // 02a: isub
      // 02b: putfield ca.Jb I
      // 02e: getstatic ca.R I
      // 031: bipush 1
      // 032: iadd
      // 033: putstatic ca.R I
      // 036: aload 0
      // 037: getfield ca.Nb Z
      // 03a: ifeq 03e
      // 03d: return
      // 03e: bipush 0
      // 03f: istore 9
      // 041: aload 0
      // 042: getfield ca.t I
      // 045: bipush -1
      // 046: ixor
      // 047: iload 9
      // 049: bipush -1
      // 04a: ixor
      // 04b: if_icmpge 084
      // 04e: iload 10
      // 050: ifne 0b1
      // 053: iload 5
      // 055: ifeq 070
      // 058: goto 05c
      // 05b: athrow
      // 05c: aload 0
      // 05d: getfield ca.Hb [I
      // 060: iload 9
      // 062: aload 0
      // 063: getfield ca.Vb I
      // 066: iastore
      // 067: iload 10
      // 069: ifeq 07c
      // 06c: goto 070
      // 06f: athrow
      // 070: aload 0
      // 071: getfield ca.Hb [I
      // 074: iload 9
      // 076: bipush 0
      // 077: iastore
      // 078: goto 07c
      // 07b: athrow
      // 07c: iinc 9 1
      // 07f: iload 10
      // 081: ifeq 041
      // 084: aload 0
      // 085: iload 4
      // 087: putfield ca.g I
      // 08a: aload 0
      // 08b: iload 1
      // 08c: putfield ca.Fb I
      // 08f: aload 0
      // 090: iload 3
      // 091: putfield ca.Bb I
      // 094: aload 0
      // 095: iload 3
      // 096: iload 3
      // 097: imul
      // 098: iload 4
      // 09a: iload 4
      // 09c: imul
      // 09d: iload 1
      // 09e: iload 1
      // 09f: imul
      // 0a0: ineg
      // 0a1: isub
      // 0a2: iadd
      // 0a3: i2d
      // 0a4: invokestatic java/lang/Math.sqrt (D)D
      // 0a7: d2i
      // 0a8: putfield ca.Ib I
      // 0ab: aload 0
      // 0ac: bipush -121
      // 0ae: invokespecial ca.e (I)V
      // 0b1: goto 112
      // 0b4: astore 8
      // 0b6: aload 8
      // 0b8: new java/lang/StringBuilder
      // 0bb: dup
      // 0bc: invokespecial java/lang/StringBuilder.<init> ()V
      // 0bf: getstatic ca.kc [Ljava/lang/String;
      // 0c2: bipush 28
      // 0c4: aaload
      // 0c5: invokevirtual java/lang/StringBuilder.append (Ljava/lang/String;)Ljava/lang/StringBuilder;
      // 0c8: iload 1
      // 0c9: invokevirtual java/lang/StringBuilder.append (I)Ljava/lang/StringBuilder;
      // 0cc: bipush 44
      // 0ce: invokevirtual java/lang/StringBuilder.append (C)Ljava/lang/StringBuilder;
      // 0d1: iload 2
      // 0d2: invokevirtual java/lang/StringBuilder.append (I)Ljava/lang/StringBuilder;
      // 0d5: bipush 44
      // 0d7: invokevirtual java/lang/StringBuilder.append (C)Ljava/lang/StringBuilder;
      // 0da: iload 3
      // 0db: invokevirtual java/lang/StringBuilder.append (I)Ljava/lang/StringBuilder;
      // 0de: bipush 44
      // 0e0: invokevirtual java/lang/StringBuilder.append (C)Ljava/lang/StringBuilder;
      // 0e3: iload 4
      // 0e5: invokevirtual java/lang/StringBuilder.append (I)Ljava/lang/StringBuilder;
      // 0e8: bipush 44
      // 0ea: invokevirtual java/lang/StringBuilder.append (C)Ljava/lang/StringBuilder;
      // 0ed: iload 5
      // 0ef: invokevirtual java/lang/StringBuilder.append (Z)Ljava/lang/StringBuilder;
      // 0f2: bipush 44
      // 0f4: invokevirtual java/lang/StringBuilder.append (C)Ljava/lang/StringBuilder;
      // 0f7: iload 6
      // 0f9: invokevirtual java/lang/StringBuilder.append (I)Ljava/lang/StringBuilder;
      // 0fc: bipush 44
      // 0fe: invokevirtual java/lang/StringBuilder.append (C)Ljava/lang/StringBuilder;
      // 101: iload 7
      // 103: invokevirtual java/lang/StringBuilder.append (I)Ljava/lang/StringBuilder;
      // 106: bipush 41
      // 108: invokevirtual java/lang/StringBuilder.append (C)Ljava/lang/StringBuilder;
      // 10b: invokevirtual java/lang/StringBuilder.toString ()Ljava/lang/String;
      // 10e: invokestatic i.a (Ljava/lang/Throwable;Ljava/lang/String;)Lla;
      // 111: athrow
      // 112: return
   }

   private final void b(int var1, int var2, int var3, int var4) {
      boolean var6 = client.vh;

      try {
         try {
            O++;
            if (var2 != -27483) {
               this.e(-7, -82, -31, -24);
            }
         } catch (RuntimeException var8) {
            throw var8;
         }

         int var5 = 0;

         while (~var5 > ~this.Db) {
            try {
               this.Gb[var5] = this.Gb[var5] * var1 >> -1363775576;
               this.ic[var5] = this.ic[var5] * var4 >> -895455096;
               this.jc[var5] = var3 * this.jc[var5] >> -242758104;
               var5++;
               if (var6 || var6) {
                  break;
               }
            } catch (RuntimeException var7) {
               throw var7;
            }
         }
      } catch (RuntimeException var9) {
         throw i.a(var9, kc[22] + var1 + ',' + var2 + ',' + var3 + ',' + var4 + ')');
      }
   }

   final int e(int param1, int param2, int param3, int param4) {
      // $VF: Couldn't be decompiled
      // Please report this to the Vineflower issue tracker, at https://github.com/Vineflower/vineflower/issues with a copy of the class file (if you have the rights to distribute it!)
      // java.lang.RuntimeException: parsing failure!
      //   at org.jetbrains.java.decompiler.modules.decompiler.decompose.DomHelper.parseGraph(DomHelper.java:211)
      //   at org.jetbrains.java.decompiler.main.rels.MethodProcessor.codeToJava(MethodProcessor.java:166)
      //
      // Bytecode:
      // 00: getstatic client.vh Z
      // 03: istore 7
      // 05: getstatic ca.ib I
      // 08: bipush 1
      // 09: iadd
      // 0a: putstatic ca.ib I
      // 0d: bipush 0
      // 0e: istore 5
      // 10: iload 5
      // 12: bipush -1
      // 13: ixor
      // 14: aload 0
      // 15: getfield ca.Db I
      // 18: bipush -1
      // 19: ixor
      // 1a: if_icmple 62
      // 1d: aload 0
      // 1e: getfield ca.a [I
      // 21: iload 5
      // 23: iaload
      // 24: bipush -1
      // 25: ixor
      // 26: iload 1
      // 27: bipush -1
      // 28: ixor
      // 29: iload 7
      // 2b: ifne 6c
      // 2e: if_icmpne 5a
      // 31: goto 35
      // 34: athrow
      // 35: iload 3
      // 36: aload 0
      // 37: getfield ca.ob [I
      // 3a: iload 5
      // 3c: iaload
      // 3d: if_icmpne 5a
      // 40: goto 44
      // 43: athrow
      // 44: iload 2
      // 45: aload 0
      // 46: getfield ca.bc [I
      // 49: iload 5
      // 4b: iaload
      // 4c: if_icmpeq 57
      // 4f: goto 53
      // 52: athrow
      // 53: goto 5a
      // 56: athrow
      // 57: iload 5
      // 59: ireturn
      // 5a: iinc 5 1
      // 5d: iload 7
      // 5f: ifeq 10
      // 62: bipush 100
      // 64: bipush -46
      // 66: iload 4
      // 68: isub
      // 69: bipush 58
      // 6b: idiv
      // 6c: idiv
      // 6d: istore 6
      // 6f: aload 0
      // 70: getfield ca.Db I
      // 73: aload 0
      // 74: getfield ca.K I
      // 77: if_icmpge 7e
      // 7a: goto 80
      // 7d: athrow
      // 7e: bipush -1
      // 7f: ireturn
      // 80: aload 0
      // 81: getfield ca.a [I
      // 84: aload 0
      // 85: getfield ca.Db I
      // 88: iload 1
      // 89: iastore
      // 8a: aload 0
      // 8b: getfield ca.ob [I
      // 8e: aload 0
      // 8f: getfield ca.Db I
      // 92: iload 3
      // 93: iastore
      // 94: aload 0
      // 95: getfield ca.bc [I
      // 98: aload 0
      // 99: getfield ca.Db I
      // 9c: iload 2
      // 9d: iastore
      // 9e: aload 0
      // 9f: dup
      // a0: getfield ca.Db I
      // a3: dup_x1
      // a4: bipush 1
      // a5: iadd
      // a6: putfield ca.Db I
      // a9: ireturn
      // aa: astore 5
      // ac: aload 5
      // ae: new java/lang/StringBuilder
      // b1: dup
      // b2: invokespecial java/lang/StringBuilder.<init> ()V
      // b5: getstatic ca.kc [Ljava/lang/String;
      // b8: bipush 13
      // ba: aaload
      // bb: invokevirtual java/lang/StringBuilder.append (Ljava/lang/String;)Ljava/lang/StringBuilder;
      // be: iload 1
      // bf: invokevirtual java/lang/StringBuilder.append (I)Ljava/lang/StringBuilder;
      // c2: bipush 44
      // c4: invokevirtual java/lang/StringBuilder.append (C)Ljava/lang/StringBuilder;
      // c7: iload 2
      // c8: invokevirtual java/lang/StringBuilder.append (I)Ljava/lang/StringBuilder;
      // cb: bipush 44
      // cd: invokevirtual java/lang/StringBuilder.append (C)Ljava/lang/StringBuilder;
      // d0: iload 3
      // d1: invokevirtual java/lang/StringBuilder.append (I)Ljava/lang/StringBuilder;
      // d4: bipush 44
      // d6: invokevirtual java/lang/StringBuilder.append (C)Ljava/lang/StringBuilder;
      // d9: iload 4
      // db: invokevirtual java/lang/StringBuilder.append (I)Ljava/lang/StringBuilder;
      // de: bipush 41
      // e0: invokevirtual java/lang/StringBuilder.append (C)Ljava/lang/StringBuilder;
      // e3: invokevirtual java/lang/StringBuilder.toString ()Ljava/lang/String;
      // e6: invokestatic i.a (Ljava/lang/Throwable;Ljava/lang/String;)Lla;
      // e9: athrow
   }

   private final void a(int[] param1, ca param2, int param3, int param4, int param5) {
      // $VF: Couldn't be decompiled
      // Please report this to the Vineflower issue tracker, at https://github.com/Vineflower/vineflower/issues with a copy of the class file (if you have the rights to distribute it!)
      // java.lang.RuntimeException: parsing failure!
      //   at org.jetbrains.java.decompiler.modules.decompiler.decompose.DomHelper.parseGraph(DomHelper.java:211)
      //   at org.jetbrains.java.decompiler.main.rels.MethodProcessor.codeToJava(MethodProcessor.java:166)
      //
      // Bytecode:
      // 000: getstatic client.vh Z
      // 003: istore 9
      // 005: getstatic ca.mb I
      // 008: bipush 1
      // 009: iadd
      // 00a: putstatic ca.mb I
      // 00d: iload 3
      // 00e: newarray 10
      // 010: astore 6
      // 012: bipush 0
      // 013: istore 7
      // 015: iload 3
      // 016: bipush -1
      // 017: ixor
      // 018: iload 7
      // 01a: bipush -1
      // 01b: ixor
      // 01c: if_icmpge 079
      // 01f: aload 6
      // 021: iload 7
      // 023: aload 2
      // 024: aload 0
      // 025: getfield ca.a [I
      // 028: aload 1
      // 029: iload 7
      // 02b: iaload
      // 02c: iaload
      // 02d: aload 0
      // 02e: getfield ca.bc [I
      // 031: aload 1
      // 032: iload 7
      // 034: iaload
      // 035: iaload
      // 036: aload 0
      // 037: getfield ca.ob [I
      // 03a: aload 1
      // 03b: iload 7
      // 03d: iaload
      // 03e: iaload
      // 03f: bipush 107
      // 041: invokevirtual ca.e (IIII)I
      // 044: dup_x2
      // 045: iastore
      // 046: istore 8
      // 048: aload 2
      // 049: getfield ca.gb [I
      // 04c: iload 8
      // 04e: aload 0
      // 04f: getfield ca.gb [I
      // 052: aload 1
      // 053: iload 7
      // 055: iaload
      // 056: iaload
      // 057: iastore
      // 058: aload 2
      // 059: getfield ca.Ab [B
      // 05c: iload 8
      // 05e: aload 0
      // 05f: getfield ca.Ab [B
      // 062: aload 1
      // 063: iload 7
      // 065: iaload
      // 066: baload
      // 067: bastore
      // 068: iinc 7 1
      // 06b: iload 9
      // 06d: ifne 0a3
      // 070: iload 9
      // 072: ifeq 015
      // 075: goto 079
      // 078: athrow
      // 079: iload 5
      // 07b: sipush 5916
      // 07e: if_icmpeq 08b
      // 081: aload 0
      // 082: bipush 77
      // 084: putfield ca.yb I
      // 087: goto 08b
      // 08a: athrow
      // 08b: aload 2
      // 08c: iload 3
      // 08d: aload 6
      // 08f: aload 0
      // 090: getfield ca.V [I
      // 093: iload 4
      // 095: iaload
      // 096: aload 0
      // 097: getfield ca.qb [I
      // 09a: iload 4
      // 09c: iaload
      // 09d: bipush 0
      // 09e: invokevirtual ca.a (I[IIIZ)I
      // 0a1: istore 7
      // 0a3: aload 2
      // 0a4: getfield ca.db Z
      // 0a7: ifne 0c7
      // 0aa: aload 0
      // 0ab: getfield ca.db Z
      // 0ae: ifeq 0b9
      // 0b1: goto 0b5
      // 0b4: athrow
      // 0b5: goto 0c7
      // 0b8: athrow
      // 0b9: aload 2
      // 0ba: getfield ca.E [I
      // 0bd: iload 7
      // 0bf: aload 0
      // 0c0: getfield ca.E [I
      // 0c3: iload 4
      // 0c5: iaload
      // 0c6: iastore
      // 0c7: aload 2
      // 0c8: getfield ca.Hb [I
      // 0cb: iload 7
      // 0cd: aload 0
      // 0ce: getfield ca.Hb [I
      // 0d1: iload 4
      // 0d3: iaload
      // 0d4: iastore
      // 0d5: aload 2
      // 0d6: getfield ca.M [I
      // 0d9: iload 7
      // 0db: aload 0
      // 0dc: getfield ca.M [I
      // 0df: iload 4
      // 0e1: iaload
      // 0e2: iastore
      // 0e3: aload 2
      // 0e4: getfield ca.k [I
      // 0e7: iload 7
      // 0e9: aload 0
      // 0ea: getfield ca.k [I
      // 0ed: iload 4
      // 0ef: iaload
      // 0f0: iastore
      // 0f1: goto 160
      // 0f4: astore 6
      // 0f6: aload 6
      // 0f8: new java/lang/StringBuilder
      // 0fb: dup
      // 0fc: invokespecial java/lang/StringBuilder.<init> ()V
      // 0ff: getstatic ca.kc [Ljava/lang/String;
      // 102: bipush 33
      // 104: aaload
      // 105: invokevirtual java/lang/StringBuilder.append (Ljava/lang/String;)Ljava/lang/StringBuilder;
      // 108: aload 1
      // 109: ifnull 115
      // 10c: getstatic ca.kc [Ljava/lang/String;
      // 10f: bipush 1
      // 110: aaload
      // 111: goto 11a
      // 114: athrow
      // 115: getstatic ca.kc [Ljava/lang/String;
      // 118: bipush 3
      // 119: aaload
      // 11a: invokevirtual java/lang/StringBuilder.append (Ljava/lang/String;)Ljava/lang/StringBuilder;
      // 11d: bipush 44
      // 11f: invokevirtual java/lang/StringBuilder.append (C)Ljava/lang/StringBuilder;
      // 122: aload 2
      // 123: ifnull 12f
      // 126: getstatic ca.kc [Ljava/lang/String;
      // 129: bipush 1
      // 12a: aaload
      // 12b: goto 134
      // 12e: athrow
      // 12f: getstatic ca.kc [Ljava/lang/String;
      // 132: bipush 3
      // 133: aaload
      // 134: invokevirtual java/lang/StringBuilder.append (Ljava/lang/String;)Ljava/lang/StringBuilder;
      // 137: bipush 44
      // 139: invokevirtual java/lang/StringBuilder.append (C)Ljava/lang/StringBuilder;
      // 13c: iload 3
      // 13d: invokevirtual java/lang/StringBuilder.append (I)Ljava/lang/StringBuilder;
      // 140: bipush 44
      // 142: invokevirtual java/lang/StringBuilder.append (C)Ljava/lang/StringBuilder;
      // 145: iload 4
      // 147: invokevirtual java/lang/StringBuilder.append (I)Ljava/lang/StringBuilder;
      // 14a: bipush 44
      // 14c: invokevirtual java/lang/StringBuilder.append (C)Ljava/lang/StringBuilder;
      // 14f: iload 5
      // 151: invokevirtual java/lang/StringBuilder.append (I)Ljava/lang/StringBuilder;
      // 154: bipush 41
      // 156: invokevirtual java/lang/StringBuilder.append (C)Ljava/lang/StringBuilder;
      // 159: invokevirtual java/lang/StringBuilder.toString ()Ljava/lang/String;
      // 15c: invokestatic i.a (Ljava/lang/Throwable;Ljava/lang/String;)Lla;
      // 15f: athrow
      // 160: return
   }

   final void c(int var1) {
      try {
         try {
            this.t = 0;
            if (var1 != 1) {
               this.Kb = true;
            }
         } catch (RuntimeException var3) {
            throw var3;
         }

         this.Db = 0;
         W++;
      } catch (RuntimeException var4) {
         throw i.a(var4, kc[0] + var1 + ')');
      }
   }

   private final void a(int param1, int param2, int param3, int param4) {
      // $VF: Couldn't be decompiled
      // Please report this to the Vineflower issue tracker, at https://github.com/Vineflower/vineflower/issues with a copy of the class file (if you have the rights to distribute it!)
      // java.lang.RuntimeException: parsing failure!
      //   at org.jetbrains.java.decompiler.modules.decompiler.decompose.DomHelper.parseGraph(DomHelper.java:211)
      //   at org.jetbrains.java.decompiler.main.rels.MethodProcessor.codeToJava(MethodProcessor.java:166)
      //
      // Bytecode:
      // 000: getstatic client.vh Z
      // 003: istore 9
      // 005: getstatic ca.ab I
      // 008: bipush 1
      // 009: iadd
      // 00a: putstatic ca.ab I
      // 00d: iload 1
      // 00e: bipush -14
      // 010: if_icmplt 01f
      // 013: aload 0
      // 014: aconst_null
      // 015: checkcast [I
      // 018: putfield ca.Cb [I
      // 01b: goto 01f
      // 01e: athrow
      // 01f: bipush 0
      // 020: istore 8
      // 022: aload 0
      // 023: getfield ca.Db I
      // 026: bipush -1
      // 027: ixor
      // 028: iload 8
      // 02a: bipush -1
      // 02b: ixor
      // 02c: if_icmpge 15d
      // 02f: iload 9
      // 031: ifne 1a0
      // 034: iload 3
      // 035: ifne 040
      // 038: goto 03c
      // 03b: athrow
      // 03c: goto 095
      // 03f: athrow
      // 040: getstatic pa.a [I
      // 043: iload 3
      // 044: sipush 256
      // 047: iadd
      // 048: iaload
      // 049: istore 6
      // 04b: getstatic pa.a [I
      // 04e: iload 3
      // 04f: iaload
      // 050: istore 5
      // 052: aload 0
      // 053: getfield ca.Gb [I
      // 056: iload 8
      // 058: iaload
      // 059: iload 6
      // 05b: imul
      // 05c: aload 0
      // 05d: getfield ca.ic [I
      // 060: iload 8
      // 062: iaload
      // 063: iload 5
      // 065: imul
      // 066: iadd
      // 067: ldc -1049305169
      // 069: ishr
      // 06a: istore 7
      // 06c: aload 0
      // 06d: getfield ca.ic [I
      // 070: iload 8
      // 072: iload 5
      // 074: aload 0
      // 075: getfield ca.Gb [I
      // 078: iload 8
      // 07a: iaload
      // 07b: imul
      // 07c: ineg
      // 07d: aload 0
      // 07e: getfield ca.ic [I
      // 081: iload 8
      // 083: iaload
      // 084: iload 6
      // 086: imul
      // 087: iadd
      // 088: ldc -1441854257
      // 08a: ishr
      // 08b: iastore
      // 08c: aload 0
      // 08d: getfield ca.Gb [I
      // 090: iload 8
      // 092: iload 7
      // 094: iastore
      // 095: bipush -1
      // 096: iload 2
      // 097: bipush -1
      // 098: ixor
      // 099: if_icmpeq 0f2
      // 09c: getstatic pa.a [I
      // 09f: iload 2
      // 0a0: iaload
      // 0a1: istore 5
      // 0a3: getstatic pa.a [I
      // 0a6: sipush 256
      // 0a9: iload 2
      // 0aa: iadd
      // 0ab: iaload
      // 0ac: istore 6
      // 0ae: iload 5
      // 0b0: aload 0
      // 0b1: getfield ca.jc [I
      // 0b4: iload 8
      // 0b6: iaload
      // 0b7: imul
      // 0b8: ineg
      // 0b9: iload 6
      // 0bb: aload 0
      // 0bc: getfield ca.ic [I
      // 0bf: iload 8
      // 0c1: iaload
      // 0c2: imul
      // 0c3: iadd
      // 0c4: ldc 1869232655
      // 0c6: ishr
      // 0c7: istore 7
      // 0c9: aload 0
      // 0ca: getfield ca.jc [I
      // 0cd: iload 8
      // 0cf: iload 5
      // 0d1: aload 0
      // 0d2: getfield ca.ic [I
      // 0d5: iload 8
      // 0d7: iaload
      // 0d8: imul
      // 0d9: iload 6
      // 0db: aload 0
      // 0dc: getfield ca.jc [I
      // 0df: iload 8
      // 0e1: iaload
      // 0e2: imul
      // 0e3: ineg
      // 0e4: isub
      // 0e5: ldc -1067157009
      // 0e7: ishr
      // 0e8: iastore
      // 0e9: aload 0
      // 0ea: getfield ca.ic [I
      // 0ed: iload 8
      // 0ef: iload 7
      // 0f1: iastore
      // 0f2: bipush -1
      // 0f3: iload 4
      // 0f5: bipush -1
      // 0f6: ixor
      // 0f7: if_icmpne 0fe
      // 0fa: goto 155
      // 0fd: athrow
      // 0fe: getstatic pa.a [I
      // 101: iload 4
      // 103: iaload
      // 104: istore 5
      // 106: getstatic pa.a [I
      // 109: sipush 256
      // 10c: iload 4
      // 10e: iadd
      // 10f: iaload
      // 110: istore 6
      // 112: iload 5
      // 114: aload 0
      // 115: getfield ca.jc [I
      // 118: iload 8
      // 11a: iaload
      // 11b: imul
      // 11c: aload 0
      // 11d: getfield ca.Gb [I
      // 120: iload 8
      // 122: iaload
      // 123: iload 6
      // 125: imul
      // 126: iadd
      // 127: ldc -1889761873
      // 129: ishr
      // 12a: istore 7
      // 12c: aload 0
      // 12d: getfield ca.jc [I
      // 130: iload 8
      // 132: aload 0
      // 133: getfield ca.Gb [I
      // 136: iload 8
      // 138: iaload
      // 139: iload 5
      // 13b: imul
      // 13c: ineg
      // 13d: aload 0
      // 13e: getfield ca.jc [I
      // 141: iload 8
      // 143: iaload
      // 144: iload 6
      // 146: imul
      // 147: iadd
      // 148: ldc 89169167
      // 14a: ishr
      // 14b: iastore
      // 14c: aload 0
      // 14d: getfield ca.Gb [I
      // 150: iload 8
      // 152: iload 7
      // 154: iastore
      // 155: iinc 8 1
      // 158: iload 9
      // 15a: ifeq 022
      // 15d: goto 1a0
      // 160: astore 5
      // 162: aload 5
      // 164: new java/lang/StringBuilder
      // 167: dup
      // 168: invokespecial java/lang/StringBuilder.<init> ()V
      // 16b: getstatic ca.kc [Ljava/lang/String;
      // 16e: bipush 17
      // 170: aaload
      // 171: invokevirtual java/lang/StringBuilder.append (Ljava/lang/String;)Ljava/lang/StringBuilder;
      // 174: iload 1
      // 175: invokevirtual java/lang/StringBuilder.append (I)Ljava/lang/StringBuilder;
      // 178: bipush 44
      // 17a: invokevirtual java/lang/StringBuilder.append (C)Ljava/lang/StringBuilder;
      // 17d: iload 2
      // 17e: invokevirtual java/lang/StringBuilder.append (I)Ljava/lang/StringBuilder;
      // 181: bipush 44
      // 183: invokevirtual java/lang/StringBuilder.append (C)Ljava/lang/StringBuilder;
      // 186: iload 3
      // 187: invokevirtual java/lang/StringBuilder.append (I)Ljava/lang/StringBuilder;
      // 18a: bipush 44
      // 18c: invokevirtual java/lang/StringBuilder.append (C)Ljava/lang/StringBuilder;
      // 18f: iload 4
      // 191: invokevirtual java/lang/StringBuilder.append (I)Ljava/lang/StringBuilder;
      // 194: bipush 41
      // 196: invokevirtual java/lang/StringBuilder.append (C)Ljava/lang/StringBuilder;
      // 199: invokevirtual java/lang/StringBuilder.toString ()Ljava/lang/String;
      // 19c: invokestatic i.a (Ljava/lang/Throwable;Ljava/lang/String;)Lla;
      // 19f: athrow
      // 1a0: return
   }

   private final void e(int param1) {
      // $VF: Couldn't be decompiled
      // Please report this to the Vineflower issue tracker, at https://github.com/Vineflower/vineflower/issues with a copy of the class file (if you have the rights to distribute it!)
      // java.lang.RuntimeException: parsing failure!
      //   at org.jetbrains.java.decompiler.modules.decompiler.decompose.DomHelper.parseGraph(DomHelper.java:211)
      //   at org.jetbrains.java.decompiler.main.rels.MethodProcessor.codeToJava(MethodProcessor.java:166)
      //
      // Bytecode:
      // 000: getstatic client.vh Z
      // 003: istore 11
      // 005: getstatic ca.l I
      // 008: bipush 1
      // 009: iadd
      // 00a: putstatic ca.l I
      // 00d: aload 0
      // 00e: getfield ca.Nb Z
      // 011: ifeq 015
      // 014: return
      // 015: aload 0
      // 016: getfield ca.Mb I
      // 019: aload 0
      // 01a: getfield ca.Ib I
      // 01d: imul
      // 01e: ldc 434666280
      // 020: ishr
      // 021: istore 2
      // 022: bipush 0
      // 023: istore 3
      // 024: aload 0
      // 025: getfield ca.t I
      // 028: iload 3
      // 029: if_icmple 07a
      // 02c: aload 0
      // 02d: getfield ca.Hb [I
      // 030: iload 3
      // 031: iaload
      // 032: iload 11
      // 034: ifne 07e
      // 037: aload 0
      // 038: getfield ca.Vb I
      // 03b: if_icmpeq 072
      // 03e: goto 042
      // 041: athrow
      // 042: aload 0
      // 043: getfield ca.Hb [I
      // 046: iload 3
      // 047: aload 0
      // 048: getfield ca.Cb [I
      // 04b: iload 3
      // 04c: iaload
      // 04d: aload 0
      // 04e: getfield ca.Bb I
      // 051: imul
      // 052: aload 0
      // 053: getfield ca.fb [I
      // 056: iload 3
      // 057: iaload
      // 058: aload 0
      // 059: getfield ca.g I
      // 05c: imul
      // 05d: aload 0
      // 05e: getfield ca.Fb I
      // 061: aload 0
      // 062: getfield ca.Pb [I
      // 065: iload 3
      // 066: iaload
      // 067: imul
      // 068: ineg
      // 069: isub
      // 06a: iadd
      // 06b: iload 2
      // 06c: idiv
      // 06d: iastore
      // 06e: goto 072
      // 071: athrow
      // 072: iinc 3 1
      // 075: iload 11
      // 077: ifeq 024
      // 07a: aload 0
      // 07b: getfield ca.Db I
      // 07e: newarray 10
      // 080: astore 3
      // 081: aload 0
      // 082: getfield ca.Db I
      // 085: newarray 10
      // 087: astore 4
      // 089: aload 0
      // 08a: getfield ca.Db I
      // 08d: newarray 10
      // 08f: astore 5
      // 091: aload 0
      // 092: getfield ca.Db I
      // 095: newarray 10
      // 097: astore 6
      // 099: bipush 0
      // 09a: istore 7
      // 09c: aload 0
      // 09d: getfield ca.Db I
      // 0a0: iload 7
      // 0a2: if_icmple 0cd
      // 0a5: aload 3
      // 0a6: iload 7
      // 0a8: bipush 0
      // 0a9: iastore
      // 0aa: aload 4
      // 0ac: iload 7
      // 0ae: bipush 0
      // 0af: iastore
      // 0b0: aload 5
      // 0b2: iload 7
      // 0b4: bipush 0
      // 0b5: iastore
      // 0b6: aload 6
      // 0b8: iload 7
      // 0ba: bipush 0
      // 0bb: iastore
      // 0bc: iinc 7 1
      // 0bf: iload 11
      // 0c1: ifne 0d9
      // 0c4: iload 11
      // 0c6: ifeq 09c
      // 0c9: goto 0cd
      // 0cc: athrow
      // 0cd: bipush -16
      // 0cf: iload 1
      // 0d0: bipush -55
      // 0d2: isub
      // 0d3: bipush 32
      // 0d5: idiv
      // 0d6: idiv
      // 0d7: istore 7
      // 0d9: bipush 0
      // 0da: istore 8
      // 0dc: iload 8
      // 0de: aload 0
      // 0df: getfield ca.t I
      // 0e2: if_icmpge 169
      // 0e5: aload 0
      // 0e6: getfield ca.Hb [I
      // 0e9: iload 8
      // 0eb: iaload
      // 0ec: bipush -1
      // 0ed: ixor
      // 0ee: aload 0
      // 0ef: getfield ca.Vb I
      // 0f2: bipush -1
      // 0f3: ixor
      // 0f4: iload 11
      // 0f6: ifne 172
      // 0f9: if_icmpne 161
      // 0fc: goto 100
      // 0ff: athrow
      // 100: bipush 0
      // 101: istore 9
      // 103: aload 0
      // 104: getfield ca.lb [I
      // 107: iload 8
      // 109: iaload
      // 10a: iload 9
      // 10c: if_icmple 161
      // 10f: aload 0
      // 110: getfield ca.o [[I
      // 113: iload 8
      // 115: aaload
      // 116: iload 9
      // 118: iaload
      // 119: istore 10
      // 11b: aload 3
      // 11c: iload 10
      // 11e: dup2
      // 11f: iaload
      // 120: aload 0
      // 121: getfield ca.fb [I
      // 124: iload 8
      // 126: iaload
      // 127: iadd
      // 128: iastore
      // 129: aload 4
      // 12b: iload 10
      // 12d: dup2
      // 12e: iaload
      // 12f: aload 0
      // 130: getfield ca.Cb [I
      // 133: iload 8
      // 135: iaload
      // 136: iadd
      // 137: iastore
      // 138: aload 5
      // 13a: iload 10
      // 13c: dup2
      // 13d: iaload
      // 13e: aload 0
      // 13f: getfield ca.Pb [I
      // 142: iload 8
      // 144: iaload
      // 145: iadd
      // 146: iastore
      // 147: aload 6
      // 149: iload 10
      // 14b: dup2
      // 14c: iaload
      // 14d: bipush 1
      // 14e: iadd
      // 14f: iastore
      // 150: iinc 9 1
      // 153: iload 11
      // 155: ifne 164
      // 158: iload 11
      // 15a: ifeq 103
      // 15d: goto 161
      // 160: athrow
      // 161: iinc 8 1
      // 164: iload 11
      // 166: ifeq 0dc
      // 169: bipush 0
      // 16a: istore 8
      // 16c: aload 0
      // 16d: getfield ca.Db I
      // 170: iload 8
      // 172: if_icmple 1c5
      // 175: iload 11
      // 177: ifne 1ea
      // 17a: goto 17e
      // 17d: athrow
      // 17e: bipush 0
      // 17f: aload 6
      // 181: iload 8
      // 183: iaload
      // 184: if_icmplt 18f
      // 187: goto 18b
      // 18a: athrow
      // 18b: goto 1bd
      // 18e: athrow
      // 18f: aload 0
      // 190: getfield ca.gb [I
      // 193: iload 8
      // 195: aload 5
      // 197: iload 8
      // 199: iaload
      // 19a: aload 0
      // 19b: getfield ca.Fb I
      // 19e: imul
      // 19f: aload 3
      // 1a0: iload 8
      // 1a2: iaload
      // 1a3: aload 0
      // 1a4: getfield ca.g I
      // 1a7: imul
      // 1a8: aload 4
      // 1aa: iload 8
      // 1ac: iaload
      // 1ad: aload 0
      // 1ae: getfield ca.Bb I
      // 1b1: imul
      // 1b2: iadd
      // 1b3: iadd
      // 1b4: iload 2
      // 1b5: aload 6
      // 1b7: iload 8
      // 1b9: iaload
      // 1ba: imul
      // 1bb: idiv
      // 1bc: iastore
      // 1bd: iinc 8 1
      // 1c0: iload 11
      // 1c2: ifeq 16c
      // 1c5: goto 1ea
      // 1c8: astore 2
      // 1c9: aload 2
      // 1ca: new java/lang/StringBuilder
      // 1cd: dup
      // 1ce: invokespecial java/lang/StringBuilder.<init> ()V
      // 1d1: getstatic ca.kc [Ljava/lang/String;
      // 1d4: bipush 9
      // 1d6: aaload
      // 1d7: invokevirtual java/lang/StringBuilder.append (Ljava/lang/String;)Ljava/lang/StringBuilder;
      // 1da: iload 1
      // 1db: invokevirtual java/lang/StringBuilder.append (I)Ljava/lang/StringBuilder;
      // 1de: bipush 41
      // 1e0: invokevirtual java/lang/StringBuilder.append (C)Ljava/lang/StringBuilder;
      // 1e3: invokevirtual java/lang/StringBuilder.toString ()Ljava/lang/String;
      // 1e6: invokestatic i.a (Ljava/lang/Throwable;Ljava/lang/String;)Lla;
      // 1e9: athrow
      // 1ea: return
   }

   final ca a(boolean var1, int var2, boolean var3, boolean var4, boolean var5) {
      try {
         I++;
         ca[] var6 = new ca[]{this};
         int var7 = 122 / ((-56 - var2) / 59);
         ca var8 = new ca(var6, 1, var4, var5, var3, var1);
         var8.hc = this.hc;
         return var8;
      } catch (RuntimeException var9) {
         throw i.a(var9, kc[11] + var1 + ',' + var2 + ',' + var3 + ',' + var4 + ',' + var5 + ')');
      }
   }

   static final int a(byte var0, String var1) {
      boolean var3 = client.vh;

      try {
         try {
            Xb++;
            if (var1.equalsIgnoreCase(kc[5])) {
               return 0;
            }
         } catch (RuntimeException var7) {
            throw var7;
         }

         try {
            if (var0 != 91) {
               B = (int[])null;
            }
         } catch (RuntimeException var6) {
            throw var6;
         }

         int var9 = 0;

         int var10;
         while (true) {
            if (var9 < ia.b) {
               try {
                  var10 = ub.c[var9].equalsIgnoreCase(var1);
                  if (var3) {
                     break;
                  }

                  if (var10 != 0) {
                     return var9;
                  }
               } catch (RuntimeException var5) {
                  throw var5;
               }

               var9++;
               if (!var3) {
                  continue;
               }
            }

            ub.c[ia.b++] = var1;
            var10 = ia.b + -1;
            break;
         }

         return var10;
      } catch (RuntimeException var8) {
         RuntimeException var2 = var8;

         RuntimeException var10000;
         StringBuilder var10001;
         try {
            var10000 = var2;
            var10001 = new StringBuilder().append(kc[4]).append((int)var0).append(',');
            if (var1 != null) {
               throw i.a(var2, var10001.append(kc[1]).append((char)41).toString());
            }
         } catch (RuntimeException var4) {
            throw var4;
         }

         throw i.a(var10000, var10001.append(kc[3]).append((char)41).toString());
      }
   }

   final void a(ca var1, int var2) {
      try {
         try {
            if (var2 != 6029) {
               this.jb = -128;
            }
         } catch (RuntimeException var5) {
            throw var5;
         }

         this.xb = var1.xb;
         y++;
         this.C = var1.C;
         this.Sb = var1.Sb;
         this.r = var1.r;
         this.X = var1.X;
         this.F = var1.F;
         this.b((byte)-113);
         this.Yb = 1;
      } catch (RuntimeException var6) {
         RuntimeException var3 = var6;

         RuntimeException var10000;
         StringBuilder var10001;
         try {
            var10000 = var3;
            var10001 = new StringBuilder().append(kc[26]);
            if (var1 != null) {
               throw i.a(var3, var10001.append(kc[1]).append(',').append(var2).append(')').toString());
            }
         } catch (RuntimeException var4) {
            throw var4;
         }

         throw i.a(var10000, var10001.append(kc[3]).append(',').append(var2).append(')').toString());
      }
   }

   final ca b(int var1) {
      try {
         wb++;
         ca[] var2 = new ca[1];

         try {
            if (var1 != -2) {
               this.b(117, -93, -34, -34);
            }
         } catch (RuntimeException var4) {
            throw var4;
         }

         var2[0] = this;
         ca var3 = new ca(var2, 1);
         var3.cb = this.cb;
         var3.hc = this.hc;
         return var3;
      } catch (RuntimeException var5) {
         throw i.a(var5, kc[10] + var1 + ')');
      }
   }

   private final void c(byte var1) {
      try {
         try {
            if (var1 < 49) {
               this.a(40, 102, 104, 108, -20, -89);
            }
         } catch (RuntimeException var3) {
            throw var3;
         }

         this.bb = new int[this.Db];
         this.Ob = new int[this.Db];
         this.cc = new int[this.Db];
         this.H = new int[this.Db];
         this.pb = new int[this.Db];
         N++;
      } catch (RuntimeException var4) {
         throw i.a(var4, kc[30] + var1 + ')');
      }
   }

   final void a(int var1, int var2, byte var3) {
      try {
         if (var3 == -61) {
            Wb++;
            this.Ab[var1] = (byte)var2;
         }
      } catch (RuntimeException var5) {
         throw i.a(var5, kc[8] + var1 + ',' + var2 + ',' + var3 + ')');
      }
   }

   private final void d(int param1) {
      // $VF: Couldn't be decompiled
      // Please report this to the Vineflower issue tracker, at https://github.com/Vineflower/vineflower/issues with a copy of the class file (if you have the rights to distribute it!)
      // java.lang.RuntimeException: parsing failure!
      //   at org.jetbrains.java.decompiler.modules.decompiler.decompose.DomHelper.parseGraph(DomHelper.java:211)
      //   at org.jetbrains.java.decompiler.main.rels.MethodProcessor.codeToJava(MethodProcessor.java:166)
      //
      // Bytecode:
      // 000: getstatic client.vh Z
      // 003: istore 3
      // 004: iload 1
      // 005: sipush 7972
      // 008: if_icmpeq 01a
      // 00b: aload 0
      // 00c: bipush 120
      // 00e: bipush 20
      // 010: bipush 57
      // 012: bipush 1
      // 013: invokevirtual ca.a (IIIZ)V
      // 016: goto 01a
      // 019: athrow
      // 01a: getstatic ca.Qb I
      // 01d: bipush 1
      // 01e: iadd
      // 01f: putstatic ca.Qb I
      // 022: bipush 2
      // 023: aload 0
      // 024: getfield ca.Yb I
      // 027: if_icmpne 09e
      // 02a: aload 0
      // 02b: bipush 0
      // 02c: putfield ca.Yb I
      // 02f: bipush 0
      // 030: istore 2
      // 031: aload 0
      // 032: getfield ca.Db I
      // 035: bipush -1
      // 036: ixor
      // 037: iload 2
      // 038: bipush -1
      // 039: ixor
      // 03a: if_icmpge 070
      // 03d: aload 0
      // 03e: getfield ca.Gb [I
      // 041: iload 2
      // 042: aload 0
      // 043: getfield ca.a [I
      // 046: iload 2
      // 047: iaload
      // 048: iastore
      // 049: aload 0
      // 04a: getfield ca.ic [I
      // 04d: iload 2
      // 04e: aload 0
      // 04f: getfield ca.ob [I
      // 052: iload 2
      // 053: iaload
      // 054: iastore
      // 055: aload 0
      // 056: getfield ca.jc [I
      // 059: iload 2
      // 05a: aload 0
      // 05b: getfield ca.bc [I
      // 05e: iload 2
      // 05f: iaload
      // 060: iastore
      // 061: iinc 2 1
      // 064: iload 3
      // 065: ifne 09a
      // 068: iload 3
      // 069: ifeq 031
      // 06c: goto 070
      // 06f: athrow
      // 070: aload 0
      // 071: ldc 9999999
      // 073: putfield ca.j I
      // 076: aload 0
      // 077: ldc 9999999
      // 079: putfield ca.e I
      // 07c: aload 0
      // 07d: ldc -9999999
      // 07f: putfield ca.P I
      // 082: aload 0
      // 083: ldc 9999999
      // 085: putfield ca.gc I
      // 088: aload 0
      // 089: ldc -9999999
      // 08b: putfield ca.ec I
      // 08e: aload 0
      // 08f: ldc 9999999
      // 091: putfield ca.sb I
      // 094: aload 0
      // 095: ldc -9999999
      // 097: putfield ca.x I
      // 09a: iload 3
      // 09b: ifeq 18b
      // 09e: aload 0
      // 09f: getfield ca.Yb I
      // 0a2: bipush -1
      // 0a3: ixor
      // 0a4: bipush -2
      // 0a6: if_icmpeq 0b1
      // 0a9: goto 0ad
      // 0ac: athrow
      // 0ad: goto 18b
      // 0b0: athrow
      // 0b1: aload 0
      // 0b2: bipush 0
      // 0b3: putfield ca.Yb I
      // 0b6: bipush 0
      // 0b7: istore 2
      // 0b8: iload 2
      // 0b9: bipush -1
      // 0ba: ixor
      // 0bb: aload 0
      // 0bc: getfield ca.Db I
      // 0bf: bipush -1
      // 0c0: ixor
      // 0c1: if_icmple 0f7
      // 0c4: aload 0
      // 0c5: getfield ca.Gb [I
      // 0c8: iload 2
      // 0c9: aload 0
      // 0ca: getfield ca.a [I
      // 0cd: iload 2
      // 0ce: iaload
      // 0cf: iastore
      // 0d0: aload 0
      // 0d1: getfield ca.ic [I
      // 0d4: iload 2
      // 0d5: aload 0
      // 0d6: getfield ca.ob [I
      // 0d9: iload 2
      // 0da: iaload
      // 0db: iastore
      // 0dc: aload 0
      // 0dd: getfield ca.jc [I
      // 0e0: iload 2
      // 0e1: aload 0
      // 0e2: getfield ca.bc [I
      // 0e5: iload 2
      // 0e6: iaload
      // 0e7: iastore
      // 0e8: iinc 2 1
      // 0eb: iload 3
      // 0ec: ifne 103
      // 0ef: iload 3
      // 0f0: ifeq 0b8
      // 0f3: goto 0f7
      // 0f6: athrow
      // 0f7: bipush 2
      // 0f8: aload 0
      // 0f9: getfield ca.jb I
      // 0fc: if_icmple 103
      // 0ff: goto 115
      // 102: athrow
      // 103: aload 0
      // 104: bipush -53
      // 106: aload 0
      // 107: getfield ca.F I
      // 10a: aload 0
      // 10b: getfield ca.C I
      // 10e: aload 0
      // 10f: getfield ca.X I
      // 112: invokespecial ca.a (IIII)V
      // 115: aload 0
      // 116: getfield ca.jb I
      // 119: bipush 3
      // 11a: if_icmpge 121
      // 11d: goto 134
      // 120: athrow
      // 121: aload 0
      // 122: aload 0
      // 123: getfield ca.yb I
      // 126: sipush -27483
      // 129: aload 0
      // 12a: getfield ca.T I
      // 12d: aload 0
      // 12e: getfield ca.i I
      // 131: invokespecial ca.b (IIII)V
      // 134: bipush 4
      // 135: aload 0
      // 136: getfield ca.jb I
      // 139: if_icmple 140
      // 13c: goto 15e
      // 13f: athrow
      // 140: aload 0
      // 141: aload 0
      // 142: getfield ca.U I
      // 145: aload 0
      // 146: getfield ca.f I
      // 149: aload 0
      // 14a: getfield ca.Tb I
      // 14d: aload 0
      // 14e: getfield ca.G I
      // 151: aload 0
      // 152: getfield ca.Y I
      // 155: aload 0
      // 156: getfield ca.eb I
      // 159: bipush -127
      // 15b: invokespecial ca.a (IIIIIIB)V
      // 15e: bipush 1
      // 15f: aload 0
      // 160: getfield ca.jb I
      // 163: if_icmpgt 17f
      // 166: aload 0
      // 167: iload 1
      // 168: sipush -7972
      // 16b: iadd
      // 16c: aload 0
      // 16d: getfield ca.xb I
      // 170: aload 0
      // 171: getfield ca.Sb I
      // 174: aload 0
      // 175: getfield ca.r I
      // 178: invokespecial ca.d (IIII)V
      // 17b: goto 17f
      // 17e: athrow
      // 17f: aload 0
      // 180: ldc 999999
      // 182: invokespecial ca.a (I)V
      // 185: aload 0
      // 186: bipush 14
      // 188: invokespecial ca.d (B)V
      // 18b: goto 1b0
      // 18e: astore 2
      // 18f: aload 2
      // 190: new java/lang/StringBuilder
      // 193: dup
      // 194: invokespecial java/lang/StringBuilder.<init> ()V
      // 197: getstatic ca.kc [Ljava/lang/String;
      // 19a: bipush 25
      // 19c: aaload
      // 19d: invokevirtual java/lang/StringBuilder.append (Ljava/lang/String;)Ljava/lang/StringBuilder;
      // 1a0: iload 1
      // 1a1: invokevirtual java/lang/StringBuilder.append (I)Ljava/lang/StringBuilder;
      // 1a4: bipush 41
      // 1a6: invokevirtual java/lang/StringBuilder.append (C)Ljava/lang/StringBuilder;
      // 1a9: invokevirtual java/lang/StringBuilder.toString ()Ljava/lang/String;
      // 1ac: invokestatic i.a (Ljava/lang/Throwable;Ljava/lang/String;)Lla;
      // 1af: athrow
      // 1b0: return
   }

   final int b(boolean var1, int var2, int var3, int var4) {
      try {
         J++;
         if (~this.K >= ~this.Db) {
            return -1;
         } else {
            try {
               this.a[this.Db] = var3;
               this.ob[this.Db] = var4;
               this.bc[this.Db] = var2;
               if (var1) {
                  a((byte)52, (String)null);
               }
            } catch (RuntimeException var6) {
               throw var6;
            }

            return this.Db++;
         }
      } catch (RuntimeException var7) {
         throw i.a(var7, kc[32] + var1 + 44 + var2 + 44 + var3 + 44 + var4 + 41);
      }
   }

   private final void d(byte param1) {
      // $VF: Couldn't be decompiled
      // Please report this to the Vineflower issue tracker, at https://github.com/Vineflower/vineflower/issues with a copy of the class file (if you have the rights to distribute it!)
      // java.lang.RuntimeException: parsing failure!
      //   at org.jetbrains.java.decompiler.modules.decompiler.decompose.DomHelper.parseGraph(DomHelper.java:211)
      //   at org.jetbrains.java.decompiler.main.rels.MethodProcessor.codeToJava(MethodProcessor.java:166)
      //
      // Bytecode:
      // 000: getstatic client.vh Z
      // 003: istore 17
      // 005: getstatic ca.Z I
      // 008: bipush 1
      // 009: iadd
      // 00a: putstatic ca.Z I
      // 00d: aload 0
      // 00e: getfield ca.Nb Z
      // 011: ifeq 024
      // 014: aload 0
      // 015: getfield ca.c Z
      // 018: ifne 023
      // 01b: goto 01f
      // 01e: athrow
      // 01f: goto 024
      // 022: athrow
      // 023: return
      // 024: iload 1
      // 025: bipush 14
      // 027: if_icmpeq 02b
      // 02a: return
      // 02b: bipush 0
      // 02c: istore 2
      // 02d: aload 0
      // 02e: getfield ca.t I
      // 031: iload 2
      // 032: if_icmple 19e
      // 035: aload 0
      // 036: getfield ca.o [[I
      // 039: iload 2
      // 03a: aaload
      // 03b: astore 3
      // 03c: aload 0
      // 03d: getfield ca.Gb [I
      // 040: aload 3
      // 041: bipush 0
      // 042: iaload
      // 043: iaload
      // 044: istore 4
      // 046: aload 0
      // 047: getfield ca.ic [I
      // 04a: aload 3
      // 04b: bipush 0
      // 04c: iaload
      // 04d: iaload
      // 04e: istore 5
      // 050: aload 0
      // 051: getfield ca.jc [I
      // 054: aload 3
      // 055: bipush 0
      // 056: iaload
      // 057: iaload
      // 058: istore 6
      // 05a: iload 4
      // 05c: ineg
      // 05d: aload 0
      // 05e: getfield ca.Gb [I
      // 061: aload 3
      // 062: bipush 1
      // 063: iaload
      // 064: iaload
      // 065: iadd
      // 066: istore 7
      // 068: aload 0
      // 069: getfield ca.ic [I
      // 06c: aload 3
      // 06d: bipush 1
      // 06e: iaload
      // 06f: iaload
      // 070: iload 5
      // 072: ineg
      // 073: iadd
      // 074: istore 8
      // 076: iload 6
      // 078: ineg
      // 079: aload 0
      // 07a: getfield ca.jc [I
      // 07d: aload 3
      // 07e: bipush 1
      // 07f: iaload
      // 080: iaload
      // 081: iadd
      // 082: istore 9
      // 084: iload 4
      // 086: ineg
      // 087: aload 0
      // 088: getfield ca.Gb [I
      // 08b: aload 3
      // 08c: bipush 2
      // 08d: iaload
      // 08e: iaload
      // 08f: iadd
      // 090: istore 10
      // 092: aload 0
      // 093: getfield ca.ic [I
      // 096: aload 3
      // 097: bipush 2
      // 098: iaload
      // 099: iaload
      // 09a: iload 5
      // 09c: isub
      // 09d: istore 11
      // 09f: iload 6
      // 0a1: ineg
      // 0a2: aload 0
      // 0a3: getfield ca.jc [I
      // 0a6: aload 3
      // 0a7: bipush 2
      // 0a8: iaload
      // 0a9: iaload
      // 0aa: iadd
      // 0ab: istore 12
      // 0ad: iload 12
      // 0af: iload 8
      // 0b1: imul
      // 0b2: iload 9
      // 0b4: iload 11
      // 0b6: imul
      // 0b7: isub
      // 0b8: istore 13
      // 0ba: iload 7
      // 0bc: iload 12
      // 0be: imul
      // 0bf: ineg
      // 0c0: iload 9
      // 0c2: iload 10
      // 0c4: imul
      // 0c5: iadd
      // 0c6: istore 14
      // 0c8: iload 17
      // 0ca: ifne 1a6
      // 0cd: iload 10
      // 0cf: iload 8
      // 0d1: imul
      // 0d2: ineg
      // 0d3: iload 7
      // 0d5: iload 11
      // 0d7: imul
      // 0d8: iadd
      // 0d9: istore 15
      // 0db: sipush 8192
      // 0de: iload 13
      // 0e0: if_icmplt 126
      // 0e3: iload 14
      // 0e5: bipush -1
      // 0e6: ixor
      // 0e7: sipush -8193
      // 0ea: iload 17
      // 0ec: ifne 135
      // 0ef: if_icmplt 126
      // 0f2: goto 0f6
      // 0f5: athrow
      // 0f6: iload 15
      // 0f8: sipush 8192
      // 0fb: if_icmpgt 126
      // 0fe: goto 102
      // 101: athrow
      // 102: iload 13
      // 104: sipush -8192
      // 107: if_icmplt 126
      // 10a: goto 10e
      // 10d: athrow
      // 10e: iload 14
      // 110: sipush -8192
      // 113: if_icmplt 126
      // 116: goto 11a
      // 119: athrow
      // 11a: sipush -8192
      // 11d: iload 15
      // 11f: if_icmple 13d
      // 122: goto 126
      // 125: athrow
      // 126: iload 14
      // 128: bipush 1
      // 129: ishr
      // 12a: istore 14
      // 12c: iload 15
      // 12e: bipush 1
      // 12f: ishr
      // 130: istore 15
      // 132: iload 13
      // 134: bipush 1
      // 135: ishr
      // 136: istore 13
      // 138: iload 17
      // 13a: ifeq 0db
      // 13d: iload 14
      // 13f: iload 14
      // 141: imul
      // 142: iload 13
      // 144: iload 13
      // 146: imul
      // 147: iload 15
      // 149: iload 15
      // 14b: imul
      // 14c: iadd
      // 14d: iadd
      // 14e: i2d
      // 14f: invokestatic java/lang/Math.sqrt (D)D
      // 152: ldc2_w 256.0
      // 155: dmul
      // 156: d2i
      // 157: istore 16
      // 159: iload 16
      // 15b: ifle 162
      // 15e: goto 165
      // 161: athrow
      // 162: bipush 1
      // 163: istore 16
      // 165: aload 0
      // 166: getfield ca.fb [I
      // 169: iload 2
      // 16a: iload 13
      // 16c: ldc 65536
      // 16e: imul
      // 16f: iload 16
      // 171: idiv
      // 172: iastore
      // 173: aload 0
      // 174: getfield ca.Cb [I
      // 177: iload 2
      // 178: ldc 65536
      // 17a: iload 14
      // 17c: imul
      // 17d: iload 16
      // 17f: idiv
      // 180: iastore
      // 181: aload 0
      // 182: getfield ca.Pb [I
      // 185: iload 2
      // 186: iload 15
      // 188: ldc 65535
      // 18a: imul
      // 18b: iload 16
      // 18d: idiv
      // 18e: iastore
      // 18f: aload 0
      // 190: getfield ca.M [I
      // 193: iload 2
      // 194: bipush -1
      // 195: iastore
      // 196: iinc 2 1
      // 199: iload 17
      // 19b: ifeq 02d
      // 19e: aload 0
      // 19f: iload 1
      // 1a0: bipush -85
      // 1a2: ixor
      // 1a3: invokespecial ca.e (I)V
      // 1a6: goto 1cb
      // 1a9: astore 2
      // 1aa: aload 2
      // 1ab: new java/lang/StringBuilder
      // 1ae: dup
      // 1af: invokespecial java/lang/StringBuilder.<init> ()V
      // 1b2: getstatic ca.kc [Ljava/lang/String;
      // 1b5: bipush 36
      // 1b7: aaload
      // 1b8: invokevirtual java/lang/StringBuilder.append (Ljava/lang/String;)Ljava/lang/StringBuilder;
      // 1bb: iload 1
      // 1bc: invokevirtual java/lang/StringBuilder.append (I)Ljava/lang/StringBuilder;
      // 1bf: bipush 41
      // 1c1: invokevirtual java/lang/StringBuilder.append (C)Ljava/lang/StringBuilder;
      // 1c4: invokevirtual java/lang/StringBuilder.toString ()Ljava/lang/String;
      // 1c7: invokestatic i.a (Ljava/lang/Throwable;Ljava/lang/String;)Lla;
      // 1ca: athrow
      // 1cb: return
   }

   final void f(int var1, int var2, int var3, int var4) {
      try {
         this.F = var4 + this.F & 0xFF;
         A++;
         this.X = var3 + this.X & 0xFF;
         if (var2 == -31616) {
            this.C = 0xFF & this.C - -var1;
            this.b((byte)-105);
            this.Yb = 1;
         }
      } catch (RuntimeException var6) {
         throw i.a(var6, kc[7] + var1 + ',' + var2 + ',' + var3 + ',' + var4 + ')');
      }
   }

   private final void d(int var1, int var2, int var3, int var4) {
      boolean var6 = client.vh;

      try {
         d++;
         int var5 = var1;

         while (this.Db > var5) {
            try {
               this.Gb[var5] = this.Gb[var5] + var4;
               this.ic[var5] = this.ic[var5] + var2;
               this.jc[var5] = this.jc[var5] + var3;
               var5++;
               if (var6 || var6) {
                  break;
               }
            } catch (RuntimeException var7) {
               throw var7;
            }
         }
      } catch (RuntimeException var8) {
         throw i.a(var8, kc[15] + var1 + ',' + var2 + ',' + var3 + ',' + var4 + ')');
      }
   }

   // $VF: Handled exception range with multiple entry points by splitting it
   // $VF: Inserted dummy exception handlers to handle obfuscated exceptions
   private final int a(byte var1, byte[] var2) {
      boolean var7 = client.vh;

      RuntimeException var10000;
      label74: {
         try {
            if (var1 != 76) {
               return 108;
            }
         } catch (RuntimeException var13) {
            var10000 = var13;
            boolean var10001 = false;
            break label74;
         }

         try {
            s++;

            label63: {
               while (true) {
                  if (~var2[this.hb] != -11) {
                     byte var16 = -14;

                     try {
                        if (var16 != ~var2[this.hb]) {
                           break label63;
                        }
                     } catch (RuntimeException var11) {
                        var10000 = var11;
                        boolean var20 = false;
                        break;
                     }
                  }

                  try {
                     this.hb++;
                     if (var7) {
                        break label63;
                     }
                  } catch (RuntimeException var10) {
                     var10000 = var10;
                     boolean var21 = false;
                     break;
                  }
               }

               throw var10000;
            }

            int var14 = pa.d[255 & var2[this.hb++]];
            int var4 = pa.d[255 & var2[this.hb++]];
            int var5 = pa.d[var2[this.hb++] & 255];
            int var6 = -131072 + var4 * 64 + 4096 * var14 + var5;

            try {
               if (-123457 != ~var6) {
                  return var6;
               }
            } catch (RuntimeException var9) {
               throw var9;
            }

            return this.Vb;
         } catch (RuntimeException var12) {
            var10000 = var12;
            boolean var18 = false;
         }
      }

      RuntimeException var3 = var10000;

      StringBuilder var19;
      try {
         var10000 = var3;
         var19 = new StringBuilder().append(kc[20]).append((int)var1).append(',');
         if (var2 != null) {
            throw i.a(var3, var19.append(kc[1]).append((char)41).toString());
         }
      } catch (RuntimeException var8) {
         throw var8;
      }

      throw i.a(var10000, var19.append(kc[3]).append((char)41).toString());
   }

   final void a(boolean var1, int var2, int var3, int var4) {
      try {
         try {
            if (var1) {
               this.Yb = 71;
            }
         } catch (RuntimeException var6) {
            throw var6;
         }

         try {
            p++;
            if (this.Nb) {
               return;
            }
         } catch (RuntimeException var7) {
            throw var7;
         }

         this.Fb = var4;
         this.Bb = var3;
         this.g = var2;
         this.Ib = (int)Math.sqrt((double)(var4 * var4 + var3 * var3 + var2 * var2));
         this.e(52);
      } catch (RuntimeException var8) {
         throw i.a(var8, kc[24] + var1 + ',' + var2 + ',' + var3 + ',' + var4 + ')');
      }
   }

   ca(int var1, int var2) {
      boolean var4 = client.vh;
      super();
      this.Bb = 155;
      this.c = false;
      this.Yb = 1;
      this.b = false;
      this.Ib = 256;
      this.v = false;
      this.cb = false;
      this.Nb = false;
      this.sb = 12345678;
      this.g = 180;
      this.dc = true;
      this.Vb = 12345678;
      this.Kb = false;
      this.rb = -1;
      this.Mb = 512;
      this.Fb = 95;
      this.db = false;
      this.Jb = 32;
      this.hc = 0;

      try {
         this.a(var2, var1, 69);
         this.fc = new int[var2][1];
         int var3 = 0;

         while (var3 < var2) {
            try {
               this.fc[var3][0] = var3++;
               if (var4 || var4) {
                  break;
               }
            } catch (RuntimeException var5) {
               throw var5;
            }
         }
      } catch (RuntimeException var6) {
         throw i.a(var6, kc[6] + var1 + ',' + var2 + ')');
      }
   }

   ca(int var1, int var2, boolean var3, boolean var4, boolean var5, boolean var6, boolean var7) {
      this.c = false;
      this.Yb = 1;
      this.b = false;
      this.Ib = 256;
      this.v = false;
      this.cb = false;
      this.Nb = false;
      this.sb = 12345678;
      this.g = 180;
      this.dc = true;
      this.Vb = 12345678;
      this.Kb = false;
      this.rb = -1;
      this.Mb = 512;
      this.Fb = 95;
      this.db = false;
      this.Jb = 32;
      this.hc = 0;

      try {
         this.c = var4;
         this.b = var7;
         this.db = var6;
         this.v = var3;
         this.Nb = var5;
         this.a(var2, var1, 69);
      } catch (RuntimeException var9) {
         throw i.a(var9, kc[6] + var1 + ',' + var2 + ',' + var3 + ',' + var4 + ',' + var5 + ',' + var6 + ',' + var7 + ')');
      }
   }

   ca(byte[] param1, int param2, boolean param3) {
      // $VF: Couldn't be decompiled
      // Please report this to the Vineflower issue tracker, at https://github.com/Vineflower/vineflower/issues with a copy of the class file (if you have the rights to distribute it!)
      // java.lang.RuntimeException: parsing failure!
      //   at org.jetbrains.java.decompiler.modules.decompiler.decompose.DomHelper.parseGraph(DomHelper.java:211)
      //   at org.jetbrains.java.decompiler.main.rels.MethodProcessor.codeToJava(MethodProcessor.java:166)
      //
      // Bytecode:
      // 000: getstatic client.vh Z
      // 003: istore 8
      // 005: aload 0
      // 006: invokespecial java/lang/Object.<init> ()V
      // 009: aload 0
      // 00a: sipush 155
      // 00d: putfield ca.Bb I
      // 010: aload 0
      // 011: bipush 0
      // 012: putfield ca.c Z
      // 015: aload 0
      // 016: bipush 1
      // 017: putfield ca.Yb I
      // 01a: aload 0
      // 01b: bipush 0
      // 01c: putfield ca.b Z
      // 01f: aload 0
      // 020: sipush 256
      // 023: putfield ca.Ib I
      // 026: aload 0
      // 027: bipush 0
      // 028: putfield ca.v Z
      // 02b: aload 0
      // 02c: bipush 0
      // 02d: putfield ca.cb Z
      // 030: aload 0
      // 031: bipush 0
      // 032: putfield ca.Nb Z
      // 035: aload 0
      // 036: ldc 12345678
      // 038: putfield ca.sb I
      // 03b: aload 0
      // 03c: sipush 180
      // 03f: putfield ca.g I
      // 042: aload 0
      // 043: bipush 1
      // 044: putfield ca.dc Z
      // 047: aload 0
      // 048: ldc 12345678
      // 04a: putfield ca.Vb I
      // 04d: aload 0
      // 04e: bipush 0
      // 04f: putfield ca.Kb Z
      // 052: aload 0
      // 053: bipush -1
      // 054: putfield ca.rb I
      // 057: aload 0
      // 058: sipush 512
      // 05b: putfield ca.Mb I
      // 05e: aload 0
      // 05f: bipush 95
      // 061: putfield ca.Fb I
      // 064: aload 0
      // 065: bipush 0
      // 066: putfield ca.db Z
      // 069: aload 0
      // 06a: bipush 32
      // 06c: putfield ca.Jb I
      // 06f: aload 0
      // 070: bipush 0
      // 071: putfield ca.hc I
      // 074: iload 2
      // 075: bipush 7
      // 077: aload 1
      // 078: invokestatic d.a (IB[B)I
      // 07b: istore 4
      // 07d: iinc 2 2
      // 080: iload 2
      // 081: bipush 8
      // 083: aload 1
      // 084: invokestatic d.a (IB[B)I
      // 087: istore 5
      // 089: iinc 2 2
      // 08c: aload 0
      // 08d: iload 5
      // 08f: iload 4
      // 091: bipush 115
      // 093: invokespecial ca.a (III)V
      // 096: aload 0
      // 097: iload 5
      // 099: bipush 1
      // 09a: multianewarray 287 2
      // 09e: putfield ca.fc [[I
      // 0a1: bipush 0
      // 0a2: istore 6
      // 0a4: iload 4
      // 0a6: iload 6
      // 0a8: if_icmple 0cc
      // 0ab: aload 0
      // 0ac: getfield ca.a [I
      // 0af: iload 6
      // 0b1: aload 1
      // 0b2: bipush -1
      // 0b3: iload 2
      // 0b4: invokestatic w.a ([BII)I
      // 0b7: iastore
      // 0b8: iinc 2 2
      // 0bb: iinc 6 1
      // 0be: iload 8
      // 0c0: ifne 0cf
      // 0c3: iload 8
      // 0c5: ifeq 0a4
      // 0c8: goto 0cc
      // 0cb: athrow
      // 0cc: bipush 0
      // 0cd: istore 6
      // 0cf: iload 4
      // 0d1: bipush -1
      // 0d2: ixor
      // 0d3: iload 6
      // 0d5: bipush -1
      // 0d6: ixor
      // 0d7: if_icmpge 0ff
      // 0da: aload 0
      // 0db: getfield ca.ob [I
      // 0de: iload 6
      // 0e0: aload 1
      // 0e1: bipush -1
      // 0e2: iload 2
      // 0e3: invokestatic w.a ([BII)I
      // 0e6: iastore
      // 0e7: iinc 2 2
      // 0ea: iinc 6 1
      // 0ed: iload 8
      // 0ef: ifne 102
      // 0f2: goto 0f6
      // 0f5: athrow
      // 0f6: iload 8
      // 0f8: ifeq 0cf
      // 0fb: goto 0ff
      // 0fe: athrow
      // 0ff: bipush 0
      // 100: istore 6
      // 102: iload 4
      // 104: iload 6
      // 106: if_icmple 12e
      // 109: aload 0
      // 10a: getfield ca.bc [I
      // 10d: iload 6
      // 10f: aload 1
      // 110: bipush -1
      // 111: iload 2
      // 112: invokestatic w.a ([BII)I
      // 115: iastore
      // 116: iinc 2 2
      // 119: iinc 6 1
      // 11c: iload 8
      // 11e: ifne 134
      // 121: goto 125
      // 124: athrow
      // 125: iload 8
      // 127: ifeq 102
      // 12a: goto 12e
      // 12d: athrow
      // 12e: aload 0
      // 12f: iload 4
      // 131: putfield ca.Db I
      // 134: bipush 0
      // 135: istore 6
      // 137: iload 5
      // 139: bipush -1
      // 13a: ixor
      // 13b: iload 6
      // 13d: bipush -1
      // 13e: ixor
      // 13f: if_icmpge 166
      // 142: aload 0
      // 143: getfield ca.lb [I
      // 146: iload 6
      // 148: sipush 255
      // 14b: aload 1
      // 14c: iload 2
      // 14d: iinc 2 1
      // 150: baload
      // 151: invokestatic ib.a (II)I
      // 154: iastore
      // 155: iinc 6 1
      // 158: iload 8
      // 15a: ifne 169
      // 15d: iload 8
      // 15f: ifeq 137
      // 162: goto 166
      // 165: athrow
      // 166: bipush 0
      // 167: istore 6
      // 169: iload 5
      // 16b: bipush -1
      // 16c: ixor
      // 16d: iload 6
      // 16f: bipush -1
      // 170: ixor
      // 171: if_icmpge 1b5
      // 174: aload 0
      // 175: getfield ca.V [I
      // 178: iload 6
      // 17a: aload 1
      // 17b: bipush -1
      // 17c: iload 2
      // 17d: invokestatic w.a ([BII)I
      // 180: iastore
      // 181: aload 0
      // 182: getfield ca.V [I
      // 185: iload 6
      // 187: iaload
      // 188: sipush 32767
      // 18b: iload 8
      // 18d: ifne 1c0
      // 190: goto 194
      // 193: athrow
      // 194: if_icmpne 1aa
      // 197: goto 19b
      // 19a: athrow
      // 19b: aload 0
      // 19c: getfield ca.V [I
      // 19f: iload 6
      // 1a1: aload 0
      // 1a2: getfield ca.Vb I
      // 1a5: iastore
      // 1a6: goto 1aa
      // 1a9: athrow
      // 1aa: iinc 2 2
      // 1ad: iinc 6 1
      // 1b0: iload 8
      // 1b2: ifeq 169
      // 1b5: bipush 0
      // 1b6: istore 6
      // 1b8: iload 6
      // 1ba: bipush -1
      // 1bb: ixor
      // 1bc: iload 5
      // 1be: bipush -1
      // 1bf: ixor
      // 1c0: if_icmple 204
      // 1c3: aload 0
      // 1c4: getfield ca.qb [I
      // 1c7: iload 6
      // 1c9: aload 1
      // 1ca: bipush -1
      // 1cb: iload 2
      // 1cc: invokestatic w.a ([BII)I
      // 1cf: iastore
      // 1d0: iinc 2 2
      // 1d3: sipush 32767
      // 1d6: aload 0
      // 1d7: getfield ca.qb [I
      // 1da: iload 6
      // 1dc: iaload
      // 1dd: iload 8
      // 1df: ifne 20f
      // 1e2: goto 1e6
      // 1e5: athrow
      // 1e6: if_icmpne 1fc
      // 1e9: goto 1ed
      // 1ec: athrow
      // 1ed: aload 0
      // 1ee: getfield ca.qb [I
      // 1f1: iload 6
      // 1f3: aload 0
      // 1f4: getfield ca.Vb I
      // 1f7: iastore
      // 1f8: goto 1fc
      // 1fb: athrow
      // 1fc: iinc 6 1
      // 1ff: iload 8
      // 201: ifeq 1b8
      // 204: bipush 0
      // 205: istore 6
      // 207: iload 5
      // 209: bipush -1
      // 20a: ixor
      // 20b: iload 6
      // 20d: bipush -1
      // 20e: ixor
      // 20f: if_icmpge 254
      // 212: sipush 255
      // 215: aload 1
      // 216: iload 2
      // 217: iinc 2 1
      // 21a: baload
      // 21b: iand
      // 21c: istore 7
      // 21e: iload 7
      // 220: iload 8
      // 222: ifne 255
      // 225: ifeq 240
      // 228: goto 22c
      // 22b: athrow
      // 22c: aload 0
      // 22d: getfield ca.Hb [I
      // 230: iload 6
      // 232: aload 0
      // 233: getfield ca.Vb I
      // 236: iastore
      // 237: iload 8
      // 239: ifeq 24c
      // 23c: goto 240
      // 23f: athrow
      // 240: aload 0
      // 241: getfield ca.Hb [I
      // 244: iload 6
      // 246: bipush 0
      // 247: iastore
      // 248: goto 24c
      // 24b: athrow
      // 24c: iinc 6 1
      // 24f: iload 8
      // 251: ifeq 207
      // 254: bipush 0
      // 255: istore 6
      // 257: iload 6
      // 259: bipush -1
      // 25a: ixor
      // 25b: iload 5
      // 25d: bipush -1
      // 25e: ixor
      // 25f: if_icmple 2da
      // 262: aload 0
      // 263: getfield ca.o [[I
      // 266: iload 6
      // 268: aload 0
      // 269: getfield ca.lb [I
      // 26c: iload 6
      // 26e: iaload
      // 26f: newarray 10
      // 271: aastore
      // 272: iload 8
      // 274: ifne 2e5
      // 277: bipush 0
      // 278: istore 7
      // 27a: aload 0
      // 27b: getfield ca.lb [I
      // 27e: iload 6
      // 280: iaload
      // 281: iload 7
      // 283: if_icmple 2d2
      // 286: iload 4
      // 288: sipush 256
      // 28b: iload 8
      // 28d: ifne 25f
      // 290: if_icmpge 2b2
      // 293: aload 0
      // 294: getfield ca.o [[I
      // 297: iload 6
      // 299: aaload
      // 29a: iload 7
      // 29c: sipush 255
      // 29f: aload 1
      // 2a0: iload 2
      // 2a1: iinc 2 1
      // 2a4: baload
      // 2a5: invokestatic ib.a (II)I
      // 2a8: iastore
      // 2a9: iload 8
      // 2ab: ifeq 2ca
      // 2ae: goto 2b2
      // 2b1: athrow
      // 2b2: aload 0
      // 2b3: getfield ca.o [[I
      // 2b6: iload 6
      // 2b8: aaload
      // 2b9: iload 7
      // 2bb: iload 2
      // 2bc: bipush 102
      // 2be: aload 1
      // 2bf: invokestatic d.a (IB[B)I
      // 2c2: iastore
      // 2c3: iinc 2 2
      // 2c6: goto 2ca
      // 2c9: athrow
      // 2ca: iinc 7 1
      // 2cd: iload 8
      // 2cf: ifeq 27a
      // 2d2: iinc 6 1
      // 2d5: iload 8
      // 2d7: ifeq 257
      // 2da: aload 0
      // 2db: iload 5
      // 2dd: putfield ca.t I
      // 2e0: aload 0
      // 2e1: bipush 1
      // 2e2: putfield ca.Yb I
      // 2e5: goto 32f
      // 2e8: astore 4
      // 2ea: aload 4
      // 2ec: new java/lang/StringBuilder
      // 2ef: dup
      // 2f0: invokespecial java/lang/StringBuilder.<init> ()V
      // 2f3: getstatic ca.kc [Ljava/lang/String;
      // 2f6: bipush 6
      // 2f8: aaload
      // 2f9: invokevirtual java/lang/StringBuilder.append (Ljava/lang/String;)Ljava/lang/StringBuilder;
      // 2fc: aload 1
      // 2fd: ifnull 309
      // 300: getstatic ca.kc [Ljava/lang/String;
      // 303: bipush 1
      // 304: aaload
      // 305: goto 30e
      // 308: athrow
      // 309: getstatic ca.kc [Ljava/lang/String;
      // 30c: bipush 3
      // 30d: aaload
      // 30e: invokevirtual java/lang/StringBuilder.append (Ljava/lang/String;)Ljava/lang/StringBuilder;
      // 311: bipush 44
      // 313: invokevirtual java/lang/StringBuilder.append (C)Ljava/lang/StringBuilder;
      // 316: iload 2
      // 317: invokevirtual java/lang/StringBuilder.append (I)Ljava/lang/StringBuilder;
      // 31a: bipush 44
      // 31c: invokevirtual java/lang/StringBuilder.append (C)Ljava/lang/StringBuilder;
      // 31f: iload 3
      // 320: invokevirtual java/lang/StringBuilder.append (Z)Ljava/lang/StringBuilder;
      // 323: bipush 41
      // 325: invokevirtual java/lang/StringBuilder.append (C)Ljava/lang/StringBuilder;
      // 328: invokevirtual java/lang/StringBuilder.toString ()Ljava/lang/String;
      // 32b: invokestatic i.a (Ljava/lang/Throwable;Ljava/lang/String;)Lla;
      // 32e: athrow
      // 32f: return
   }

   ca(String param1) {
      // $VF: Couldn't be decompiled
      // Please report this to the Vineflower issue tracker, at https://github.com/Vineflower/vineflower/issues with a copy of the class file (if you have the rights to distribute it!)
      // java.lang.RuntimeException: parsing failure!
      //   at org.jetbrains.java.decompiler.modules.decompiler.decompose.DomHelper.parseGraph(DomHelper.java:211)
      //   at org.jetbrains.java.decompiler.main.rels.MethodProcessor.codeToJava(MethodProcessor.java:166)
      //
      // Bytecode:
      // 000: getstatic client.vh Z
      // 003: istore 19
      // 005: aload 0
      // 006: invokespecial java/lang/Object.<init> ()V
      // 009: aload 0
      // 00a: sipush 155
      // 00d: putfield ca.Bb I
      // 010: aload 0
      // 011: bipush 0
      // 012: putfield ca.c Z
      // 015: aload 0
      // 016: bipush 1
      // 017: putfield ca.Yb I
      // 01a: aload 0
      // 01b: bipush 0
      // 01c: putfield ca.b Z
      // 01f: aload 0
      // 020: sipush 256
      // 023: putfield ca.Ib I
      // 026: aload 0
      // 027: bipush 0
      // 028: putfield ca.v Z
      // 02b: aload 0
      // 02c: bipush 0
      // 02d: putfield ca.cb Z
      // 030: aload 0
      // 031: bipush 0
      // 032: putfield ca.Nb Z
      // 035: aload 0
      // 036: ldc 12345678
      // 038: putfield ca.sb I
      // 03b: aload 0
      // 03c: sipush 180
      // 03f: putfield ca.g I
      // 042: aload 0
      // 043: bipush 1
      // 044: putfield ca.dc Z
      // 047: aload 0
      // 048: ldc 12345678
      // 04a: putfield ca.Vb I
      // 04d: aload 0
      // 04e: bipush 0
      // 04f: putfield ca.Kb Z
      // 052: aload 0
      // 053: bipush -1
      // 054: putfield ca.rb I
      // 057: aload 0
      // 058: sipush 512
      // 05b: putfield ca.Mb I
      // 05e: aload 0
      // 05f: bipush 95
      // 061: putfield ca.Fb I
      // 064: aload 0
      // 065: bipush 0
      // 066: putfield ca.db Z
      // 069: aload 0
      // 06a: bipush 32
      // 06c: putfield ca.Jb I
      // 06f: aload 0
      // 070: bipush 0
      // 071: putfield ca.hc I
      // 074: bipush 0
      // 075: istore 2
      // 076: bipush 0
      // 077: istore 3
      // 078: aconst_null
      // 079: astore 4
      // 07b: bipush 1
      // 07c: aload 1
      // 07d: invokestatic nb.a (ZLjava/lang/String;)Ljava/io/InputStream;
      // 080: astore 5
      // 082: new java/io/DataInputStream
      // 085: dup
      // 086: aload 5
      // 088: invokespecial java/io/DataInputStream.<init> (Ljava/io/InputStream;)V
      // 08b: astore 6
      // 08d: bipush 3
      // 08e: newarray 8
      // 090: astore 4
      // 092: bipush 0
      // 093: istore 2
      // 094: aload 0
      // 095: bipush 0
      // 096: putfield ca.hb I
      // 099: iload 2
      // 09a: bipush -1
      // 09b: ixor
      // 09c: bipush -4
      // 09e: if_icmple 0be
      // 0a1: iload 2
      // 0a2: aload 6
      // 0a4: aload 4
      // 0a6: iload 2
      // 0a7: iload 2
      // 0a8: ineg
      // 0a9: bipush 3
      // 0aa: iadd
      // 0ab: invokevirtual java/io/DataInputStream.read ([BII)I
      // 0ae: iadd
      // 0af: istore 2
      // 0b0: iload 19
      // 0b2: ifne 0ce
      // 0b5: iload 19
      // 0b7: ifeq 099
      // 0ba: goto 0be
      // 0bd: athrow
      // 0be: aload 0
      // 0bf: bipush 76
      // 0c1: aload 4
      // 0c3: invokespecial ca.a (B[B)I
      // 0c6: istore 3
      // 0c7: bipush 0
      // 0c8: istore 2
      // 0c9: aload 0
      // 0ca: bipush 0
      // 0cb: putfield ca.hb I
      // 0ce: iload 3
      // 0cf: newarray 8
      // 0d1: astore 4
      // 0d3: iload 2
      // 0d4: bipush -1
      // 0d5: ixor
      // 0d6: iload 3
      // 0d7: bipush -1
      // 0d8: ixor
      // 0d9: if_icmple 0f8
      // 0dc: iload 2
      // 0dd: aload 6
      // 0df: aload 4
      // 0e1: iload 2
      // 0e2: iload 3
      // 0e3: iload 2
      // 0e4: isub
      // 0e5: invokevirtual java/io/DataInputStream.read ([BII)I
      // 0e8: iadd
      // 0e9: istore 2
      // 0ea: iload 19
      // 0ec: ifne 0fd
      // 0ef: iload 19
      // 0f1: ifeq 0d3
      // 0f4: goto 0f8
      // 0f7: athrow
      // 0f8: aload 6
      // 0fa: invokevirtual java/io/DataInputStream.close ()V
      // 0fd: goto 10d
      // 100: astore 5
      // 102: aload 0
      // 103: bipush 0
      // 104: putfield ca.t I
      // 107: aload 0
      // 108: bipush 0
      // 109: putfield ca.Db I
      // 10c: return
      // 10d: aload 0
      // 10e: bipush 76
      // 110: aload 4
      // 112: invokespecial ca.a (B[B)I
      // 115: istore 5
      // 117: aload 0
      // 118: bipush 76
      // 11a: aload 4
      // 11c: invokespecial ca.a (B[B)I
      // 11f: istore 6
      // 121: bipush 0
      // 122: istore 14
      // 124: aload 0
      // 125: iload 6
      // 127: iload 5
      // 129: bipush 97
      // 12b: invokespecial ca.a (III)V
      // 12e: aload 0
      // 12f: iload 6
      // 131: anewarray 285
      // 134: putfield ca.fc [[I
      // 137: bipush 0
      // 138: istore 15
      // 13a: iload 5
      // 13c: iload 15
      // 13e: if_icmple 17d
      // 141: aload 0
      // 142: bipush 76
      // 144: aload 4
      // 146: invokespecial ca.a (B[B)I
      // 149: istore 7
      // 14b: aload 0
      // 14c: bipush 76
      // 14e: aload 4
      // 150: invokespecial ca.a (B[B)I
      // 153: istore 8
      // 155: aload 0
      // 156: bipush 76
      // 158: aload 4
      // 15a: invokespecial ca.a (B[B)I
      // 15d: istore 9
      // 15f: aload 0
      // 160: iload 7
      // 162: iload 9
      // 164: iload 8
      // 166: bipush 52
      // 168: invokevirtual ca.e (IIII)I
      // 16b: pop
      // 16c: iinc 15 1
      // 16f: iload 19
      // 171: ifne 180
      // 174: iload 19
      // 176: ifeq 13a
      // 179: goto 17d
      // 17c: athrow
      // 17d: bipush 0
      // 17e: istore 15
      // 180: iload 6
      // 182: bipush -1
      // 183: ixor
      // 184: iload 15
      // 186: bipush -1
      // 187: ixor
      // 188: if_icmpge 27c
      // 18b: aload 0
      // 18c: bipush 76
      // 18e: aload 4
      // 190: invokespecial ca.a (B[B)I
      // 193: istore 10
      // 195: aload 0
      // 196: bipush 76
      // 198: aload 4
      // 19a: invokespecial ca.a (B[B)I
      // 19d: istore 11
      // 19f: aload 0
      // 1a0: bipush 76
      // 1a2: aload 4
      // 1a4: invokespecial ca.a (B[B)I
      // 1a7: istore 12
      // 1a9: aload 0
      // 1aa: bipush 76
      // 1ac: aload 4
      // 1ae: invokespecial ca.a (B[B)I
      // 1b1: istore 13
      // 1b3: aload 0
      // 1b4: aload 0
      // 1b5: bipush 76
      // 1b7: aload 4
      // 1b9: invokespecial ca.a (B[B)I
      // 1bc: putfield ca.Mb I
      // 1bf: aload 0
      // 1c0: aload 0
      // 1c1: bipush 76
      // 1c3: aload 4
      // 1c5: invokespecial ca.a (B[B)I
      // 1c8: putfield ca.Jb I
      // 1cb: aload 0
      // 1cc: bipush 76
      // 1ce: aload 4
      // 1d0: invokespecial ca.a (B[B)I
      // 1d3: istore 14
      // 1d5: iload 10
      // 1d7: newarray 10
      // 1d9: astore 16
      // 1db: iload 19
      // 1dd: ifne 281
      // 1e0: bipush 0
      // 1e1: istore 17
      // 1e3: iload 17
      // 1e5: iload 10
      // 1e7: if_icmpge 204
      // 1ea: aload 16
      // 1ec: iload 17
      // 1ee: aload 0
      // 1ef: bipush 76
      // 1f1: aload 4
      // 1f3: invokespecial ca.a (B[B)I
      // 1f6: iastore
      // 1f7: iinc 17 1
      // 1fa: iload 19
      // 1fc: ifne 180
      // 1ff: iload 19
      // 201: ifeq 1e3
      // 204: iload 13
      // 206: newarray 10
      // 208: astore 17
      // 20a: bipush 0
      // 20b: istore 18
      // 20d: iload 18
      // 20f: bipush -1
      // 210: ixor
      // 211: iload 13
      // 213: bipush -1
      // 214: ixor
      // 215: if_icmple 236
      // 218: aload 17
      // 21a: iload 18
      // 21c: aload 0
      // 21d: bipush 76
      // 21f: aload 4
      // 221: invokespecial ca.a (B[B)I
      // 224: iastore
      // 225: iinc 18 1
      // 228: iload 19
      // 22a: ifne 24e
      // 22d: iload 19
      // 22f: ifeq 20d
      // 232: goto 236
      // 235: athrow
      // 236: aload 0
      // 237: iload 10
      // 239: aload 16
      // 23b: iload 11
      // 23d: iload 12
      // 23f: bipush 0
      // 240: invokevirtual ca.a (I[IIIZ)I
      // 243: istore 18
      // 245: aload 0
      // 246: getfield ca.fc [[I
      // 249: iload 15
      // 24b: aload 17
      // 24d: aastore
      // 24e: bipush 0
      // 24f: iload 14
      // 251: if_icmpne 265
      // 254: aload 0
      // 255: getfield ca.Hb [I
      // 258: iload 18
      // 25a: bipush 0
      // 25b: iastore
      // 25c: iload 19
      // 25e: ifeq 274
      // 261: goto 265
      // 264: athrow
      // 265: aload 0
      // 266: getfield ca.Hb [I
      // 269: iload 18
      // 26b: aload 0
      // 26c: getfield ca.Vb I
      // 26f: iastore
      // 270: goto 274
      // 273: athrow
      // 274: iinc 15 1
      // 277: iload 19
      // 279: ifeq 180
      // 27c: aload 0
      // 27d: bipush 1
      // 27e: putfield ca.Yb I
      // 281: goto 2b7
      // 284: astore 2
      // 285: aload 2
      // 286: new java/lang/StringBuilder
      // 289: dup
      // 28a: invokespecial java/lang/StringBuilder.<init> ()V
      // 28d: getstatic ca.kc [Ljava/lang/String;
      // 290: bipush 6
      // 292: aaload
      // 293: invokevirtual java/lang/StringBuilder.append (Ljava/lang/String;)Ljava/lang/StringBuilder;
      // 296: aload 1
      // 297: ifnull 2a3
      // 29a: getstatic ca.kc [Ljava/lang/String;
      // 29d: bipush 1
      // 29e: aaload
      // 29f: goto 2a8
      // 2a2: athrow
      // 2a3: getstatic ca.kc [Ljava/lang/String;
      // 2a6: bipush 3
      // 2a7: aaload
      // 2a8: invokevirtual java/lang/StringBuilder.append (Ljava/lang/String;)Ljava/lang/StringBuilder;
      // 2ab: bipush 41
      // 2ad: invokevirtual java/lang/StringBuilder.append (C)Ljava/lang/StringBuilder;
      // 2b0: invokevirtual java/lang/StringBuilder.toString ()Ljava/lang/String;
      // 2b3: invokestatic i.a (Ljava/lang/Throwable;Ljava/lang/String;)Lla;
      // 2b6: athrow
      // 2b7: return
   }

   private ca(ca[] var1, int var2, boolean var3, boolean var4, boolean var5, boolean var6) {
      this.c = false;
      this.Yb = 1;
      this.b = false;
      this.Ib = 256;
      this.v = false;
      this.cb = false;
      this.Nb = false;
      this.sb = 12345678;
      this.g = 180;
      this.dc = true;
      this.Vb = 12345678;
      this.Kb = false;
      this.rb = -1;
      this.Mb = 512;
      this.Fb = 95;
      this.db = false;
      this.Jb = 32;
      this.hc = 0;

      try {
         this.Nb = var5;
         this.c = var4;
         this.db = var6;
         this.v = var3;
         this.a(0, var1, false, var2);
      } catch (RuntimeException var9) {
         RuntimeException var7 = var9;

         RuntimeException var10000;
         StringBuilder var10001;
         try {
            var10000 = var7;
            var10001 = new StringBuilder().append(kc[6]);
            if (var1 != null) {
               throw i.a(
                  var7,
                  var10001.append(kc[1])
                     .append(',')
                     .append(var2)
                     .append(',')
                     .append(var3)
                     .append(',')
                     .append(var4)
                     .append(',')
                     .append(var5)
                     .append(',')
                     .append(var6)
                     .append(')')
                     .toString()
               );
            }
         } catch (RuntimeException var8) {
            throw var8;
         }

         throw i.a(
            var10000,
            var10001.append(kc[3])
               .append(',')
               .append(var2)
               .append(',')
               .append(var3)
               .append(',')
               .append(var4)
               .append(',')
               .append(var5)
               .append(',')
               .append(var6)
               .append(')')
               .toString()
         );
      }
   }

   private ca(ca[] var1, int var2) {
      this.c = false;
      this.Yb = 1;
      this.b = false;
      this.Ib = 256;
      this.v = false;
      this.cb = false;
      this.Nb = false;
      this.sb = 12345678;
      this.g = 180;
      this.dc = true;
      this.Vb = 12345678;
      this.Kb = false;
      this.rb = -1;
      this.Mb = 512;
      this.Fb = 95;
      this.db = false;
      this.Jb = 32;
      this.hc = 0;

      try {
         this.a(0, var1, true, var2);
      } catch (RuntimeException var5) {
         RuntimeException var3 = var5;

         RuntimeException var10000;
         StringBuilder var10001;
         try {
            var10000 = var3;
            var10001 = new StringBuilder().append(kc[6]);
            if (var1 != null) {
               throw i.a(var3, var10001.append(kc[1]).append(',').append(var2).append(')').toString());
            }
         } catch (RuntimeException var4) {
            throw var4;
         }

         throw i.a(var10000, var10001.append(kc[3]).append(',').append(var2).append(')').toString());
      }
   }

   private static char[] z(String var0) {
      char[] var10000 = var0.toCharArray();
      if (var10000.length < 2) {
         var10000[0] = (char)(var10000[0] ^ '%');
      }

      return var10000;
   }

   private static String z(char[] var0) {
      int var10002 = var0.length;
      char[] var10001 = var0;
      int var10000 = var10002;

      for (int var1 = 0; var10000 > var1; var1++) {
         char var10004 = var10001[var1];
         byte var10005;
         switch (var1 % 5) {
            case 0:
               var10005 = 27;
               break;
            case 1:
               var10005 = 119;
               break;
            case 2:
               var10005 = 10;
               break;
            case 3:
               var10005 = 61;
               break;
            default:
               var10005 = 37;
         }

         var10001[var1] = (char)(var10004 ^ var10005);
      }

      return new String(var10001).intern();
   }
}
