import java.awt.image.ColorModel;
import java.io.IOException;
import java.net.Socket;

abstract class m {
   static byte[][] b = new byte[50][];
   static int[] g;
   static int k;
   String h;
   static ob e = null;
   static int[] i = new int[256];
   int f;
   static int a;
   static ColorModel d;
   static int c;
   static int j;
   private static final String[] z = new String[]{
      z(z(".aKU")),
      z(z(";:\t\u0017#")),
      z(z("-:f\u0011")),
      z(z("-:e\u0011")),
      z(z(")zS\\9%f\t]?4")),
      z(z("\u0019{R\u00190%qC\u0019*/4E\\~!4J\\3\"qU\u0019*/4RJ;``OP-`{ES;#`")),
      z(z("\rqJ[;2g\u0007V<*qDM")),
      z(z("3`UP0':CX*")),
      z(z("-:d\u0011"))
   };

   static final int a(boolean var0, int var1, byte[] var2) {
      try {
         try {
            if (!var0) {
               b = (byte[][])null;
            }
         } catch (RuntimeException var5) {
            throw var5;
         }

         a++;
         return (var2[var1 + 3] & 0xFF)
            + (var2[var1 - -2] << -1719048248 & 0xFF00)
            + ((0xFF & var2[var1]) << -523457256)
            - -((0xFF & var2[1 + var1]) << -728162096);
      } catch (RuntimeException var6) {
         RuntimeException var3 = var6;

         RuntimeException var10000;
         StringBuilder var10001;
         try {
            var10000 = var3;
            var10001 = new StringBuilder().append(z[2]).append(var0).append(',').append(var1).append(',');
            if (var2 != null) {
               throw i.a(var3, var10001.append(z[1]).append((char)41).toString());
            }
         } catch (RuntimeException var4) {
            throw var4;
         }

         throw i.a(var10000, var10001.append(z[0]).append((char)41).toString());
      }
   }

   final Socket a(boolean var1) throws IOException {
      try {
         try {
            k++;
            if (var1) {
               i = (int[])null;
            }
         } catch (RuntimeException var3) {
            throw var3;
         }

         return new Socket(this.h, this.f);
      } catch (RuntimeException var4) {
         throw i.a(var4, z[8] + var1 + ')');
      }
   }

   static final void a(byte[] param0, byte param1, boolean param2) {
      // $VF: Couldn't be decompiled
      // Please report this to the Vineflower issue tracker, at https://github.com/Vineflower/vineflower/issues with a copy of the class file (if you have the rights to distribute it!)
      // java.lang.RuntimeException: parsing failure!
      //   at org.jetbrains.java.decompiler.modules.decompiler.decompose.DomHelper.parseGraph(DomHelper.java:211)
      //   at org.jetbrains.java.decompiler.main.rels.MethodProcessor.codeToJava(MethodProcessor.java:166)
      //
      // Bytecode:
      // 000: getstatic client.vh Z
      // 003: istore 6
      // 005: getstatic m.z [Ljava/lang/String;
      // 008: bipush 7
      // 00a: aaload
      // 00b: bipush 0
      // 00c: aload 0
      // 00d: bipush -124
      // 00f: invokestatic na.a (Ljava/lang/String;I[BI)[B
      // 012: putstatic kb.d [B
      // 015: getstatic m.c I
      // 018: bipush 1
      // 019: iadd
      // 01a: putstatic m.c I
      // 01d: bipush 0
      // 01e: putstatic jb.p I
      // 021: getstatic m.z [Ljava/lang/String;
      // 024: bipush 4
      // 025: aaload
      // 026: bipush 0
      // 027: aload 0
      // 028: bipush -125
      // 02a: invokestatic na.a (Ljava/lang/String;I[BI)[B
      // 02d: putstatic b.v [B
      // 030: bipush 0
      // 031: putstatic ka.b I
      // 034: ldc 65525
      // 036: invokestatic t.a (I)I
      // 039: putstatic gb.p I
      // 03c: getstatic gb.p I
      // 03f: newarray 10
      // 041: putstatic fa.e [I
      // 044: getstatic gb.p I
      // 047: anewarray 152
      // 04a: putstatic ac.x [Ljava/lang/String;
      // 04d: getstatic gb.p I
      // 050: newarray 10
      // 052: putstatic ka.c [I
      // 055: getstatic gb.p I
      // 058: newarray 10
      // 05a: putstatic h.c [I
      // 05d: getstatic gb.p I
      // 060: anewarray 152
      // 063: putstatic lb.ac [Ljava/lang/String;
      // 066: getstatic gb.p I
      // 069: newarray 10
      // 06b: putstatic ua.Bb [I
      // 06e: getstatic gb.p I
      // 071: newarray 10
      // 073: putstatic kb.b [I
      // 076: getstatic gb.p I
      // 079: newarray 10
      // 07b: putstatic mb.k [I
      // 07e: getstatic gb.p I
      // 081: newarray 10
      // 083: putstatic kb.c [I
      // 086: getstatic gb.p I
      // 089: anewarray 152
      // 08c: putstatic ga.b [Ljava/lang/String;
      // 08f: getstatic gb.p I
      // 092: newarray 10
      // 094: putstatic gb.s [I
      // 097: bipush 0
      // 098: istore 3
      // 099: getstatic gb.p I
      // 09c: iload 3
      // 09d: if_icmple 0bb
      // 0a0: getstatic ac.x [Ljava/lang/String;
      // 0a3: iload 3
      // 0a4: bipush 38
      // 0a6: invokestatic o.a (B)Ljava/lang/String;
      // 0a9: aastore
      // 0aa: iinc 3 1
      // 0ad: iload 6
      // 0af: ifne 0bd
      // 0b2: iload 6
      // 0b4: ifeq 099
      // 0b7: goto 0bb
      // 0ba: athrow
      // 0bb: bipush 0
      // 0bc: istore 3
      // 0bd: iload 3
      // 0be: bipush -1
      // 0bf: ixor
      // 0c0: getstatic gb.p I
      // 0c3: bipush -1
      // 0c4: ixor
      // 0c5: if_icmple 0e7
      // 0c8: getstatic ga.b [Ljava/lang/String;
      // 0cb: iload 3
      // 0cc: bipush 38
      // 0ce: invokestatic o.a (B)Ljava/lang/String;
      // 0d1: aastore
      // 0d2: iinc 3 1
      // 0d5: iload 6
      // 0d7: ifne 0e9
      // 0da: goto 0de
      // 0dd: athrow
      // 0de: iload 6
      // 0e0: ifeq 0bd
      // 0e3: goto 0e7
      // 0e6: athrow
      // 0e7: bipush 0
      // 0e8: istore 3
      // 0e9: getstatic gb.p I
      // 0ec: iload 3
      // 0ed: if_icmple 10f
      // 0f0: getstatic lb.ac [Ljava/lang/String;
      // 0f3: iload 3
      // 0f4: bipush 38
      // 0f6: invokestatic o.a (B)Ljava/lang/String;
      // 0f9: aastore
      // 0fa: iinc 3 1
      // 0fd: iload 6
      // 0ff: ifne 111
      // 102: goto 106
      // 105: athrow
      // 106: iload 6
      // 108: ifeq 0e9
      // 10b: goto 10f
      // 10e: athrow
      // 10f: bipush 0
      // 110: istore 3
      // 111: getstatic gb.p I
      // 114: iload 3
      // 115: if_icmple 155
      // 118: getstatic ua.Bb [I
      // 11b: iload 3
      // 11c: ldc 65525
      // 11e: invokestatic t.a (I)I
      // 121: iastore
      // 122: getstatic mb.l I
      // 125: bipush -1
      // 126: ixor
      // 127: getstatic ua.Bb [I
      // 12a: iload 3
      // 12b: iaload
      // 12c: bipush 1
      // 12d: iadd
      // 12e: bipush -1
      // 12f: ixor
      // 130: iload 6
      // 132: ifne 15f
      // 135: goto 139
      // 138: athrow
      // 139: if_icmpgt 143
      // 13c: goto 140
      // 13f: athrow
      // 140: goto 14d
      // 143: getstatic ua.Bb [I
      // 146: iload 3
      // 147: iaload
      // 148: bipush 1
      // 149: iadd
      // 14a: putstatic mb.l I
      // 14d: iinc 3 1
      // 150: iload 6
      // 152: ifeq 111
      // 155: bipush 0
      // 156: istore 3
      // 157: iload 3
      // 158: bipush -1
      // 159: ixor
      // 15a: getstatic gb.p I
      // 15d: bipush -1
      // 15e: ixor
      // 15f: if_icmple 181
      // 162: getstatic kb.b [I
      // 165: iload 3
      // 166: bipush -105
      // 168: invokestatic ub.a (B)I
      // 16b: iastore
      // 16c: iinc 3 1
      // 16f: iload 6
      // 171: ifne 183
      // 174: goto 178
      // 177: athrow
      // 178: iload 6
      // 17a: ifeq 157
      // 17d: goto 181
      // 180: athrow
      // 181: bipush 0
      // 182: istore 3
      // 183: getstatic gb.p I
      // 186: iload 3
      // 187: if_icmple 1aa
      // 18a: getstatic fa.e [I
      // 18d: iload 3
      // 18e: sipush -30504
      // 191: invokestatic v.a (I)I
      // 194: iastore
      // 195: iinc 3 1
      // 198: iload 6
      // 19a: ifne 1ac
      // 19d: goto 1a1
      // 1a0: athrow
      // 1a1: iload 6
      // 1a3: ifeq 183
      // 1a6: goto 1aa
      // 1a9: athrow
      // 1aa: bipush 0
      // 1ab: istore 3
      // 1ac: getstatic gb.p I
      // 1af: iload 3
      // 1b0: if_icmple 1d3
      // 1b3: getstatic gb.s [I
      // 1b6: iload 3
      // 1b7: sipush -30504
      // 1ba: invokestatic v.a (I)I
      // 1bd: iastore
      // 1be: iinc 3 1
      // 1c1: iload 6
      // 1c3: ifne 1d5
      // 1c6: goto 1ca
      // 1c9: athrow
      // 1ca: iload 6
      // 1cc: ifeq 1ac
      // 1cf: goto 1d3
      // 1d2: athrow
      // 1d3: bipush 0
      // 1d4: istore 3
      // 1d5: getstatic gb.p I
      // 1d8: bipush -1
      // 1d9: ixor
      // 1da: iload 3
      // 1db: bipush -1
      // 1dc: ixor
      // 1dd: if_icmpge 1ff
      // 1e0: getstatic mb.k [I
      // 1e3: iload 3
      // 1e4: ldc 65525
      // 1e6: invokestatic t.a (I)I
      // 1e9: iastore
      // 1ea: iinc 3 1
      // 1ed: iload 6
      // 1ef: ifne 201
      // 1f2: goto 1f6
      // 1f5: athrow
      // 1f6: iload 6
      // 1f8: ifeq 1d5
      // 1fb: goto 1ff
      // 1fe: athrow
      // 1ff: bipush 0
      // 200: istore 3
      // 201: iload 3
      // 202: getstatic gb.p I
      // 205: if_icmpge 227
      // 208: getstatic h.c [I
      // 20b: iload 3
      // 20c: bipush -105
      // 20e: invokestatic ub.a (B)I
      // 211: iastore
      // 212: iinc 3 1
      // 215: iload 6
      // 217: ifne 229
      // 21a: goto 21e
      // 21d: athrow
      // 21e: iload 6
      // 220: ifeq 201
      // 223: goto 227
      // 226: athrow
      // 227: bipush 0
      // 228: istore 3
      // 229: getstatic gb.p I
      // 22c: iload 3
      // 22d: if_icmple 250
      // 230: getstatic kb.c [I
      // 233: iload 3
      // 234: sipush -30504
      // 237: invokestatic v.a (I)I
      // 23a: iastore
      // 23b: iinc 3 1
      // 23e: iload 6
      // 240: ifne 252
      // 243: goto 247
      // 246: athrow
      // 247: iload 6
      // 249: ifeq 229
      // 24c: goto 250
      // 24f: athrow
      // 250: bipush 0
      // 251: istore 3
      // 252: getstatic gb.p I
      // 255: iload 3
      // 256: if_icmple 279
      // 259: getstatic ka.c [I
      // 25c: iload 3
      // 25d: sipush -30504
      // 260: invokestatic v.a (I)I
      // 263: iastore
      // 264: iinc 3 1
      // 267: iload 6
      // 269: ifne 27b
      // 26c: goto 270
      // 26f: athrow
      // 270: iload 6
      // 272: ifeq 252
      // 275: goto 279
      // 278: athrow
      // 279: bipush 0
      // 27a: istore 3
      // 27b: iload 3
      // 27c: getstatic gb.p I
      // 27f: if_icmpge 2e4
      // 282: bipush 1
      // 283: iload 2
      // 284: iload 6
      // 286: ifne 36c
      // 289: goto 28d
      // 28c: athrow
      // 28d: if_icmpeq 2dc
      // 290: goto 294
      // 293: athrow
      // 294: bipush -2
      // 296: getstatic ka.c [I
      // 299: iload 3
      // 29a: iaload
      // 29b: bipush -1
      // 29c: ixor
      // 29d: if_icmpeq 2a8
      // 2a0: goto 2a4
      // 2a3: athrow
      // 2a4: goto 2dc
      // 2a7: athrow
      // 2a8: getstatic ac.x [Ljava/lang/String;
      // 2ab: iload 3
      // 2ac: getstatic m.z [Ljava/lang/String;
      // 2af: bipush 6
      // 2b1: aaload
      // 2b2: aastore
      // 2b3: getstatic ga.b [Ljava/lang/String;
      // 2b6: iload 3
      // 2b7: getstatic m.z [Ljava/lang/String;
      // 2ba: bipush 5
      // 2bb: aaload
      // 2bc: aastore
      // 2bd: getstatic kb.b [I
      // 2c0: iload 3
      // 2c1: bipush 0
      // 2c2: iastore
      // 2c3: getstatic lb.ac [Ljava/lang/String;
      // 2c6: iload 3
      // 2c7: ldc ""
      // 2c9: aastore
      // 2ca: getstatic gb.s [I
      // 2cd: bipush 0
      // 2ce: bipush 0
      // 2cf: iastore
      // 2d0: getstatic mb.k [I
      // 2d3: iload 3
      // 2d4: bipush 0
      // 2d5: iastore
      // 2d6: getstatic kb.c [I
      // 2d9: iload 3
      // 2da: bipush 1
      // 2db: iastore
      // 2dc: iinc 3 1
      // 2df: iload 6
      // 2e1: ifeq 27b
      // 2e4: ldc 65525
      // 2e6: invokestatic t.a (I)I
      // 2e9: putstatic la.d I
      // 2ec: getstatic la.d I
      // 2ef: newarray 10
      // 2f1: putstatic fb.d [I
      // 2f4: getstatic la.d I
      // 2f7: newarray 10
      // 2f9: putstatic b.h [I
      // 2fc: getstatic la.d I
      // 2ff: newarray 10
      // 301: putstatic jb.k [I
      // 304: getstatic la.d I
      // 307: newarray 10
      // 309: putstatic ob.h [I
      // 30c: getstatic la.d I
      // 30f: newarray 10
      // 311: putstatic la.a [I
      // 314: getstatic la.d I
      // 317: newarray 10
      // 319: putstatic m.g [I
      // 31c: getstatic la.d I
      // 31f: newarray 10
      // 321: putstatic v.e [I
      // 324: getstatic la.d I
      // 327: newarray 10
      // 329: putstatic o.a [I
      // 32c: getstatic la.d I
      // 32f: anewarray 152
      // 332: putstatic ba.ac [Ljava/lang/String;
      // 335: getstatic la.d I
      // 338: newarray 10
      // 33a: putstatic fb.c [I
      // 33d: getstatic la.d I
      // 340: anewarray 152
      // 343: putstatic p.e [Ljava/lang/String;
      // 346: getstatic la.d I
      // 349: newarray 10
      // 34b: putstatic da.T [I
      // 34e: getstatic la.d I
      // 351: anewarray 152
      // 354: putstatic e.Mb [Ljava/lang/String;
      // 357: getstatic la.d I
      // 35a: newarray 10
      // 35c: putstatic na.a [I
      // 35f: getstatic la.d I
      // 362: newarray 10
      // 364: putstatic db.j [I
      // 367: getstatic la.d I
      // 36a: bipush 12
      // 36c: multianewarray 126 2
      // 370: putstatic qb.d [[I
      // 373: getstatic la.d I
      // 376: newarray 10
      // 378: putstatic eb.b [I
      // 37b: getstatic la.d I
      // 37e: newarray 10
      // 380: putstatic ua.Ab [I
      // 383: bipush 0
      // 384: istore 3
      // 385: getstatic la.d I
      // 388: bipush -1
      // 389: ixor
      // 38a: iload 3
      // 38b: bipush -1
      // 38c: ixor
      // 38d: if_icmpge 3ab
      // 390: getstatic e.Mb [Ljava/lang/String;
      // 393: iload 3
      // 394: bipush 38
      // 396: invokestatic o.a (B)Ljava/lang/String;
      // 399: aastore
      // 39a: iinc 3 1
      // 39d: iload 6
      // 39f: ifne 3ad
      // 3a2: iload 6
      // 3a4: ifeq 385
      // 3a7: goto 3ab
      // 3aa: athrow
      // 3ab: bipush 0
      // 3ac: istore 3
      // 3ad: iload 3
      // 3ae: bipush -1
      // 3af: ixor
      // 3b0: getstatic la.d I
      // 3b3: bipush -1
      // 3b4: ixor
      // 3b5: if_icmple 3d7
      // 3b8: getstatic ba.ac [Ljava/lang/String;
      // 3bb: iload 3
      // 3bc: bipush 38
      // 3be: invokestatic o.a (B)Ljava/lang/String;
      // 3c1: aastore
      // 3c2: iinc 3 1
      // 3c5: iload 6
      // 3c7: ifne 3d9
      // 3ca: goto 3ce
      // 3cd: athrow
      // 3ce: iload 6
      // 3d0: ifeq 3ad
      // 3d3: goto 3d7
      // 3d6: athrow
      // 3d7: bipush 0
      // 3d8: istore 3
      // 3d9: getstatic la.d I
      // 3dc: iload 3
      // 3dd: if_icmple 400
      // 3e0: getstatic la.a [I
      // 3e3: iload 3
      // 3e4: sipush -30504
      // 3e7: invokestatic v.a (I)I
      // 3ea: iastore
      // 3eb: iinc 3 1
      // 3ee: iload 6
      // 3f0: ifne 402
      // 3f3: goto 3f7
      // 3f6: athrow
      // 3f7: iload 6
      // 3f9: ifeq 3d9
      // 3fc: goto 400
      // 3ff: athrow
      // 400: bipush 0
      // 401: istore 3
      // 402: getstatic la.d I
      // 405: bipush -1
      // 406: ixor
      // 407: iload 3
      // 408: bipush -1
      // 409: ixor
      // 40a: if_icmpge 42d
      // 40d: getstatic eb.b [I
      // 410: iload 3
      // 411: sipush -30504
      // 414: invokestatic v.a (I)I
      // 417: iastore
      // 418: iinc 3 1
      // 41b: iload 6
      // 41d: ifne 42f
      // 420: goto 424
      // 423: athrow
      // 424: iload 6
      // 426: ifeq 402
      // 429: goto 42d
      // 42c: athrow
      // 42d: bipush 0
      // 42e: istore 3
      // 42f: getstatic la.d I
      // 432: bipush -1
      // 433: ixor
      // 434: iload 3
      // 435: bipush -1
      // 436: ixor
      // 437: if_icmpge 45a
      // 43a: getstatic fb.d [I
      // 43d: iload 3
      // 43e: sipush -30504
      // 441: invokestatic v.a (I)I
      // 444: iastore
      // 445: iinc 3 1
      // 448: iload 6
      // 44a: ifne 45c
      // 44d: goto 451
      // 450: athrow
      // 451: iload 6
      // 453: ifeq 42f
      // 456: goto 45a
      // 459: athrow
      // 45a: bipush 0
      // 45b: istore 3
      // 45c: iload 3
      // 45d: bipush -1
      // 45e: ixor
      // 45f: getstatic la.d I
      // 462: bipush -1
      // 463: ixor
      // 464: if_icmple 487
      // 467: getstatic jb.k [I
      // 46a: iload 3
      // 46b: sipush -30504
      // 46e: invokestatic v.a (I)I
      // 471: iastore
      // 472: iinc 3 1
      // 475: iload 6
      // 477: ifne 489
      // 47a: goto 47e
      // 47d: athrow
      // 47e: iload 6
      // 480: ifeq 45c
      // 483: goto 487
      // 486: athrow
      // 487: bipush 0
      // 488: istore 3
      // 489: getstatic la.d I
      // 48c: iload 3
      // 48d: if_icmple 4b0
      // 490: getstatic o.a [I
      // 493: iload 3
      // 494: sipush -30504
      // 497: invokestatic v.a (I)I
      // 49a: iastore
      // 49b: iinc 3 1
      // 49e: iload 6
      // 4a0: ifne 4b2
      // 4a3: goto 4a7
      // 4a6: athrow
      // 4a7: iload 6
      // 4a9: ifeq 489
      // 4ac: goto 4b0
      // 4af: athrow
      // 4b0: bipush 0
      // 4b1: istore 3
      // 4b2: getstatic la.d I
      // 4b5: bipush -1
      // 4b6: ixor
      // 4b7: iload 3
      // 4b8: bipush -1
      // 4b9: ixor
      // 4ba: if_icmpge 509
      // 4bd: bipush 0
      // 4be: iload 6
      // 4c0: ifne 50a
      // 4c3: istore 4
      // 4c5: iload 4
      // 4c7: bipush 12
      // 4c9: if_icmpge 501
      // 4cc: getstatic qb.d [[I
      // 4cf: iload 3
      // 4d0: aaload
      // 4d1: iload 4
      // 4d3: sipush -30504
      // 4d6: invokestatic v.a (I)I
      // 4d9: iastore
      // 4da: getstatic qb.d [[I
      // 4dd: iload 3
      // 4de: aaload
      // 4df: iload 4
      // 4e1: iaload
      // 4e2: sipush 255
      // 4e5: iload 6
      // 4e7: ifne 4ba
      // 4ea: if_icmpeq 4f0
      // 4ed: goto 4f9
      // 4f0: getstatic qb.d [[I
      // 4f3: iload 3
      // 4f4: aaload
      // 4f5: iload 4
      // 4f7: bipush -1
      // 4f8: iastore
      // 4f9: iinc 4 1
      // 4fc: iload 6
      // 4fe: ifeq 4c5
      // 501: iinc 3 1
      // 504: iload 6
      // 506: ifeq 4b2
      // 509: bipush 0
      // 50a: istore 3
      // 50b: iload 3
      // 50c: getstatic la.d I
      // 50f: if_icmpge 52d
      // 512: getstatic da.T [I
      // 515: iload 3
      // 516: bipush -105
      // 518: invokestatic ub.a (B)I
      // 51b: iastore
      // 51c: iinc 3 1
      // 51f: iload 6
      // 521: ifne 52f
      // 524: iload 6
      // 526: ifeq 50b
      // 529: goto 52d
      // 52c: athrow
      // 52d: bipush 0
      // 52e: istore 3
      // 52f: iload 3
      // 530: bipush -1
      // 531: ixor
      // 532: getstatic la.d I
      // 535: bipush -1
      // 536: ixor
      // 537: if_icmple 559
      // 53a: getstatic m.g [I
      // 53d: iload 3
      // 53e: bipush -105
      // 540: invokestatic ub.a (B)I
      // 543: iastore
      // 544: iinc 3 1
      // 547: iload 6
      // 549: ifne 55b
      // 54c: goto 550
      // 54f: athrow
      // 550: iload 6
      // 552: ifeq 52f
      // 555: goto 559
      // 558: athrow
      // 559: bipush 0
      // 55a: istore 3
      // 55b: iload 3
      // 55c: bipush -1
      // 55d: ixor
      // 55e: getstatic la.d I
      // 561: bipush -1
      // 562: ixor
      // 563: if_icmple 585
      // 566: getstatic ua.Ab [I
      // 569: iload 3
      // 56a: bipush -105
      // 56c: invokestatic ub.a (B)I
      // 56f: iastore
      // 570: iinc 3 1
      // 573: iload 6
      // 575: ifne 58c
      // 578: goto 57c
      // 57b: athrow
      // 57c: iload 6
      // 57e: ifeq 55b
      // 581: goto 585
      // 584: athrow
      // 585: iload 1
      // 586: bipush 10
      // 588: if_icmpge 58c
      // 58b: return
      // 58c: bipush 0
      // 58d: istore 3
      // 58e: getstatic la.d I
      // 591: iload 3
      // 592: if_icmple 5b0
      // 595: getstatic v.e [I
      // 598: iload 3
      // 599: bipush -105
      // 59b: invokestatic ub.a (B)I
      // 59e: iastore
      // 59f: iinc 3 1
      // 5a2: iload 6
      // 5a4: ifne 5b2
      // 5a7: iload 6
      // 5a9: ifeq 58e
      // 5ac: goto 5b0
      // 5af: athrow
      // 5b0: bipush 0
      // 5b1: istore 3
      // 5b2: iload 3
      // 5b3: bipush -1
      // 5b4: ixor
      // 5b5: getstatic la.d I
      // 5b8: bipush -1
      // 5b9: ixor
      // 5ba: if_icmple 5dc
      // 5bd: getstatic fb.c [I
      // 5c0: iload 3
      // 5c1: ldc 65525
      // 5c3: invokestatic t.a (I)I
      // 5c6: iastore
      // 5c7: iinc 3 1
      // 5ca: iload 6
      // 5cc: ifne 5de
      // 5cf: goto 5d3
      // 5d2: athrow
      // 5d3: iload 6
      // 5d5: ifeq 5b2
      // 5d8: goto 5dc
      // 5db: athrow
      // 5dc: bipush 0
      // 5dd: istore 3
      // 5de: iload 3
      // 5df: bipush -1
      // 5e0: ixor
      // 5e1: getstatic la.d I
      // 5e4: bipush -1
      // 5e5: ixor
      // 5e6: if_icmple 608
      // 5e9: getstatic b.h [I
      // 5ec: iload 3
      // 5ed: ldc 65525
      // 5ef: invokestatic t.a (I)I
      // 5f2: iastore
      // 5f3: iinc 3 1
      // 5f6: iload 6
      // 5f8: ifne 60a
      // 5fb: goto 5ff
      // 5fe: athrow
      // 5ff: iload 6
      // 601: ifeq 5de
      // 604: goto 608
      // 607: athrow
      // 608: bipush 0
      // 609: istore 3
      // 60a: iload 3
      // 60b: bipush -1
      // 60c: ixor
      // 60d: getstatic la.d I
      // 610: bipush -1
      // 611: ixor
      // 612: if_icmple 635
      // 615: getstatic ob.h [I
      // 618: iload 3
      // 619: sipush -30504
      // 61c: invokestatic v.a (I)I
      // 61f: iastore
      // 620: iinc 3 1
      // 623: iload 6
      // 625: ifne 637
      // 628: goto 62c
      // 62b: athrow
      // 62c: iload 6
      // 62e: ifeq 60a
      // 631: goto 635
      // 634: athrow
      // 635: bipush 0
      // 636: istore 3
      // 637: iload 3
      // 638: bipush -1
      // 639: ixor
      // 63a: getstatic la.d I
      // 63d: bipush -1
      // 63e: ixor
      // 63f: if_icmple 662
      // 642: getstatic na.a [I
      // 645: iload 3
      // 646: sipush -30504
      // 649: invokestatic v.a (I)I
      // 64c: iastore
      // 64d: iinc 3 1
      // 650: iload 6
      // 652: ifne 664
      // 655: goto 659
      // 658: athrow
      // 659: iload 6
      // 65b: ifeq 637
      // 65e: goto 662
      // 661: athrow
      // 662: bipush 0
      // 663: istore 3
      // 664: iload 3
      // 665: getstatic la.d I
      // 668: if_icmpge 68b
      // 66b: getstatic db.j [I
      // 66e: iload 3
      // 66f: sipush -30504
      // 672: invokestatic v.a (I)I
      // 675: iastore
      // 676: iinc 3 1
      // 679: iload 6
      // 67b: ifne 68d
      // 67e: goto 682
      // 681: athrow
      // 682: iload 6
      // 684: ifeq 664
      // 687: goto 68b
      // 68a: athrow
      // 68b: bipush 0
      // 68c: istore 3
      // 68d: iload 3
      // 68e: getstatic la.d I
      // 691: if_icmpge 6b3
      // 694: getstatic p.e [Ljava/lang/String;
      // 697: iload 3
      // 698: bipush 38
      // 69a: invokestatic o.a (B)Ljava/lang/String;
      // 69d: aastore
      // 69e: iinc 3 1
      // 6a1: iload 6
      // 6a3: ifne 6cd
      // 6a6: goto 6aa
      // 6a9: athrow
      // 6aa: iload 6
      // 6ac: ifeq 68d
      // 6af: goto 6b3
      // 6b2: athrow
      // 6b3: ldc 65525
      // 6b5: invokestatic t.a (I)I
      // 6b8: putstatic jb.o I
      // 6bb: getstatic jb.o I
      // 6be: anewarray 152
      // 6c1: putstatic p.c [Ljava/lang/String;
      // 6c4: getstatic jb.o I
      // 6c7: anewarray 152
      // 6ca: putstatic mb.g [Ljava/lang/String;
      // 6cd: bipush 0
      // 6ce: istore 3
      // 6cf: iload 3
      // 6d0: getstatic jb.o I
      // 6d3: if_icmpge 6f1
      // 6d6: getstatic mb.g [Ljava/lang/String;
      // 6d9: iload 3
      // 6da: bipush 38
      // 6dc: invokestatic o.a (B)Ljava/lang/String;
      // 6df: aastore
      // 6e0: iinc 3 1
      // 6e3: iload 6
      // 6e5: ifne 6f3
      // 6e8: iload 6
      // 6ea: ifeq 6cf
      // 6ed: goto 6f1
      // 6f0: athrow
      // 6f1: bipush 0
      // 6f2: istore 3
      // 6f3: getstatic jb.o I
      // 6f6: iload 3
      // 6f7: if_icmple 719
      // 6fa: getstatic p.c [Ljava/lang/String;
      // 6fd: iload 3
      // 6fe: bipush 38
      // 700: invokestatic o.a (B)Ljava/lang/String;
      // 703: aastore
      // 704: iinc 3 1
      // 707: iload 6
      // 709: ifne 752
      // 70c: goto 710
      // 70f: athrow
      // 710: iload 6
      // 712: ifeq 6f3
      // 715: goto 719
      // 718: athrow
      // 719: ldc 65525
      // 71b: invokestatic t.a (I)I
      // 71e: putstatic na.e I
      // 721: getstatic na.e I
      // 724: newarray 10
      // 726: putstatic aa.c [I
      // 729: getstatic na.e I
      // 72c: anewarray 152
      // 72f: putstatic cb.e [Ljava/lang/String;
      // 732: getstatic na.e I
      // 735: newarray 10
      // 737: putstatic nb.d [I
      // 73a: getstatic na.e I
      // 73d: newarray 10
      // 73f: putstatic n.m [I
      // 742: getstatic na.e I
      // 745: newarray 10
      // 747: putstatic w.g [I
      // 74a: getstatic na.e I
      // 74d: newarray 10
      // 74f: putstatic db.l [I
      // 752: bipush 0
      // 753: istore 3
      // 754: iload 3
      // 755: getstatic na.e I
      // 758: if_icmpge 776
      // 75b: getstatic cb.e [Ljava/lang/String;
      // 75e: iload 3
      // 75f: bipush 38
      // 761: invokestatic o.a (B)Ljava/lang/String;
      // 764: aastore
      // 765: iinc 3 1
      // 768: iload 6
      // 76a: ifne 778
      // 76d: iload 6
      // 76f: ifeq 754
      // 772: goto 776
      // 775: athrow
      // 776: bipush 0
      // 777: istore 3
      // 778: iload 3
      // 779: bipush -1
      // 77a: ixor
      // 77b: getstatic na.e I
      // 77e: bipush -1
      // 77f: ixor
      // 780: if_icmple 7a2
      // 783: getstatic db.l [I
      // 786: iload 3
      // 787: bipush -105
      // 789: invokestatic ub.a (B)I
      // 78c: iastore
      // 78d: iinc 3 1
      // 790: iload 6
      // 792: ifne 7a4
      // 795: goto 799
      // 798: athrow
      // 799: iload 6
      // 79b: ifeq 778
      // 79e: goto 7a2
      // 7a1: athrow
      // 7a2: bipush 0
      // 7a3: istore 3
      // 7a4: getstatic na.e I
      // 7a7: bipush -1
      // 7a8: ixor
      // 7a9: iload 3
      // 7aa: bipush -1
      // 7ab: ixor
      // 7ac: if_icmpge 7cf
      // 7af: getstatic n.m [I
      // 7b2: iload 3
      // 7b3: sipush -30504
      // 7b6: invokestatic v.a (I)I
      // 7b9: iastore
      // 7ba: iinc 3 1
      // 7bd: iload 6
      // 7bf: ifne 7d1
      // 7c2: goto 7c6
      // 7c5: athrow
      // 7c6: iload 6
      // 7c8: ifeq 7a4
      // 7cb: goto 7cf
      // 7ce: athrow
      // 7cf: bipush 0
      // 7d0: istore 3
      // 7d1: iload 3
      // 7d2: getstatic na.e I
      // 7d5: if_icmpge 7f8
      // 7d8: getstatic nb.d [I
      // 7db: iload 3
      // 7dc: sipush -30504
      // 7df: invokestatic v.a (I)I
      // 7e2: iastore
      // 7e3: iinc 3 1
      // 7e6: iload 6
      // 7e8: ifne 7fa
      // 7eb: goto 7ef
      // 7ee: athrow
      // 7ef: iload 6
      // 7f1: ifeq 7d1
      // 7f4: goto 7f8
      // 7f7: athrow
      // 7f8: bipush 0
      // 7f9: istore 3
      // 7fa: iload 3
      // 7fb: bipush -1
      // 7fc: ixor
      // 7fd: getstatic na.e I
      // 800: bipush -1
      // 801: ixor
      // 802: if_icmple 825
      // 805: getstatic aa.c [I
      // 808: iload 3
      // 809: sipush -30504
      // 80c: invokestatic v.a (I)I
      // 80f: iastore
      // 810: iinc 3 1
      // 813: iload 6
      // 815: ifne 827
      // 818: goto 81c
      // 81b: athrow
      // 81c: iload 6
      // 81e: ifeq 7fa
      // 821: goto 825
      // 824: athrow
      // 825: bipush 0
      // 826: istore 3
      // 827: getstatic na.e I
      // 82a: iload 3
      // 82b: if_icmple 84e
      // 82e: getstatic w.g [I
      // 831: iload 3
      // 832: sipush -30504
      // 835: invokestatic v.a (I)I
      // 838: iastore
      // 839: iinc 3 1
      // 83c: iload 6
      // 83e: ifne 8a2
      // 841: goto 845
      // 844: athrow
      // 845: iload 6
      // 847: ifeq 827
      // 84a: goto 84e
      // 84d: athrow
      // 84e: ldc 65525
      // 850: invokestatic t.a (I)I
      // 853: putstatic ua.Db I
      // 856: getstatic ua.Db I
      // 859: newarray 10
      // 85b: putstatic mb.a [I
      // 85e: getstatic ua.Db I
      // 861: newarray 10
      // 863: putstatic ub.g [I
      // 866: getstatic ua.Db I
      // 869: anewarray 152
      // 86c: putstatic la.f [Ljava/lang/String;
      // 86f: getstatic ua.Db I
      // 872: anewarray 152
      // 875: putstatic l.a [Ljava/lang/String;
      // 878: getstatic ua.Db I
      // 87b: newarray 10
      // 87d: putstatic f.f [I
      // 880: getstatic ua.Db I
      // 883: anewarray 152
      // 886: putstatic p.a [Ljava/lang/String;
      // 889: getstatic ua.Db I
      // 88c: anewarray 152
      // 88f: putstatic s.f [Ljava/lang/String;
      // 892: getstatic ua.Db I
      // 895: newarray 10
      // 897: putstatic fb.f [I
      // 89a: getstatic ua.Db I
      // 89d: newarray 10
      // 89f: putstatic h.b [I
      // 8a2: bipush 0
      // 8a3: istore 3
      // 8a4: getstatic ua.Db I
      // 8a7: bipush -1
      // 8a8: ixor
      // 8a9: iload 3
      // 8aa: bipush -1
      // 8ab: ixor
      // 8ac: if_icmpge 8ca
      // 8af: getstatic l.a [Ljava/lang/String;
      // 8b2: iload 3
      // 8b3: bipush 38
      // 8b5: invokestatic o.a (B)Ljava/lang/String;
      // 8b8: aastore
      // 8b9: iinc 3 1
      // 8bc: iload 6
      // 8be: ifne 8cc
      // 8c1: iload 6
      // 8c3: ifeq 8a4
      // 8c6: goto 8ca
      // 8c9: athrow
      // 8ca: bipush 0
      // 8cb: istore 3
      // 8cc: iload 3
      // 8cd: getstatic ua.Db I
      // 8d0: if_icmpge 8f2
      // 8d3: getstatic la.f [Ljava/lang/String;
      // 8d6: iload 3
      // 8d7: bipush 38
      // 8d9: invokestatic o.a (B)Ljava/lang/String;
      // 8dc: aastore
      // 8dd: iinc 3 1
      // 8e0: iload 6
      // 8e2: ifne 8f4
      // 8e5: goto 8e9
      // 8e8: athrow
      // 8e9: iload 6
      // 8eb: ifeq 8cc
      // 8ee: goto 8f2
      // 8f1: athrow
      // 8f2: bipush 0
      // 8f3: istore 3
      // 8f4: iload 3
      // 8f5: bipush -1
      // 8f6: ixor
      // 8f7: getstatic ua.Db I
      // 8fa: bipush -1
      // 8fb: ixor
      // 8fc: if_icmple 91e
      // 8ff: getstatic s.f [Ljava/lang/String;
      // 902: iload 3
      // 903: bipush 38
      // 905: invokestatic o.a (B)Ljava/lang/String;
      // 908: aastore
      // 909: iinc 3 1
      // 90c: iload 6
      // 90e: ifne 920
      // 911: goto 915
      // 914: athrow
      // 915: iload 6
      // 917: ifeq 8f4
      // 91a: goto 91e
      // 91d: athrow
      // 91e: bipush 0
      // 91f: istore 3
      // 920: getstatic ua.Db I
      // 923: bipush -1
      // 924: ixor
      // 925: iload 3
      // 926: bipush -1
      // 927: ixor
      // 928: if_icmpge 94a
      // 92b: getstatic p.a [Ljava/lang/String;
      // 92e: iload 3
      // 92f: bipush 38
      // 931: invokestatic o.a (B)Ljava/lang/String;
      // 934: aastore
      // 935: iinc 3 1
      // 938: iload 6
      // 93a: ifne 94c
      // 93d: goto 941
      // 940: athrow
      // 941: iload 6
      // 943: ifeq 920
      // 946: goto 94a
      // 949: athrow
      // 94a: bipush 0
      // 94b: istore 3
      // 94c: iload 3
      // 94d: getstatic ua.Db I
      // 950: if_icmpge 977
      // 953: getstatic fb.f [I
      // 956: iload 3
      // 957: bipush 91
      // 959: bipush 38
      // 95b: invokestatic o.a (B)Ljava/lang/String;
      // 95e: invokestatic ca.a (BLjava/lang/String;)I
      // 961: iastore
      // 962: iinc 3 1
      // 965: iload 6
      // 967: ifne 979
      // 96a: goto 96e
      // 96d: athrow
      // 96e: iload 6
      // 970: ifeq 94c
      // 973: goto 977
      // 976: athrow
      // 977: bipush 0
      // 978: istore 3
      // 979: iload 3
      // 97a: bipush -1
      // 97b: ixor
      // 97c: getstatic ua.Db I
      // 97f: bipush -1
      // 980: ixor
      // 981: if_icmple 9a4
      // 984: getstatic f.f [I
      // 987: iload 3
      // 988: sipush -30504
      // 98b: invokestatic v.a (I)I
      // 98e: iastore
      // 98f: iinc 3 1
      // 992: iload 6
      // 994: ifne 9a6
      // 997: goto 99b
      // 99a: athrow
      // 99b: iload 6
      // 99d: ifeq 979
      // 9a0: goto 9a4
      // 9a3: athrow
      // 9a4: bipush 0
      // 9a5: istore 3
      // 9a6: getstatic ua.Db I
      // 9a9: bipush -1
      // 9aa: ixor
      // 9ab: iload 3
      // 9ac: bipush -1
      // 9ad: ixor
      // 9ae: if_icmpge 9d1
      // 9b1: getstatic ub.g [I
      // 9b4: iload 3
      // 9b5: sipush -30504
      // 9b8: invokestatic v.a (I)I
      // 9bb: iastore
      // 9bc: iinc 3 1
      // 9bf: iload 6
      // 9c1: ifne 9d3
      // 9c4: goto 9c8
      // 9c7: athrow
      // 9c8: iload 6
      // 9ca: ifeq 9a6
      // 9cd: goto 9d1
      // 9d0: athrow
      // 9d1: bipush 0
      // 9d2: istore 3
      // 9d3: getstatic ua.Db I
      // 9d6: bipush -1
      // 9d7: ixor
      // 9d8: iload 3
      // 9d9: bipush -1
      // 9da: ixor
      // 9db: if_icmpge 9fe
      // 9de: getstatic mb.a [I
      // 9e1: iload 3
      // 9e2: sipush -30504
      // 9e5: invokestatic v.a (I)I
      // 9e8: iastore
      // 9e9: iinc 3 1
      // 9ec: iload 6
      // 9ee: ifne a00
      // 9f1: goto 9f5
      // 9f4: athrow
      // 9f5: iload 6
      // 9f7: ifeq 9d3
      // 9fa: goto 9fe
      // 9fd: athrow
      // 9fe: bipush 0
      // 9ff: istore 3
      // a00: iload 3
      // a01: bipush -1
      // a02: ixor
      // a03: getstatic ua.Db I
      // a06: bipush -1
      // a07: ixor
      // a08: if_icmple a2b
      // a0b: getstatic h.b [I
      // a0e: iload 3
      // a0f: sipush -30504
      // a12: invokestatic v.a (I)I
      // a15: iastore
      // a16: iinc 3 1
      // a19: iload 6
      // a1b: ifne a7f
      // a1e: goto a22
      // a21: athrow
      // a22: iload 6
      // a24: ifeq a00
      // a27: goto a2b
      // a2a: athrow
      // a2b: ldc 65525
      // a2d: invokestatic t.a (I)I
      // a30: putstatic h.a I
      // a33: getstatic h.a I
      // a36: anewarray 152
      // a39: putstatic u.b [Ljava/lang/String;
      // a3c: getstatic h.a I
      // a3f: newarray 10
      // a41: putstatic u.a [I
      // a44: getstatic h.a I
      // a47: newarray 10
      // a49: putstatic v.a [I
      // a4c: getstatic h.a I
      // a4f: anewarray 152
      // a52: putstatic f.e [Ljava/lang/String;
      // a55: getstatic h.a I
      // a58: newarray 10
      // a5a: putstatic client.Jk [I
      // a5d: getstatic h.a I
      // a60: newarray 10
      // a62: putstatic lb.Tb [I
      // a65: getstatic h.a I
      // a68: anewarray 152
      // a6b: putstatic ub.b [Ljava/lang/String;
      // a6e: getstatic h.a I
      // a71: anewarray 152
      // a74: putstatic ta.r [Ljava/lang/String;
      // a77: getstatic h.a I
      // a7a: newarray 10
      // a7c: putstatic ib.d [I
      // a7f: bipush 0
      // a80: istore 3
      // a81: getstatic h.a I
      // a84: iload 3
      // a85: if_icmple aa3
      // a88: getstatic ta.r [Ljava/lang/String;
      // a8b: iload 3
      // a8c: bipush 38
      // a8e: invokestatic o.a (B)Ljava/lang/String;
      // a91: aastore
      // a92: iinc 3 1
      // a95: iload 6
      // a97: ifne aa5
      // a9a: iload 6
      // a9c: ifeq a81
      // a9f: goto aa3
      // aa2: athrow
      // aa3: bipush 0
      // aa4: istore 3
      // aa5: iload 3
      // aa6: bipush -1
      // aa7: ixor
      // aa8: getstatic h.a I
      // aab: bipush -1
      // aac: ixor
      // aad: if_icmple acf
      // ab0: getstatic ub.b [Ljava/lang/String;
      // ab3: iload 3
      // ab4: bipush 38
      // ab6: invokestatic o.a (B)Ljava/lang/String;
      // ab9: aastore
      // aba: iinc 3 1
      // abd: iload 6
      // abf: ifne ad1
      // ac2: goto ac6
      // ac5: athrow
      // ac6: iload 6
      // ac8: ifeq aa5
      // acb: goto acf
      // ace: athrow
      // acf: bipush 0
      // ad0: istore 3
      // ad1: getstatic h.a I
      // ad4: bipush -1
      // ad5: ixor
      // ad6: iload 3
      // ad7: bipush -1
      // ad8: ixor
      // ad9: if_icmpge afb
      // adc: getstatic u.b [Ljava/lang/String;
      // adf: iload 3
      // ae0: bipush 38
      // ae2: invokestatic o.a (B)Ljava/lang/String;
      // ae5: aastore
      // ae6: iinc 3 1
      // ae9: iload 6
      // aeb: ifne afd
      // aee: goto af2
      // af1: athrow
      // af2: iload 6
      // af4: ifeq ad1
      // af7: goto afb
      // afa: athrow
      // afb: bipush 0
      // afc: istore 3
      // afd: getstatic h.a I
      // b00: bipush -1
      // b01: ixor
      // b02: iload 3
      // b03: bipush -1
      // b04: ixor
      // b05: if_icmpge b27
      // b08: getstatic f.e [Ljava/lang/String;
      // b0b: iload 3
      // b0c: bipush 38
      // b0e: invokestatic o.a (B)Ljava/lang/String;
      // b11: aastore
      // b12: iinc 3 1
      // b15: iload 6
      // b17: ifne b29
      // b1a: goto b1e
      // b1d: athrow
      // b1e: iload 6
      // b20: ifeq afd
      // b23: goto b27
      // b26: athrow
      // b27: bipush 0
      // b28: istore 3
      // b29: iload 3
      // b2a: getstatic h.a I
      // b2d: if_icmpge b4f
      // b30: getstatic ib.d [I
      // b33: iload 3
      // b34: ldc 65525
      // b36: invokestatic t.a (I)I
      // b39: iastore
      // b3a: iinc 3 1
      // b3d: iload 6
      // b3f: ifne b51
      // b42: goto b46
      // b45: athrow
      // b46: iload 6
      // b48: ifeq b29
      // b4b: goto b4f
      // b4e: athrow
      // b4f: bipush 0
      // b50: istore 3
      // b51: getstatic h.a I
      // b54: bipush -1
      // b55: ixor
      // b56: iload 3
      // b57: bipush -1
      // b58: ixor
      // b59: if_icmpge b7b
      // b5c: getstatic v.a [I
      // b5f: iload 3
      // b60: bipush -105
      // b62: invokestatic ub.a (B)I
      // b65: iastore
      // b66: iinc 3 1
      // b69: iload 6
      // b6b: ifne b7d
      // b6e: goto b72
      // b71: athrow
      // b72: iload 6
      // b74: ifeq b51
      // b77: goto b7b
      // b7a: athrow
      // b7b: bipush 0
      // b7c: istore 3
      // b7d: iload 3
      // b7e: getstatic h.a I
      // b81: if_icmpge ba3
      // b84: getstatic client.Jk [I
      // b87: iload 3
      // b88: bipush -105
      // b8a: invokestatic ub.a (B)I
      // b8d: iastore
      // b8e: iinc 3 1
      // b91: iload 6
      // b93: ifne ba5
      // b96: goto b9a
      // b99: athrow
      // b9a: iload 6
      // b9c: ifeq b7d
      // b9f: goto ba3
      // ba2: athrow
      // ba3: bipush 0
      // ba4: istore 3
      // ba5: getstatic h.a I
      // ba8: bipush -1
      // ba9: ixor
      // baa: iload 3
      // bab: bipush -1
      // bac: ixor
      // bad: if_icmpge bd0
      // bb0: getstatic u.a [I
      // bb3: iload 3
      // bb4: sipush -30504
      // bb7: invokestatic v.a (I)I
      // bba: iastore
      // bbb: iinc 3 1
      // bbe: iload 6
      // bc0: ifne bd2
      // bc3: goto bc7
      // bc6: athrow
      // bc7: iload 6
      // bc9: ifeq ba5
      // bcc: goto bd0
      // bcf: athrow
      // bd0: bipush 0
      // bd1: istore 3
      // bd2: iload 3
      // bd3: bipush -1
      // bd4: ixor
      // bd5: getstatic h.a I
      // bd8: bipush -1
      // bd9: ixor
      // bda: if_icmple bfd
      // bdd: getstatic lb.Tb [I
      // be0: iload 3
      // be1: sipush -30504
      // be4: invokestatic v.a (I)I
      // be7: iastore
      // be8: iinc 3 1
      // beb: iload 6
      // bed: ifne c15
      // bf0: goto bf4
      // bf3: athrow
      // bf4: iload 6
      // bf6: ifeq bd2
      // bf9: goto bfd
      // bfc: athrow
      // bfd: ldc 65525
      // bff: invokestatic t.a (I)I
      // c02: putstatic v.h I
      // c05: getstatic v.h I
      // c08: newarray 10
      // c0a: putstatic d.g [I
      // c0d: getstatic v.h I
      // c10: newarray 10
      // c12: putstatic i.g [I
      // c15: bipush 0
      // c16: istore 3
      // c17: iload 3
      // c18: bipush -1
      // c19: ixor
      // c1a: getstatic v.h I
      // c1d: bipush -1
      // c1e: ixor
      // c1f: if_icmple c3e
      // c22: getstatic i.g [I
      // c25: iload 3
      // c26: sipush -30504
      // c29: invokestatic v.a (I)I
      // c2c: iastore
      // c2d: iinc 3 1
      // c30: iload 6
      // c32: ifne c40
      // c35: iload 6
      // c37: ifeq c17
      // c3a: goto c3e
      // c3d: athrow
      // c3e: bipush 0
      // c3f: istore 3
      // c40: getstatic v.h I
      // c43: bipush -1
      // c44: ixor
      // c45: iload 3
      // c46: bipush -1
      // c47: ixor
      // c48: if_icmpge c6b
      // c4b: getstatic d.g [I
      // c4e: iload 3
      // c4f: sipush -30504
      // c52: invokestatic v.a (I)I
      // c55: iastore
      // c56: iinc 3 1
      // c59: iload 6
      // c5b: ifne c8b
      // c5e: goto c62
      // c61: athrow
      // c62: iload 6
      // c64: ifeq c40
      // c67: goto c6b
      // c6a: athrow
      // c6b: ldc 65525
      // c6d: invokestatic t.a (I)I
      // c70: putstatic ia.h I
      // c73: getstatic ia.h I
      // c76: newarray 10
      // c78: putstatic da.N [I
      // c7b: getstatic ia.h I
      // c7e: newarray 10
      // c80: putstatic ac.l [I
      // c83: getstatic ia.h I
      // c86: newarray 10
      // c88: putstatic qa.K [I
      // c8b: bipush 0
      // c8c: istore 3
      // c8d: getstatic ia.h I
      // c90: iload 3
      // c91: if_icmple caf
      // c94: getstatic qa.K [I
      // c97: iload 3
      // c98: bipush -105
      // c9a: invokestatic ub.a (B)I
      // c9d: iastore
      // c9e: iinc 3 1
      // ca1: iload 6
      // ca3: ifne cb1
      // ca6: iload 6
      // ca8: ifeq c8d
      // cab: goto caf
      // cae: athrow
      // caf: bipush 0
      // cb0: istore 3
      // cb1: iload 3
      // cb2: bipush -1
      // cb3: ixor
      // cb4: getstatic ia.h I
      // cb7: bipush -1
      // cb8: ixor
      // cb9: if_icmple cdc
      // cbc: getstatic da.N [I
      // cbf: iload 3
      // cc0: sipush -30504
      // cc3: invokestatic v.a (I)I
      // cc6: iastore
      // cc7: iinc 3 1
      // cca: iload 6
      // ccc: ifne cde
      // ccf: goto cd3
      // cd2: athrow
      // cd3: iload 6
      // cd5: ifeq cb1
      // cd8: goto cdc
      // cdb: athrow
      // cdc: bipush 0
      // cdd: istore 3
      // cde: iload 3
      // cdf: getstatic ia.h I
      // ce2: if_icmpge d05
      // ce5: getstatic ac.l [I
      // ce8: iload 3
      // ce9: sipush -30504
      // cec: invokestatic v.a (I)I
      // cef: iastore
      // cf0: iinc 3 1
      // cf3: iload 6
      // cf5: ifne d51
      // cf8: goto cfc
      // cfb: athrow
      // cfc: iload 6
      // cfe: ifeq cde
      // d01: goto d05
      // d04: athrow
      // d05: ldc 65525
      // d07: invokestatic t.a (I)I
      // d0a: putstatic n.c I
      // d0d: ldc 65525
      // d0f: invokestatic t.a (I)I
      // d12: putstatic fa.b I
      // d15: getstatic fa.b I
      // d18: anewarray 124
      // d1b: putstatic oa.d [[I
      // d1e: getstatic fa.b I
      // d21: newarray 10
      // d23: putstatic qb.e [I
      // d26: getstatic fa.b I
      // d29: anewarray 124
      // d2c: putstatic da.J [[I
      // d2f: getstatic fa.b I
      // d32: anewarray 152
      // d35: putstatic ja.L [Ljava/lang/String;
      // d38: getstatic fa.b I
      // d3b: anewarray 152
      // d3e: putstatic oa.a [Ljava/lang/String;
      // d41: getstatic fa.b I
      // d44: newarray 10
      // d46: putstatic pa.f [I
      // d49: getstatic fa.b I
      // d4c: newarray 10
      // d4e: putstatic o.p [I
      // d51: bipush 0
      // d52: istore 3
      // d53: iload 3
      // d54: bipush -1
      // d55: ixor
      // d56: getstatic fa.b I
      // d59: bipush -1
      // d5a: ixor
      // d5b: if_icmple d79
      // d5e: getstatic ja.L [Ljava/lang/String;
      // d61: iload 3
      // d62: bipush 38
      // d64: invokestatic o.a (B)Ljava/lang/String;
      // d67: aastore
      // d68: iinc 3 1
      // d6b: iload 6
      // d6d: ifne d7b
      // d70: iload 6
      // d72: ifeq d53
      // d75: goto d79
      // d78: athrow
      // d79: bipush 0
      // d7a: istore 3
      // d7b: getstatic fa.b I
      // d7e: iload 3
      // d7f: if_icmple da1
      // d82: getstatic oa.a [Ljava/lang/String;
      // d85: iload 3
      // d86: bipush 38
      // d88: invokestatic o.a (B)Ljava/lang/String;
      // d8b: aastore
      // d8c: iinc 3 1
      // d8f: iload 6
      // d91: ifne da3
      // d94: goto d98
      // d97: athrow
      // d98: iload 6
      // d9a: ifeq d7b
      // d9d: goto da1
      // da0: athrow
      // da1: bipush 0
      // da2: istore 3
      // da3: getstatic fa.b I
      // da6: iload 3
      // da7: if_icmple dca
      // daa: getstatic pa.f [I
      // dad: iload 3
      // dae: sipush -30504
      // db1: invokestatic v.a (I)I
      // db4: iastore
      // db5: iinc 3 1
      // db8: iload 6
      // dba: ifne dcc
      // dbd: goto dc1
      // dc0: athrow
      // dc1: iload 6
      // dc3: ifeq da3
      // dc6: goto dca
      // dc9: athrow
      // dca: bipush 0
      // dcb: istore 3
      // dcc: iload 3
      // dcd: getstatic fa.b I
      // dd0: if_icmpge df3
      // dd3: getstatic o.p [I
      // dd6: iload 3
      // dd7: sipush -30504
      // dda: invokestatic v.a (I)I
      // ddd: iastore
      // dde: iinc 3 1
      // de1: iload 6
      // de3: ifne df5
      // de6: goto dea
      // de9: athrow
      // dea: iload 6
      // dec: ifeq dcc
      // def: goto df3
      // df2: athrow
      // df3: bipush 0
      // df4: istore 3
      // df5: getstatic fa.b I
      // df8: bipush -1
      // df9: ixor
      // dfa: iload 3
      // dfb: bipush -1
      // dfc: ixor
      // dfd: if_icmpge e20
      // e00: getstatic qb.e [I
      // e03: iload 3
      // e04: sipush -30504
      // e07: invokestatic v.a (I)I
      // e0a: iastore
      // e0b: iinc 3 1
      // e0e: iload 6
      // e10: ifne e22
      // e13: goto e17
      // e16: athrow
      // e17: iload 6
      // e19: ifeq df5
      // e1c: goto e20
      // e1f: athrow
      // e20: bipush 0
      // e21: istore 3
      // e22: iload 3
      // e23: getstatic fa.b I
      // e26: if_icmpge e73
      // e29: sipush -30504
      // e2c: invokestatic v.a (I)I
      // e2f: istore 4
      // e31: getstatic oa.d [[I
      // e34: iload 3
      // e35: iload 4
      // e37: newarray 10
      // e39: aastore
      // e3a: bipush 0
      // e3b: iload 6
      // e3d: ifne e74
      // e40: istore 5
      // e42: iload 4
      // e44: bipush -1
      // e45: ixor
      // e46: iload 5
      // e48: bipush -1
      // e49: ixor
      // e4a: if_icmpge e6b
      // e4d: getstatic oa.d [[I
      // e50: iload 3
      // e51: aaload
      // e52: iload 5
      // e54: ldc 65525
      // e56: invokestatic t.a (I)I
      // e59: iastore
      // e5a: iinc 5 1
      // e5d: iload 6
      // e5f: ifne e6e
      // e62: iload 6
      // e64: ifeq e42
      // e67: goto e6b
      // e6a: athrow
      // e6b: iinc 3 1
      // e6e: iload 6
      // e70: ifeq e22
      // e73: bipush 0
      // e74: istore 3
      // e75: iload 3
      // e76: getstatic fa.b I
      // e79: if_icmpge ec7
      // e7c: sipush -30504
      // e7f: invokestatic v.a (I)I
      // e82: istore 4
      // e84: getstatic da.J [[I
      // e87: iload 3
      // e88: iload 4
      // e8a: newarray 10
      // e8c: aastore
      // e8d: bipush 0
      // e8e: iload 6
      // e90: ifne ef2
      // e93: istore 5
      // e95: iload 5
      // e97: bipush -1
      // e98: ixor
      // e99: iload 4
      // e9b: bipush -1
      // e9c: ixor
      // e9d: if_icmple ebf
      // ea0: getstatic da.J [[I
      // ea3: iload 3
      // ea4: aaload
      // ea5: iload 5
      // ea7: sipush -30504
      // eaa: invokestatic v.a (I)I
      // ead: iastore
      // eae: iinc 5 1
      // eb1: iload 6
      // eb3: ifne ec2
      // eb6: iload 6
      // eb8: ifeq e95
      // ebb: goto ebf
      // ebe: athrow
      // ebf: iinc 3 1
      // ec2: iload 6
      // ec4: ifeq e75
      // ec7: ldc 65525
      // ec9: invokestatic t.a (I)I
      // ecc: putstatic t.g I
      // ecf: getstatic t.g I
      // ed2: anewarray 152
      // ed5: putstatic t.h [Ljava/lang/String;
      // ed8: getstatic t.g I
      // edb: newarray 10
      // edd: putstatic ca.B [I
      // ee0: getstatic t.g I
      // ee3: newarray 10
      // ee5: putstatic fa.c [I
      // ee8: getstatic t.g I
      // eeb: anewarray 152
      // eee: putstatic h.e [Ljava/lang/String;
      // ef1: bipush 0
      // ef2: istore 3
      // ef3: iload 3
      // ef4: getstatic t.g I
      // ef7: if_icmpge f15
      // efa: getstatic t.h [Ljava/lang/String;
      // efd: iload 3
      // efe: bipush 38
      // f00: invokestatic o.a (B)Ljava/lang/String;
      // f03: aastore
      // f04: iinc 3 1
      // f07: iload 6
      // f09: ifne f17
      // f0c: iload 6
      // f0e: ifeq ef3
      // f11: goto f15
      // f14: athrow
      // f15: bipush 0
      // f16: istore 3
      // f17: iload 3
      // f18: getstatic t.g I
      // f1b: if_icmpge f3d
      // f1e: getstatic h.e [Ljava/lang/String;
      // f21: iload 3
      // f22: bipush 38
      // f24: invokestatic o.a (B)Ljava/lang/String;
      // f27: aastore
      // f28: iinc 3 1
      // f2b: iload 6
      // f2d: ifne f3f
      // f30: goto f34
      // f33: athrow
      // f34: iload 6
      // f36: ifeq f17
      // f39: goto f3d
      // f3c: athrow
      // f3d: bipush 0
      // f3e: istore 3
      // f3f: getstatic t.g I
      // f42: iload 3
      // f43: if_icmple f66
      // f46: getstatic ca.B [I
      // f49: iload 3
      // f4a: sipush -30504
      // f4d: invokestatic v.a (I)I
      // f50: iastore
      // f51: iinc 3 1
      // f54: iload 6
      // f56: ifne f68
      // f59: goto f5d
      // f5c: athrow
      // f5d: iload 6
      // f5f: ifeq f3f
      // f62: goto f66
      // f65: athrow
      // f66: bipush 0
      // f67: istore 3
      // f68: getstatic t.g I
      // f6b: iload 3
      // f6c: if_icmple f8f
      // f6f: getstatic fa.c [I
      // f72: iload 3
      // f73: sipush -30504
      // f76: invokestatic v.a (I)I
      // f79: iastore
      // f7a: iinc 3 1
      // f7d: iload 6
      // f7f: ifne f97
      // f82: goto f86
      // f85: athrow
      // f86: iload 6
      // f88: ifeq f68
      // f8b: goto f8f
      // f8e: athrow
      // f8f: aconst_null
      // f90: putstatic b.v [B
      // f93: aconst_null
      // f94: putstatic kb.d [B
      // f97: goto fde
      // f9a: astore 3
      // f9b: aload 3
      // f9c: new java/lang/StringBuilder
      // f9f: dup
      // fa0: invokespecial java/lang/StringBuilder.<init> ()V
      // fa3: getstatic m.z [Ljava/lang/String;
      // fa6: bipush 3
      // fa7: aaload
      // fa8: invokevirtual java/lang/StringBuilder.append (Ljava/lang/String;)Ljava/lang/StringBuilder;
      // fab: aload 0
      // fac: ifnull fb8
      // faf: getstatic m.z [Ljava/lang/String;
      // fb2: bipush 1
      // fb3: aaload
      // fb4: goto fbd
      // fb7: athrow
      // fb8: getstatic m.z [Ljava/lang/String;
      // fbb: bipush 0
      // fbc: aaload
      // fbd: invokevirtual java/lang/StringBuilder.append (Ljava/lang/String;)Ljava/lang/StringBuilder;
      // fc0: bipush 44
      // fc2: invokevirtual java/lang/StringBuilder.append (C)Ljava/lang/StringBuilder;
      // fc5: iload 1
      // fc6: invokevirtual java/lang/StringBuilder.append (I)Ljava/lang/StringBuilder;
      // fc9: bipush 44
      // fcb: invokevirtual java/lang/StringBuilder.append (C)Ljava/lang/StringBuilder;
      // fce: iload 2
      // fcf: invokevirtual java/lang/StringBuilder.append (Z)Ljava/lang/StringBuilder;
      // fd2: bipush 41
      // fd4: invokevirtual java/lang/StringBuilder.append (C)Ljava/lang/StringBuilder;
      // fd7: invokevirtual java/lang/StringBuilder.toString ()Ljava/lang/String;
      // fda: invokestatic i.a (Ljava/lang/Throwable;Ljava/lang/String;)Lla;
      // fdd: athrow
      // fde: return
   }

   abstract Socket a(byte var1) throws IOException;

   private static char[] z(String var0) {
      char[] var10000 = var0.toCharArray();
      if (var10000.length < 2) {
         var10000[0] = (char)(var10000[0] ^ '^');
      }

      return var10000;
   }

   private static String z(char[] var0) {
      int var10002 = var0.length;
      char[] var10001 = var0;
      int var10000 = var10002;

      for (int var1 = 0; var10000 > var1; var1++) {
         char var10004 = var10001[var1];
         byte var10005;
         switch (var1 % 5) {
            case 0:
               var10005 = 64;
               break;
            case 1:
               var10005 = 20;
               break;
            case 2:
               var10005 = 39;
               break;
            case 3:
               var10005 = 57;
               break;
            default:
               var10005 = 94;
         }

         var10001[var1] = (char)(var10004 ^ var10005);
      }

      return new String(var10001).intern();
   }
}
