import java.io.DataInputStream;
import java.net.URL;

final class mb {
   static int c;
   private static int b = 0;
   static int[] i = new int[]{
      0,
      1,
      3,
      7,
      15,
      31,
      63,
      127,
      255,
      511,
      1023,
      2047,
      4095,
      8191,
      16383,
      32767,
      65535,
      131071,
      262143,
      524287,
      1048575,
      2097151,
      4194303,
      8388607,
      16777215,
      33554431,
      67108863,
      134217727,
      268435455,
      536870911,
      1073741823,
      Integer.MAX_VALUE,
      -1
   };
   static int[] a;
   static int d;
   static int e;
   static int[] k;
   static int l = 0;
   static String[] g;
   static int h;
   static int f;
   static int j;
   private static final String[] z = new String[]{
      z(z("U<HS\u001e")),
      z(z("U<HV\u001e")),
      z(z("U<HP\u001e")),
      z(z("V+\ny")),
      z(z("CpH;K")),
      z(z("a1\u00135B]2\n5")),
      z(z("\u0018*\u0003yZK~\u001fzC\u0002~")),
      z(z("\u0002~")),
      z(z("\u0018)\u000ff^]-FaY\u0018*\u0014tR]~\u0011|BP~\u001fzC\u0016")),
      z(z("U<HQ\u001e")),
      z(z("\u0018\"F")),
      z(z("[2\u000fpXL;\u0014gYJp\u0011f\t[c")),
      z(z("\u001djV")),
      z(z("\u001dlU")),
      z(z("\u001e;[")),
      z(z("\u001dm\u0007")),
      z(z("\u001dlP")),
      z(z("\u001e(W(")),
      z(z("\u001e(T(")),
      z(z("\u001e+[")),
      z(z("s~&b^Q\u001eN")),
      z(z("x=\u001ftv")),
      z(z("\u00183\u000fyZQ1\b5vO6\u000fU\u001e")),
      z(z("U<HW\u001e")),
      z(z("x9\u0014pv"))
   };

   static final synchronized byte[] a(int param0, byte param1) {
      // $VF: Couldn't be decompiled
      // Please report this to the Vineflower issue tracker, at https://github.com/Vineflower/vineflower/issues with a copy of the class file (if you have the rights to distribute it!)
      // java.lang.RuntimeException: parsing failure!
      //   at org.jetbrains.java.decompiler.modules.decompiler.decompose.DomHelper.parseGraph(DomHelper.java:211)
      //   at org.jetbrains.java.decompiler.main.rels.MethodProcessor.codeToJava(MethodProcessor.java:166)
      //
      // Bytecode:
      // 000: getstatic client.vh Z
      // 003: istore 4
      // 005: getstatic mb.j I
      // 008: bipush 1
      // 009: iadd
      // 00a: putstatic mb.j I
      // 00d: iload 0
      // 00e: bipush 100
      // 010: if_icmpne 03c
      // 013: getstatic n.b I
      // 016: bipush -1
      // 017: ixor
      // 018: bipush -1
      // 019: if_icmplt 024
      // 01c: goto 020
      // 01f: athrow
      // 020: goto 03c
      // 023: athrow
      // 024: getstatic ob.j [[B
      // 027: getstatic n.b I
      // 02a: bipush 1
      // 02b: isub
      // 02c: dup
      // 02d: putstatic n.b I
      // 030: aaload
      // 031: astore 2
      // 032: getstatic ob.j [[B
      // 035: getstatic n.b I
      // 038: aconst_null
      // 039: aastore
      // 03a: aload 2
      // 03b: areturn
      // 03c: sipush 5000
      // 03f: iload 0
      // 040: if_icmpne 06c
      // 043: getstatic s.d I
      // 046: bipush -1
      // 047: ixor
      // 048: bipush -1
      // 049: if_icmplt 054
      // 04c: goto 050
      // 04f: athrow
      // 050: goto 06c
      // 053: athrow
      // 054: getstatic e.kb [[B
      // 057: getstatic s.d I
      // 05a: bipush 1
      // 05b: isub
      // 05c: dup
      // 05d: putstatic s.d I
      // 060: aaload
      // 061: astore 2
      // 062: getstatic e.kb [[B
      // 065: getstatic s.d I
      // 068: aconst_null
      // 069: aastore
      // 06a: aload 2
      // 06b: areturn
      // 06c: iload 1
      // 06d: bipush -97
      // 06f: if_icmple 077
      // 072: aconst_null
      // 073: checkcast [B
      // 076: areturn
      // 077: sipush -30001
      // 07a: iload 0
      // 07b: bipush -1
      // 07c: ixor
      // 07d: if_icmpne 0a9
      // 080: getstatic mb.b I
      // 083: bipush -1
      // 084: ixor
      // 085: bipush -1
      // 086: if_icmplt 091
      // 089: goto 08d
      // 08c: athrow
      // 08d: goto 0a9
      // 090: athrow
      // 091: getstatic ca.tb [[B
      // 094: getstatic mb.b I
      // 097: bipush 1
      // 098: isub
      // 099: dup
      // 09a: putstatic mb.b I
      // 09d: aaload
      // 09e: astore 2
      // 09f: getstatic ca.tb [[B
      // 0a2: getstatic mb.b I
      // 0a5: aconst_null
      // 0a6: aastore
      // 0a7: aload 2
      // 0a8: areturn
      // 0a9: aconst_null
      // 0aa: getstatic t.n [[[B
      // 0ad: if_acmpne 0b4
      // 0b0: goto 10c
      // 0b3: athrow
      // 0b4: bipush 0
      // 0b5: istore 2
      // 0b6: getstatic e.wb [I
      // 0b9: arraylength
      // 0ba: bipush -1
      // 0bb: ixor
      // 0bc: iload 2
      // 0bd: bipush -1
      // 0be: ixor
      // 0bf: if_icmpge 10c
      // 0c2: getstatic e.wb [I
      // 0c5: iload 2
      // 0c6: iaload
      // 0c7: bipush -1
      // 0c8: ixor
      // 0c9: iload 4
      // 0cb: ifne 10d
      // 0ce: iload 0
      // 0cf: bipush -1
      // 0d0: ixor
      // 0d1: if_icmpne 104
      // 0d4: goto 0d8
      // 0d7: athrow
      // 0d8: bipush 0
      // 0d9: getstatic v.g [I
      // 0dc: iload 2
      // 0dd: iaload
      // 0de: if_icmpge 104
      // 0e1: goto 0e5
      // 0e4: athrow
      // 0e5: getstatic t.n [[[B
      // 0e8: iload 2
      // 0e9: aaload
      // 0ea: getstatic v.g [I
      // 0ed: iload 2
      // 0ee: dup2
      // 0ef: iaload
      // 0f0: bipush 1
      // 0f1: isub
      // 0f2: dup_x2
      // 0f3: iastore
      // 0f4: aaload
      // 0f5: astore 3
      // 0f6: getstatic t.n [[[B
      // 0f9: iload 2
      // 0fa: aaload
      // 0fb: getstatic v.g [I
      // 0fe: iload 2
      // 0ff: iaload
      // 100: aconst_null
      // 101: aastore
      // 102: aload 3
      // 103: areturn
      // 104: iinc 2 1
      // 107: iload 4
      // 109: ifeq 0b6
      // 10c: iload 0
      // 10d: newarray 8
      // 10f: areturn
      // 110: astore 2
      // 111: aload 2
      // 112: new java/lang/StringBuilder
      // 115: dup
      // 116: invokespecial java/lang/StringBuilder.<init> ()V
      // 119: getstatic mb.z [Ljava/lang/String;
      // 11c: bipush 1
      // 11d: aaload
      // 11e: invokevirtual java/lang/StringBuilder.append (Ljava/lang/String;)Ljava/lang/StringBuilder;
      // 121: iload 0
      // 122: invokevirtual java/lang/StringBuilder.append (I)Ljava/lang/StringBuilder;
      // 125: bipush 44
      // 127: invokevirtual java/lang/StringBuilder.append (C)Ljava/lang/StringBuilder;
      // 12a: iload 1
      // 12b: invokevirtual java/lang/StringBuilder.append (I)Ljava/lang/StringBuilder;
      // 12e: bipush 41
      // 130: invokevirtual java/lang/StringBuilder.append (C)Ljava/lang/StringBuilder;
      // 133: invokevirtual java/lang/StringBuilder.toString ()Ljava/lang/String;
      // 136: invokestatic i.a (Ljava/lang/Throwable;Ljava/lang/String;)Lla;
      // 139: athrow
   }

   static final void a(int param0, long param1) {
      // $VF: Couldn't be decompiled
      // Please report this to the Vineflower issue tracker, at https://github.com/Vineflower/vineflower/issues with a copy of the class file (if you have the rights to distribute it!)
      // java.lang.RuntimeException: parsing failure!
      //   at org.jetbrains.java.decompiler.modules.decompiler.decompose.DomHelper.parseGraph(DomHelper.java:211)
      //   at org.jetbrains.java.decompiler.main.rels.MethodProcessor.codeToJava(MethodProcessor.java:166)
      //
      // Bytecode:
      // 00: getstatic mb.h I
      // 03: bipush 1
      // 04: iadd
      // 05: putstatic mb.h I
      // 08: iload 0
      // 09: sipush 11200
      // 0c: if_icmpeq 1a
      // 0f: aconst_null
      // 10: checkcast [Ljava/lang/String;
      // 13: putstatic mb.g [Ljava/lang/String;
      // 16: goto 1a
      // 19: athrow
      // 1a: lconst_0
      // 1b: lload 1
      // 1c: lcmp
      // 1d: ifge 24
      // 20: goto 25
      // 23: athrow
      // 24: return
      // 25: lload 1
      // 26: ldc2_w 10
      // 29: lrem
      // 2a: lconst_0
      // 2b: lcmp
      // 2c: ifne 4b
      // 2f: iload 0
      // 30: sipush -11200
      // 33: iadd
      // 34: ldc2_w -1
      // 37: lload 1
      // 38: ladd
      // 39: invokestatic u.a (IJ)V
      // 3c: bipush 0
      // 3d: lconst_1
      // 3e: invokestatic u.a (IJ)V
      // 41: getstatic client.vh Z
      // 44: ifeq 54
      // 47: goto 4b
      // 4a: athrow
      // 4b: bipush 0
      // 4c: lload 1
      // 4d: invokestatic u.a (IJ)V
      // 50: goto 54
      // 53: athrow
      // 54: goto 81
      // 57: astore 3
      // 58: aload 3
      // 59: new java/lang/StringBuilder
      // 5c: dup
      // 5d: invokespecial java/lang/StringBuilder.<init> ()V
      // 60: getstatic mb.z [Ljava/lang/String;
      // 63: bipush 0
      // 64: aaload
      // 65: invokevirtual java/lang/StringBuilder.append (Ljava/lang/String;)Ljava/lang/StringBuilder;
      // 68: iload 0
      // 69: invokevirtual java/lang/StringBuilder.append (I)Ljava/lang/StringBuilder;
      // 6c: bipush 44
      // 6e: invokevirtual java/lang/StringBuilder.append (C)Ljava/lang/StringBuilder;
      // 71: lload 1
      // 72: invokevirtual java/lang/StringBuilder.append (J)Ljava/lang/StringBuilder;
      // 75: bipush 41
      // 77: invokevirtual java/lang/StringBuilder.append (C)Ljava/lang/StringBuilder;
      // 7a: invokevirtual java/lang/StringBuilder.toString ()Ljava/lang/String;
      // 7d: invokestatic i.a (Ljava/lang/Throwable;Ljava/lang/String;)Lla;
      // 80: athrow
      // 81: return
   }

   static final String a(int param0, int param1) {
      // $VF: Couldn't be decompiled
      // Please report this to the Vineflower issue tracker, at https://github.com/Vineflower/vineflower/issues with a copy of the class file (if you have the rights to distribute it!)
      // java.lang.RuntimeException: parsing failure!
      //   at org.jetbrains.java.decompiler.modules.decompiler.decompose.DomHelper.parseGraph(DomHelper.java:211)
      //   at org.jetbrains.java.decompiler.main.rels.MethodProcessor.codeToJava(MethodProcessor.java:166)
      //
      // Bytecode:
      // 000: getstatic client.vh Z
      // 003: istore 4
      // 005: getstatic mb.f I
      // 008: bipush 1
      // 009: iadd
      // 00a: putstatic mb.f I
      // 00d: new java/lang/StringBuilder
      // 010: dup
      // 011: invokespecial java/lang/StringBuilder.<init> ()V
      // 014: ldc ""
      // 016: invokevirtual java/lang/StringBuilder.append (Ljava/lang/String;)Ljava/lang/StringBuilder;
      // 019: iload 0
      // 01a: invokevirtual java/lang/StringBuilder.append (I)Ljava/lang/StringBuilder;
      // 01d: invokevirtual java/lang/StringBuilder.toString ()Ljava/lang/String;
      // 020: astore 2
      // 021: bipush -3
      // 023: aload 2
      // 024: invokevirtual java/lang/String.length ()I
      // 027: iadd
      // 028: istore 3
      // 029: bipush -1
      // 02a: iload 3
      // 02b: bipush -1
      // 02c: ixor
      // 02d: if_icmple 062
      // 030: new java/lang/StringBuilder
      // 033: dup
      // 034: invokespecial java/lang/StringBuilder.<init> ()V
      // 037: aload 2
      // 038: bipush 0
      // 039: iload 3
      // 03a: invokevirtual java/lang/String.substring (II)Ljava/lang/String;
      // 03d: invokevirtual java/lang/StringBuilder.append (Ljava/lang/String;)Ljava/lang/StringBuilder;
      // 040: ldc ","
      // 042: invokevirtual java/lang/StringBuilder.append (Ljava/lang/String;)Ljava/lang/StringBuilder;
      // 045: aload 2
      // 046: iload 3
      // 047: invokevirtual java/lang/String.substring (I)Ljava/lang/String;
      // 04a: invokevirtual java/lang/StringBuilder.append (Ljava/lang/String;)Ljava/lang/StringBuilder;
      // 04d: invokevirtual java/lang/StringBuilder.toString ()Ljava/lang/String;
      // 050: astore 2
      // 051: iinc 3 -3
      // 054: iload 4
      // 056: ifne 078
      // 059: iload 4
      // 05b: ifeq 029
      // 05e: goto 062
      // 061: athrow
      // 062: iload 1
      // 063: ldc 131071
      // 065: if_icmpeq 078
      // 068: aconst_null
      // 069: checkcast [B
      // 06c: bipush -74
      // 06e: bipush 53
      // 070: invokestatic mb.a ([BII)I
      // 073: pop
      // 074: goto 078
      // 077: athrow
      // 078: bipush -9
      // 07a: aload 2
      // 07b: invokevirtual java/lang/String.length ()I
      // 07e: bipush -1
      // 07f: ixor
      // 080: if_icmple 0bd
      // 083: new java/lang/StringBuilder
      // 086: dup
      // 087: invokespecial java/lang/StringBuilder.<init> ()V
      // 08a: getstatic mb.z [Ljava/lang/String;
      // 08d: bipush 24
      // 08f: aaload
      // 090: invokevirtual java/lang/StringBuilder.append (Ljava/lang/String;)Ljava/lang/StringBuilder;
      // 093: aload 2
      // 094: bipush 0
      // 095: aload 2
      // 096: invokevirtual java/lang/String.length ()I
      // 099: bipush -8
      // 09b: iadd
      // 09c: invokevirtual java/lang/String.substring (II)Ljava/lang/String;
      // 09f: invokevirtual java/lang/StringBuilder.append (Ljava/lang/String;)Ljava/lang/StringBuilder;
      // 0a2: getstatic mb.z [Ljava/lang/String;
      // 0a5: bipush 22
      // 0a7: aaload
      // 0a8: invokevirtual java/lang/StringBuilder.append (Ljava/lang/String;)Ljava/lang/StringBuilder;
      // 0ab: aload 2
      // 0ac: invokevirtual java/lang/StringBuilder.append (Ljava/lang/String;)Ljava/lang/StringBuilder;
      // 0af: ldc ")"
      // 0b1: invokevirtual java/lang/StringBuilder.append (Ljava/lang/String;)Ljava/lang/StringBuilder;
      // 0b4: invokevirtual java/lang/StringBuilder.toString ()Ljava/lang/String;
      // 0b7: astore 2
      // 0b8: iload 4
      // 0ba: ifeq 105
      // 0bd: aload 2
      // 0be: invokevirtual java/lang/String.length ()I
      // 0c1: bipush -1
      // 0c2: ixor
      // 0c3: bipush -5
      // 0c5: if_icmplt 0d0
      // 0c8: goto 0cc
      // 0cb: athrow
      // 0cc: goto 105
      // 0cf: athrow
      // 0d0: new java/lang/StringBuilder
      // 0d3: dup
      // 0d4: invokespecial java/lang/StringBuilder.<init> ()V
      // 0d7: getstatic mb.z [Ljava/lang/String;
      // 0da: bipush 21
      // 0dc: aaload
      // 0dd: invokevirtual java/lang/StringBuilder.append (Ljava/lang/String;)Ljava/lang/StringBuilder;
      // 0e0: aload 2
      // 0e1: bipush 0
      // 0e2: bipush -4
      // 0e4: aload 2
      // 0e5: invokevirtual java/lang/String.length ()I
      // 0e8: iadd
      // 0e9: invokevirtual java/lang/String.substring (II)Ljava/lang/String;
      // 0ec: invokevirtual java/lang/StringBuilder.append (Ljava/lang/String;)Ljava/lang/StringBuilder;
      // 0ef: getstatic mb.z [Ljava/lang/String;
      // 0f2: bipush 20
      // 0f4: aaload
      // 0f5: invokevirtual java/lang/StringBuilder.append (Ljava/lang/String;)Ljava/lang/StringBuilder;
      // 0f8: aload 2
      // 0f9: invokevirtual java/lang/StringBuilder.append (Ljava/lang/String;)Ljava/lang/StringBuilder;
      // 0fc: ldc ")"
      // 0fe: invokevirtual java/lang/StringBuilder.append (Ljava/lang/String;)Ljava/lang/StringBuilder;
      // 101: invokevirtual java/lang/StringBuilder.toString ()Ljava/lang/String;
      // 104: astore 2
      // 105: aload 2
      // 106: areturn
      // 107: astore 2
      // 108: aload 2
      // 109: new java/lang/StringBuilder
      // 10c: dup
      // 10d: invokespecial java/lang/StringBuilder.<init> ()V
      // 110: getstatic mb.z [Ljava/lang/String;
      // 113: bipush 23
      // 115: aaload
      // 116: invokevirtual java/lang/StringBuilder.append (Ljava/lang/String;)Ljava/lang/StringBuilder;
      // 119: iload 0
      // 11a: invokevirtual java/lang/StringBuilder.append (I)Ljava/lang/StringBuilder;
      // 11d: bipush 44
      // 11f: invokevirtual java/lang/StringBuilder.append (C)Ljava/lang/StringBuilder;
      // 122: iload 1
      // 123: invokevirtual java/lang/StringBuilder.append (I)Ljava/lang/StringBuilder;
      // 126: bipush 41
      // 128: invokevirtual java/lang/StringBuilder.append (C)Ljava/lang/StringBuilder;
      // 12b: invokevirtual java/lang/StringBuilder.toString ()Ljava/lang/String;
      // 12e: invokestatic i.a (Ljava/lang/Throwable;Ljava/lang/String;)Lla;
      // 131: athrow
   }

   static final String a(String param0, String param1, boolean param2, int param3) {
      // $VF: Couldn't be decompiled
      // Please report this to the Vineflower issue tracker, at https://github.com/Vineflower/vineflower/issues with a copy of the class file (if you have the rights to distribute it!)
      // java.lang.RuntimeException: parsing failure!
      //   at org.jetbrains.java.decompiler.modules.decompiler.decompose.DomHelper.parseGraph(DomHelper.java:211)
      //   at org.jetbrains.java.decompiler.main.rels.MethodProcessor.codeToJava(MethodProcessor.java:166)
      //
      // Bytecode:
      // 000: getstatic client.vh Z
      // 003: istore 5
      // 005: getstatic mb.d I
      // 008: bipush 1
      // 009: iadd
      // 00a: putstatic mb.d I
      // 00d: iload 2
      // 00e: bipush 1
      // 00f: if_icmpeq 01b
      // 012: bipush 90
      // 014: putstatic mb.l I
      // 017: goto 01b
      // 01a: athrow
      // 01b: iload 3
      // 01c: istore 4
      // 01e: bipush 0
      // 01f: iload 4
      // 021: if_icmpne 02d
      // 024: iload 5
      // 026: ifeq 0aa
      // 029: goto 02d
      // 02c: athrow
      // 02d: iload 4
      // 02f: bipush 1
      // 030: if_icmpeq 0de
      // 033: goto 037
      // 036: athrow
      // 037: iload 4
      // 039: bipush 2
      // 03a: if_icmpne 04a
      // 03d: goto 041
      // 040: athrow
      // 041: iload 5
      // 043: ifeq 10b
      // 046: goto 04a
      // 049: athrow
      // 04a: iload 4
      // 04c: bipush 3
      // 04d: if_icmpne 05d
      // 050: goto 054
      // 053: athrow
      // 054: iload 5
      // 056: ifeq 148
      // 059: goto 05d
      // 05c: athrow
      // 05d: iload 4
      // 05f: bipush -1
      // 060: ixor
      // 061: bipush -5
      // 063: if_icmpne 073
      // 066: goto 06a
      // 069: athrow
      // 06a: iload 5
      // 06c: ifeq 179
      // 06f: goto 073
      // 072: athrow
      // 073: iload 4
      // 075: bipush -1
      // 076: ixor
      // 077: bipush -6
      // 079: if_icmpeq 1aa
      // 07c: goto 080
      // 07f: athrow
      // 080: bipush 6
      // 082: iload 4
      // 084: if_icmpne 094
      // 087: goto 08b
      // 08a: athrow
      // 08b: iload 5
      // 08d: ifeq 1ac
      // 090: goto 094
      // 093: athrow
      // 094: bipush -8
      // 096: iload 4
      // 098: bipush -1
      // 099: ixor
      // 09a: if_icmpne 1f5
      // 09d: goto 0a1
      // 0a0: athrow
      // 0a1: iload 5
      // 0a3: ifeq 1c4
      // 0a6: goto 0aa
      // 0a9: athrow
      // 0aa: aload 1
      // 0ab: ifnull 0dc
      // 0ae: goto 0b2
      // 0b1: athrow
      // 0b2: bipush -1
      // 0b3: aload 1
      // 0b4: invokevirtual java/lang/String.length ()I
      // 0b7: bipush -1
      // 0b8: ixor
      // 0b9: if_icmpeq 0dc
      // 0bc: goto 0c0
      // 0bf: athrow
      // 0c0: new java/lang/StringBuilder
      // 0c3: dup
      // 0c4: invokespecial java/lang/StringBuilder.<init> ()V
      // 0c7: aload 1
      // 0c8: invokevirtual java/lang/StringBuilder.append (Ljava/lang/String;)Ljava/lang/StringBuilder;
      // 0cb: getstatic mb.z [Ljava/lang/String;
      // 0ce: bipush 7
      // 0d0: aaload
      // 0d1: invokevirtual java/lang/StringBuilder.append (Ljava/lang/String;)Ljava/lang/StringBuilder;
      // 0d4: aload 0
      // 0d5: invokevirtual java/lang/StringBuilder.append (Ljava/lang/String;)Ljava/lang/StringBuilder;
      // 0d8: invokevirtual java/lang/StringBuilder.toString ()Ljava/lang/String;
      // 0db: areturn
      // 0dc: aload 0
      // 0dd: areturn
      // 0de: aload 1
      // 0df: ifnull 0ed
      // 0e2: aload 1
      // 0e3: invokevirtual java/lang/String.length ()I
      // 0e6: ifne 0ef
      // 0e9: goto 0ed
      // 0ec: athrow
      // 0ed: aload 0
      // 0ee: areturn
      // 0ef: new java/lang/StringBuilder
      // 0f2: dup
      // 0f3: invokespecial java/lang/StringBuilder.<init> ()V
      // 0f6: aload 1
      // 0f7: invokevirtual java/lang/StringBuilder.append (Ljava/lang/String;)Ljava/lang/StringBuilder;
      // 0fa: getstatic mb.z [Ljava/lang/String;
      // 0fd: bipush 6
      // 0ff: aaload
      // 100: invokevirtual java/lang/StringBuilder.append (Ljava/lang/String;)Ljava/lang/StringBuilder;
      // 103: aload 0
      // 104: invokevirtual java/lang/StringBuilder.append (Ljava/lang/String;)Ljava/lang/StringBuilder;
      // 107: invokevirtual java/lang/StringBuilder.toString ()Ljava/lang/String;
      // 10a: areturn
      // 10b: aconst_null
      // 10c: aload 1
      // 10d: if_acmpeq 122
      // 110: bipush -1
      // 111: aload 1
      // 112: invokevirtual java/lang/String.length ()I
      // 115: bipush -1
      // 116: ixor
      // 117: if_icmpeq 122
      // 11a: goto 11e
      // 11d: athrow
      // 11e: goto 124
      // 121: athrow
      // 122: aload 0
      // 123: areturn
      // 124: new java/lang/StringBuilder
      // 127: dup
      // 128: invokespecial java/lang/StringBuilder.<init> ()V
      // 12b: getstatic mb.z [Ljava/lang/String;
      // 12e: bipush 5
      // 12f: aaload
      // 130: invokevirtual java/lang/StringBuilder.append (Ljava/lang/String;)Ljava/lang/StringBuilder;
      // 133: aload 1
      // 134: invokevirtual java/lang/StringBuilder.append (Ljava/lang/String;)Ljava/lang/StringBuilder;
      // 137: getstatic mb.z [Ljava/lang/String;
      // 13a: bipush 7
      // 13c: aaload
      // 13d: invokevirtual java/lang/StringBuilder.append (Ljava/lang/String;)Ljava/lang/StringBuilder;
      // 140: aload 0
      // 141: invokevirtual java/lang/StringBuilder.append (Ljava/lang/String;)Ljava/lang/StringBuilder;
      // 144: invokevirtual java/lang/StringBuilder.toString ()Ljava/lang/String;
      // 147: areturn
      // 148: aconst_null
      // 149: aload 1
      // 14a: if_acmpeq 177
      // 14d: aload 1
      // 14e: invokevirtual java/lang/String.length ()I
      // 151: bipush -1
      // 152: ixor
      // 153: bipush -1
      // 154: if_icmpeq 177
      // 157: goto 15b
      // 15a: athrow
      // 15b: new java/lang/StringBuilder
      // 15e: dup
      // 15f: invokespecial java/lang/StringBuilder.<init> ()V
      // 162: aload 1
      // 163: invokevirtual java/lang/StringBuilder.append (Ljava/lang/String;)Ljava/lang/StringBuilder;
      // 166: getstatic mb.z [Ljava/lang/String;
      // 169: bipush 7
      // 16b: aaload
      // 16c: invokevirtual java/lang/StringBuilder.append (Ljava/lang/String;)Ljava/lang/StringBuilder;
      // 16f: aload 0
      // 170: invokevirtual java/lang/StringBuilder.append (Ljava/lang/String;)Ljava/lang/StringBuilder;
      // 173: invokevirtual java/lang/StringBuilder.toString ()Ljava/lang/String;
      // 176: areturn
      // 177: aload 0
      // 178: areturn
      // 179: aconst_null
      // 17a: aload 1
      // 17b: if_acmpeq 18c
      // 17e: aload 1
      // 17f: invokevirtual java/lang/String.length ()I
      // 182: bipush -1
      // 183: ixor
      // 184: bipush -1
      // 185: if_icmpne 18e
      // 188: goto 18c
      // 18b: athrow
      // 18c: aload 0
      // 18d: areturn
      // 18e: new java/lang/StringBuilder
      // 191: dup
      // 192: invokespecial java/lang/StringBuilder.<init> ()V
      // 195: aload 1
      // 196: invokevirtual java/lang/StringBuilder.append (Ljava/lang/String;)Ljava/lang/StringBuilder;
      // 199: getstatic mb.z [Ljava/lang/String;
      // 19c: bipush 7
      // 19e: aaload
      // 19f: invokevirtual java/lang/StringBuilder.append (Ljava/lang/String;)Ljava/lang/StringBuilder;
      // 1a2: aload 0
      // 1a3: invokevirtual java/lang/StringBuilder.append (Ljava/lang/String;)Ljava/lang/StringBuilder;
      // 1a6: invokevirtual java/lang/StringBuilder.toString ()Ljava/lang/String;
      // 1a9: areturn
      // 1aa: aload 0
      // 1ab: areturn
      // 1ac: new java/lang/StringBuilder
      // 1af: dup
      // 1b0: invokespecial java/lang/StringBuilder.<init> ()V
      // 1b3: aload 1
      // 1b4: invokevirtual java/lang/StringBuilder.append (Ljava/lang/String;)Ljava/lang/StringBuilder;
      // 1b7: getstatic mb.z [Ljava/lang/String;
      // 1ba: bipush 8
      // 1bc: aaload
      // 1bd: invokevirtual java/lang/StringBuilder.append (Ljava/lang/String;)Ljava/lang/StringBuilder;
      // 1c0: invokevirtual java/lang/StringBuilder.toString ()Ljava/lang/String;
      // 1c3: areturn
      // 1c4: aconst_null
      // 1c5: aload 1
      // 1c6: if_acmpeq 1d7
      // 1c9: aload 1
      // 1ca: invokevirtual java/lang/String.length ()I
      // 1cd: bipush -1
      // 1ce: ixor
      // 1cf: bipush -1
      // 1d0: if_icmpne 1d9
      // 1d3: goto 1d7
      // 1d6: athrow
      // 1d7: aload 0
      // 1d8: areturn
      // 1d9: new java/lang/StringBuilder
      // 1dc: dup
      // 1dd: invokespecial java/lang/StringBuilder.<init> ()V
      // 1e0: aload 1
      // 1e1: invokevirtual java/lang/StringBuilder.append (Ljava/lang/String;)Ljava/lang/StringBuilder;
      // 1e4: getstatic mb.z [Ljava/lang/String;
      // 1e7: bipush 7
      // 1e9: aaload
      // 1ea: invokevirtual java/lang/StringBuilder.append (Ljava/lang/String;)Ljava/lang/StringBuilder;
      // 1ed: aload 0
      // 1ee: invokevirtual java/lang/StringBuilder.append (Ljava/lang/String;)Ljava/lang/StringBuilder;
      // 1f1: invokevirtual java/lang/StringBuilder.toString ()Ljava/lang/String;
      // 1f4: areturn
      // 1f5: ldc ""
      // 1f7: areturn
      // 1f8: astore 4
      // 1fa: aload 4
      // 1fc: new java/lang/StringBuilder
      // 1ff: dup
      // 200: invokespecial java/lang/StringBuilder.<init> ()V
      // 203: getstatic mb.z [Ljava/lang/String;
      // 206: bipush 9
      // 208: aaload
      // 209: invokevirtual java/lang/StringBuilder.append (Ljava/lang/String;)Ljava/lang/StringBuilder;
      // 20c: aload 0
      // 20d: ifnull 219
      // 210: getstatic mb.z [Ljava/lang/String;
      // 213: bipush 4
      // 214: aaload
      // 215: goto 21e
      // 218: athrow
      // 219: getstatic mb.z [Ljava/lang/String;
      // 21c: bipush 3
      // 21d: aaload
      // 21e: invokevirtual java/lang/StringBuilder.append (Ljava/lang/String;)Ljava/lang/StringBuilder;
      // 221: bipush 44
      // 223: invokevirtual java/lang/StringBuilder.append (C)Ljava/lang/StringBuilder;
      // 226: aload 1
      // 227: ifnull 233
      // 22a: getstatic mb.z [Ljava/lang/String;
      // 22d: bipush 4
      // 22e: aaload
      // 22f: goto 238
      // 232: athrow
      // 233: getstatic mb.z [Ljava/lang/String;
      // 236: bipush 3
      // 237: aaload
      // 238: invokevirtual java/lang/StringBuilder.append (Ljava/lang/String;)Ljava/lang/StringBuilder;
      // 23b: bipush 44
      // 23d: invokevirtual java/lang/StringBuilder.append (C)Ljava/lang/StringBuilder;
      // 240: iload 2
      // 241: invokevirtual java/lang/StringBuilder.append (Z)Ljava/lang/StringBuilder;
      // 244: bipush 44
      // 246: invokevirtual java/lang/StringBuilder.append (C)Ljava/lang/StringBuilder;
      // 249: iload 3
      // 24a: invokevirtual java/lang/StringBuilder.append (I)Ljava/lang/StringBuilder;
      // 24d: bipush 41
      // 24f: invokevirtual java/lang/StringBuilder.append (C)Ljava/lang/StringBuilder;
      // 252: invokevirtual java/lang/StringBuilder.toString ()Ljava/lang/String;
      // 255: invokestatic i.a (Ljava/lang/Throwable;Ljava/lang/String;)Lla;
      // 258: athrow
   }

   static final void a(int var0, Throwable var1, String var2) {
      boolean var6 = client.vh;

      try {
         e++;

         try {
            String var3 = "";

            try {
               if (var0 != 2097151) {
                  a((String)null, (String)null, true, 27);
               }
            } catch (Exception var8) {
               throw var8;
            }

            label92: {
               try {
                  if (var1 == null) {
                     break label92;
                  }
               } catch (Exception var12) {
                  throw var12;
               }

               var3 = gb.a(false, var1);
            }

            label87: {
               label86: {
                  try {
                     if (null == var2) {
                        break label87;
                     }

                     if (var1 == null) {
                        break label86;
                     }
                  } catch (Exception var11) {
                     throw var11;
                  }

                  var3 = var3 + z[10];
               }

               var3 = var3 + var2;
            }

            n.a((byte)-93, var3);
            var3 = jb.a(true, z[15], ":", var3);
            var3 = jb.a(true, z[12], "@", var3);
            var3 = jb.a(true, z[16], "&", var3);
            var3 = jb.a(true, z[13], "#", var3);

            try {
               if (null == l.b) {
                  return;
               }
            } catch (Exception var7) {
               throw var7;
            }

            c var10000;
            byte var10001;
            URL var10002;
            URL var10004;
            StringBuilder var10005;
            String var10006;
            label77: {
               try {
                  var10000 = pa.b;
                  var10001 = 74;
                  var10004 = l.b.getCodeBase();
                  var10005 = new StringBuilder().append(z[11]).append(db.d).append(z[19]);
                  if (ka.a != null) {
                     var10006 = ka.a;
                     break label77;
                  }
               } catch (Exception var10) {
                  throw var10;
               }

               var10006 = "" + pa.h;
            }

            var10002 = new URL(
               var10004, var10005.append(var10006).append(z[17]).append(c.q).append(z[18]).append(c.k).append(z[14]).append(var3).toString()
            );
            g var4 = var10000.a(var10001, var10002);

            while (~var4.b == -1) {
               try {
                  a(11200, 1L);
                  if (var6) {
                     return;
                  }

                  if (var6) {
                     break;
                  }
               } catch (Exception var9) {
                  throw var9;
               }
            }

            if (-2 == ~var4.b) {
               DataInputStream var5 = (DataInputStream)var4.d;
               var5.read();
               var5.close();
            }
         } catch (Exception var13) {
         }
      } catch (RuntimeException var14) {
         throw var14;
      }
   }

   static final int a(byte[] var0, int var1, int var2) {
      try {
         if (var2 != 0) {
            return 6;
         } else {
            c++;
            return w.a(var1, -49, var0, 0);
         }
      } catch (RuntimeException var5) {
         RuntimeException var3 = var5;

         RuntimeException var10000;
         StringBuilder var10001;
         try {
            var10000 = var3;
            var10001 = new StringBuilder().append(z[2]);
            if (var0 != null) {
               throw i.a(var3, var10001.append(z[4]).append((char)44).append(var1).append((char)44).append(var2).append((char)41).toString());
            }
         } catch (RuntimeException var4) {
            throw var4;
         }

         throw i.a(var10000, var10001.append(z[3]).append((char)44).append(var1).append((char)44).append(var2).append((char)41).toString());
      }
   }

   private static char[] z(String var0) {
      char[] var10000 = var0.toCharArray();
      if (var10000.length < 2) {
         var10000[0] = (char)(var10000[0] ^ '6');
      }

      return var10000;
   }

   private static String z(char[] var0) {
      int var10002 = var0.length;
      char[] var10001 = var0;
      int var10000 = var10002;

      for (int var1 = 0; var10000 > var1; var1++) {
         char var10004 = var10001[var1];
         byte var10005;
         switch (var1 % 5) {
            case 0:
               var10005 = 56;
               break;
            case 1:
               var10005 = 94;
               break;
            case 2:
               var10005 = 102;
               break;
            case 3:
               var10005 = 21;
               break;
            default:
               var10005 = 54;
         }

         var10001[var1] = (char)(var10004 ^ var10005);
      }

      return new String(var10001).intern();
   }
}
