final class qa {
   private String[][] Ab;
   static int s;
   static int P;
   static int L;
   private int[] N;
   static int ub;
   int[] j;
   static int x;
   private int hb;
   static int Gb;
   static int M;
   static int lb;
   static int r;
   static int nb;
   static int db;
   private String[] yb;
   static int mb;
   private String[][] p;
   private String[][] Fb;
   private int R;
   static int xb;
   private int gb = -1;
   static int[] K;
   private int i;
   private int tb;
   static int rb;
   private int[] O;
   static int H;
   private int G;
   static int y;
   static int a;
   static int o;
   static int wb;
   static int u;
   private int[] kb;
   private ua w;
   private int eb = 0;
   private boolean[] D;
   static int ab;
   static byte[] l = pa.a(-126);
   static int z;
   private int Eb;
   private int[] ob;
   private int ib;
   static int h;
   static int X;
   static int Db;
   static int e;
   private int[] B;
   private int F;
   private int[] sb;
   private boolean[] Y;
   static int n;
   static int q;
   private boolean t;
   static int V;
   static int Bb;
   static int v;
   static int jb;
   static int b;
   private int f;
   private int zb;
   private int E;
   private int bb;
   private int Hb;
   private int[] k;
   static int I;
   private int C;
   private int[] vb;
   static int Z;
   private boolean[] d;
   private boolean[] cb;
   static int T;
   private int J;
   static int Q;
   private boolean[] g;
   static int Cb;
   static int c;
   private int fb;
   private int[] U;
   int[] pb;
   static int S;
   private int[][] m;
   static int A;
   private int qb;
   private static final String[] W = new String[]{
      z(z("\u0004I$CY")),
      z(z("\u001b]fe")),
      z(z("\u000e\u0006$'\f")),
      z(z("\u0004I$B0]")),
      z(z("\u0004I$KY")),
      z(z("\u0004I$X0]")),
      z(z("\u0004I$AY")),
      z(
         z(
            "4jIM43oB@;>dGG>%yXZ% ~]Q(/Ihj\u0015\u0010Nma\u0018\u001fCfd\u001f\u001aX{{\u0002\u0001]|~\t\fR:8CF\u001c??FM\u0011++ÒQ\rT/[]\u0001'VL^sqT\fN\u0012-IR\u000b\u00046'OZ\u0017VuQ"
         )
      ),
      z(z("\u0004I$OY")),
      z(z("\u0004I$C0]")),
      z(z("\u0004I$_Y")),
      z(z("\u0004I$A0]")),
      z(z("\u0004I$FY")),
      z(z("\u0004I$NY")),
      z(z("\u0004I$Y0]")),
      z(z("\u0004I$@0]")),
      z(z("\u0004I$EY")),
      z(z("\u0004I$L0]")),
      z(z("\u0004I$G0]")),
      z(z("\u0004I$M0]")),
      z(z("U\b")),
      z(z("\u0004I$\\Y")),
      z(z("\u0004I$5\u0018\u001bA~7Y")),
      z(z("\u0004I$JY")),
      z(z("\u0004I$O0]")),
      z(z("\u0004I$^Y")),
      z(z("\u0004I$XY")),
      z(z("\u0004I$J0]")),
      z(z("\u0004I$ZY")),
      z(z("[Bl")),
      z(z("\u0004I$N0]")),
      z(z("=Mf\u007f\u0014\u0001Aih")),
      z(z("\u001dMf\u007f\u0014\u0001Aih")),
      z(z("\u0004I$GY")),
      z(z("\u0004I$[Y")),
      z(z("\u0004I$MY")),
      z(z("\u0004I$@Y")),
      z(z("\u0004I$DY")),
      z(z("\u0004I$[0]")),
      z(z("\u0004I$BY")),
      z(z("\u0004I$]Y")),
      z(z("\u0004I$K0]")),
      z(z("\u0004I$F0]")),
      z(z("\u0004I$H0]")),
      z(z("\u0004I$E0]")),
      z(z("\u0004I$LY")),
      z(z("\u0004I$HY")),
      z(z("\u0004I$YY")),
      z(z("\u0004I$D0]"))
   };

   final void c(byte var1, int var2) {
      try {
         int var3 = 60 / ((19 - var1) / 44);
         this.pb[var2] = 0;
         r++;
      } catch (RuntimeException var4) {
         throw i.a(var4, W[47] + var1 + ',' + var2 + ')');
      }
   }

   final int a(int var1, int var2, boolean var3, int var4, int var5, int var6, int var7, int var8, boolean var9) {
      try {
         h++;
         this.U[this.eb] = 5;
         this.g[this.eb] = true;
         this.cb[this.eb] = var3;
         if (var7 != 14179) {
            return 2;
         } else {
            this.D[this.eb] = false;
            this.k[this.eb] = var5;
            this.Y[this.eb] = var9;
            this.kb[this.eb] = var4;
            this.B[this.eb] = var6;
            this.ob[this.eb] = var8;
            this.O[this.eb] = var2;
            this.sb[this.eb] = var1;
            this.yb[this.eb] = "";
            return this.eb++;
         }
      } catch (RuntimeException var11) {
         throw i.a(var11, W[16] + var1 + 44 + var2 + 44 + var3 + 44 + var4 + 44 + var5 + 44 + var6 + 44 + var7 + 44 + var8 + 44 + var9 + 41);
      }
   }

   private final int a(int var1, int var2, int var3, byte var4) {
      try {
         try {
            y++;
            if (var4 >= -70) {
               this.kb = (int[])null;
            }
         } catch (RuntimeException var6) {
            throw var6;
         }

         return o.a(ua.C * var3 / 114, 9570, ta.g * var1 / 176, var2 * aa.d / 114);
      } catch (RuntimeException var7) {
         throw i.a(var7, W[5] + var1 + 44 + var2 + 44 + var3 + 44 + var4 + 41);
      }
   }

   final int d(int var1, int var2, int var3, int var4, int var5) {
      try {
         this.U[this.eb] = 10;
         x++;
         this.g[this.eb] = true;
         this.D[this.eb] = false;
         int var6 = 118 / ((var4 - -22) / 48);
         this.kb[this.eb] = -(var2 / 2) + var1;
         this.B[this.eb] = -(var5 / 2) + var3;
         this.ob[this.eb] = var2;
         this.O[this.eb] = var5;
         return this.eb++;
      } catch (RuntimeException var7) {
         throw i.a(var7, W[13] + var1 + 44 + var2 + 44 + var3 + 44 + var4 + 44 + var5 + 41);
      }
   }

   final void a(byte param1) {
      // $VF: Couldn't be decompiled
      // Please report this to the Vineflower issue tracker, at https://github.com/Vineflower/vineflower/issues with a copy of the class file (if you have the rights to distribute it!)
      // java.lang.RuntimeException: parsing failure!
      //   at org.jetbrains.java.decompiler.modules.decompiler.decompose.DomHelper.parseGraph(DomHelper.java:211)
      //   at org.jetbrains.java.decompiler.main.rels.MethodProcessor.codeToJava(MethodProcessor.java:166)
      //
      // Bytecode:
      // 000: getstatic client.vh Z
      // 003: istore 3
      // 004: getstatic qa.Gb I
      // 007: bipush 1
      // 008: iadd
      // 009: putstatic qa.Gb I
      // 00c: iload 1
      // 00d: ifle 01a
      // 010: aload 0
      // 011: bipush -121
      // 013: putfield qa.R I
      // 016: goto 01a
      // 019: athrow
      // 01a: bipush 0
      // 01b: istore 2
      // 01c: iload 2
      // 01d: aload 0
      // 01e: getfield qa.eb I
      // 021: if_icmpge 322
      // 024: iload 3
      // 025: ifne 327
      // 028: bipush 0
      // 029: aload 0
      // 02a: getfield qa.g [Z
      // 02d: iload 2
      // 02e: baload
      // 02f: ifne 03b
      // 032: goto 036
      // 035: athrow
      // 036: bipush 1
      // 037: goto 03c
      // 03a: athrow
      // 03b: bipush 0
      // 03c: if_icmpeq 042
      // 03f: goto 31b
      // 042: aload 0
      // 043: getfield qa.U [I
      // 046: iload 2
      // 047: iaload
      // 048: ifeq 2f7
      // 04b: bipush 1
      // 04c: aload 0
      // 04d: getfield qa.U [I
      // 050: iload 2
      // 051: iaload
      // 052: if_icmpne 099
      // 055: goto 059
      // 058: athrow
      // 059: aload 0
      // 05a: aload 0
      // 05b: getfield qa.yb [Ljava/lang/String;
      // 05e: iload 2
      // 05f: aaload
      // 060: aload 0
      // 061: getfield qa.B [I
      // 064: iload 2
      // 065: iaload
      // 066: bipush 117
      // 068: aload 0
      // 069: getfield qa.k [I
      // 06c: iload 2
      // 06d: iaload
      // 06e: aload 0
      // 06f: getfield qa.kb [I
      // 072: iload 2
      // 073: iaload
      // 074: aload 0
      // 075: getfield qa.w Lua;
      // 078: aload 0
      // 079: getfield qa.k [I
      // 07c: iload 2
      // 07d: iaload
      // 07e: bipush 108
      // 080: aload 0
      // 081: getfield qa.yb [Ljava/lang/String;
      // 084: iload 2
      // 085: aaload
      // 086: invokevirtual ua.a (IILjava/lang/String;)I
      // 089: bipush 2
      // 08a: idiv
      // 08b: isub
      // 08c: iload 2
      // 08d: bipush 0
      // 08e: invokespecial qa.a (Ljava/lang/String;IBIIII)V
      // 091: iload 3
      // 092: ifeq 31b
      // 095: goto 099
      // 098: athrow
      // 099: aload 0
      // 09a: getfield qa.U [I
      // 09d: iload 2
      // 09e: iaload
      // 09f: bipush 2
      // 0a0: if_icmpne 0cd
      // 0a3: goto 0a7
      // 0a6: athrow
      // 0a7: aload 0
      // 0a8: aload 0
      // 0a9: getfield qa.ob [I
      // 0ac: iload 2
      // 0ad: iaload
      // 0ae: bipush 69
      // 0b0: aload 0
      // 0b1: getfield qa.O [I
      // 0b4: iload 2
      // 0b5: iaload
      // 0b6: aload 0
      // 0b7: getfield qa.kb [I
      // 0ba: iload 2
      // 0bb: iaload
      // 0bc: aload 0
      // 0bd: getfield qa.B [I
      // 0c0: iload 2
      // 0c1: iaload
      // 0c2: invokespecial qa.a (IBIII)V
      // 0c5: iload 3
      // 0c6: ifeq 31b
      // 0c9: goto 0cd
      // 0cc: athrow
      // 0cd: bipush 3
      // 0ce: aload 0
      // 0cf: getfield qa.U [I
      // 0d2: iload 2
      // 0d3: iaload
      // 0d4: if_icmpeq 2d8
      // 0d7: goto 0db
      // 0da: athrow
      // 0db: bipush 4
      // 0dc: aload 0
      // 0dd: getfield qa.U [I
      // 0e0: iload 2
      // 0e1: iaload
      // 0e2: if_icmpeq 294
      // 0e5: goto 0e9
      // 0e8: athrow
      // 0e9: bipush 5
      // 0ea: aload 0
      // 0eb: getfield qa.U [I
      // 0ee: iload 2
      // 0ef: iaload
      // 0f0: if_icmpeq 106
      // 0f3: goto 0f7
      // 0f6: athrow
      // 0f7: aload 0
      // 0f8: getfield qa.U [I
      // 0fb: iload 2
      // 0fc: iaload
      // 0fd: bipush 6
      // 0ff: if_icmpne 138
      // 102: goto 106
      // 105: athrow
      // 106: aload 0
      // 107: aload 0
      // 108: getfield qa.k [I
      // 10b: iload 2
      // 10c: iaload
      // 10d: aload 0
      // 10e: getfield qa.yb [Ljava/lang/String;
      // 111: iload 2
      // 112: aaload
      // 113: aload 0
      // 114: getfield qa.ob [I
      // 117: iload 2
      // 118: iaload
      // 119: aload 0
      // 11a: getfield qa.O [I
      // 11d: iload 2
      // 11e: iaload
      // 11f: bipush 1
      // 120: aload 0
      // 121: getfield qa.kb [I
      // 124: iload 2
      // 125: iaload
      // 126: aload 0
      // 127: getfield qa.B [I
      // 12a: iload 2
      // 12b: iaload
      // 12c: iload 2
      // 12d: invokespecial qa.a (ILjava/lang/String;IIZIII)V
      // 130: iload 3
      // 131: ifeq 31b
      // 134: goto 138
      // 137: athrow
      // 138: aload 0
      // 139: getfield qa.U [I
      // 13c: iload 2
      // 13d: iaload
      // 13e: bipush 7
      // 140: if_icmpeq 26d
      // 143: goto 147
      // 146: athrow
      // 147: aload 0
      // 148: getfield qa.U [I
      // 14b: iload 2
      // 14c: iaload
      // 14d: bipush 8
      // 14f: if_icmpne 17d
      // 152: goto 156
      // 155: athrow
      // 156: aload 0
      // 157: aload 0
      // 158: getfield qa.Ab [[Ljava/lang/String;
      // 15b: iload 2
      // 15c: aaload
      // 15d: iload 2
      // 15e: bipush -121
      // 160: aload 0
      // 161: getfield qa.k [I
      // 164: iload 2
      // 165: iaload
      // 166: aload 0
      // 167: getfield qa.kb [I
      // 16a: iload 2
      // 16b: iaload
      // 16c: aload 0
      // 16d: getfield qa.B [I
      // 170: iload 2
      // 171: iaload
      // 172: invokespecial qa.a ([Ljava/lang/String;IIIII)V
      // 175: iload 3
      // 176: ifeq 31b
      // 179: goto 17d
      // 17c: athrow
      // 17d: bipush -10
      // 17f: aload 0
      // 180: getfield qa.U [I
      // 183: iload 2
      // 184: iaload
      // 185: bipush -1
      // 186: ixor
      // 187: if_icmpne 1d2
      // 18a: goto 18e
      // 18d: athrow
      // 18e: aload 0
      // 18f: aload 0
      // 190: getfield qa.O [I
      // 193: iload 2
      // 194: iaload
      // 195: aload 0
      // 196: getfield qa.kb [I
      // 199: iload 2
      // 19a: iaload
      // 19b: iload 2
      // 19c: aload 0
      // 19d: getfield qa.Ab [[Ljava/lang/String;
      // 1a0: iload 2
      // 1a1: aaload
      // 1a2: aload 0
      // 1a3: getfield qa.pb [I
      // 1a6: iload 2
      // 1a7: iaload
      // 1a8: aload 0
      // 1a9: getfield qa.k [I
      // 1ac: iload 2
      // 1ad: iaload
      // 1ae: aload 0
      // 1af: getfield qa.B [I
      // 1b2: iload 2
      // 1b3: iaload
      // 1b4: aload 0
      // 1b5: getfield qa.m [[I
      // 1b8: iload 2
      // 1b9: aaload
      // 1ba: bipush 0
      // 1bb: aload 0
      // 1bc: getfield qa.j [I
      // 1bf: iload 2
      // 1c0: iaload
      // 1c1: aload 0
      // 1c2: getfield qa.ob [I
      // 1c5: iload 2
      // 1c6: iaload
      // 1c7: invokespecial qa.a (III[Ljava/lang/String;III[IIII)V
      // 1ca: iload 3
      // 1cb: ifeq 31b
      // 1ce: goto 1d2
      // 1d1: athrow
      // 1d2: aload 0
      // 1d3: getfield qa.U [I
      // 1d6: iload 2
      // 1d7: iaload
      // 1d8: bipush 11
      // 1da: if_icmpeq 248
      // 1dd: goto 1e1
      // 1e0: athrow
      // 1e1: aload 0
      // 1e2: getfield qa.U [I
      // 1e5: iload 2
      // 1e6: iaload
      // 1e7: bipush -1
      // 1e8: ixor
      // 1e9: bipush -13
      // 1eb: if_icmpeq 228
      // 1ee: goto 1f2
      // 1f1: athrow
      // 1f2: bipush 14
      // 1f4: aload 0
      // 1f5: getfield qa.U [I
      // 1f8: iload 2
      // 1f9: iaload
      // 1fa: if_icmpne 31b
      // 1fd: goto 201
      // 200: athrow
      // 201: aload 0
      // 202: bipush 52
      // 204: aload 0
      // 205: getfield qa.kb [I
      // 208: iload 2
      // 209: iaload
      // 20a: aload 0
      // 20b: getfield qa.O [I
      // 20e: iload 2
      // 20f: iaload
      // 210: aload 0
      // 211: getfield qa.B [I
      // 214: iload 2
      // 215: iaload
      // 216: aload 0
      // 217: getfield qa.ob [I
      // 21a: iload 2
      // 21b: iaload
      // 21c: iload 2
      // 21d: invokespecial qa.a (BIIIII)V
      // 220: iload 3
      // 221: ifeq 31b
      // 224: goto 228
      // 227: athrow
      // 228: aload 0
      // 229: bipush -82
      // 22b: aload 0
      // 22c: getfield qa.B [I
      // 22f: iload 2
      // 230: iaload
      // 231: aload 0
      // 232: getfield qa.kb [I
      // 235: iload 2
      // 236: iaload
      // 237: aload 0
      // 238: getfield qa.k [I
      // 23b: iload 2
      // 23c: iaload
      // 23d: invokespecial qa.b (IIII)V
      // 240: iload 3
      // 241: ifeq 31b
      // 244: goto 248
      // 247: athrow
      // 248: aload 0
      // 249: aload 0
      // 24a: getfield qa.B [I
      // 24d: iload 2
      // 24e: iaload
      // 24f: aload 0
      // 250: getfield qa.ob [I
      // 253: iload 2
      // 254: iaload
      // 255: bipush 1
      // 256: aload 0
      // 257: getfield qa.kb [I
      // 25a: iload 2
      // 25b: iaload
      // 25c: aload 0
      // 25d: getfield qa.O [I
      // 260: iload 2
      // 261: iaload
      // 262: invokespecial qa.a (IIZII)V
      // 265: iload 3
      // 266: ifeq 31b
      // 269: goto 26d
      // 26c: athrow
      // 26d: aload 0
      // 26e: aload 0
      // 26f: getfield qa.kb [I
      // 272: iload 2
      // 273: iaload
      // 274: aload 0
      // 275: getfield qa.k [I
      // 278: iload 2
      // 279: iaload
      // 27a: bipush -73
      // 27c: aload 0
      // 27d: getfield qa.Ab [[Ljava/lang/String;
      // 280: iload 2
      // 281: aaload
      // 282: iload 2
      // 283: aload 0
      // 284: getfield qa.B [I
      // 287: iload 2
      // 288: iaload
      // 289: invokespecial qa.a (IIB[Ljava/lang/String;II)V
      // 28c: iload 3
      // 28d: ifeq 31b
      // 290: goto 294
      // 293: athrow
      // 294: aload 0
      // 295: aload 0
      // 296: getfield qa.m [[I
      // 299: iload 2
      // 29a: aaload
      // 29b: aload 0
      // 29c: getfield qa.j [I
      // 29f: iload 2
      // 2a0: iaload
      // 2a1: iload 2
      // 2a2: aload 0
      // 2a3: getfield qa.kb [I
      // 2a6: iload 2
      // 2a7: iaload
      // 2a8: aload 0
      // 2a9: getfield qa.B [I
      // 2ac: iload 2
      // 2ad: iaload
      // 2ae: aload 0
      // 2af: getfield qa.ob [I
      // 2b2: iload 2
      // 2b3: iaload
      // 2b4: aload 0
      // 2b5: getfield qa.O [I
      // 2b8: iload 2
      // 2b9: iaload
      // 2ba: aload 0
      // 2bb: getfield qa.pb [I
      // 2be: iload 2
      // 2bf: iaload
      // 2c0: aload 0
      // 2c1: getfield qa.Ab [[Ljava/lang/String;
      // 2c4: iload 2
      // 2c5: aaload
      // 2c6: aload 0
      // 2c7: getfield qa.k [I
      // 2ca: iload 2
      // 2cb: iaload
      // 2cc: bipush 0
      // 2cd: invokespecial qa.a ([IIIIIIII[Ljava/lang/String;IZ)V
      // 2d0: iload 3
      // 2d1: ifeq 31b
      // 2d4: goto 2d8
      // 2d7: athrow
      // 2d8: aload 0
      // 2d9: aload 0
      // 2da: getfield qa.B [I
      // 2dd: iload 2
      // 2de: iaload
      // 2df: bipush 0
      // 2e0: aload 0
      // 2e1: getfield qa.kb [I
      // 2e4: iload 2
      // 2e5: iaload
      // 2e6: aload 0
      // 2e7: getfield qa.ob [I
      // 2ea: iload 2
      // 2eb: iaload
      // 2ec: invokespecial qa.a (IIII)V
      // 2ef: iload 3
      // 2f0: ifeq 31b
      // 2f3: goto 2f7
      // 2f6: athrow
      // 2f7: aload 0
      // 2f8: aload 0
      // 2f9: getfield qa.yb [Ljava/lang/String;
      // 2fc: iload 2
      // 2fd: aaload
      // 2fe: aload 0
      // 2ff: getfield qa.B [I
      // 302: iload 2
      // 303: iaload
      // 304: bipush -65
      // 306: aload 0
      // 307: getfield qa.k [I
      // 30a: iload 2
      // 30b: iaload
      // 30c: aload 0
      // 30d: getfield qa.kb [I
      // 310: iload 2
      // 311: iaload
      // 312: iload 2
      // 313: bipush 0
      // 314: invokespecial qa.a (Ljava/lang/String;IBIIII)V
      // 317: goto 31b
      // 31a: athrow
      // 31b: iinc 2 1
      // 31e: iload 3
      // 31f: ifeq 01c
      // 322: aload 0
      // 323: bipush 0
      // 324: putfield qa.zb I
      // 327: goto 34c
      // 32a: astore 2
      // 32b: aload 2
      // 32c: new java/lang/StringBuilder
      // 32f: dup
      // 330: invokespecial java/lang/StringBuilder.<init> ()V
      // 333: getstatic qa.W [Ljava/lang/String;
      // 336: bipush 11
      // 338: aaload
      // 339: invokevirtual java/lang/StringBuilder.append (Ljava/lang/String;)Ljava/lang/StringBuilder;
      // 33c: iload 1
      // 33d: invokevirtual java/lang/StringBuilder.append (I)Ljava/lang/StringBuilder;
      // 340: bipush 41
      // 342: invokevirtual java/lang/StringBuilder.append (C)Ljava/lang/StringBuilder;
      // 345: invokevirtual java/lang/StringBuilder.toString ()Ljava/lang/String;
      // 348: invokestatic i.a (Ljava/lang/Throwable;Ljava/lang/String;)Lla;
      // 34b: athrow
      // 34c: return
   }

   final int a(boolean var1, byte var2, int var3, int var4, String var5, int var6) {
      try {
         try {
            this.U[this.eb] = 1;
            if (var2 >= -71) {
               this.a(-106, (String)null, 31, 96, (String)null, (String)null, 36);
            }
         } catch (RuntimeException var9) {
            throw var9;
         }

         A++;
         this.g[this.eb] = true;
         this.D[this.eb] = false;
         this.k[this.eb] = var3;
         this.Y[this.eb] = var1;
         this.kb[this.eb] = var4;
         this.B[this.eb] = var6;
         this.yb[this.eb] = var5;
         return this.eb++;
      } catch (RuntimeException var10) {
         RuntimeException var7 = var10;

         RuntimeException var10000;
         StringBuilder var10001;
         try {
            var10000 = var7;
            var10001 = new StringBuilder()
               .append(W[28])
               .append(var1)
               .append(',')
               .append((int)var2)
               .append(',')
               .append(var3)
               .append(',')
               .append(var4)
               .append(',');
            if (var5 != null) {
               throw i.a(var7, var10001.append(W[2]).append((char)44).append(var6).append((char)41).toString());
            }
         } catch (RuntimeException var8) {
            throw var8;
         }

         throw i.a(var10000, var10001.append(W[1]).append((char)44).append(var6).append((char)41).toString());
      }
   }

   final int a(int var1, int var2, int var3, int var4, int var5, int var6, int var7, boolean var8) {
      try {
         try {
            v++;
            this.U[this.eb] = 4;
            this.g[this.eb] = true;
            this.D[this.eb] = false;
            this.kb[this.eb] = var3;
            this.B[this.eb] = var5;
            this.ob[this.eb] = var1;
            this.O[this.eb] = var2;
            this.Y[this.eb] = var8;
            this.k[this.eb] = var6;
            this.sb[this.eb] = var4;
            this.pb[this.eb] = 0;
            this.j[this.eb] = 0;
            this.Ab[this.eb] = new String[var4];
            if (var7 != 63) {
               this.a(39, 117, 98, -16);
            }
         } catch (RuntimeException var10) {
            throw var10;
         }

         this.m[this.eb] = new int[var4];
         this.Fb[this.eb] = new String[var4];
         this.p[this.eb] = new String[var4];
         return this.eb++;
      } catch (RuntimeException var11) {
         throw i.a(var11, W[45] + var1 + 44 + var2 + 44 + var3 + 44 + var4 + 44 + var5 + 44 + var6 + 44 + var7 + 44 + var8 + 41);
      }
   }

   final String a(int var1, int var2, int var3) {
      try {
         try {
            if (var2 >= -90) {
               this.d = (boolean[])null;
            }
         } catch (RuntimeException var5) {
            throw var5;
         }

         X++;
         return this.p[var3][var1];
      } catch (RuntimeException var6) {
         throw i.a(var6, W[36] + var1 + ',' + var2 + ',' + var3 + ')');
      }
   }

   final void e(int var1, int var2) {
      try {
         try {
            if (var2 != 14) {
               this.d(-43, 43, 111, -105, -59);
            }
         } catch (RuntimeException var4) {
            throw var4;
         }

         ab++;
         this.j[var1] = 0;
         this.N[var1] = -1;
      } catch (RuntimeException var5) {
         throw i.a(var5, W[33] + var1 + ',' + var2 + ')');
      }
   }

   private final void a(
      int[] param1, int param2, int param3, int param4, int param5, int param6, int param7, int param8, String[] param9, int param10, boolean param11
   ) {
      // $VF: Couldn't be decompiled
      // Please report this to the Vineflower issue tracker, at https://github.com/Vineflower/vineflower/issues with a copy of the class file (if you have the rights to distribute it!)
      // java.lang.RuntimeException: parsing failure!
      //   at org.jetbrains.java.decompiler.modules.decompiler.decompose.DomHelper.parseGraph(DomHelper.java:211)
      //   at org.jetbrains.java.decompiler.main.rels.MethodProcessor.codeToJava(MethodProcessor.java:166)
      //
      // Bytecode:
      // 000: getstatic client.vh Z
      // 003: istore 17
      // 005: getstatic qa.o I
      // 008: bipush 1
      // 009: iadd
      // 00a: putstatic qa.o I
      // 00d: iload 7
      // 00f: aload 0
      // 010: getfield qa.w Lua;
      // 013: ldc 508305352
      // 015: iload 10
      // 017: invokevirtual ua.a (II)I
      // 01a: idiv
      // 01b: istore 12
      // 01d: iload 2
      // 01e: iload 12
      // 020: ineg
      // 021: iload 8
      // 023: iadd
      // 024: if_icmple 02d
      // 027: iload 8
      // 029: iload 12
      // 02b: isub
      // 02c: istore 2
      // 02d: iload 2
      // 02e: bipush -1
      // 02f: ixor
      // 030: bipush -1
      // 031: if_icmple 036
      // 034: bipush 0
      // 035: istore 2
      // 036: iload 11
      // 038: ifeq 051
      // 03b: aload 0
      // 03c: aconst_null
      // 03d: checkcast [Ljava/lang/String;
      // 040: bipush -61
      // 042: bipush -120
      // 044: bipush -114
      // 046: bipush 65
      // 048: bipush -8
      // 04a: invokespecial qa.a ([Ljava/lang/String;IIIII)V
      // 04d: goto 051
      // 050: athrow
      // 051: aload 0
      // 052: getfield qa.j [I
      // 055: iload 3
      // 056: iload 2
      // 057: iastore
      // 058: iload 8
      // 05a: iload 12
      // 05c: if_icmple 246
      // 05f: bipush -12
      // 061: iload 6
      // 063: iadd
      // 064: iload 4
      // 066: iadd
      // 067: istore 13
      // 069: iload 12
      // 06b: iload 7
      // 06d: bipush -27
      // 06f: iadd
      // 070: imul
      // 071: iload 8
      // 073: idiv
      // 074: istore 14
      // 076: bipush 6
      // 078: iload 14
      // 07a: if_icmpgt 081
      // 07d: goto 085
      // 080: athrow
      // 081: bipush 6
      // 083: istore 14
      // 085: iload 14
      // 087: ineg
      // 088: bipush -27
      // 08a: iadd
      // 08b: iload 7
      // 08d: iadd
      // 08e: iload 2
      // 08f: imul
      // 090: iload 12
      // 092: ineg
      // 093: iload 8
      // 095: iadd
      // 096: idiv
      // 097: istore 15
      // 099: bipush -2
      // 09b: aload 0
      // 09c: getfield qa.Hb I
      // 09f: bipush -1
      // 0a0: ixor
      // 0a1: if_icmpne 137
      // 0a4: aload 0
      // 0a5: getfield qa.bb I
      // 0a8: bipush -1
      // 0a9: ixor
      // 0aa: iload 13
      // 0ac: bipush -1
      // 0ad: ixor
      // 0ae: if_icmpgt 137
      // 0b1: goto 0b5
      // 0b4: athrow
      // 0b5: bipush 12
      // 0b7: iload 13
      // 0b9: iadd
      // 0ba: bipush -1
      // 0bb: ixor
      // 0bc: aload 0
      // 0bd: getfield qa.bb I
      // 0c0: bipush -1
      // 0c1: ixor
      // 0c2: if_icmple 0cd
      // 0c5: goto 0c9
      // 0c8: athrow
      // 0c9: goto 137
      // 0cc: athrow
      // 0cd: aload 0
      // 0ce: getfield qa.hb I
      // 0d1: iload 5
      // 0d3: if_icmple 0f9
      // 0d6: aload 0
      // 0d7: getfield qa.hb I
      // 0da: bipush -1
      // 0db: ixor
      // 0dc: iload 5
      // 0de: bipush -12
      // 0e0: isub
      // 0e1: bipush -1
      // 0e2: ixor
      // 0e3: if_icmple 0f9
      // 0e6: goto 0ea
      // 0e9: athrow
      // 0ea: iload 2
      // 0eb: ifle 0f9
      // 0ee: goto 0f2
      // 0f1: athrow
      // 0f2: iinc 2 -1
      // 0f5: goto 0f9
      // 0f8: athrow
      // 0f9: bipush -12
      // 0fb: iload 7
      // 0fd: iload 5
      // 0ff: iadd
      // 100: iadd
      // 101: aload 0
      // 102: getfield qa.hb I
      // 105: if_icmpge 130
      // 108: aload 0
      // 109: getfield qa.hb I
      // 10c: iload 7
      // 10e: iload 5
      // 110: iadd
      // 111: if_icmpge 130
      // 114: goto 118
      // 117: athrow
      // 118: iload 2
      // 119: bipush -1
      // 11a: ixor
      // 11b: iload 8
      // 11d: iload 12
      // 11f: isub
      // 120: bipush -1
      // 121: ixor
      // 122: if_icmple 130
      // 125: goto 129
      // 128: athrow
      // 129: iinc 2 1
      // 12c: goto 130
      // 12f: athrow
      // 130: aload 0
      // 131: getfield qa.j [I
      // 134: iload 3
      // 135: iload 2
      // 136: iastore
      // 137: aload 0
      // 138: getfield qa.Hb I
      // 13b: bipush -1
      // 13c: ixor
      // 13d: bipush -2
      // 13f: if_icmpne 198
      // 142: iload 13
      // 144: bipush -1
      // 145: ixor
      // 146: aload 0
      // 147: getfield qa.bb I
      // 14a: bipush -1
      // 14b: ixor
      // 14c: if_icmplt 167
      // 14f: goto 153
      // 152: athrow
      // 153: iload 13
      // 155: bipush 12
      // 157: iadd
      // 158: bipush -1
      // 159: ixor
      // 15a: aload 0
      // 15b: getfield qa.bb I
      // 15e: bipush -1
      // 15f: ixor
      // 160: if_icmple 1a8
      // 163: goto 167
      // 166: athrow
      // 167: aload 0
      // 168: getfield qa.bb I
      // 16b: bipush -12
      // 16d: iload 13
      // 16f: iadd
      // 170: if_icmplt 198
      // 173: goto 177
      // 176: athrow
      // 177: aload 0
      // 178: getfield qa.bb I
      // 17b: bipush -1
      // 17c: ixor
      // 17d: bipush 24
      // 17f: iload 13
      // 181: iadd
      // 182: bipush -1
      // 183: ixor
      // 184: if_icmplt 198
      // 187: goto 18b
      // 18a: athrow
      // 18b: aload 0
      // 18c: getfield qa.d [Z
      // 18f: iload 3
      // 190: baload
      // 191: ifne 1a8
      // 194: goto 198
      // 197: athrow
      // 198: aload 0
      // 199: getfield qa.d [Z
      // 19c: iload 3
      // 19d: bipush 0
      // 19e: bastore
      // 19f: iload 17
      // 1a1: ifeq 220
      // 1a4: goto 1a8
      // 1a7: athrow
      // 1a8: aload 0
      // 1a9: getfield qa.hb I
      // 1ac: bipush 12
      // 1ae: iload 5
      // 1b0: iadd
      // 1b1: if_icmple 220
      // 1b4: goto 1b8
      // 1b7: athrow
      // 1b8: iload 5
      // 1ba: iload 7
      // 1bc: ineg
      // 1bd: isub
      // 1be: bipush 12
      // 1c0: isub
      // 1c1: bipush -1
      // 1c2: ixor
      // 1c3: aload 0
      // 1c4: getfield qa.hb I
      // 1c7: bipush -1
      // 1c8: ixor
      // 1c9: if_icmplt 1d4
      // 1cc: goto 1d0
      // 1cf: athrow
      // 1d0: goto 220
      // 1d3: athrow
      // 1d4: aload 0
      // 1d5: getfield qa.d [Z
      // 1d8: iload 3
      // 1d9: bipush 1
      // 1da: bastore
      // 1db: iload 14
      // 1dd: bipush 2
      // 1de: idiv
      // 1df: ineg
      // 1e0: aload 0
      // 1e1: getfield qa.hb I
      // 1e4: iadd
      // 1e5: iload 5
      // 1e7: isub
      // 1e8: bipush -12
      // 1ea: iadd
      // 1eb: istore 16
      // 1ed: iload 16
      // 1ef: iload 8
      // 1f1: imul
      // 1f2: iload 7
      // 1f4: bipush -24
      // 1f6: iadd
      // 1f7: idiv
      // 1f8: istore 2
      // 1f9: iload 12
      // 1fb: ineg
      // 1fc: iload 8
      // 1fe: iadd
      // 1ff: iload 2
      // 200: if_icmplt 207
      // 203: goto 20e
      // 206: athrow
      // 207: iload 8
      // 209: iload 12
      // 20b: ineg
      // 20c: iadd
      // 20d: istore 2
      // 20e: bipush 0
      // 20f: iload 2
      // 210: if_icmpgt 217
      // 213: goto 219
      // 216: athrow
      // 217: bipush 0
      // 218: istore 2
      // 219: aload 0
      // 21a: getfield qa.j [I
      // 21d: iload 3
      // 21e: iload 2
      // 21f: iastore
      // 220: iload 2
      // 221: iload 14
      // 223: ineg
      // 224: bipush -27
      // 226: iload 7
      // 228: iadd
      // 229: iadd
      // 22a: imul
      // 22b: iload 8
      // 22d: iload 12
      // 22f: ineg
      // 230: iadd
      // 231: idiv
      // 232: istore 15
      // 234: aload 0
      // 235: iload 14
      // 237: iload 15
      // 239: iload 4
      // 23b: iload 6
      // 23d: iload 7
      // 23f: iload 5
      // 241: bipush 113
      // 243: invokespecial qa.a (IIIIIIB)V
      // 246: aload 0
      // 247: getfield qa.w Lua;
      // 24a: ldc 508305352
      // 24c: iload 10
      // 24e: invokevirtual ua.a (II)I
      // 251: iload 12
      // 253: imul
      // 254: ineg
      // 255: iload 7
      // 257: iadd
      // 258: istore 13
      // 25a: iload 5
      // 25c: bipush 5
      // 25d: aload 0
      // 25e: getfield qa.w Lua;
      // 261: ldc 508305352
      // 263: iload 10
      // 265: invokevirtual ua.a (II)I
      // 268: imul
      // 269: bipush 6
      // 26b: idiv
      // 26c: iload 13
      // 26e: bipush 2
      // 26f: idiv
      // 270: iadd
      // 271: iadd
      // 272: istore 14
      // 274: iload 2
      // 275: istore 15
      // 277: iload 8
      // 279: iload 15
      // 27b: if_icmple 34e
      // 27e: iload 17
      // 280: ifne 3f9
      // 283: aload 0
      // 284: getfield qa.zb I
      // 287: ifeq 30b
      // 28a: goto 28e
      // 28d: athrow
      // 28e: bipush 2
      // 28f: iload 4
      // 291: iadd
      // 292: aload 0
      // 293: getfield qa.bb I
      // 296: if_icmpgt 30b
      // 299: goto 29d
      // 29c: athrow
      // 29d: aload 0
      // 29e: getfield qa.bb I
      // 2a1: bipush -1
      // 2a2: ixor
      // 2a3: aload 0
      // 2a4: getfield qa.w Lua;
      // 2a7: iload 10
      // 2a9: bipush 97
      // 2ab: aload 9
      // 2ad: iload 15
      // 2af: aaload
      // 2b0: invokevirtual ua.a (IILjava/lang/String;)I
      // 2b3: iload 4
      // 2b5: iadd
      // 2b6: bipush -2
      // 2b8: isub
      // 2b9: bipush -1
      // 2ba: ixor
      // 2bb: if_icmplt 30b
      // 2be: goto 2c2
      // 2c1: athrow
      // 2c2: iload 14
      // 2c4: bipush -2
      // 2c6: aload 0
      // 2c7: getfield qa.hb I
      // 2ca: iadd
      // 2cb: if_icmplt 30b
      // 2ce: goto 2d2
      // 2d1: athrow
      // 2d2: aload 0
      // 2d3: getfield qa.hb I
      // 2d6: bipush 2
      // 2d7: isub
      // 2d8: aload 0
      // 2d9: getfield qa.w Lua;
      // 2dc: ldc 508305352
      // 2de: iload 10
      // 2e0: invokevirtual ua.a (II)I
      // 2e3: ineg
      // 2e4: iload 14
      // 2e6: iadd
      // 2e7: if_icmple 30b
      // 2ea: goto 2ee
      // 2ed: athrow
      // 2ee: aload 0
      // 2ef: getfield qa.D [Z
      // 2f2: iload 3
      // 2f3: bipush 1
      // 2f4: bastore
      // 2f5: aload 0
      // 2f6: getfield qa.vb [I
      // 2f9: iload 3
      // 2fa: aload 0
      // 2fb: getfield qa.zb I
      // 2fe: ldc -259102544
      // 300: ishl
      // 301: iload 15
      // 303: invokestatic d.a (II)I
      // 306: iastore
      // 307: goto 30b
      // 30a: athrow
      // 30b: aload 0
      // 30c: iload 10
      // 30e: iload 3
      // 30f: bipush 1
      // 310: aload 1
      // 311: iload 15
      // 313: iaload
      // 314: bipush 2
      // 315: iload 4
      // 317: iadd
      // 318: iload 14
      // 31a: aload 9
      // 31c: iload 15
      // 31e: aaload
      // 31f: invokespecial qa.a (IIZIIILjava/lang/String;)V
      // 322: iload 14
      // 324: aload 0
      // 325: getfield qa.w Lua;
      // 328: ldc 508305352
      // 32a: iload 10
      // 32c: invokevirtual ua.a (II)I
      // 32f: getstatic ia.i I
      // 332: ineg
      // 333: iadd
      // 334: iadd
      // 335: istore 14
      // 337: iload 14
      // 339: iload 5
      // 33b: iload 7
      // 33d: ineg
      // 33e: isub
      // 33f: if_icmpge 34e
      // 342: iinc 15 1
      // 345: iload 17
      // 347: ifeq 277
      // 34a: goto 34e
      // 34d: athrow
      // 34e: goto 3f9
      // 351: astore 12
      // 353: aload 12
      // 355: new java/lang/StringBuilder
      // 358: dup
      // 359: invokespecial java/lang/StringBuilder.<init> ()V
      // 35c: getstatic qa.W [Ljava/lang/String;
      // 35f: bipush 37
      // 361: aaload
      // 362: invokevirtual java/lang/StringBuilder.append (Ljava/lang/String;)Ljava/lang/StringBuilder;
      // 365: aload 1
      // 366: ifnull 372
      // 369: getstatic qa.W [Ljava/lang/String;
      // 36c: bipush 2
      // 36d: aaload
      // 36e: goto 377
      // 371: athrow
      // 372: getstatic qa.W [Ljava/lang/String;
      // 375: bipush 1
      // 376: aaload
      // 377: invokevirtual java/lang/StringBuilder.append (Ljava/lang/String;)Ljava/lang/StringBuilder;
      // 37a: bipush 44
      // 37c: invokevirtual java/lang/StringBuilder.append (C)Ljava/lang/StringBuilder;
      // 37f: iload 2
      // 380: invokevirtual java/lang/StringBuilder.append (I)Ljava/lang/StringBuilder;
      // 383: bipush 44
      // 385: invokevirtual java/lang/StringBuilder.append (C)Ljava/lang/StringBuilder;
      // 388: iload 3
      // 389: invokevirtual java/lang/StringBuilder.append (I)Ljava/lang/StringBuilder;
      // 38c: bipush 44
      // 38e: invokevirtual java/lang/StringBuilder.append (C)Ljava/lang/StringBuilder;
      // 391: iload 4
      // 393: invokevirtual java/lang/StringBuilder.append (I)Ljava/lang/StringBuilder;
      // 396: bipush 44
      // 398: invokevirtual java/lang/StringBuilder.append (C)Ljava/lang/StringBuilder;
      // 39b: iload 5
      // 39d: invokevirtual java/lang/StringBuilder.append (I)Ljava/lang/StringBuilder;
      // 3a0: bipush 44
      // 3a2: invokevirtual java/lang/StringBuilder.append (C)Ljava/lang/StringBuilder;
      // 3a5: iload 6
      // 3a7: invokevirtual java/lang/StringBuilder.append (I)Ljava/lang/StringBuilder;
      // 3aa: bipush 44
      // 3ac: invokevirtual java/lang/StringBuilder.append (C)Ljava/lang/StringBuilder;
      // 3af: iload 7
      // 3b1: invokevirtual java/lang/StringBuilder.append (I)Ljava/lang/StringBuilder;
      // 3b4: bipush 44
      // 3b6: invokevirtual java/lang/StringBuilder.append (C)Ljava/lang/StringBuilder;
      // 3b9: iload 8
      // 3bb: invokevirtual java/lang/StringBuilder.append (I)Ljava/lang/StringBuilder;
      // 3be: bipush 44
      // 3c0: invokevirtual java/lang/StringBuilder.append (C)Ljava/lang/StringBuilder;
      // 3c3: aload 9
      // 3c5: ifnull 3d1
      // 3c8: getstatic qa.W [Ljava/lang/String;
      // 3cb: bipush 2
      // 3cc: aaload
      // 3cd: goto 3d6
      // 3d0: athrow
      // 3d1: getstatic qa.W [Ljava/lang/String;
      // 3d4: bipush 1
      // 3d5: aaload
      // 3d6: invokevirtual java/lang/StringBuilder.append (Ljava/lang/String;)Ljava/lang/StringBuilder;
      // 3d9: bipush 44
      // 3db: invokevirtual java/lang/StringBuilder.append (C)Ljava/lang/StringBuilder;
      // 3de: iload 10
      // 3e0: invokevirtual java/lang/StringBuilder.append (I)Ljava/lang/StringBuilder;
      // 3e3: bipush 44
      // 3e5: invokevirtual java/lang/StringBuilder.append (C)Ljava/lang/StringBuilder;
      // 3e8: iload 11
      // 3ea: invokevirtual java/lang/StringBuilder.append (Z)Ljava/lang/StringBuilder;
      // 3ed: bipush 41
      // 3ef: invokevirtual java/lang/StringBuilder.append (C)Ljava/lang/StringBuilder;
      // 3f2: invokevirtual java/lang/StringBuilder.toString ()Ljava/lang/String;
      // 3f5: invokestatic i.a (Ljava/lang/Throwable;Ljava/lang/String;)Lla;
      // 3f8: athrow
      // 3f9: return
   }

   private final void a(int var1, int var2, boolean var3, int var4, int var5, int var6, String var7) {
      try {
         try {
            Cb++;
            if (!var3) {
               this.a(-3, 44, (byte)37, (String[])null, -78, 86);
            }
         } catch (RuntimeException var9) {
            throw var9;
         }

         int var12;
         label37: {
            if (!this.Y[var2]) {
               var12 = 0;
               if (!client.vh) {
                  break label37;
               }
            }

            var12 = 16777215;
         }

         this.w.a(var4, var6, var7, var5, var12, (byte)-54, var1);
      } catch (RuntimeException var11) {
         RuntimeException var8 = var11;

         RuntimeException var10000;
         StringBuilder var10001;
         try {
            var10000 = var8;
            var10001 = new StringBuilder()
               .append(W[15])
               .append(var1)
               .append(',')
               .append(var2)
               .append(',')
               .append(var3)
               .append(',')
               .append(var4)
               .append(',')
               .append(var5)
               .append(',')
               .append(var6)
               .append(',');
            if (var7 != null) {
               throw i.a(var8, var10001.append(W[2]).append(')').toString());
            }
         } catch (RuntimeException var10) {
            throw var10;
         }

         throw i.a(var10000, var10001.append(W[1]).append(')').toString());
      }
   }

   final void a(int var1, String var2, int var3) {
      try {
         if (var3 == 27642) {
            this.yb[var1] = var2;
            mb++;
         }
      } catch (RuntimeException var6) {
         RuntimeException var4 = var6;

         RuntimeException var10000;
         StringBuilder var10001;
         try {
            var10000 = var4;
            var10001 = new StringBuilder().append(W[48]).append(var1).append(',');
            if (var2 != null) {
               throw i.a(var4, var10001.append(W[2]).append(',').append(var3).append(')').toString());
            }
         } catch (RuntimeException var5) {
            throw var5;
         }

         throw i.a(var10000, var10001.append(W[1]).append(',').append(var3).append(')').toString());
      }
   }

   private final void a(byte var1, int var2, int var3, int var4, int var5, int var6) {
      boolean var8 = client.vh;

      try {
         this.w.a(var2, (byte)100, 16777215, var4, var3, var5);
         if (var1 == 52) {
            try {
               Db++;
               this.w.b(var5, this.tb, var2, var4, (byte)-116);
               this.w.b(var2, var4, this.tb, var3, 0);
               this.w.b(var5, this.J, var2, -1 + var3 + var4, (byte)-124);
               this.w.b(var5 + var2 - 1, var4, this.J, var3, var1 ^ 52);
               if (this.vb[var6] != 1) {
                  return;
               }
            } catch (RuntimeException var10) {
               throw var10;
            }

            int var7 = 0;

            while (~var3 < ~var7) {
               try {
                  this.w.b(1, 0, var7 + var2, var4 + var7, (byte)88);
                  this.w.b(1, 0, var5 + var2 + (-1 - var7), var7 + var4, (byte)106);
                  var7++;
                  if (var8 || var8) {
                     break;
                  }
               } catch (RuntimeException var9) {
                  throw var9;
               }
            }
         }
      } catch (RuntimeException var11) {
         throw i.a(var11, W[39] + var1 + ',' + var2 + ',' + var3 + ',' + var4 + ',' + var5 + ',' + var6 + ')');
      }
   }

   final void b(int param1, int param2, int param3, int param4, int param5) {
      // $VF: Couldn't be decompiled
      // Please report this to the Vineflower issue tracker, at https://github.com/Vineflower/vineflower/issues with a copy of the class file (if you have the rights to distribute it!)
      // java.lang.RuntimeException: parsing failure!
      //   at org.jetbrains.java.decompiler.modules.decompiler.decompose.DomHelper.parseGraph(DomHelper.java:211)
      //   at org.jetbrains.java.decompiler.main.rels.MethodProcessor.codeToJava(MethodProcessor.java:166)
      //
      // Bytecode:
      // 000: getstatic client.vh Z
      // 003: istore 7
      // 005: aload 0
      // 006: iload 2
      // 007: putfield qa.hb I
      // 00a: aload 0
      // 00b: iload 5
      // 00d: putfield qa.bb I
      // 010: bipush -1
      // 011: iload 4
      // 013: bipush -1
      // 014: ixor
      // 015: if_icmpeq 022
      // 018: aload 0
      // 019: iload 4
      // 01b: putfield qa.zb I
      // 01e: goto 022
      // 021: athrow
      // 022: aload 0
      // 023: iload 1
      // 024: putfield qa.Hb I
      // 027: getstatic qa.xb I
      // 02a: bipush 1
      // 02b: iadd
      // 02c: putstatic qa.xb I
      // 02f: bipush -2
      // 031: iload 4
      // 033: bipush -1
      // 034: ixor
      // 035: if_icmpeq 03c
      // 038: goto 161
      // 03b: athrow
      // 03c: bipush 0
      // 03d: istore 6
      // 03f: aload 0
      // 040: getfield qa.eb I
      // 043: bipush -1
      // 044: ixor
      // 045: iload 6
      // 047: bipush -1
      // 048: ixor
      // 049: if_icmpge 161
      // 04c: aload 0
      // 04d: getfield qa.g [Z
      // 050: iload 6
      // 052: baload
      // 053: iload 7
      // 055: ifne 162
      // 058: ifeq 0d3
      // 05b: goto 05f
      // 05e: athrow
      // 05f: bipush 10
      // 061: aload 0
      // 062: getfield qa.U [I
      // 065: iload 6
      // 067: iaload
      // 068: if_icmpne 0d3
      // 06b: goto 06f
      // 06e: athrow
      // 06f: aload 0
      // 070: getfield qa.kb [I
      // 073: iload 6
      // 075: iaload
      // 076: aload 0
      // 077: getfield qa.bb I
      // 07a: if_icmpgt 0d3
      // 07d: goto 081
      // 080: athrow
      // 081: aload 0
      // 082: getfield qa.hb I
      // 085: aload 0
      // 086: getfield qa.B [I
      // 089: iload 6
      // 08b: iaload
      // 08c: if_icmplt 0d3
      // 08f: goto 093
      // 092: athrow
      // 093: aload 0
      // 094: getfield qa.ob [I
      // 097: iload 6
      // 099: iaload
      // 09a: aload 0
      // 09b: getfield qa.kb [I
      // 09e: iload 6
      // 0a0: iaload
      // 0a1: iadd
      // 0a2: aload 0
      // 0a3: getfield qa.bb I
      // 0a6: if_icmplt 0d3
      // 0a9: goto 0ad
      // 0ac: athrow
      // 0ad: aload 0
      // 0ae: getfield qa.hb I
      // 0b1: aload 0
      // 0b2: getfield qa.O [I
      // 0b5: iload 6
      // 0b7: iaload
      // 0b8: aload 0
      // 0b9: getfield qa.B [I
      // 0bc: iload 6
      // 0be: iaload
      // 0bf: iadd
      // 0c0: if_icmpgt 0d3
      // 0c3: goto 0c7
      // 0c6: athrow
      // 0c7: aload 0
      // 0c8: getfield qa.D [Z
      // 0cb: iload 6
      // 0cd: bipush 1
      // 0ce: bastore
      // 0cf: goto 0d3
      // 0d2: athrow
      // 0d3: aload 0
      // 0d4: getfield qa.g [Z
      // 0d7: iload 6
      // 0d9: baload
      // 0da: ifeq 159
      // 0dd: aload 0
      // 0de: getfield qa.U [I
      // 0e1: iload 6
      // 0e3: iaload
      // 0e4: bipush 14
      // 0e6: if_icmpne 159
      // 0e9: goto 0ed
      // 0ec: athrow
      // 0ed: aload 0
      // 0ee: getfield qa.bb I
      // 0f1: aload 0
      // 0f2: getfield qa.kb [I
      // 0f5: iload 6
      // 0f7: iaload
      // 0f8: if_icmplt 159
      // 0fb: goto 0ff
      // 0fe: athrow
      // 0ff: aload 0
      // 100: getfield qa.hb I
      // 103: aload 0
      // 104: getfield qa.B [I
      // 107: iload 6
      // 109: iaload
      // 10a: if_icmplt 159
      // 10d: goto 111
      // 110: athrow
      // 111: aload 0
      // 112: getfield qa.ob [I
      // 115: iload 6
      // 117: iaload
      // 118: aload 0
      // 119: getfield qa.kb [I
      // 11c: iload 6
      // 11e: iaload
      // 11f: iadd
      // 120: aload 0
      // 121: getfield qa.bb I
      // 124: if_icmplt 159
      // 127: goto 12b
      // 12a: athrow
      // 12b: aload 0
      // 12c: getfield qa.O [I
      // 12f: iload 6
      // 131: iaload
      // 132: aload 0
      // 133: getfield qa.B [I
      // 136: iload 6
      // 138: iaload
      // 139: iadd
      // 13a: aload 0
      // 13b: getfield qa.hb I
      // 13e: if_icmpge 149
      // 141: goto 145
      // 144: athrow
      // 145: goto 159
      // 148: athrow
      // 149: aload 0
      // 14a: getfield qa.vb [I
      // 14d: iload 6
      // 14f: bipush 1
      // 150: aload 0
      // 151: getfield qa.vb [I
      // 154: iload 6
      // 156: iaload
      // 157: isub
      // 158: iastore
      // 159: iinc 6 1
      // 15c: iload 7
      // 15e: ifeq 03f
      // 161: iload 3
      // 162: sipush -9989
      // 165: if_icmpeq 174
      // 168: aload 0
      // 169: bipush -43
      // 16b: bipush 104
      // 16d: invokevirtual qa.a (II)V
      // 170: goto 174
      // 173: athrow
      // 174: bipush 1
      // 175: iload 1
      // 176: if_icmpne 18c
      // 179: aload 0
      // 17a: dup
      // 17b: getfield qa.G I
      // 17e: bipush 1
      // 17f: iadd
      // 180: putfield qa.G I
      // 183: iload 7
      // 185: ifeq 195
      // 188: goto 18c
      // 18b: athrow
      // 18c: aload 0
      // 18d: bipush 0
      // 18e: putfield qa.G I
      // 191: goto 195
      // 194: athrow
      // 195: bipush -2
      // 197: iload 4
      // 199: bipush -1
      // 19a: ixor
      // 19b: if_icmpeq 1b1
      // 19e: aload 0
      // 19f: getfield qa.G I
      // 1a2: bipush -1
      // 1a3: ixor
      // 1a4: bipush -21
      // 1a6: if_icmplt 1b1
      // 1a9: goto 1ad
      // 1ac: athrow
      // 1ad: goto 25e
      // 1b0: athrow
      // 1b1: bipush 0
      // 1b2: istore 6
      // 1b4: aload 0
      // 1b5: getfield qa.eb I
      // 1b8: iload 6
      // 1ba: if_icmple 254
      // 1bd: aload 0
      // 1be: iload 7
      // 1c0: ifne 255
      // 1c3: getfield qa.g [Z
      // 1c6: iload 6
      // 1c8: baload
      // 1c9: ifeq 24c
      // 1cc: goto 1d0
      // 1cf: athrow
      // 1d0: aload 0
      // 1d1: getfield qa.U [I
      // 1d4: iload 6
      // 1d6: iaload
      // 1d7: bipush 15
      // 1d9: if_icmpne 24c
      // 1dc: goto 1e0
      // 1df: athrow
      // 1e0: aload 0
      // 1e1: getfield qa.kb [I
      // 1e4: iload 6
      // 1e6: iaload
      // 1e7: bipush -1
      // 1e8: ixor
      // 1e9: aload 0
      // 1ea: getfield qa.bb I
      // 1ed: bipush -1
      // 1ee: ixor
      // 1ef: if_icmplt 24c
      // 1f2: goto 1f6
      // 1f5: athrow
      // 1f6: aload 0
      // 1f7: getfield qa.hb I
      // 1fa: aload 0
      // 1fb: getfield qa.B [I
      // 1fe: iload 6
      // 200: iaload
      // 201: if_icmplt 24c
      // 204: goto 208
      // 207: athrow
      // 208: aload 0
      // 209: getfield qa.ob [I
      // 20c: iload 6
      // 20e: iaload
      // 20f: aload 0
      // 210: getfield qa.kb [I
      // 213: iload 6
      // 215: iaload
      // 216: iadd
      // 217: aload 0
      // 218: getfield qa.bb I
      // 21b: if_icmplt 24c
      // 21e: goto 222
      // 221: athrow
      // 222: aload 0
      // 223: getfield qa.B [I
      // 226: iload 6
      // 228: iaload
      // 229: aload 0
      // 22a: getfield qa.O [I
      // 22d: iload 6
      // 22f: iaload
      // 230: iadd
      // 231: bipush -1
      // 232: ixor
      // 233: aload 0
      // 234: getfield qa.hb I
      // 237: bipush -1
      // 238: ixor
      // 239: if_icmple 244
      // 23c: goto 240
      // 23f: athrow
      // 240: goto 24c
      // 243: athrow
      // 244: aload 0
      // 245: getfield qa.D [Z
      // 248: iload 6
      // 24a: bipush 1
      // 24b: bastore
      // 24c: iinc 6 1
      // 24f: iload 7
      // 251: ifeq 1b4
      // 254: aload 0
      // 255: dup
      // 256: getfield qa.G I
      // 259: bipush 5
      // 25a: isub
      // 25b: putfield qa.G I
      // 25e: goto 2ab
      // 261: astore 6
      // 263: aload 6
      // 265: new java/lang/StringBuilder
      // 268: dup
      // 269: invokespecial java/lang/StringBuilder.<init> ()V
      // 26c: getstatic qa.W [Ljava/lang/String;
      // 26f: bipush 12
      // 271: aaload
      // 272: invokevirtual java/lang/StringBuilder.append (Ljava/lang/String;)Ljava/lang/StringBuilder;
      // 275: iload 1
      // 276: invokevirtual java/lang/StringBuilder.append (I)Ljava/lang/StringBuilder;
      // 279: bipush 44
      // 27b: invokevirtual java/lang/StringBuilder.append (C)Ljava/lang/StringBuilder;
      // 27e: iload 2
      // 27f: invokevirtual java/lang/StringBuilder.append (I)Ljava/lang/StringBuilder;
      // 282: bipush 44
      // 284: invokevirtual java/lang/StringBuilder.append (C)Ljava/lang/StringBuilder;
      // 287: iload 3
      // 288: invokevirtual java/lang/StringBuilder.append (I)Ljava/lang/StringBuilder;
      // 28b: bipush 44
      // 28d: invokevirtual java/lang/StringBuilder.append (C)Ljava/lang/StringBuilder;
      // 290: iload 4
      // 292: invokevirtual java/lang/StringBuilder.append (I)Ljava/lang/StringBuilder;
      // 295: bipush 44
      // 297: invokevirtual java/lang/StringBuilder.append (C)Ljava/lang/StringBuilder;
      // 29a: iload 5
      // 29c: invokevirtual java/lang/StringBuilder.append (I)Ljava/lang/StringBuilder;
      // 29f: bipush 41
      // 2a1: invokevirtual java/lang/StringBuilder.append (C)Ljava/lang/StringBuilder;
      // 2a4: invokevirtual java/lang/StringBuilder.toString ()Ljava/lang/String;
      // 2a7: invokestatic i.a (Ljava/lang/Throwable;Ljava/lang/String;)Lla;
      // 2aa: athrow
      // 2ab: return
   }

   final int a(int var1, int var2, int var3, int var4, int var5) {
      try {
         P++;
         this.U[this.eb] = 11;
         if (var4 != 26531) {
            return 59;
         } else {
            this.g[this.eb] = true;
            this.D[this.eb] = false;
            this.kb[this.eb] = -(var3 / 2) + var2;
            this.B[this.eb] = -(var1 / 2) + var5;
            this.ob[this.eb] = var3;
            this.O[this.eb] = var1;
            return this.eb++;
         }
      } catch (RuntimeException var7) {
         throw i.a(var7, W[0] + var1 + 44 + var2 + 44 + var3 + 44 + var4 + 44 + var5 + 41);
      }
   }

   private final void a(
      int param1, int param2, int param3, String[] param4, int param5, int param6, int param7, int[] param8, int param9, int param10, int param11
   ) {
      // $VF: Couldn't be decompiled
      // Please report this to the Vineflower issue tracker, at https://github.com/Vineflower/vineflower/issues with a copy of the class file (if you have the rights to distribute it!)
      // java.lang.RuntimeException: parsing failure!
      //   at org.jetbrains.java.decompiler.modules.decompiler.decompose.DomHelper.parseGraph(DomHelper.java:211)
      //   at org.jetbrains.java.decompiler.main.rels.MethodProcessor.codeToJava(MethodProcessor.java:166)
      //
      // Bytecode:
      // 000: getstatic client.vh Z
      // 003: istore 17
      // 005: getstatic qa.db I
      // 008: bipush 1
      // 009: iadd
      // 00a: putstatic qa.db I
      // 00d: iload 9
      // 00f: ifeq 01e
      // 012: aload 0
      // 013: bipush 56
      // 015: bipush -19
      // 017: invokevirtual qa.a (II)V
      // 01a: goto 01e
      // 01d: athrow
      // 01e: iload 1
      // 01f: aload 0
      // 020: getfield qa.w Lua;
      // 023: iload 9
      // 025: ldc 508305352
      // 027: iadd
      // 028: iload 6
      // 02a: invokevirtual ua.a (II)I
      // 02d: idiv
      // 02e: istore 12
      // 030: iload 12
      // 032: bipush -1
      // 033: ixor
      // 034: iload 5
      // 036: bipush -1
      // 037: ixor
      // 038: if_icmpgt 04a
      // 03b: bipush 0
      // 03c: istore 10
      // 03e: aload 0
      // 03f: getfield qa.j [I
      // 042: iload 3
      // 043: bipush 0
      // 044: iastore
      // 045: iload 17
      // 047: ifeq 231
      // 04a: bipush -12
      // 04c: iload 11
      // 04e: iadd
      // 04f: iload 2
      // 050: iadd
      // 051: istore 13
      // 053: iload 12
      // 055: iload 1
      // 056: bipush -27
      // 058: iadd
      // 059: imul
      // 05a: iload 5
      // 05c: idiv
      // 05d: istore 14
      // 05f: bipush -7
      // 061: iload 14
      // 063: bipush -1
      // 064: ixor
      // 065: if_icmpge 06c
      // 068: bipush 6
      // 06a: istore 14
      // 06c: iload 14
      // 06e: ineg
      // 06f: iload 1
      // 070: bipush -27
      // 072: iadd
      // 073: iadd
      // 074: iload 10
      // 076: imul
      // 077: iload 5
      // 079: iload 12
      // 07b: isub
      // 07c: idiv
      // 07d: istore 15
      // 07f: bipush -2
      // 081: aload 0
      // 082: getfield qa.Hb I
      // 085: bipush -1
      // 086: ixor
      // 087: if_icmpne 11f
      // 08a: aload 0
      // 08b: getfield qa.bb I
      // 08e: iload 13
      // 090: if_icmplt 11f
      // 093: goto 097
      // 096: athrow
      // 097: aload 0
      // 098: getfield qa.bb I
      // 09b: bipush -1
      // 09c: ixor
      // 09d: bipush 12
      // 09f: iload 13
      // 0a1: iadd
      // 0a2: bipush -1
      // 0a3: ixor
      // 0a4: if_icmpge 0af
      // 0a7: goto 0ab
      // 0aa: athrow
      // 0ab: goto 11f
      // 0ae: athrow
      // 0af: iload 7
      // 0b1: aload 0
      // 0b2: getfield qa.hb I
      // 0b5: if_icmpge 0dc
      // 0b8: bipush 12
      // 0ba: iload 7
      // 0bc: iadd
      // 0bd: bipush -1
      // 0be: ixor
      // 0bf: aload 0
      // 0c0: getfield qa.hb I
      // 0c3: bipush -1
      // 0c4: ixor
      // 0c5: if_icmpge 0dc
      // 0c8: goto 0cc
      // 0cb: athrow
      // 0cc: iload 10
      // 0ce: ifgt 0d9
      // 0d1: goto 0d5
      // 0d4: athrow
      // 0d5: goto 0dc
      // 0d8: athrow
      // 0d9: iinc 10 -1
      // 0dc: aload 0
      // 0dd: getfield qa.hb I
      // 0e0: bipush -12
      // 0e2: iload 1
      // 0e3: iadd
      // 0e4: iload 7
      // 0e6: iadd
      // 0e7: if_icmple 117
      // 0ea: iload 7
      // 0ec: iload 1
      // 0ed: iadd
      // 0ee: bipush -1
      // 0ef: ixor
      // 0f0: aload 0
      // 0f1: getfield qa.hb I
      // 0f4: bipush -1
      // 0f5: ixor
      // 0f6: if_icmpge 117
      // 0f9: goto 0fd
      // 0fc: athrow
      // 0fd: iload 12
      // 0ff: ineg
      // 100: iload 5
      // 102: iadd
      // 103: bipush -1
      // 104: ixor
      // 105: iload 10
      // 107: bipush -1
      // 108: ixor
      // 109: if_icmpge 117
      // 10c: goto 110
      // 10f: athrow
      // 110: iinc 10 1
      // 113: goto 117
      // 116: athrow
      // 117: aload 0
      // 118: getfield qa.j [I
      // 11b: iload 3
      // 11c: iload 10
      // 11e: iastore
      // 11f: bipush 1
      // 120: aload 0
      // 121: getfield qa.Hb I
      // 124: if_icmpne 203
      // 127: iload 13
      // 129: bipush -1
      // 12a: ixor
      // 12b: aload 0
      // 12c: getfield qa.bb I
      // 12f: bipush -1
      // 130: ixor
      // 131: if_icmplt 14c
      // 134: goto 138
      // 137: athrow
      // 138: aload 0
      // 139: getfield qa.bb I
      // 13c: bipush -1
      // 13d: ixor
      // 13e: bipush 12
      // 140: iload 13
      // 142: iadd
      // 143: bipush -1
      // 144: ixor
      // 145: if_icmpge 181
      // 148: goto 14c
      // 14b: athrow
      // 14c: bipush -12
      // 14e: iload 13
      // 150: iadd
      // 151: bipush -1
      // 152: ixor
      // 153: aload 0
      // 154: getfield qa.bb I
      // 157: bipush -1
      // 158: ixor
      // 159: if_icmplt 203
      // 15c: goto 160
      // 15f: athrow
      // 160: aload 0
      // 161: getfield qa.bb I
      // 164: bipush -1
      // 165: ixor
      // 166: iload 13
      // 168: bipush 24
      // 16a: iadd
      // 16b: bipush -1
      // 16c: ixor
      // 16d: if_icmplt 203
      // 170: goto 174
      // 173: athrow
      // 174: aload 0
      // 175: getfield qa.d [Z
      // 178: iload 3
      // 179: baload
      // 17a: ifeq 203
      // 17d: goto 181
      // 180: athrow
      // 181: bipush 12
      // 183: iload 7
      // 185: iadd
      // 186: bipush -1
      // 187: ixor
      // 188: aload 0
      // 189: getfield qa.hb I
      // 18c: bipush -1
      // 18d: ixor
      // 18e: if_icmple 20e
      // 191: goto 195
      // 194: athrow
      // 195: iload 7
      // 197: iload 1
      // 198: ineg
      // 199: bipush -12
      // 19b: isub
      // 19c: isub
      // 19d: aload 0
      // 19e: getfield qa.hb I
      // 1a1: if_icmple 20e
      // 1a4: goto 1a8
      // 1a7: athrow
      // 1a8: aload 0
      // 1a9: getfield qa.d [Z
      // 1ac: iload 3
      // 1ad: bipush 1
      // 1ae: bastore
      // 1af: bipush -12
      // 1b1: aload 0
      // 1b2: getfield qa.hb I
      // 1b5: iadd
      // 1b6: iload 7
      // 1b8: ineg
      // 1b9: iload 14
      // 1bb: bipush 2
      // 1bc: idiv
      // 1bd: isub
      // 1be: iadd
      // 1bf: istore 16
      // 1c1: iload 5
      // 1c3: iload 16
      // 1c5: imul
      // 1c6: iload 1
      // 1c7: bipush 24
      // 1c9: isub
      // 1ca: idiv
      // 1cb: istore 10
      // 1cd: bipush -1
      // 1ce: iload 10
      // 1d0: bipush -1
      // 1d1: ixor
      // 1d2: if_icmplt 1d9
      // 1d5: goto 1dc
      // 1d8: athrow
      // 1d9: bipush 0
      // 1da: istore 10
      // 1dc: iload 10
      // 1de: bipush -1
      // 1df: ixor
      // 1e0: iload 5
      // 1e2: iload 12
      // 1e4: isub
      // 1e5: bipush -1
      // 1e6: ixor
      // 1e7: if_icmplt 1ee
      // 1ea: goto 1f6
      // 1ed: athrow
      // 1ee: iload 5
      // 1f0: iload 12
      // 1f2: ineg
      // 1f3: iadd
      // 1f4: istore 10
      // 1f6: aload 0
      // 1f7: getfield qa.j [I
      // 1fa: iload 3
      // 1fb: iload 10
      // 1fd: iastore
      // 1fe: iload 17
      // 200: ifeq 20e
      // 203: aload 0
      // 204: getfield qa.d [Z
      // 207: iload 3
      // 208: bipush 0
      // 209: bastore
      // 20a: goto 20e
      // 20d: athrow
      // 20e: bipush -27
      // 210: iload 1
      // 211: iload 14
      // 213: isub
      // 214: iadd
      // 215: iload 10
      // 217: imul
      // 218: iload 12
      // 21a: ineg
      // 21b: iload 5
      // 21d: iadd
      // 21e: idiv
      // 21f: istore 15
      // 221: aload 0
      // 222: iload 14
      // 224: iload 15
      // 226: iload 2
      // 227: iload 11
      // 229: iload 1
      // 22a: iload 7
      // 22c: bipush -25
      // 22e: invokespecial qa.a (IIIIIIB)V
      // 231: aload 0
      // 232: getfield qa.N [I
      // 235: iload 3
      // 236: bipush -1
      // 237: iastore
      // 238: iload 1
      // 239: aload 0
      // 23a: getfield qa.w Lua;
      // 23d: ldc 508305352
      // 23f: iload 6
      // 241: invokevirtual ua.a (II)I
      // 244: iload 12
      // 246: imul
      // 247: ineg
      // 248: iadd
      // 249: istore 13
      // 24b: bipush 5
      // 24c: aload 0
      // 24d: getfield qa.w Lua;
      // 250: ldc 508305352
      // 252: iload 6
      // 254: invokevirtual ua.a (II)I
      // 257: imul
      // 258: bipush 6
      // 25a: idiv
      // 25b: iload 7
      // 25d: iload 13
      // 25f: bipush 2
      // 260: idiv
      // 261: ineg
      // 262: isub
      // 263: iadd
      // 264: istore 14
      // 266: iload 10
      // 268: istore 15
      // 26a: iload 15
      // 26c: iload 5
      // 26e: if_icmpge 38b
      // 271: iload 17
      // 273: ifne 436
      // 276: aload 0
      // 277: getfield qa.Y [Z
      // 27a: iload 3
      // 27b: baload
      // 27c: ifeq 28c
      // 27f: goto 283
      // 282: athrow
      // 283: ldc 16777215
      // 285: istore 16
      // 287: iload 17
      // 289: ifeq 28f
      // 28c: bipush 0
      // 28d: istore 16
      // 28f: aload 0
      // 290: getfield qa.bb I
      // 293: bipush 2
      // 294: iload 2
      // 295: iadd
      // 296: if_icmplt 322
      // 299: aload 0
      // 29a: getfield qa.bb I
      // 29d: aload 0
      // 29e: getfield qa.w Lua;
      // 2a1: iload 6
      // 2a3: bipush 95
      // 2a5: aload 4
      // 2a7: iload 15
      // 2a9: aaload
      // 2aa: invokevirtual ua.a (IILjava/lang/String;)I
      // 2ad: bipush 2
      // 2ae: iload 2
      // 2af: iadd
      // 2b0: iadd
      // 2b1: if_icmpgt 322
      // 2b4: goto 2b8
      // 2b7: athrow
      // 2b8: bipush -2
      // 2ba: aload 0
      // 2bb: getfield qa.hb I
      // 2be: iadd
      // 2bf: iload 14
      // 2c1: if_icmpgt 322
      // 2c4: goto 2c8
      // 2c7: athrow
      // 2c8: bipush -2
      // 2ca: aload 0
      // 2cb: getfield qa.hb I
      // 2ce: iadd
      // 2cf: aload 0
      // 2d0: getfield qa.w Lua;
      // 2d3: ldc 508305352
      // 2d5: iload 6
      // 2d7: invokevirtual ua.a (II)I
      // 2da: ineg
      // 2db: iload 14
      // 2dd: iadd
      // 2de: if_icmple 322
      // 2e1: goto 2e5
      // 2e4: athrow
      // 2e5: aload 0
      // 2e6: getfield qa.Y [Z
      // 2e9: iload 3
      // 2ea: baload
      // 2eb: ifeq 2fb
      // 2ee: goto 2f2
      // 2f1: athrow
      // 2f2: ldc 8421504
      // 2f4: istore 16
      // 2f6: iload 17
      // 2f8: ifeq 2ff
      // 2fb: ldc 16777215
      // 2fd: istore 16
      // 2ff: aload 0
      // 300: getfield qa.N [I
      // 303: iload 3
      // 304: iload 15
      // 306: iastore
      // 307: aload 0
      // 308: getfield qa.zb I
      // 30b: bipush 1
      // 30c: if_icmpeq 313
      // 30f: goto 322
      // 312: athrow
      // 313: aload 0
      // 314: getfield qa.vb [I
      // 317: iload 3
      // 318: iload 15
      // 31a: iastore
      // 31b: aload 0
      // 31c: getfield qa.D [Z
      // 31f: iload 3
      // 320: bipush 1
      // 321: bastore
      // 322: aload 0
      // 323: getfield qa.vb [I
      // 326: iload 3
      // 327: iaload
      // 328: bipush -1
      // 329: ixor
      // 32a: iload 15
      // 32c: bipush -1
      // 32d: ixor
      // 32e: if_icmpne 340
      // 331: aload 0
      // 332: getfield qa.t Z
      // 335: ifeq 340
      // 338: goto 33c
      // 33b: athrow
      // 33c: ldc 16711680
      // 33e: istore 16
      // 340: aload 0
      // 341: getfield qa.w Lua;
      // 344: aload 8
      // 346: iload 15
      // 348: iaload
      // 349: iload 14
      // 34b: aload 4
      // 34d: iload 15
      // 34f: aaload
      // 350: iload 2
      // 351: bipush -2
      // 353: isub
      // 354: iload 16
      // 356: bipush -9
      // 358: iload 6
      // 35a: invokevirtual ua.a (IILjava/lang/String;IIBI)V
      // 35d: iload 14
      // 35f: aload 0
      // 360: getfield qa.w Lua;
      // 363: ldc 508305352
      // 365: iload 6
      // 367: invokevirtual ua.a (II)I
      // 36a: iadd
      // 36b: istore 14
      // 36d: iload 14
      // 36f: iload 1
      // 370: iload 7
      // 372: iadd
      // 373: if_icmplt 37f
      // 376: iload 17
      // 378: ifeq 38b
      // 37b: goto 37f
      // 37e: athrow
      // 37f: iinc 15 1
      // 382: iload 17
      // 384: ifeq 26a
      // 387: goto 38b
      // 38a: athrow
      // 38b: goto 436
      // 38e: astore 12
      // 390: aload 12
      // 392: new java/lang/StringBuilder
      // 395: dup
      // 396: invokespecial java/lang/StringBuilder.<init> ()V
      // 399: getstatic qa.W [Ljava/lang/String;
      // 39c: bipush 35
      // 39e: aaload
      // 39f: invokevirtual java/lang/StringBuilder.append (Ljava/lang/String;)Ljava/lang/StringBuilder;
      // 3a2: iload 1
      // 3a3: invokevirtual java/lang/StringBuilder.append (I)Ljava/lang/StringBuilder;
      // 3a6: bipush 44
      // 3a8: invokevirtual java/lang/StringBuilder.append (C)Ljava/lang/StringBuilder;
      // 3ab: iload 2
      // 3ac: invokevirtual java/lang/StringBuilder.append (I)Ljava/lang/StringBuilder;
      // 3af: bipush 44
      // 3b1: invokevirtual java/lang/StringBuilder.append (C)Ljava/lang/StringBuilder;
      // 3b4: iload 3
      // 3b5: invokevirtual java/lang/StringBuilder.append (I)Ljava/lang/StringBuilder;
      // 3b8: bipush 44
      // 3ba: invokevirtual java/lang/StringBuilder.append (C)Ljava/lang/StringBuilder;
      // 3bd: aload 4
      // 3bf: ifnull 3cb
      // 3c2: getstatic qa.W [Ljava/lang/String;
      // 3c5: bipush 2
      // 3c6: aaload
      // 3c7: goto 3d0
      // 3ca: athrow
      // 3cb: getstatic qa.W [Ljava/lang/String;
      // 3ce: bipush 1
      // 3cf: aaload
      // 3d0: invokevirtual java/lang/StringBuilder.append (Ljava/lang/String;)Ljava/lang/StringBuilder;
      // 3d3: bipush 44
      // 3d5: invokevirtual java/lang/StringBuilder.append (C)Ljava/lang/StringBuilder;
      // 3d8: iload 5
      // 3da: invokevirtual java/lang/StringBuilder.append (I)Ljava/lang/StringBuilder;
      // 3dd: bipush 44
      // 3df: invokevirtual java/lang/StringBuilder.append (C)Ljava/lang/StringBuilder;
      // 3e2: iload 6
      // 3e4: invokevirtual java/lang/StringBuilder.append (I)Ljava/lang/StringBuilder;
      // 3e7: bipush 44
      // 3e9: invokevirtual java/lang/StringBuilder.append (C)Ljava/lang/StringBuilder;
      // 3ec: iload 7
      // 3ee: invokevirtual java/lang/StringBuilder.append (I)Ljava/lang/StringBuilder;
      // 3f1: bipush 44
      // 3f3: invokevirtual java/lang/StringBuilder.append (C)Ljava/lang/StringBuilder;
      // 3f6: aload 8
      // 3f8: ifnull 404
      // 3fb: getstatic qa.W [Ljava/lang/String;
      // 3fe: bipush 2
      // 3ff: aaload
      // 400: goto 409
      // 403: athrow
      // 404: getstatic qa.W [Ljava/lang/String;
      // 407: bipush 1
      // 408: aaload
      // 409: invokevirtual java/lang/StringBuilder.append (Ljava/lang/String;)Ljava/lang/StringBuilder;
      // 40c: bipush 44
      // 40e: invokevirtual java/lang/StringBuilder.append (C)Ljava/lang/StringBuilder;
      // 411: iload 9
      // 413: invokevirtual java/lang/StringBuilder.append (I)Ljava/lang/StringBuilder;
      // 416: bipush 44
      // 418: invokevirtual java/lang/StringBuilder.append (C)Ljava/lang/StringBuilder;
      // 41b: iload 10
      // 41d: invokevirtual java/lang/StringBuilder.append (I)Ljava/lang/StringBuilder;
      // 420: bipush 44
      // 422: invokevirtual java/lang/StringBuilder.append (C)Ljava/lang/StringBuilder;
      // 425: iload 11
      // 427: invokevirtual java/lang/StringBuilder.append (I)Ljava/lang/StringBuilder;
      // 42a: bipush 41
      // 42c: invokevirtual java/lang/StringBuilder.append (C)Ljava/lang/StringBuilder;
      // 42f: invokevirtual java/lang/StringBuilder.toString ()Ljava/lang/String;
      // 432: invokestatic i.a (Ljava/lang/Throwable;Ljava/lang/String;)Lla;
      // 435: athrow
      // 436: return
   }

   private final void a(int param1, String param2, int param3, int param4, boolean param5, int param6, int param7, int param8) {
      // $VF: Couldn't be decompiled
      // Please report this to the Vineflower issue tracker, at https://github.com/Vineflower/vineflower/issues with a copy of the class file (if you have the rights to distribute it!)
      // java.lang.RuntimeException: parsing failure!
      //   at org.jetbrains.java.decompiler.modules.decompiler.decompose.DomHelper.parseGraph(DomHelper.java:211)
      //   at org.jetbrains.java.decompiler.main.rels.MethodProcessor.codeToJava(MethodProcessor.java:166)
      //
      // Bytecode:
      // 000: getstatic client.vh Z
      // 003: istore 11
      // 005: getstatic qa.wb I
      // 008: bipush 1
      // 009: iadd
      // 00a: putstatic qa.wb I
      // 00d: bipush 0
      // 00e: aload 0
      // 00f: getfield qa.cb [Z
      // 012: iload 8
      // 014: baload
      // 015: ifne 01d
      // 018: bipush 1
      // 019: goto 01e
      // 01c: athrow
      // 01d: bipush 0
      // 01e: if_icmpeq 024
      // 021: goto 060
      // 024: aload 2
      // 025: invokevirtual java/lang/String.length ()I
      // 028: istore 9
      // 02a: ldc ""
      // 02c: astore 2
      // 02d: bipush 0
      // 02e: istore 10
      // 030: iload 9
      // 032: bipush -1
      // 033: ixor
      // 034: iload 10
      // 036: bipush -1
      // 037: ixor
      // 038: if_icmpge 060
      // 03b: new java/lang/StringBuilder
      // 03e: dup
      // 03f: invokespecial java/lang/StringBuilder.<init> ()V
      // 042: aload 2
      // 043: invokevirtual java/lang/StringBuilder.append (Ljava/lang/String;)Ljava/lang/StringBuilder;
      // 046: ldc "X"
      // 048: invokevirtual java/lang/StringBuilder.append (Ljava/lang/String;)Ljava/lang/StringBuilder;
      // 04b: invokevirtual java/lang/StringBuilder.toString ()Ljava/lang/String;
      // 04e: astore 2
      // 04f: iinc 10 1
      // 052: iload 11
      // 054: ifne 0d3
      // 057: iload 11
      // 059: ifeq 030
      // 05c: goto 060
      // 05f: athrow
      // 060: aload 0
      // 061: getfield qa.U [I
      // 064: iload 8
      // 066: iaload
      // 067: bipush -1
      // 068: ixor
      // 069: bipush -6
      // 06b: if_icmpne 0d3
      // 06e: aload 0
      // 06f: getfield qa.zb I
      // 072: bipush 1
      // 073: if_icmpne 15d
      // 076: goto 07a
      // 079: athrow
      // 07a: iload 6
      // 07c: aload 0
      // 07d: getfield qa.bb I
      // 080: if_icmpgt 15d
      // 083: goto 087
      // 086: athrow
      // 087: aload 0
      // 088: getfield qa.hb I
      // 08b: bipush -1
      // 08c: ixor
      // 08d: iload 4
      // 08f: bipush 2
      // 090: idiv
      // 091: ineg
      // 092: iload 7
      // 094: iadd
      // 095: bipush -1
      // 096: ixor
      // 097: if_icmpgt 15d
      // 09a: goto 09e
      // 09d: athrow
      // 09e: aload 0
      // 09f: getfield qa.bb I
      // 0a2: iload 6
      // 0a4: iload 3
      // 0a5: ineg
      // 0a6: isub
      // 0a7: if_icmpgt 15d
      // 0aa: goto 0ae
      // 0ad: athrow
      // 0ae: aload 0
      // 0af: getfield qa.hb I
      // 0b2: bipush -1
      // 0b3: ixor
      // 0b4: iload 4
      // 0b6: bipush 2
      // 0b7: idiv
      // 0b8: iload 7
      // 0ba: iadd
      // 0bb: bipush -1
      // 0bc: ixor
      // 0bd: if_icmplt 15d
      // 0c0: goto 0c4
      // 0c3: athrow
      // 0c4: aload 0
      // 0c5: iload 8
      // 0c7: putfield qa.gb I
      // 0ca: iload 11
      // 0cc: ifeq 15d
      // 0cf: goto 0d3
      // 0d2: athrow
      // 0d3: bipush -7
      // 0d5: aload 0
      // 0d6: getfield qa.U [I
      // 0d9: iload 8
      // 0db: iaload
      // 0dc: bipush -1
      // 0dd: ixor
      // 0de: if_icmpne 15d
      // 0e1: bipush 1
      // 0e2: aload 0
      // 0e3: getfield qa.zb I
      // 0e6: if_icmpne 14b
      // 0e9: goto 0ed
      // 0ec: athrow
      // 0ed: aload 0
      // 0ee: getfield qa.bb I
      // 0f1: bipush -1
      // 0f2: ixor
      // 0f3: iload 3
      // 0f4: bipush 2
      // 0f5: idiv
      // 0f6: ineg
      // 0f7: iload 6
      // 0f9: iadd
      // 0fa: bipush -1
      // 0fb: ixor
      // 0fc: if_icmpgt 14b
      // 0ff: goto 103
      // 102: athrow
      // 103: iload 4
      // 105: bipush 2
      // 106: idiv
      // 107: ineg
      // 108: iload 7
      // 10a: iadd
      // 10b: bipush -1
      // 10c: ixor
      // 10d: aload 0
      // 10e: getfield qa.hb I
      // 111: bipush -1
      // 112: ixor
      // 113: if_icmplt 14b
      // 116: goto 11a
      // 119: athrow
      // 11a: iload 3
      // 11b: bipush 2
      // 11c: idiv
      // 11d: iload 6
      // 11f: iadd
      // 120: aload 0
      // 121: getfield qa.bb I
      // 124: if_icmplt 14b
      // 127: goto 12b
      // 12a: athrow
      // 12b: iload 7
      // 12d: iload 4
      // 12f: bipush 2
      // 130: idiv
      // 131: iadd
      // 132: bipush -1
      // 133: ixor
      // 134: aload 0
      // 135: getfield qa.hb I
      // 138: bipush -1
      // 139: ixor
      // 13a: if_icmpgt 14b
      // 13d: goto 141
      // 140: athrow
      // 141: aload 0
      // 142: iload 8
      // 144: putfield qa.gb I
      // 147: goto 14b
      // 14a: athrow
      // 14b: iload 6
      // 14d: aload 0
      // 14e: getfield qa.w Lua;
      // 151: iload 1
      // 152: bipush 76
      // 154: aload 2
      // 155: invokevirtual ua.a (IILjava/lang/String;)I
      // 158: bipush 2
      // 159: idiv
      // 15a: isub
      // 15b: istore 6
      // 15d: aload 0
      // 15e: getfield qa.gb I
      // 161: iload 8
      // 163: if_icmpeq 16a
      // 166: goto 17e
      // 169: athrow
      // 16a: new java/lang/StringBuilder
      // 16d: dup
      // 16e: invokespecial java/lang/StringBuilder.<init> ()V
      // 171: aload 2
      // 172: invokevirtual java/lang/StringBuilder.append (Ljava/lang/String;)Ljava/lang/StringBuilder;
      // 175: ldc "*"
      // 177: invokevirtual java/lang/StringBuilder.append (Ljava/lang/String;)Ljava/lang/StringBuilder;
      // 17a: invokevirtual java/lang/StringBuilder.toString ()Ljava/lang/String;
      // 17d: astore 2
      // 17e: iload 5
      // 180: bipush 1
      // 181: if_icmpeq 196
      // 184: aload 0
      // 185: bipush 28
      // 187: bipush 94
      // 189: bipush -2
      // 18b: bipush 23
      // 18d: bipush 126
      // 18f: invokespecial qa.a (IBIII)V
      // 192: goto 196
      // 195: athrow
      // 196: aload 0
      // 197: getfield qa.w Lua;
      // 19a: ldc 508305352
      // 19c: iload 1
      // 19d: invokevirtual ua.a (II)I
      // 1a0: bipush 3
      // 1a1: idiv
      // 1a2: iload 7
      // 1a4: iadd
      // 1a5: istore 9
      // 1a7: aload 0
      // 1a8: iload 1
      // 1a9: iload 8
      // 1ab: iload 5
      // 1ad: bipush 0
      // 1ae: iload 6
      // 1b0: iload 9
      // 1b2: aload 2
      // 1b3: invokespecial qa.a (IIZIIILjava/lang/String;)V
      // 1b6: goto 231
      // 1b9: astore 9
      // 1bb: aload 9
      // 1bd: new java/lang/StringBuilder
      // 1c0: dup
      // 1c1: invokespecial java/lang/StringBuilder.<init> ()V
      // 1c4: getstatic qa.W [Ljava/lang/String;
      // 1c7: bipush 3
      // 1c8: aaload
      // 1c9: invokevirtual java/lang/StringBuilder.append (Ljava/lang/String;)Ljava/lang/StringBuilder;
      // 1cc: iload 1
      // 1cd: invokevirtual java/lang/StringBuilder.append (I)Ljava/lang/StringBuilder;
      // 1d0: bipush 44
      // 1d2: invokevirtual java/lang/StringBuilder.append (C)Ljava/lang/StringBuilder;
      // 1d5: aload 2
      // 1d6: ifnull 1e2
      // 1d9: getstatic qa.W [Ljava/lang/String;
      // 1dc: bipush 2
      // 1dd: aaload
      // 1de: goto 1e7
      // 1e1: athrow
      // 1e2: getstatic qa.W [Ljava/lang/String;
      // 1e5: bipush 1
      // 1e6: aaload
      // 1e7: invokevirtual java/lang/StringBuilder.append (Ljava/lang/String;)Ljava/lang/StringBuilder;
      // 1ea: bipush 44
      // 1ec: invokevirtual java/lang/StringBuilder.append (C)Ljava/lang/StringBuilder;
      // 1ef: iload 3
      // 1f0: invokevirtual java/lang/StringBuilder.append (I)Ljava/lang/StringBuilder;
      // 1f3: bipush 44
      // 1f5: invokevirtual java/lang/StringBuilder.append (C)Ljava/lang/StringBuilder;
      // 1f8: iload 4
      // 1fa: invokevirtual java/lang/StringBuilder.append (I)Ljava/lang/StringBuilder;
      // 1fd: bipush 44
      // 1ff: invokevirtual java/lang/StringBuilder.append (C)Ljava/lang/StringBuilder;
      // 202: iload 5
      // 204: invokevirtual java/lang/StringBuilder.append (Z)Ljava/lang/StringBuilder;
      // 207: bipush 44
      // 209: invokevirtual java/lang/StringBuilder.append (C)Ljava/lang/StringBuilder;
      // 20c: iload 6
      // 20e: invokevirtual java/lang/StringBuilder.append (I)Ljava/lang/StringBuilder;
      // 211: bipush 44
      // 213: invokevirtual java/lang/StringBuilder.append (C)Ljava/lang/StringBuilder;
      // 216: iload 7
      // 218: invokevirtual java/lang/StringBuilder.append (I)Ljava/lang/StringBuilder;
      // 21b: bipush 44
      // 21d: invokevirtual java/lang/StringBuilder.append (C)Ljava/lang/StringBuilder;
      // 220: iload 8
      // 222: invokevirtual java/lang/StringBuilder.append (I)Ljava/lang/StringBuilder;
      // 225: bipush 41
      // 227: invokevirtual java/lang/StringBuilder.append (C)Ljava/lang/StringBuilder;
      // 22a: invokevirtual java/lang/StringBuilder.toString ()Ljava/lang/String;
      // 22d: invokestatic i.a (Ljava/lang/Throwable;Ljava/lang/String;)Lla;
      // 230: athrow
      // 231: return
   }

   final boolean a(byte var1, int var2) {
      try {
         V++;
         if (var1 > -95) {
            return true;
         } else {
            label29: {
               try {
                  if (this.g[var2] && this.D[var2]) {
                     break label29;
                  }
               } catch (RuntimeException var4) {
                  throw var4;
               }

               return false;
            }

            this.D[var2] = false;
            return true;
         }
      } catch (RuntimeException var5) {
         throw i.a(var5, W[25] + var1 + ',' + var2 + ')');
      }
   }

   static final boolean a(e param0, String param1, int param2, int param3) {
      // $VF: Couldn't be decompiled
      // Please report this to the Vineflower issue tracker, at https://github.com/Vineflower/vineflower/issues with a copy of the class file (if you have the rights to distribute it!)
      // java.lang.RuntimeException: parsing failure!
      //   at org.jetbrains.java.decompiler.modules.decompiler.decompose.DomHelper.parseGraph(DomHelper.java:211)
      //   at org.jetbrains.java.decompiler.main.rels.MethodProcessor.codeToJava(MethodProcessor.java:166)
      //
      // Bytecode:
      // 000: getstatic client.vh Z
      // 003: istore 12
      // 005: getstatic qa.Bb I
      // 008: bipush 1
      // 009: iadd
      // 00a: putstatic qa.Bb I
      // 00d: bipush 0
      // 00e: istore 4
      // 010: aload 1
      // 011: invokevirtual java/lang/String.toLowerCase ()Ljava/lang/String;
      // 014: astore 1
      // 015: bipush 0
      // 016: istore 5
      // 018: aload 1
      // 019: getstatic qa.W [Ljava/lang/String;
      // 01c: bipush 32
      // 01e: aaload
      // 01f: invokevirtual java/lang/String.startsWith (Ljava/lang/String;)Z
      // 022: ifne 029
      // 025: goto 030
      // 028: athrow
      // 029: aload 1
      // 02a: bipush 9
      // 02c: invokevirtual java/lang/String.substring (I)Ljava/lang/String;
      // 02f: astore 1
      // 030: aload 1
      // 031: ldc "h"
      // 033: invokevirtual java/lang/String.startsWith (Ljava/lang/String;)Z
      // 036: ifeq 03f
      // 039: aload 1
      // 03a: bipush 1
      // 03b: invokevirtual java/lang/String.substring (I)Ljava/lang/String;
      // 03e: astore 1
      // 03f: aload 1
      // 040: ldc "f"
      // 042: invokevirtual java/lang/String.startsWith (Ljava/lang/String;)Z
      // 045: ifeq 051
      // 048: aload 1
      // 049: bipush 1
      // 04a: invokevirtual java/lang/String.substring (I)Ljava/lang/String;
      // 04d: astore 1
      // 04e: bipush 1
      // 04f: istore 4
      // 051: aload 1
      // 052: ldc "d"
      // 054: invokevirtual java/lang/String.startsWith (Ljava/lang/String;)Z
      // 057: ifeq 063
      // 05a: aload 1
      // 05b: bipush 1
      // 05c: invokevirtual java/lang/String.substring (I)Ljava/lang/String;
      // 05f: astore 1
      // 060: bipush 1
      // 061: istore 5
      // 063: aload 1
      // 064: getstatic qa.W [Ljava/lang/String;
      // 067: bipush 29
      // 069: aaload
      // 06a: invokevirtual java/lang/String.endsWith (Ljava/lang/String;)Z
      // 06d: ifeq 07d
      // 070: aload 1
      // 071: bipush 0
      // 072: bipush -3
      // 074: aload 1
      // 075: invokevirtual java/lang/String.length ()I
      // 078: iadd
      // 079: invokevirtual java/lang/String.substring (II)Ljava/lang/String;
      // 07c: astore 1
      // 07d: bipush 0
      // 07e: istore 6
      // 080: aload 1
      // 081: ldc "b"
      // 083: invokevirtual java/lang/String.endsWith (Ljava/lang/String;)Z
      // 086: ifne 08d
      // 089: goto 09c
      // 08c: athrow
      // 08d: bipush 1
      // 08e: istore 6
      // 090: aload 1
      // 091: bipush 0
      // 092: aload 1
      // 093: invokevirtual java/lang/String.length ()I
      // 096: bipush -1
      // 097: iadd
      // 098: invokevirtual java/lang/String.substring (II)Ljava/lang/String;
      // 09b: astore 1
      // 09c: aload 1
      // 09d: ldc "p"
      // 09f: invokevirtual java/lang/String.endsWith (Ljava/lang/String;)Z
      // 0a2: ifeq 0b1
      // 0a5: aload 1
      // 0a6: bipush 0
      // 0a7: bipush -1
      // 0a8: aload 1
      // 0a9: invokevirtual java/lang/String.length ()I
      // 0ac: iadd
      // 0ad: invokevirtual java/lang/String.substring (II)Ljava/lang/String;
      // 0b0: astore 1
      // 0b1: aload 1
      // 0b2: invokestatic java/lang/Integer.parseInt (Ljava/lang/String;)I
      // 0b5: istore 7
      // 0b7: new java/awt/Font
      // 0ba: dup
      // 0bb: getstatic qa.W [Ljava/lang/String;
      // 0be: bipush 31
      // 0c0: aaload
      // 0c1: iload 6
      // 0c3: iload 7
      // 0c5: invokespecial java/awt/Font.<init> (Ljava/lang/String;II)V
      // 0c8: astore 8
      // 0ca: aload 0
      // 0cb: aload 8
      // 0cd: invokevirtual e.getFontMetrics (Ljava/awt/Font;)Ljava/awt/FontMetrics;
      // 0d0: astore 9
      // 0d2: getstatic qa.W [Ljava/lang/String;
      // 0d5: bipush 7
      // 0d7: aaload
      // 0d8: astore 10
      // 0da: sipush 855
      // 0dd: putstatic b.c I
      // 0e0: bipush 0
      // 0e1: istore 11
      // 0e3: bipush -96
      // 0e5: iload 11
      // 0e7: bipush -1
      // 0e8: ixor
      // 0e9: if_icmpge 11b
      // 0ec: iload 2
      // 0ed: aload 8
      // 0ef: iload 11
      // 0f1: bipush -95
      // 0f3: aload 0
      // 0f4: aload 10
      // 0f6: iload 11
      // 0f8: invokevirtual java/lang/String.charAt (I)C
      // 0fb: aload 9
      // 0fd: iload 5
      // 0ff: invokestatic s.a (ILjava/awt/Font;IILe;CLjava/awt/FontMetrics;Z)Z
      // 102: iload 12
      // 104: ifne 126
      // 107: ifeq 111
      // 10a: goto 10e
      // 10d: athrow
      // 10e: goto 113
      // 111: bipush 0
      // 112: ireturn
      // 113: iinc 11 1
      // 116: iload 12
      // 118: ifeq 0e3
      // 11b: getstatic m.b [[B
      // 11e: iload 2
      // 11f: getstatic b.c I
      // 122: newarray 8
      // 124: aastore
      // 125: iload 3
      // 126: istore 11
      // 128: iload 11
      // 12a: bipush -1
      // 12b: ixor
      // 12c: getstatic b.c I
      // 12f: bipush -1
      // 130: ixor
      // 131: if_icmple 153
      // 134: getstatic m.b [[B
      // 137: iload 2
      // 138: aaload
      // 139: iload 11
      // 13b: getstatic qb.k [B
      // 13e: iload 11
      // 140: baload
      // 141: bastore
      // 142: iinc 11 1
      // 145: iload 12
      // 147: ifne 197
      // 14a: iload 12
      // 14c: ifeq 128
      // 14f: goto 153
      // 152: athrow
      // 153: bipush 1
      // 154: iload 6
      // 156: if_icmpne 197
      // 159: getstatic fb.k [Z
      // 15c: iload 2
      // 15d: baload
      // 15e: ifne 169
      // 161: goto 165
      // 164: athrow
      // 165: goto 197
      // 168: athrow
      // 169: getstatic fb.k [Z
      // 16c: iload 2
      // 16d: bipush 0
      // 16e: bastore
      // 16f: aload 0
      // 170: new java/lang/StringBuilder
      // 173: dup
      // 174: invokespecial java/lang/StringBuilder.<init> ()V
      // 177: ldc "f"
      // 179: invokevirtual java/lang/StringBuilder.append (Ljava/lang/String;)Ljava/lang/StringBuilder;
      // 17c: iload 7
      // 17e: invokevirtual java/lang/StringBuilder.append (I)Ljava/lang/StringBuilder;
      // 181: ldc "p"
      // 183: invokevirtual java/lang/StringBuilder.append (Ljava/lang/String;)Ljava/lang/StringBuilder;
      // 186: invokevirtual java/lang/StringBuilder.toString ()Ljava/lang/String;
      // 189: iload 2
      // 18a: bipush 0
      // 18b: invokestatic qa.a (Le;Ljava/lang/String;II)Z
      // 18e: ifeq 195
      // 191: goto 197
      // 194: athrow
      // 195: bipush 0
      // 196: ireturn
      // 197: iload 4
      // 199: ifeq 1dc
      // 19c: getstatic fb.k [Z
      // 19f: iload 2
      // 1a0: baload
      // 1a1: ifne 1dc
      // 1a4: goto 1a8
      // 1a7: athrow
      // 1a8: getstatic fb.k [Z
      // 1ab: iload 2
      // 1ac: bipush 0
      // 1ad: bastore
      // 1ae: aload 0
      // 1af: new java/lang/StringBuilder
      // 1b2: dup
      // 1b3: invokespecial java/lang/StringBuilder.<init> ()V
      // 1b6: ldc "d"
      // 1b8: invokevirtual java/lang/StringBuilder.append (Ljava/lang/String;)Ljava/lang/StringBuilder;
      // 1bb: iload 7
      // 1bd: invokevirtual java/lang/StringBuilder.append (I)Ljava/lang/StringBuilder;
      // 1c0: ldc "p"
      // 1c2: invokevirtual java/lang/StringBuilder.append (Ljava/lang/String;)Ljava/lang/StringBuilder;
      // 1c5: invokevirtual java/lang/StringBuilder.toString ()Ljava/lang/String;
      // 1c8: iload 2
      // 1c9: iload 3
      // 1ca: bipush 0
      // 1cb: ixor
      // 1cc: invokestatic qa.a (Le;Ljava/lang/String;II)Z
      // 1cf: ifeq 1da
      // 1d2: goto 1d6
      // 1d5: athrow
      // 1d6: goto 1dc
      // 1d9: athrow
      // 1da: bipush 0
      // 1db: ireturn
      // 1dc: bipush 1
      // 1dd: ireturn
      // 1de: astore 4
      // 1e0: aload 4
      // 1e2: new java/lang/StringBuilder
      // 1e5: dup
      // 1e6: invokespecial java/lang/StringBuilder.<init> ()V
      // 1e9: getstatic qa.W [Ljava/lang/String;
      // 1ec: bipush 30
      // 1ee: aaload
      // 1ef: invokevirtual java/lang/StringBuilder.append (Ljava/lang/String;)Ljava/lang/StringBuilder;
      // 1f2: aload 0
      // 1f3: ifnull 1ff
      // 1f6: getstatic qa.W [Ljava/lang/String;
      // 1f9: bipush 2
      // 1fa: aaload
      // 1fb: goto 204
      // 1fe: athrow
      // 1ff: getstatic qa.W [Ljava/lang/String;
      // 202: bipush 1
      // 203: aaload
      // 204: invokevirtual java/lang/StringBuilder.append (Ljava/lang/String;)Ljava/lang/StringBuilder;
      // 207: bipush 44
      // 209: invokevirtual java/lang/StringBuilder.append (C)Ljava/lang/StringBuilder;
      // 20c: aload 1
      // 20d: ifnull 219
      // 210: getstatic qa.W [Ljava/lang/String;
      // 213: bipush 2
      // 214: aaload
      // 215: goto 21e
      // 218: athrow
      // 219: getstatic qa.W [Ljava/lang/String;
      // 21c: bipush 1
      // 21d: aaload
      // 21e: invokevirtual java/lang/StringBuilder.append (Ljava/lang/String;)Ljava/lang/StringBuilder;
      // 221: bipush 44
      // 223: invokevirtual java/lang/StringBuilder.append (C)Ljava/lang/StringBuilder;
      // 226: iload 2
      // 227: invokevirtual java/lang/StringBuilder.append (I)Ljava/lang/StringBuilder;
      // 22a: bipush 44
      // 22c: invokevirtual java/lang/StringBuilder.append (C)Ljava/lang/StringBuilder;
      // 22f: iload 3
      // 230: invokevirtual java/lang/StringBuilder.append (I)Ljava/lang/StringBuilder;
      // 233: bipush 41
      // 235: invokevirtual java/lang/StringBuilder.append (C)Ljava/lang/StringBuilder;
      // 238: invokevirtual java/lang/StringBuilder.toString ()Ljava/lang/String;
      // 23b: invokestatic i.a (Ljava/lang/Throwable;Ljava/lang/String;)Lla;
      // 23e: athrow
   }

   private final void a(int param1, int param2, byte param3, String[] param4, int param5, int param6) {
      // $VF: Couldn't be decompiled
      // Please report this to the Vineflower issue tracker, at https://github.com/Vineflower/vineflower/issues with a copy of the class file (if you have the rights to distribute it!)
      // java.lang.RuntimeException: parsing failure!
      //   at org.jetbrains.java.decompiler.modules.decompiler.decompose.DomHelper.parseGraph(DomHelper.java:211)
      //   at org.jetbrains.java.decompiler.main.rels.MethodProcessor.codeToJava(MethodProcessor.java:166)
      //
      // Bytecode:
      // 000: getstatic client.vh Z
      // 003: istore 13
      // 005: getstatic qa.M I
      // 008: bipush 1
      // 009: iadd
      // 00a: putstatic qa.M I
      // 00d: bipush 0
      // 00e: istore 7
      // 010: aload 4
      // 012: arraylength
      // 013: istore 8
      // 015: iload 3
      // 016: bipush -73
      // 018: if_icmpeq 01c
      // 01b: return
      // 01c: bipush 0
      // 01d: istore 9
      // 01f: iload 8
      // 021: iload 9
      // 023: if_icmple 070
      // 026: iload 7
      // 028: aload 0
      // 029: getfield qa.w Lua;
      // 02c: iload 2
      // 02d: bipush 106
      // 02f: aload 4
      // 031: iload 9
      // 033: aaload
      // 034: invokevirtual ua.a (IILjava/lang/String;)I
      // 037: iadd
      // 038: istore 7
      // 03a: iload 8
      // 03c: bipush 1
      // 03d: isub
      // 03e: bipush -1
      // 03f: ixor
      // 040: iload 9
      // 042: bipush -1
      // 043: ixor
      // 044: iload 13
      // 046: ifne 089
      // 049: if_icmplt 053
      // 04c: goto 050
      // 04f: athrow
      // 050: goto 068
      // 053: iload 7
      // 055: aload 0
      // 056: getfield qa.w Lua;
      // 059: iload 2
      // 05a: bipush 92
      // 05c: getstatic qa.W [Ljava/lang/String;
      // 05f: bipush 20
      // 061: aaload
      // 062: invokevirtual ua.a (IILjava/lang/String;)I
      // 065: iadd
      // 066: istore 7
      // 068: iinc 9 1
      // 06b: iload 13
      // 06d: ifeq 01f
      // 070: iload 1
      // 071: iload 7
      // 073: bipush 2
      // 074: idiv
      // 075: ineg
      // 076: iadd
      // 077: istore 9
      // 079: aload 0
      // 07a: getfield qa.w Lua;
      // 07d: iload 3
      // 07e: ldc 508305425
      // 080: iadd
      // 081: iload 2
      // 082: invokevirtual ua.a (II)I
      // 085: bipush 3
      // 086: idiv
      // 087: iload 6
      // 089: iadd
      // 08a: istore 10
      // 08c: bipush 0
      // 08d: istore 11
      // 08f: iload 8
      // 091: iload 11
      // 093: if_icmple 1b8
      // 096: iload 13
      // 098: ifne 220
      // 09b: aload 0
      // 09c: getfield qa.Y [Z
      // 09f: iload 5
      // 0a1: baload
      // 0a2: ifne 0b1
      // 0a5: goto 0a9
      // 0a8: athrow
      // 0a9: bipush 0
      // 0aa: istore 12
      // 0ac: iload 13
      // 0ae: ifeq 0b5
      // 0b1: ldc 16777215
      // 0b3: istore 12
      // 0b5: iload 9
      // 0b7: bipush -1
      // 0b8: ixor
      // 0b9: aload 0
      // 0ba: getfield qa.bb I
      // 0bd: bipush -1
      // 0be: ixor
      // 0bf: if_icmplt 145
      // 0c2: aload 0
      // 0c3: getfield qa.bb I
      // 0c6: bipush -1
      // 0c7: ixor
      // 0c8: iload 9
      // 0ca: aload 0
      // 0cb: getfield qa.w Lua;
      // 0ce: iload 2
      // 0cf: bipush 73
      // 0d1: aload 4
      // 0d3: iload 11
      // 0d5: aaload
      // 0d6: invokevirtual ua.a (IILjava/lang/String;)I
      // 0d9: iadd
      // 0da: bipush -1
      // 0db: ixor
      // 0dc: if_icmplt 145
      // 0df: goto 0e3
      // 0e2: athrow
      // 0e3: aload 0
      // 0e4: getfield qa.hb I
      // 0e7: iload 10
      // 0e9: if_icmpgt 145
      // 0ec: goto 0f0
      // 0ef: athrow
      // 0f0: aload 0
      // 0f1: getfield qa.hb I
      // 0f4: bipush -1
      // 0f5: ixor
      // 0f6: iload 10
      // 0f8: aload 0
      // 0f9: getfield qa.w Lua;
      // 0fc: ldc 508305352
      // 0fe: iload 2
      // 0ff: invokevirtual ua.a (II)I
      // 102: ineg
      // 103: iadd
      // 104: bipush -1
      // 105: ixor
      // 106: if_icmplt 111
      // 109: goto 10d
      // 10c: athrow
      // 10d: goto 145
      // 110: athrow
      // 111: aload 0
      // 112: getfield qa.Y [Z
      // 115: iload 5
      // 117: baload
      // 118: ifeq 124
      // 11b: ldc 8421504
      // 11d: istore 12
      // 11f: iload 13
      // 121: ifeq 128
      // 124: ldc 16777215
      // 126: istore 12
      // 128: aload 0
      // 129: getfield qa.zb I
      // 12c: bipush 1
      // 12d: if_icmpeq 134
      // 130: goto 145
      // 133: athrow
      // 134: aload 0
      // 135: getfield qa.vb [I
      // 138: iload 5
      // 13a: iload 11
      // 13c: iastore
      // 13d: aload 0
      // 13e: getfield qa.D [Z
      // 141: iload 5
      // 143: bipush 1
      // 144: bastore
      // 145: aload 0
      // 146: getfield qa.vb [I
      // 149: iload 5
      // 14b: iaload
      // 14c: bipush -1
      // 14d: ixor
      // 14e: iload 11
      // 150: bipush -1
      // 151: ixor
      // 152: if_icmpne 170
      // 155: aload 0
      // 156: getfield qa.Y [Z
      // 159: iload 5
      // 15b: baload
      // 15c: ifeq 16c
      // 15f: goto 163
      // 162: athrow
      // 163: ldc 16711680
      // 165: istore 12
      // 167: iload 13
      // 169: ifeq 170
      // 16c: ldc 12582912
      // 16e: istore 12
      // 170: aload 0
      // 171: getfield qa.w Lua;
      // 174: bipush 0
      // 175: iload 10
      // 177: aload 4
      // 179: iload 11
      // 17b: aaload
      // 17c: iload 9
      // 17e: iload 12
      // 180: bipush -53
      // 182: iload 2
      // 183: invokevirtual ua.a (IILjava/lang/String;IIBI)V
      // 186: iload 9
      // 188: aload 0
      // 189: getfield qa.w Lua;
      // 18c: iload 2
      // 18d: bipush 127
      // 18f: new java/lang/StringBuilder
      // 192: dup
      // 193: invokespecial java/lang/StringBuilder.<init> ()V
      // 196: aload 4
      // 198: iload 11
      // 19a: aaload
      // 19b: invokevirtual java/lang/StringBuilder.append (Ljava/lang/String;)Ljava/lang/StringBuilder;
      // 19e: getstatic qa.W [Ljava/lang/String;
      // 1a1: bipush 20
      // 1a3: aaload
      // 1a4: invokevirtual java/lang/StringBuilder.append (Ljava/lang/String;)Ljava/lang/StringBuilder;
      // 1a7: invokevirtual java/lang/StringBuilder.toString ()Ljava/lang/String;
      // 1aa: invokevirtual ua.a (IILjava/lang/String;)I
      // 1ad: iadd
      // 1ae: istore 9
      // 1b0: iinc 11 1
      // 1b3: iload 13
      // 1b5: ifeq 08f
      // 1b8: goto 220
      // 1bb: astore 7
      // 1bd: aload 7
      // 1bf: new java/lang/StringBuilder
      // 1c2: dup
      // 1c3: invokespecial java/lang/StringBuilder.<init> ()V
      // 1c6: getstatic qa.W [Ljava/lang/String;
      // 1c9: bipush 19
      // 1cb: aaload
      // 1cc: invokevirtual java/lang/StringBuilder.append (Ljava/lang/String;)Ljava/lang/StringBuilder;
      // 1cf: iload 1
      // 1d0: invokevirtual java/lang/StringBuilder.append (I)Ljava/lang/StringBuilder;
      // 1d3: bipush 44
      // 1d5: invokevirtual java/lang/StringBuilder.append (C)Ljava/lang/StringBuilder;
      // 1d8: iload 2
      // 1d9: invokevirtual java/lang/StringBuilder.append (I)Ljava/lang/StringBuilder;
      // 1dc: bipush 44
      // 1de: invokevirtual java/lang/StringBuilder.append (C)Ljava/lang/StringBuilder;
      // 1e1: iload 3
      // 1e2: invokevirtual java/lang/StringBuilder.append (I)Ljava/lang/StringBuilder;
      // 1e5: bipush 44
      // 1e7: invokevirtual java/lang/StringBuilder.append (C)Ljava/lang/StringBuilder;
      // 1ea: aload 4
      // 1ec: ifnull 1f8
      // 1ef: getstatic qa.W [Ljava/lang/String;
      // 1f2: bipush 2
      // 1f3: aaload
      // 1f4: goto 1fd
      // 1f7: athrow
      // 1f8: getstatic qa.W [Ljava/lang/String;
      // 1fb: bipush 1
      // 1fc: aaload
      // 1fd: invokevirtual java/lang/StringBuilder.append (Ljava/lang/String;)Ljava/lang/StringBuilder;
      // 200: bipush 44
      // 202: invokevirtual java/lang/StringBuilder.append (C)Ljava/lang/StringBuilder;
      // 205: iload 5
      // 207: invokevirtual java/lang/StringBuilder.append (I)Ljava/lang/StringBuilder;
      // 20a: bipush 44
      // 20c: invokevirtual java/lang/StringBuilder.append (C)Ljava/lang/StringBuilder;
      // 20f: iload 6
      // 211: invokevirtual java/lang/StringBuilder.append (I)Ljava/lang/StringBuilder;
      // 214: bipush 41
      // 216: invokevirtual java/lang/StringBuilder.append (C)Ljava/lang/StringBuilder;
      // 219: invokevirtual java/lang/StringBuilder.toString ()Ljava/lang/String;
      // 21c: invokestatic i.a (Ljava/lang/Throwable;Ljava/lang/String;)Lla;
      // 21f: athrow
      // 220: return
   }

   final void d(int var1, int var2) {
      try {
         this.gb = var1;
         T++;
         if (var2 > -70) {
            this.b(33, -60, -29);
         }
      } catch (RuntimeException var4) {
         throw i.a(var4, W[42] + var1 + ',' + var2 + ')');
      }
   }

   private final void a(String var1, int var2, byte var3, int var4, int var5, int var6, int var7) {
      try {
         Z++;
         int var9 = -109 / ((var3 - 14) / 62);
         int var12 = var2 - -(this.w.a(508305352, var4) / 3);
         this.a(var4, var6, true, var7, var5, var12, var1);
      } catch (RuntimeException var11) {
         RuntimeException var8 = var11;

         RuntimeException var10000;
         StringBuilder var10001;
         try {
            var10000 = var8;
            var10001 = new StringBuilder().append(W[34]);
            if (var1 != null) {
               throw i.a(
                  var8,
                  var10001.append(W[2])
                     .append(',')
                     .append(var2)
                     .append(',')
                     .append((int)var3)
                     .append(',')
                     .append(var4)
                     .append(',')
                     .append(var5)
                     .append(',')
                     .append(var6)
                     .append(',')
                     .append(var7)
                     .append(')')
                     .toString()
               );
            }
         } catch (RuntimeException var10) {
            throw var10;
         }

         throw i.a(
            var10000,
            var10001.append(W[1])
               .append(',')
               .append(var2)
               .append(',')
               .append((int)var3)
               .append(',')
               .append(var4)
               .append(',')
               .append(var5)
               .append(',')
               .append(var6)
               .append(',')
               .append(var7)
               .append(')')
               .toString()
         );
      }
   }

   final int c(int var1, int var2, int var3, int var4, int var5) {
      try {
         try {
            s++;
            this.U[this.eb] = 2;
            if (var1 > -56) {
               this.a(127, 127);
            }
         } catch (RuntimeException var7) {
            throw var7;
         }

         this.g[this.eb] = true;
         this.D[this.eb] = false;
         this.kb[this.eb] = var4 - var2 / 2;
         this.B[this.eb] = var5 + -(var3 / 2);
         this.ob[this.eb] = var2;
         this.O[this.eb] = var3;
         return this.eb++;
      } catch (RuntimeException var8) {
         throw i.a(var8, W[4] + var1 + 44 + var2 + 44 + var3 + 44 + var4 + 44 + var5 + 41);
      }
   }

   private final void a(int var1, byte var2, int var3, int var4, int var5) {
      boolean var8 = client.vh;

      try {
         int var10000;
         label63: {
            label68: {
               try {
                  this.w.a(var4, var4 - -var1, var5 + var3, var5, (byte)30);
                  b++;
                  this.w.b(var4, this.J, var1, this.tb, var3, var5, 19020);
                  if (!p.d) {
                     break label68;
                  }
               } catch (RuntimeException var11) {
                  throw var11;
               }

               int var6 = -(var5 & 63) + var4;

               while (var6 < var1 + var4) {
                  var10000 = -(31 & var5) + var5;
                  if (var8) {
                     break label63;
                  }

                  int var7 = var10000;

                  label54: {
                     while (var5 - -var3 > var7) {
                        try {
                           this.w.a(6 - -u.g, 0, var6, 128, var7);
                           var7 += 128;
                           if (var8) {
                              break label54;
                           }

                           if (var8) {
                              break;
                           }
                        } catch (RuntimeException var10) {
                           throw var10;
                        }
                     }

                     var6 += 128;
                  }

                  if (var8) {
                     break;
                  }
               }
            }

            this.w.b(var1, this.tb, var4, var5, (byte)111);
            var10000 = var2;
         }

         try {
            if (var10000 != 69) {
               l = (byte[])null;
            }
         } catch (RuntimeException var9) {
            throw var9;
         }

         this.w.b(var1 - 2, this.tb, 1 + var4, var5 - -1, (byte)-124);
         this.w.b(-4 + var1, this.F, 2 + var4, 2 + var5, (byte)-99);
         this.w.b(var4, var5, this.tb, var3, 0);
         this.w.b(1 + var4, var5 - -1, this.tb, -2 + var3, 0);
         this.w.b(var4 - -2, var5 + 2, this.F, -4 + var3, var2 ^ 69);
         this.w.b(var1, this.J, var4, var5 + (var3 - 1), (byte)100);
         this.w.b(var1 - 2, this.J, var4 - -1, var5 + (var3 - 2), (byte)103);
         this.w.b(-4 + var1, this.Eb, 2 + var4, -3 + (var5 - -var3), (byte)73);
         this.w.b(-1 + var1 + var4, var5, this.J, var3, 0);
         this.w.b(var1 + var4 - 2, var5 + 1, this.J, var3 + -2, 0);
         this.w.b(var4 + (var1 - 3), var5 - -2, this.Eb, var3 - 4, 0);
         this.w.a(-1);
      } catch (RuntimeException var12) {
         throw i.a(var12, W[8] + var1 + ',' + var2 + ',' + var3 + ',' + var4 + ',' + var5 + ')');
      }
   }

   private final void b(int var1, int var2, int var3, int var4) {
      try {
         this.w.b(-1, var4, var2, var3);
         int var5 = 71 / ((var1 - 67) / 32);
         I++;
      } catch (RuntimeException var6) {
         throw i.a(var6, W[44] + var1 + ',' + var2 + ',' + var3 + ',' + var4 + ')');
      }
   }

   final void c(int var1, int var2) {
      try {
         a++;
         this.g[var1] = true;
         if (var2 < 114) {
            this.a(7, -8, false, -58, -39, 47, (String)null);
         }
      } catch (RuntimeException var4) {
         throw i.a(var4, W[18] + var1 + ',' + var2 + ')');
      }
   }

   final int a(int var1, int var2, int var3, boolean var4, int var5, int var6, int var7, boolean var8, int var9) {
      try {
         try {
            if (var1 != 0) {
               this.B = (int[])null;
            }
         } catch (RuntimeException var11) {
            throw var11;
         }

         this.U[this.eb] = 6;
         c++;
         this.g[this.eb] = true;
         this.cb[this.eb] = var8;
         this.D[this.eb] = false;
         this.k[this.eb] = var6;
         this.Y[this.eb] = var4;
         this.kb[this.eb] = var9;
         this.B[this.eb] = var5;
         this.ob[this.eb] = var3;
         this.O[this.eb] = var7;
         this.sb[this.eb] = var2;
         this.yb[this.eb] = "";
         return this.eb++;
      } catch (RuntimeException var12) {
         throw i.a(var12, W[21] + var1 + 44 + var2 + 44 + var3 + 44 + var4 + 44 + var5 + 44 + var6 + 44 + var7 + 44 + var8 + 44 + var9 + 41);
      }
   }

   final int a(int var1, int var2, int var3, boolean var4, int var5, int var6, int var7, int var8) {
      try {
         this.U[this.eb] = 9;
         jb++;
         this.g[this.eb] = true;
         this.D[this.eb] = false;
         this.k[this.eb] = var8;
         this.Y[this.eb] = var4;
         this.kb[this.eb] = var1;
         if (var5 < 40) {
            return 21;
         } else {
            this.B[this.eb] = var7;
            this.ob[this.eb] = var2;
            this.O[this.eb] = var3;
            this.sb[this.eb] = var6;
            this.Ab[this.eb] = new String[var6];
            this.m[this.eb] = new int[var6];
            this.Fb[this.eb] = new String[var6];
            this.p[this.eb] = new String[var6];
            this.pb[this.eb] = 0;
            this.j[this.eb] = 0;
            this.vb[this.eb] = -1;
            this.N[this.eb] = -1;
            return this.eb++;
         }
      } catch (RuntimeException var10) {
         throw i.a(var10, W[43] + var1 + 44 + var2 + 44 + var3 + 44 + var4 + 44 + var5 + 44 + var6 + 44 + var7 + 44 + var8 + 41);
      }
   }

   private final void a(int var1, int var2, int var3, int var4) {
      try {
         Q++;
         this.w.b(var4, var2, var3, var1, (byte)-119);
      } catch (RuntimeException var6) {
         throw i.a(var6, W[38] + var1 + ',' + var2 + ',' + var3 + ',' + var4 + ')');
      }
   }

   final void b(byte var1, int var2) {
      try {
         try {
            this.g[var2] = false;
            if (var1 <= 33) {
               this.R = -86;
            }
         } catch (RuntimeException var4) {
            throw var4;
         }

         rb++;
      } catch (RuntimeException var5) {
         throw i.a(var5, W[17] + var1 + ',' + var2 + ')');
      }
   }

   final String g(int var1, int var2) {
      try {
         nb++;
         if (var2 != 4) {
            return (String)null;
         } else {
            return null == this.yb[var1] ? W[1] : this.yb[var1];
         }
      } catch (RuntimeException var4) {
         throw i.a(var4, W[41] + var1 + ',' + var2 + ')');
      }
   }

   final void a(int var1, String var2, int var3, int var4, String var5, String var6, int var7) {
      try {
         ub++;
         this.Ab[var7][var1] = var6;
         int var14 = 78 % ((var3 - -14) / 54);

         try {
            this.m[var7][var1] = var4;
            this.Fb[var7][var1] = var5;
            this.p[var7][var1] = var2;
            if (var1 - -1 <= this.pb[var7]) {
               return;
            }
         } catch (RuntimeException var12) {
            throw var12;
         }

         this.pb[var7] = var1 + 1;
      } catch (RuntimeException var13) {
         RuntimeException var8 = var13;

         RuntimeException var10000;
         StringBuilder var10001;
         String var10002;
         label50: {
            try {
               var10000 = var8;
               var10001 = new StringBuilder().append(W[26]).append(var1).append(',');
               if (var2 != null) {
                  var10002 = W[2];
                  break label50;
               }
            } catch (RuntimeException var11) {
               throw var11;
            }

            var10002 = W[1];
         }

         label43: {
            try {
               var10001 = var10001.append(var10002).append(',').append(var3).append(',').append(var4).append(',');
               if (var5 != null) {
                  var10002 = W[2];
                  break label43;
               }
            } catch (RuntimeException var10) {
               throw var10;
            }

            var10002 = W[1];
         }

         try {
            var10001 = var10001.append(var10002).append(',');
            if (var6 != null) {
               throw i.a(var10000, var10001.append(W[2]).append(',').append(var7).append(')').toString());
            }
         } catch (RuntimeException var9) {
            throw var9;
         }

         throw i.a(var10000, var10001.append(W[1]).append(',').append(var7).append(')').toString());
      }
   }

   final int f(int var1, int var2) {
      try {
         try {
            H++;
            if (var1 != 14458) {
               this.t = true;
            }
         } catch (RuntimeException var4) {
            throw var4;
         }

         return this.vb[var2];
      } catch (RuntimeException var5) {
         throw i.a(var5, W[27] + var1 + 44 + var2 + 41);
      }
   }

   final void a(int param1, int param2) {
      // $VF: Couldn't be decompiled
      // Please report this to the Vineflower issue tracker, at https://github.com/Vineflower/vineflower/issues with a copy of the class file (if you have the rights to distribute it!)
      // java.lang.RuntimeException: parsing failure!
      //   at org.jetbrains.java.decompiler.modules.decompiler.decompose.DomHelper.parseGraph(DomHelper.java:211)
      //   at org.jetbrains.java.decompiler.main.rels.MethodProcessor.codeToJava(MethodProcessor.java:166)
      //
      // Bytecode:
      // 000: getstatic client.vh Z
      // 003: istore 6
      // 005: iload 1
      // 006: bipush -12
      // 008: if_icmpeq 017
      // 00b: aload 0
      // 00c: bipush -17
      // 00e: bipush 7
      // 010: invokevirtual qa.d (II)V
      // 013: goto 017
      // 016: athrow
      // 017: getstatic qa.q I
      // 01a: bipush 1
      // 01b: iadd
      // 01c: putstatic qa.q I
      // 01f: bipush -1
      // 020: iload 2
      // 021: bipush -1
      // 022: ixor
      // 023: if_icmpeq 02a
      // 026: goto 02b
      // 029: athrow
      // 02a: return
      // 02b: bipush 0
      // 02c: aload 0
      // 02d: getfield qa.gb I
      // 030: bipush -1
      // 031: ixor
      // 032: if_icmpeq 15f
      // 035: aconst_null
      // 036: aload 0
      // 037: getfield qa.yb [Ljava/lang/String;
      // 03a: aload 0
      // 03b: getfield qa.gb I
      // 03e: aaload
      // 03f: if_acmpeq 15f
      // 042: goto 046
      // 045: athrow
      // 046: aload 0
      // 047: getfield qa.g [Z
      // 04a: aload 0
      // 04b: getfield qa.gb I
      // 04e: baload
      // 04f: ifeq 15f
      // 052: goto 056
      // 055: athrow
      // 056: aload 0
      // 057: getfield qa.yb [Ljava/lang/String;
      // 05a: aload 0
      // 05b: getfield qa.gb I
      // 05e: aaload
      // 05f: invokevirtual java/lang/String.length ()I
      // 062: istore 3
      // 063: bipush 8
      // 065: iload 2
      // 066: if_icmpne 08f
      // 069: bipush 0
      // 06a: iload 3
      // 06b: if_icmpge 08f
      // 06e: goto 072
      // 071: athrow
      // 072: aload 0
      // 073: getfield qa.yb [Ljava/lang/String;
      // 076: aload 0
      // 077: getfield qa.gb I
      // 07a: aload 0
      // 07b: getfield qa.yb [Ljava/lang/String;
      // 07e: aload 0
      // 07f: getfield qa.gb I
      // 082: aaload
      // 083: bipush 0
      // 084: bipush -1
      // 085: iload 3
      // 086: iadd
      // 087: invokevirtual java/lang/String.substring (II)Ljava/lang/String;
      // 08a: aastore
      // 08b: goto 08f
      // 08e: athrow
      // 08f: iload 2
      // 090: bipush 10
      // 092: if_icmpeq 09f
      // 095: bipush 13
      // 097: iload 2
      // 098: if_icmpne 0b5
      // 09b: goto 09f
      // 09e: athrow
      // 09f: iload 3
      // 0a0: ifgt 0ab
      // 0a3: goto 0a7
      // 0a6: athrow
      // 0a7: goto 0b5
      // 0aa: athrow
      // 0ab: aload 0
      // 0ac: getfield qa.D [Z
      // 0af: aload 0
      // 0b0: getfield qa.gb I
      // 0b3: bipush 1
      // 0b4: bastore
      // 0b5: getstatic qa.W [Ljava/lang/String;
      // 0b8: bipush 7
      // 0ba: aaload
      // 0bb: astore 4
      // 0bd: iload 3
      // 0be: aload 0
      // 0bf: getfield qa.sb [I
      // 0c2: aload 0
      // 0c3: getfield qa.gb I
      // 0c6: iaload
      // 0c7: if_icmplt 0ce
      // 0ca: goto 120
      // 0cd: athrow
      // 0ce: bipush 0
      // 0cf: istore 5
      // 0d1: aload 4
      // 0d3: invokevirtual java/lang/String.length ()I
      // 0d6: bipush -1
      // 0d7: ixor
      // 0d8: iload 5
      // 0da: bipush -1
      // 0db: ixor
      // 0dc: if_icmpge 120
      // 0df: aload 4
      // 0e1: iload 5
      // 0e3: invokevirtual java/lang/String.charAt (I)C
      // 0e6: bipush -1
      // 0e7: ixor
      // 0e8: iload 2
      // 0e9: bipush -1
      // 0ea: ixor
      // 0eb: iload 6
      // 0ed: ifne 125
      // 0f0: if_icmpne 118
      // 0f3: goto 0f7
      // 0f6: athrow
      // 0f7: new java/lang/StringBuilder
      // 0fa: dup
      // 0fb: invokespecial java/lang/StringBuilder.<init> ()V
      // 0fe: aload 0
      // 0ff: getfield qa.yb [Ljava/lang/String;
      // 102: aload 0
      // 103: getfield qa.gb I
      // 106: dup2_x1
      // 107: aaload
      // 108: invokevirtual java/lang/StringBuilder.append (Ljava/lang/String;)Ljava/lang/StringBuilder;
      // 10b: iload 2
      // 10c: i2c
      // 10d: invokevirtual java/lang/StringBuilder.append (C)Ljava/lang/StringBuilder;
      // 110: invokevirtual java/lang/StringBuilder.toString ()Ljava/lang/String;
      // 113: aastore
      // 114: goto 118
      // 117: athrow
      // 118: iinc 5 1
      // 11b: iload 6
      // 11d: ifeq 0d1
      // 120: iload 2
      // 121: bipush -1
      // 122: ixor
      // 123: bipush -10
      // 125: if_icmpne 15f
      // 128: aload 0
      // 129: bipush 1
      // 12a: aload 0
      // 12b: getfield qa.gb I
      // 12e: iadd
      // 12f: aload 0
      // 130: getfield qa.eb I
      // 133: irem
      // 134: putfield qa.gb I
      // 137: bipush 5
      // 138: aload 0
      // 139: getfield qa.U [I
      // 13c: aload 0
      // 13d: getfield qa.gb I
      // 140: iaload
      // 141: if_icmpeq 15f
      // 144: goto 148
      // 147: athrow
      // 148: aload 0
      // 149: getfield qa.U [I
      // 14c: aload 0
      // 14d: getfield qa.gb I
      // 150: iaload
      // 151: bipush 6
      // 153: if_icmpne 128
      // 156: iload 6
      // 158: ifne 18d
      // 15b: goto 15f
      // 15e: athrow
      // 15f: goto 18d
      // 162: astore 3
      // 163: aload 3
      // 164: new java/lang/StringBuilder
      // 167: dup
      // 168: invokespecial java/lang/StringBuilder.<init> ()V
      // 16b: getstatic qa.W [Ljava/lang/String;
      // 16e: bipush 6
      // 170: aaload
      // 171: invokevirtual java/lang/StringBuilder.append (Ljava/lang/String;)Ljava/lang/StringBuilder;
      // 174: iload 1
      // 175: invokevirtual java/lang/StringBuilder.append (I)Ljava/lang/StringBuilder;
      // 178: bipush 44
      // 17a: invokevirtual java/lang/StringBuilder.append (C)Ljava/lang/StringBuilder;
      // 17d: iload 2
      // 17e: invokevirtual java/lang/StringBuilder.append (I)Ljava/lang/StringBuilder;
      // 181: bipush 41
      // 183: invokevirtual java/lang/StringBuilder.append (C)Ljava/lang/StringBuilder;
      // 186: invokevirtual java/lang/StringBuilder.toString ()Ljava/lang/String;
      // 189: invokestatic i.a (Ljava/lang/Throwable;Ljava/lang/String;)Lla;
      // 18c: athrow
      // 18d: return
   }

   private final void a(int var1, int var2, boolean var3, int var4, int var5) {
      try {
         this.w.a(var4, (byte)-127, 0, var1, var5, var2);
         n++;
         this.w.e(var4, var2, var1, 27785, var5, this.fb);
         if (var3) {
            this.w.e(1 + var4, var2 + -2, 1 + var1, 27785, -2 + var5, this.E);
            this.w.e(var4 - -2, -4 + var2, 2 + var1, 27785, -4 + var5, this.f);
            this.w.b(-1, u.g + 2, var1, var4);
            this.w.b(-1, 3 - -u.g, var1, -7 + var2 + var4);
            this.w.b(-1, 4 + u.g, var1 - (-var5 - -7), var4);
            this.w.b(-1, 5 + u.g, -7 + var5 + var1, -7 + (var4 - -var2));
         }
      } catch (RuntimeException var7) {
         throw i.a(var7, W[10] + var1 + ',' + var2 + ',' + var3 + ',' + var4 + ',' + var5 + ')');
      }
   }

   private final void a(int var1, int var2, int var3, int var4, int var5, int var6, byte var7) {
      try {
         L++;
         int var8 = var3 - -var4 + -12;
         int var9 = -91 % ((58 - var7) / 33);
         this.w.e(var8, 12, var6, 27785, var5, 0);
         this.w.b(-1, 0 + u.g, var6 + 1, 1 + var8);
         this.w.b(-1, u.g + 1, -12 + var5 + var6, 1 + var8);
         this.w.b(12, 0, var8, 13 + var6, (byte)-49);
         this.w.b(12, 0, var8, -13 + var6 - -var5, (byte)-119);
         this.w.b(1 + var8, this.R, 11, this.qb, -27 + var5, 14 + var6, 19020);
         this.w.a(var8 - -3, (byte)-105, this.i, 14 + var6 + var2, var1, 7);
         this.w.b(var8 - -2, var6 + var2 + 14, this.C, var1, 0);
         this.w.b(var8 + 10, 14 + var2 - -var6, this.ib, var1, 0);
      } catch (RuntimeException var10) {
         throw i.a(var10, W[46] + var1 + ',' + var2 + ',' + var3 + ',' + var4 + ',' + var5 + ',' + var6 + ',' + var7 + ')');
      }
   }

   final int b(int var1, int var2) {
      try {
         try {
            lb++;
            if (var2 != 17050) {
               this.E = 56;
            }
         } catch (RuntimeException var4) {
            throw var4;
         }

         return this.N[var1];
      } catch (RuntimeException var5) {
         throw i.a(var5, W[23] + var1 + 44 + var2 + 41);
      }
   }

   final int c(int var1, int var2, int var3, int var4) {
      try {
         try {
            if (var4 >= -52) {
               this.d = (boolean[])null;
            }
         } catch (RuntimeException var7) {
            throw var7;
         }

         S++;
         int var5 = this.w.kb[var1];
         int var6 = this.w.R[var1];
         this.U[this.eb] = 12;
         this.g[this.eb] = true;
         this.D[this.eb] = false;
         this.kb[this.eb] = var3 + -(var5 / 2);
         this.B[this.eb] = -(var6 / 2) + var2;
         this.ob[this.eb] = var5;
         this.O[this.eb] = var6;
         this.k[this.eb] = var1;
         return this.eb++;
      } catch (RuntimeException var8) {
         throw i.a(var8, W[14] + var1 + 44 + var2 + 44 + var3 + 44 + var4 + 41);
      }
   }

   final void a(String var1, boolean var2, int var3, String var4, String var5, byte var6, int var7) {
      boolean var10 = client.vh;

      try {
         z++;
         int var19 = this.pb[var7]++;

         label93: {
            label99: {
               try {
                  if (~this.sb[var7] < ~var19) {
                     break label99;
                  }
               } catch (RuntimeException var17) {
                  throw var17;
               }

               this.pb[var7]--;
               var19--;
               int var9 = 0;

               while (var19 > var9) {
                  try {
                     this.Ab[var7][var9] = this.Ab[var7][1 + var9];
                     this.m[var7][var9] = this.m[var7][var9 - -1];
                     this.Fb[var7][var9] = this.Fb[var7][var9 + 1];
                     this.p[var7][var9] = this.p[var7][var9 + 1];
                     var9++;
                     if (var10) {
                        break label93;
                     }

                     if (var10) {
                        break;
                     }
                  } catch (RuntimeException var16) {
                     throw var16;
                  }
               }
            }

            this.Ab[var7][var19] = var1;
            this.m[var7][var19] = var3;
         }

         try {
            if (var6 > -39) {
               this.pb = (int[])null;
            }
         } catch (RuntimeException var15) {
            throw var15;
         }

         try {
            this.Fb[var7][var19] = var5;
            this.p[var7][var19] = var4;
            if (var2) {
               this.j[var7] = 999999;
            }
         } catch (RuntimeException var11) {
            throw var11;
         }
      } catch (RuntimeException var18) {
         RuntimeException var8 = var18;

         RuntimeException var10000;
         StringBuilder var10001;
         String var10002;
         label71: {
            try {
               var10000 = var8;
               var10001 = new StringBuilder().append(W[9]);
               if (var1 != null) {
                  var10002 = W[2];
                  break label71;
               }
            } catch (RuntimeException var14) {
               throw var14;
            }

            var10002 = W[1];
         }

         label64: {
            try {
               var10001 = var10001.append(var10002).append(',').append(var2).append(',').append(var3).append(',');
               if (var4 != null) {
                  var10002 = W[2];
                  break label64;
               }
            } catch (RuntimeException var13) {
               throw var13;
            }

            var10002 = W[1];
         }

         try {
            var10001 = var10001.append(var10002).append(',');
            if (var5 != null) {
               throw i.a(var10000, var10001.append(W[2]).append(',').append((int)var6).append(',').append(var7).append(')').toString());
            }
         } catch (RuntimeException var12) {
            throw var12;
         }

         throw i.a(var10000, var10001.append(W[1]).append(',').append((int)var6).append(',').append(var7).append(')').toString());
      }
   }

   private final void a(String[] param1, int param2, int param3, int param4, int param5, int param6) {
      // $VF: Couldn't be decompiled
      // Please report this to the Vineflower issue tracker, at https://github.com/Vineflower/vineflower/issues with a copy of the class file (if you have the rights to distribute it!)
      // java.lang.RuntimeException: parsing failure!
      //   at org.jetbrains.java.decompiler.modules.decompiler.decompose.DomHelper.parseGraph(DomHelper.java:211)
      //   at org.jetbrains.java.decompiler.main.rels.MethodProcessor.codeToJava(MethodProcessor.java:166)
      //
      // Bytecode:
      // 000: getstatic client.vh Z
      // 003: istore 13
      // 005: getstatic qa.u I
      // 008: bipush 1
      // 009: iadd
      // 00a: putstatic qa.u I
      // 00d: aload 1
      // 00e: arraylength
      // 00f: istore 7
      // 011: bipush 80
      // 013: iload 3
      // 014: bipush -55
      // 016: isub
      // 017: bipush 61
      // 019: idiv
      // 01a: irem
      // 01b: istore 8
      // 01d: iload 7
      // 01f: bipush 1
      // 020: isub
      // 021: aload 0
      // 022: getfield qa.w Lua;
      // 025: ldc 508305352
      // 027: iload 4
      // 029: invokevirtual ua.a (II)I
      // 02c: imul
      // 02d: bipush 2
      // 02e: idiv
      // 02f: ineg
      // 030: iload 6
      // 032: iadd
      // 033: istore 9
      // 035: bipush 0
      // 036: istore 10
      // 038: iload 10
      // 03a: bipush -1
      // 03b: ixor
      // 03c: iload 7
      // 03e: bipush -1
      // 03f: ixor
      // 040: if_icmple 15e
      // 043: iload 13
      // 045: ifne 1c6
      // 048: aload 0
      // 049: getfield qa.Y [Z
      // 04c: iload 2
      // 04d: baload
      // 04e: ifeq 05e
      // 051: goto 055
      // 054: athrow
      // 055: ldc 16777215
      // 057: istore 11
      // 059: iload 13
      // 05b: ifeq 061
      // 05e: bipush 0
      // 05f: istore 11
      // 061: aload 0
      // 062: getfield qa.w Lua;
      // 065: iload 4
      // 067: bipush 112
      // 069: aload 1
      // 06a: iload 10
      // 06c: aaload
      // 06d: invokevirtual ua.a (IILjava/lang/String;)I
      // 070: istore 12
      // 072: iload 12
      // 074: bipush 2
      // 075: idiv
      // 076: ineg
      // 077: iload 5
      // 079: iadd
      // 07a: bipush -1
      // 07b: ixor
      // 07c: aload 0
      // 07d: getfield qa.bb I
      // 080: bipush -1
      // 081: ixor
      // 082: if_icmplt 101
      // 085: aload 0
      // 086: getfield qa.bb I
      // 089: iload 5
      // 08b: iload 12
      // 08d: bipush 2
      // 08e: idiv
      // 08f: ineg
      // 090: isub
      // 091: if_icmpgt 101
      // 094: goto 098
      // 097: athrow
      // 098: iload 9
      // 09a: bipush -1
      // 09b: ixor
      // 09c: bipush -2
      // 09e: aload 0
      // 09f: getfield qa.hb I
      // 0a2: iadd
      // 0a3: bipush -1
      // 0a4: ixor
      // 0a5: if_icmpgt 101
      // 0a8: goto 0ac
      // 0ab: athrow
      // 0ac: aload 0
      // 0ad: getfield qa.hb I
      // 0b0: bipush 2
      // 0b1: isub
      // 0b2: bipush -1
      // 0b3: ixor
      // 0b4: aload 0
      // 0b5: getfield qa.w Lua;
      // 0b8: ldc 508305352
      // 0ba: iload 4
      // 0bc: invokevirtual ua.a (II)I
      // 0bf: ineg
      // 0c0: iload 9
      // 0c2: iadd
      // 0c3: bipush -1
      // 0c4: ixor
      // 0c5: if_icmpge 101
      // 0c8: goto 0cc
      // 0cb: athrow
      // 0cc: aload 0
      // 0cd: getfield qa.Y [Z
      // 0d0: iload 2
      // 0d1: baload
      // 0d2: ifeq 0e2
      // 0d5: goto 0d9
      // 0d8: athrow
      // 0d9: ldc 8421504
      // 0db: istore 11
      // 0dd: iload 13
      // 0df: ifeq 0e6
      // 0e2: ldc 16777215
      // 0e4: istore 11
      // 0e6: aload 0
      // 0e7: getfield qa.zb I
      // 0ea: bipush 1
      // 0eb: if_icmpeq 0f2
      // 0ee: goto 101
      // 0f1: athrow
      // 0f2: aload 0
      // 0f3: getfield qa.vb [I
      // 0f6: iload 2
      // 0f7: iload 10
      // 0f9: iastore
      // 0fa: aload 0
      // 0fb: getfield qa.D [Z
      // 0fe: iload 2
      // 0ff: bipush 1
      // 100: bastore
      // 101: aload 0
      // 102: getfield qa.vb [I
      // 105: iload 2
      // 106: iaload
      // 107: bipush -1
      // 108: ixor
      // 109: iload 10
      // 10b: bipush -1
      // 10c: ixor
      // 10d: if_icmpeq 114
      // 110: goto 12a
      // 113: athrow
      // 114: aload 0
      // 115: getfield qa.Y [Z
      // 118: iload 2
      // 119: baload
      // 11a: ifne 126
      // 11d: ldc 12582912
      // 11f: istore 11
      // 121: iload 13
      // 123: ifeq 12a
      // 126: ldc 16711680
      // 128: istore 11
      // 12a: aload 0
      // 12b: getfield qa.w Lua;
      // 12e: bipush 0
      // 12f: iload 9
      // 131: aload 1
      // 132: iload 10
      // 134: aaload
      // 135: iload 12
      // 137: bipush 2
      // 138: idiv
      // 139: ineg
      // 13a: iload 5
      // 13c: iadd
      // 13d: iload 11
      // 13f: bipush -126
      // 141: iload 4
      // 143: invokevirtual ua.a (IILjava/lang/String;IIBI)V
      // 146: iload 9
      // 148: aload 0
      // 149: getfield qa.w Lua;
      // 14c: ldc 508305352
      // 14e: iload 4
      // 150: invokevirtual ua.a (II)I
      // 153: iadd
      // 154: istore 9
      // 156: iinc 10 1
      // 159: iload 13
      // 15b: ifeq 038
      // 15e: goto 1c6
      // 161: astore 7
      // 163: aload 7
      // 165: new java/lang/StringBuilder
      // 168: dup
      // 169: invokespecial java/lang/StringBuilder.<init> ()V
      // 16c: getstatic qa.W [Ljava/lang/String;
      // 16f: bipush 24
      // 171: aaload
      // 172: invokevirtual java/lang/StringBuilder.append (Ljava/lang/String;)Ljava/lang/StringBuilder;
      // 175: aload 1
      // 176: ifnull 182
      // 179: getstatic qa.W [Ljava/lang/String;
      // 17c: bipush 2
      // 17d: aaload
      // 17e: goto 187
      // 181: athrow
      // 182: getstatic qa.W [Ljava/lang/String;
      // 185: bipush 1
      // 186: aaload
      // 187: invokevirtual java/lang/StringBuilder.append (Ljava/lang/String;)Ljava/lang/StringBuilder;
      // 18a: bipush 44
      // 18c: invokevirtual java/lang/StringBuilder.append (C)Ljava/lang/StringBuilder;
      // 18f: iload 2
      // 190: invokevirtual java/lang/StringBuilder.append (I)Ljava/lang/StringBuilder;
      // 193: bipush 44
      // 195: invokevirtual java/lang/StringBuilder.append (C)Ljava/lang/StringBuilder;
      // 198: iload 3
      // 199: invokevirtual java/lang/StringBuilder.append (I)Ljava/lang/StringBuilder;
      // 19c: bipush 44
      // 19e: invokevirtual java/lang/StringBuilder.append (C)Ljava/lang/StringBuilder;
      // 1a1: iload 4
      // 1a3: invokevirtual java/lang/StringBuilder.append (I)Ljava/lang/StringBuilder;
      // 1a6: bipush 44
      // 1a8: invokevirtual java/lang/StringBuilder.append (C)Ljava/lang/StringBuilder;
      // 1ab: iload 5
      // 1ad: invokevirtual java/lang/StringBuilder.append (I)Ljava/lang/StringBuilder;
      // 1b0: bipush 44
      // 1b2: invokevirtual java/lang/StringBuilder.append (C)Ljava/lang/StringBuilder;
      // 1b5: iload 6
      // 1b7: invokevirtual java/lang/StringBuilder.append (I)Ljava/lang/StringBuilder;
      // 1ba: bipush 41
      // 1bc: invokevirtual java/lang/StringBuilder.append (C)Ljava/lang/StringBuilder;
      // 1bf: invokevirtual java/lang/StringBuilder.toString ()Ljava/lang/String;
      // 1c2: invokestatic i.a (Ljava/lang/Throwable;Ljava/lang/String;)Lla;
      // 1c5: athrow
      // 1c6: return
   }

   final String b(int var1, int var2, int var3) {
      try {
         try {
            e++;
            if (var2 != 19680) {
               this.a(38, -6, -46, -34, -108, -42, (byte)-17);
            }
         } catch (RuntimeException var5) {
            throw var5;
         }

         return this.Fb[var3][var1];
      } catch (RuntimeException var6) {
         throw i.a(var6, W[40] + var1 + ',' + var2 + ',' + var3 + ')');
      }
   }

   qa(ua var1, int var2) {
      this.hb = 0;
      this.zb = 0;
      this.t = true;
      this.G = 0;
      this.Hb = 0;
      this.bb = 0;

      try {
         this.Fb = new String[var2][];
         this.Y = new boolean[var2];
         this.B = new int[var2];
         this.cb = new boolean[var2];
         this.k = new int[var2];
         this.pb = new int[var2];
         this.ob = new int[var2];
         this.g = new boolean[var2];
         this.w = var1;
         this.N = new int[var2];
         this.vb = new int[var2];
         this.U = new int[var2];
         this.m = new int[var2][];
         this.yb = new String[var2];
         this.d = new boolean[var2];
         this.j = new int[var2];
         this.Ab = new String[var2][];
         this.O = new int[var2];
         this.D = new boolean[var2];
         this.p = new String[var2][];
         this.kb = new int[var2];
         this.sb = new int[var2];
         this.R = this.a(176, 114, 114, (byte)-98);
         this.qb = this.a(62, 14, 14, (byte)-75);
         this.C = this.a(232, 208, 200, (byte)-88);
         this.i = this.a(184, 129, 96, (byte)-79);
         this.ib = this.a(115, 95, 53, (byte)-92);
         this.fb = this.a(171, 142, 117, (byte)-124);
         this.E = this.a(158, 122, 98, (byte)-117);
         this.f = this.a(136, 100, 86, (byte)-113);
         this.tb = this.a(179, 146, 135, (byte)-89);
         this.F = this.a(151, 112, 97, (byte)-122);
         this.Eb = this.a(136, 102, 88, (byte)-124);
         this.J = this.a(120, 93, 84, (byte)-92);
      } catch (RuntimeException var5) {
         RuntimeException var3 = var5;

         RuntimeException var10000;
         StringBuilder var10001;
         try {
            var10000 = var3;
            var10001 = new StringBuilder().append(W[22]);
            if (var1 != null) {
               throw i.a(var3, var10001.append(W[2]).append(',').append(var2).append(')').toString());
            }
         } catch (RuntimeException var4) {
            throw var4;
         }

         throw i.a(var10000, var10001.append(W[1]).append(',').append(var2).append(')').toString());
      }
   }

   private static char[] z(String var0) {
      char[] var10000 = var0.toCharArray();
      if (var10000.length < 2) {
         var10000[0] = (char)(var10000[0] ^ 'q');
      }

      return var10000;
   }

   private static String z(char[] var0) {
      int var10002 = var0.length;
      char[] var10001 = var0;
      int var10000 = var10002;

      for (int var1 = 0; var10000 > var1; var1++) {
         char var10004 = var10001[var1];
         byte var10005;
         switch (var1 % 5) {
            case 0:
               var10005 = 117;
               break;
            case 1:
               var10005 = 40;
               break;
            case 2:
               var10005 = 10;
               break;
            case 3:
               var10005 = 9;
               break;
            default:
               var10005 = 113;
         }

         var10001[var1] = (char)(var10004 ^ var10005);
      }

      return new String(var10001).intern();
   }
}
