final class t {
   int e;
   int i;
   static int f;
   int j;
   int l;
   int m;
   static int c;
   String b;
   static int a;
   String p;
   String o = null;
   int d;
   static int k;
   static int g;
   static String[] h;
   static byte[][][] n;
   private static final String[] z = new String[]{
      z(z("9}_\u0015\t")), z(z(",&\u001dW")), z(z("6}3\u0013")), z(z("6}2\u0013")), z(z("6}5\u0013")), z(z("6}0\u0013"))
   };

   static final void a(int param0, int param1, int param2, int[] param3, int[] param4, int param5, int param6, int param7) {
      // $VF: Couldn't be decompiled
      // Please report this to the Vineflower issue tracker, at https://github.com/Vineflower/vineflower/issues with a copy of the class file (if you have the rights to distribute it!)
      // java.lang.RuntimeException: parsing failure!
      //   at org.jetbrains.java.decompiler.modules.decompiler.decompose.DomHelper.parseGraph(DomHelper.java:211)
      //   at org.jetbrains.java.decompiler.main.rels.MethodProcessor.codeToJava(MethodProcessor.java:166)
      //
      // Bytecode:
      // 000: getstatic client.vh Z
      // 003: istore 10
      // 005: getstatic t.a I
      // 008: bipush 1
      // 009: iadd
      // 00a: putstatic t.a I
      // 00d: iload 2
      // 00e: iflt 012
      // 011: return
      // 012: aload 4
      // 014: sipush 255
      // 017: iload 5
      // 019: ldc -1455207192
      // 01b: ishr
      // 01c: iand
      // 01d: iaload
      // 01e: istore 0
      // 01f: iload 1
      // 020: bipush 2
      // 021: ishl
      // 022: istore 1
      // 023: iload 5
      // 025: iload 1
      // 026: iadd
      // 027: istore 5
      // 029: iload 2
      // 02a: bipush 16
      // 02c: idiv
      // 02d: istore 8
      // 02f: iload 8
      // 031: istore 9
      // 033: bipush -1
      // 034: iload 9
      // 036: bipush -1
      // 037: ixor
      // 038: if_icmpge 115
      // 03b: aload 3
      // 03c: iload 6
      // 03e: iinc 6 1
      // 041: iload 0
      // 042: iastore
      // 043: aload 3
      // 044: iload 6
      // 046: iinc 6 1
      // 049: iload 0
      // 04a: iastore
      // 04b: aload 3
      // 04c: iload 6
      // 04e: iinc 6 1
      // 051: iload 0
      // 052: iastore
      // 053: aload 3
      // 054: iload 6
      // 056: iinc 6 1
      // 059: iload 0
      // 05a: iastore
      // 05b: aload 4
      // 05d: iload 5
      // 05f: ldc 65525
      // 061: iand
      // 062: ldc 59579400
      // 064: ishr
      // 065: iaload
      // 066: istore 0
      // 067: iload 5
      // 069: iload 1
      // 06a: iadd
      // 06b: istore 5
      // 06d: aload 3
      // 06e: iload 6
      // 070: iinc 6 1
      // 073: iload 0
      // 074: iastore
      // 075: aload 3
      // 076: iload 6
      // 078: iinc 6 1
      // 07b: iload 0
      // 07c: iastore
      // 07d: aload 3
      // 07e: iload 6
      // 080: iinc 6 1
      // 083: iload 0
      // 084: iastore
      // 085: aload 3
      // 086: iload 6
      // 088: iinc 6 1
      // 08b: iload 0
      // 08c: iastore
      // 08d: aload 4
      // 08f: ldc 65469
      // 091: iload 5
      // 093: iand
      // 094: ldc 1966207912
      // 096: ishr
      // 097: iaload
      // 098: istore 0
      // 099: aload 3
      // 09a: iload 6
      // 09c: iinc 6 1
      // 09f: iload 0
      // 0a0: iastore
      // 0a1: iload 5
      // 0a3: iload 1
      // 0a4: iadd
      // 0a5: istore 5
      // 0a7: aload 3
      // 0a8: iload 6
      // 0aa: iinc 6 1
      // 0ad: iload 0
      // 0ae: iastore
      // 0af: aload 3
      // 0b0: iload 6
      // 0b2: iinc 6 1
      // 0b5: iload 0
      // 0b6: iastore
      // 0b7: aload 3
      // 0b8: iload 6
      // 0ba: iinc 6 1
      // 0bd: iload 0
      // 0be: iastore
      // 0bf: aload 4
      // 0c1: sipush 255
      // 0c4: iload 5
      // 0c6: ldc 1256567432
      // 0c8: ishr
      // 0c9: iand
      // 0ca: iaload
      // 0cb: istore 0
      // 0cc: iload 5
      // 0ce: iload 1
      // 0cf: iadd
      // 0d0: istore 5
      // 0d2: aload 3
      // 0d3: iload 6
      // 0d5: iinc 6 1
      // 0d8: iload 0
      // 0d9: iastore
      // 0da: aload 3
      // 0db: iload 6
      // 0dd: iinc 6 1
      // 0e0: iload 0
      // 0e1: iastore
      // 0e2: aload 3
      // 0e3: iload 6
      // 0e5: iinc 6 1
      // 0e8: iload 0
      // 0e9: iastore
      // 0ea: aload 3
      // 0eb: iload 6
      // 0ed: iinc 6 1
      // 0f0: iload 0
      // 0f1: iastore
      // 0f2: aload 4
      // 0f4: ldc 65330
      // 0f6: iload 5
      // 0f8: iand
      // 0f9: ldc 1042063560
      // 0fb: ishr
      // 0fc: iaload
      // 0fd: istore 0
      // 0fe: iload 5
      // 100: iload 1
      // 101: iadd
      // 102: istore 5
      // 104: iinc 9 1
      // 107: iload 10
      // 109: ifne 11c
      // 10c: iload 10
      // 10e: ifeq 033
      // 111: goto 115
      // 114: athrow
      // 115: iload 2
      // 116: bipush 16
      // 118: irem
      // 119: ineg
      // 11a: istore 8
      // 11c: iload 7
      // 11e: ldc 418609192
      // 120: if_icmpeq 13e
      // 123: bipush 76
      // 125: bipush -63
      // 127: bipush -59
      // 129: aconst_null
      // 12a: checkcast [I
      // 12d: aconst_null
      // 12e: checkcast [I
      // 131: bipush 124
      // 133: bipush -66
      // 135: bipush -99
      // 137: invokestatic t.a (III[I[IIII)V
      // 13a: goto 13e
      // 13d: athrow
      // 13e: bipush 0
      // 13f: istore 9
      // 141: iload 8
      // 143: iload 9
      // 145: if_icmple 183
      // 148: aload 3
      // 149: iload 6
      // 14b: iinc 6 1
      // 14e: iload 0
      // 14f: iastore
      // 150: iload 10
      // 152: ifne 20e
      // 155: bipush 3
      // 156: iload 9
      // 158: iand
      // 159: bipush -1
      // 15a: ixor
      // 15b: bipush -4
      // 15d: if_icmpeq 168
      // 160: goto 164
      // 163: athrow
      // 164: goto 17b
      // 167: athrow
      // 168: aload 4
      // 16a: sipush 255
      // 16d: iload 5
      // 16f: ldc 418609192
      // 171: ishr
      // 172: iand
      // 173: iaload
      // 174: istore 0
      // 175: iload 5
      // 177: iload 1
      // 178: iadd
      // 179: istore 5
      // 17b: iinc 9 1
      // 17e: iload 10
      // 180: ifeq 141
      // 183: goto 20e
      // 186: astore 8
      // 188: aload 8
      // 18a: new java/lang/StringBuilder
      // 18d: dup
      // 18e: invokespecial java/lang/StringBuilder.<init> ()V
      // 191: getstatic t.z [Ljava/lang/String;
      // 194: bipush 3
      // 195: aaload
      // 196: invokevirtual java/lang/StringBuilder.append (Ljava/lang/String;)Ljava/lang/StringBuilder;
      // 199: iload 0
      // 19a: invokevirtual java/lang/StringBuilder.append (I)Ljava/lang/StringBuilder;
      // 19d: bipush 44
      // 19f: invokevirtual java/lang/StringBuilder.append (C)Ljava/lang/StringBuilder;
      // 1a2: iload 1
      // 1a3: invokevirtual java/lang/StringBuilder.append (I)Ljava/lang/StringBuilder;
      // 1a6: bipush 44
      // 1a8: invokevirtual java/lang/StringBuilder.append (C)Ljava/lang/StringBuilder;
      // 1ab: iload 2
      // 1ac: invokevirtual java/lang/StringBuilder.append (I)Ljava/lang/StringBuilder;
      // 1af: bipush 44
      // 1b1: invokevirtual java/lang/StringBuilder.append (C)Ljava/lang/StringBuilder;
      // 1b4: aload 3
      // 1b5: ifnull 1c1
      // 1b8: getstatic t.z [Ljava/lang/String;
      // 1bb: bipush 0
      // 1bc: aaload
      // 1bd: goto 1c6
      // 1c0: athrow
      // 1c1: getstatic t.z [Ljava/lang/String;
      // 1c4: bipush 1
      // 1c5: aaload
      // 1c6: invokevirtual java/lang/StringBuilder.append (Ljava/lang/String;)Ljava/lang/StringBuilder;
      // 1c9: bipush 44
      // 1cb: invokevirtual java/lang/StringBuilder.append (C)Ljava/lang/StringBuilder;
      // 1ce: aload 4
      // 1d0: ifnull 1dc
      // 1d3: getstatic t.z [Ljava/lang/String;
      // 1d6: bipush 0
      // 1d7: aaload
      // 1d8: goto 1e1
      // 1db: athrow
      // 1dc: getstatic t.z [Ljava/lang/String;
      // 1df: bipush 1
      // 1e0: aaload
      // 1e1: invokevirtual java/lang/StringBuilder.append (Ljava/lang/String;)Ljava/lang/StringBuilder;
      // 1e4: bipush 44
      // 1e6: invokevirtual java/lang/StringBuilder.append (C)Ljava/lang/StringBuilder;
      // 1e9: iload 5
      // 1eb: invokevirtual java/lang/StringBuilder.append (I)Ljava/lang/StringBuilder;
      // 1ee: bipush 44
      // 1f0: invokevirtual java/lang/StringBuilder.append (C)Ljava/lang/StringBuilder;
      // 1f3: iload 6
      // 1f5: invokevirtual java/lang/StringBuilder.append (I)Ljava/lang/StringBuilder;
      // 1f8: bipush 44
      // 1fa: invokevirtual java/lang/StringBuilder.append (C)Ljava/lang/StringBuilder;
      // 1fd: iload 7
      // 1ff: invokevirtual java/lang/StringBuilder.append (I)Ljava/lang/StringBuilder;
      // 202: bipush 41
      // 204: invokevirtual java/lang/StringBuilder.append (C)Ljava/lang/StringBuilder;
      // 207: invokevirtual java/lang/StringBuilder.toString ()Ljava/lang/String;
      // 20a: invokestatic i.a (Ljava/lang/Throwable;Ljava/lang/String;)Lla;
      // 20d: athrow
      // 20e: return
   }

   static final byte[] a(byte[] var0, int var1, int var2, String var3, byte[] var4) {
      boolean var13 = client.vh;

      try {
         k++;
         int var21 = (255 & var0[1]) + (var0[0] & 255) * 256;
         var3 = var3.toUpperCase();
         int var6 = 0;
         int var7 = 0;

         while (true) {
            if (~var3.length() < ~var7) {
               int var23 = 61 * var6 + (var3.charAt(var7) - ' ');
               if (var13) {
                  break;
               }

               var6 = var23;
               var7++;
               if (!var13) {
                  continue;
               }
            }

            int var24 = 74 % ((var1 - -74) / 49);
            break;
         }

         var7 = 2 + 10 * var21;
         int var8 = 0;

         while (var8 < var21) {
            int var9 = (255 & var0[5 + var8 * 10])
               + (255 & var0[var8 * 10 + 4]) * 256
               + (var0[3 + 10 * var8] & 255) * 65536
               + (255 & var0[2 + 10 * var8]) * 16777216;
            int var10 = (var0[10 * var8 + 7] & 255) * 256 + (var0[var8 * 10 + 6] & 255) * 65536 + (255 & var0[var8 * 10 + 8]);
            int var11 = (var0[10 + 10 * var8] & 255) * 256 + 65536 * (255 & var0[var8 * 10 + 9]) + (var0[10 * var8 + 11] & 255);

            label108: {
               try {
                  if (var9 == var6) {
                     break label108;
                  }
               } catch (RuntimeException var19) {
                  throw var19;
               }

               var7 += var11;
               var8++;
               if (!var13) {
                  continue;
               }
               break;
            }

            if (null == var4) {
               var4 = new byte[var2 + var10];
            }

            try {
               if (var11 != var10) {
                  ea.a(var4, var10, var0, var11, var7);
                  if (!var13) {
                     return var4;
                  }
               }
            } catch (RuntimeException var18) {
               throw var18;
            }

            int var12 = 0;

            while (var12 < var10) {
               try {
                  if (var13) {
                     return var4;
                  }

                  var4[var12] = var0[var12 + var7];
                  var12++;
                  if (var13) {
                     break;
                  }
               } catch (RuntimeException var17) {
                  throw var17;
               }
            }

            return var4;
         }

         return null;
      } catch (RuntimeException var20) {
         RuntimeException var5 = var20;

         RuntimeException var10000;
         StringBuilder var10001;
         String var10002;
         label76: {
            try {
               var10000 = var5;
               var10001 = new StringBuilder().append(z[4]);
               if (var0 != null) {
                  var10002 = z[0];
                  break label76;
               }
            } catch (RuntimeException var16) {
               throw var16;
            }

            var10002 = z[1];
         }

         label69: {
            try {
               var10001 = var10001.append(var10002).append(',').append(var1).append(',').append(var2).append(',');
               if (var3 != null) {
                  var10002 = z[0];
                  break label69;
               }
            } catch (RuntimeException var15) {
               throw var15;
            }

            var10002 = z[1];
         }

         try {
            var10001 = var10001.append(var10002).append(',');
            if (var4 != null) {
               throw i.a(var10000, var10001.append(z[0]).append(')').toString());
            }
         } catch (RuntimeException var14) {
            throw var14;
         }

         throw i.a(var10000, var10001.append(z[1]).append(')').toString());
      }
   }

   static final int a(int var0) {
      try {
         try {
            if (var0 != 65525) {
               h = (String[])null;
            }
         } catch (RuntimeException var2) {
            throw var2;
         }

         c++;
         int var1 = d.a(ka.b, (byte)100, b.v);
         ka.b += 2;
         return var1;
      } catch (RuntimeException var3) {
         throw i.a(var3, z[5] + var0 + 41);
      }
   }

   final void a(String var1, int var2, int var3, int var4, int var5, String var6, int var7, int var8, String var9, String var10, int var11, String var12) {
      try {
         f++;
         this.p = var1;
         this.l = var2;
         this.m = var4;
         if (var7 > 69) {
            this.d = var8;
            this.e = var3;
            this.o = var9;
            this.i = var5;
            this.j = var11;
            this.b = var12;
         }
      } catch (RuntimeException var19) {
         RuntimeException var13 = var19;

         RuntimeException var10000;
         StringBuilder var10001;
         String var10002;
         label74: {
            try {
               var10000 = var13;
               var10001 = new StringBuilder().append(z[2]);
               if (var1 != null) {
                  var10002 = z[0];
                  break label74;
               }
            } catch (RuntimeException var18) {
               throw var18;
            }

            var10002 = z[1];
         }

         label67: {
            try {
               var10001 = var10001.append(var10002)
                  .append(',')
                  .append(var2)
                  .append(',')
                  .append(var3)
                  .append(',')
                  .append(var4)
                  .append(',')
                  .append(var5)
                  .append(',');
               if (var6 != null) {
                  var10002 = z[0];
                  break label67;
               }
            } catch (RuntimeException var17) {
               throw var17;
            }

            var10002 = z[1];
         }

         label60: {
            try {
               var10001 = var10001.append(var10002).append(',').append(var7).append(',').append(var8).append(',');
               if (var9 != null) {
                  var10002 = z[0];
                  break label60;
               }
            } catch (RuntimeException var16) {
               throw var16;
            }

            var10002 = z[1];
         }

         label53: {
            try {
               var10001 = var10001.append(var10002).append(',');
               if (var10 != null) {
                  var10002 = z[0];
                  break label53;
               }
            } catch (RuntimeException var15) {
               throw var15;
            }

            var10002 = z[1];
         }

         try {
            var10001 = var10001.append(var10002).append(',').append(var11).append(',');
            if (var12 != null) {
               throw i.a(var10000, var10001.append(z[0]).append(')').toString());
            }
         } catch (RuntimeException var14) {
            throw var14;
         }

         throw i.a(var10000, var10001.append(z[1]).append(')').toString());
      }
   }

   t() {
      this.p = null;
   }

   private static char[] z(String var0) {
      char[] var10000 = var0.toCharArray();
      if (var10000.length < 2) {
         var10000[0] = (char)(var10000[0] ^ 't');
      }

      return var10000;
   }

   private static String z(char[] var0) {
      int var10002 = var0.length;
      char[] var10001 = var0;
      int var10000 = var10002;

      for (int var1 = 0; var10000 > var1; var1++) {
         char var10004 = var10001[var1];
         byte var10005;
         switch (var1 % 5) {
            case 0:
               var10005 = 66;
               break;
            case 1:
               var10005 = 83;
               break;
            case 2:
               var10005 = 113;
               break;
            case 3:
               var10005 = 59;
               break;
            default:
               var10005 = 116;
         }

         var10001[var1] = (char)(var10004 ^ var10005);
      }

      return new String(var10001).intern();
   }
}
