final class wb {
   static int B;
   static int C;
   static int z;
   static int H;
   static int d;
   static int a;
   private int I;
   static int o;
   private ba t;
   static int K;
   static long w;
   private int n;
   static int l;
   static int u;
   static int x;
   static int c;
   static aa p = new aa(
      new byte[]{
         22,
         22,
         22,
         22,
         22,
         22,
         21,
         22,
         22,
         20,
         22,
         22,
         22,
         21,
         22,
         22,
         22,
         22,
         22,
         22,
         22,
         22,
         22,
         22,
         22,
         22,
         22,
         22,
         22,
         22,
         22,
         22,
         3,
         8,
         22,
         16,
         22,
         16,
         17,
         7,
         13,
         13,
         13,
         16,
         7,
         10,
         6,
         16,
         10,
         11,
         12,
         12,
         12,
         12,
         13,
         13,
         14,
         14,
         11,
         14,
         19,
         15,
         17,
         8,
         11,
         9,
         10,
         10,
         10,
         10,
         11,
         10,
         9,
         7,
         12,
         11,
         10,
         10,
         9,
         10,
         10,
         12,
         10,
         9,
         8,
         12,
         12,
         9,
         14,
         8,
         12,
         17,
         16,
         17,
         22,
         13,
         21,
         4,
         7,
         6,
         5,
         3,
         6,
         6,
         5,
         4,
         10,
         7,
         5,
         6,
         4,
         4,
         6,
         10,
         5,
         4,
         4,
         5,
         7,
         6,
         10,
         6,
         10,
         22,
         19,
         22,
         14,
         22,
         22,
         22,
         22,
         22,
         22,
         22,
         22,
         22,
         22,
         22,
         22,
         22,
         22,
         22,
         22,
         22,
         22,
         22,
         22,
         22,
         22,
         22,
         22,
         22,
         22,
         22,
         22,
         22,
         22,
         22,
         22,
         22,
         22,
         22,
         22,
         22,
         22,
         22,
         22,
         22,
         22,
         22,
         22,
         22,
         22,
         22,
         22,
         22,
         22,
         22,
         22,
         22,
         22,
         22,
         22,
         22,
         22,
         22,
         22,
         22,
         22,
         22,
         22,
         22,
         22,
         22,
         22,
         22,
         22,
         22,
         22,
         22,
         22,
         22,
         22,
         22,
         22,
         22,
         22,
         22,
         22,
         22,
         22,
         22,
         22,
         22,
         22,
         22,
         22,
         22,
         22,
         22,
         22,
         22,
         22,
         22,
         22,
         22,
         22,
         22,
         22,
         22,
         22,
         22,
         22,
         22,
         22,
         22,
         22,
         22,
         22,
         22,
         22,
         22,
         22,
         22,
         22,
         22,
         22,
         21,
         22,
         21,
         22,
         22,
         22,
         21,
         22,
         22
      }
   );
   static int k;
   static int F;
   private int D;
   static int f;
   static int j;
   static int v;
   static int y;
   static int M;
   static int s;
   private int i;
   private String m;
   static int E;
   static int r;
   static int e;
   static int J;
   static int L;
   private t[] b;
   static int[] q = new int[256];
   static int G;
   static int h;
   static int g;
   private static final String[] A = new String[]{
      z(z("\u0013l\u000b\u0016:")),
      z(z("\u00067IT")),
      z(z("\u001f \u000b}o")),
      z(z("\u001f \u000b|\u0006@")),
      z(z("\u001f \u000bqo")),
      z(z("\u001f \u000blo")),
      z(z("\u001f \u000bz\u0006@")),
      z(z("\u001f \u000bvo")),
      z(z("\u001f \u000bmo")),
      z(z("\u001f \u000bso")),
      z(z("\u001f \u000bzo")),
      z(z("\u001f \u000bho")),
      z(z("\u001f \u000bko")),
      z(z("\u001f \u000byo")),
      z(z("\u001f \u000b\u0004.\u0006+Q\u0006o")),
      z(z("\u001f \u000bro")),
      z(z("\u001f \u000bpo")),
      z(z("\u001f \u000b\u007fo")),
      z(z("\u001f \u000b|o")),
      z(z("\u001f \u000bio")),
      z(z("\u001f \u000bto")),
      z(z("\u001f \u000b~o")),
      z(z("\u001f \u000by\u0006@")),
      z(z("\u001f \u000b{\u0006@")),
      z(z("\u001f \u000b{o")),
      z(z("\u001f \u000bwo")),
      z(z("\u001f \u000buo")),
      z(z("\u001f \u000b}\u0006@")),
      z(z("\u001f \u000bno")),
      z(z("\u001f \u000bjo")),
      z(z("\u001f \u000boo"))
   };

   final int a(int var1) {
      try {
         try {
            j++;
            if (var1 != -21224) {
               this.b(false, 0);
            }
         } catch (RuntimeException var3) {
            throw var3;
         }

         return this.I;
      } catch (RuntimeException var4) {
         throw i.a(var4, A[5] + var1 + 41);
      }
   }

   final int a(boolean var1, int var2) {
      try {
         try {
            if (!var1) {
               this.b((byte)30, 75);
            }
         } catch (RuntimeException var4) {
            throw var4;
         }

         h++;
         return this.b[var2].e;
      } catch (RuntimeException var5) {
         throw i.a(var5, A[24] + var1 + 44 + var2 + 41);
      }
   }

   final String b(byte var1, int var2) {
      try {
         E++;
         return var1 <= 13 ? (String)null : this.b[var2].o;
      } catch (RuntimeException var4) {
         throw i.a(var4, A[25] + var1 + ',' + var2 + ')');
      }
   }

   final void b(int param1, int param2) {
      // $VF: Couldn't be decompiled
      // Please report this to the Vineflower issue tracker, at https://github.com/Vineflower/vineflower/issues with a copy of the class file (if you have the rights to distribute it!)
      // java.lang.RuntimeException: parsing failure!
      //   at org.jetbrains.java.decompiler.modules.decompiler.decompose.DomHelper.parseGraph(DomHelper.java:211)
      //   at org.jetbrains.java.decompiler.main.rels.MethodProcessor.codeToJava(MethodProcessor.java:166)
      //
      // Bytecode:
      // 00: getstatic client.vh Z
      // 03: istore 6
      // 05: getstatic wb.F I
      // 08: bipush 1
      // 09: iadd
      // 0a: putstatic wb.F I
      // 0d: bipush -1
      // 0e: iload 2
      // 0f: bipush -1
      // 10: ixor
      // 11: if_icmplt 28
      // 14: iload 2
      // 15: bipush -1
      // 16: ixor
      // 17: aload 0
      // 18: getfield wb.n I
      // 1b: bipush -1
      // 1c: ixor
      // 1d: if_icmple 28
      // 20: goto 24
      // 23: athrow
      // 24: goto 29
      // 27: athrow
      // 28: return
      // 29: aload 0
      // 2a: getfield wb.b [Lt;
      // 2d: iload 2
      // 2e: aaload
      // 2f: astore 3
      // 30: iload 2
      // 31: istore 4
      // 33: bipush -66
      // 35: iload 1
      // 36: bipush 37
      // 38: isub
      // 39: bipush 52
      // 3b: idiv
      // 3c: irem
      // 3d: istore 5
      // 3f: aload 0
      // 40: getfield wb.n I
      // 43: bipush -1
      // 44: iadd
      // 45: bipush -1
      // 46: ixor
      // 47: iload 4
      // 49: bipush -1
      // 4a: ixor
      // 4b: if_icmpge 6f
      // 4e: aload 0
      // 4f: getfield wb.b [Lt;
      // 52: iload 4
      // 54: aload 0
      // 55: getfield wb.b [Lt;
      // 58: bipush 1
      // 59: iload 4
      // 5b: iadd
      // 5c: aaload
      // 5d: aastore
      // 5e: iinc 4 1
      // 61: iload 6
      // 63: ifne 85
      // 66: iload 6
      // 68: ifeq 3f
      // 6b: goto 6f
      // 6e: athrow
      // 6f: aload 0
      // 70: getfield wb.b [Lt;
      // 73: aload 0
      // 74: dup
      // 75: getfield wb.n I
      // 78: bipush 1
      // 79: isub
      // 7a: dup_x1
      // 7b: putfield wb.n I
      // 7e: aload 3
      // 7f: aastore
      // 80: aload 0
      // 81: bipush 1
      // 82: invokespecial wb.a (Z)V
      // 85: goto b3
      // 88: astore 3
      // 89: aload 3
      // 8a: new java/lang/StringBuilder
      // 8d: dup
      // 8e: invokespecial java/lang/StringBuilder.<init> ()V
      // 91: getstatic wb.A [Ljava/lang/String;
      // 94: bipush 17
      // 96: aaload
      // 97: invokevirtual java/lang/StringBuilder.append (Ljava/lang/String;)Ljava/lang/StringBuilder;
      // 9a: iload 1
      // 9b: invokevirtual java/lang/StringBuilder.append (I)Ljava/lang/StringBuilder;
      // 9e: bipush 44
      // a0: invokevirtual java/lang/StringBuilder.append (C)Ljava/lang/StringBuilder;
      // a3: iload 2
      // a4: invokevirtual java/lang/StringBuilder.append (I)Ljava/lang/StringBuilder;
      // a7: bipush 41
      // a9: invokevirtual java/lang/StringBuilder.append (C)Ljava/lang/StringBuilder;
      // ac: invokevirtual java/lang/StringBuilder.toString ()Ljava/lang/String;
      // af: invokestatic i.a (Ljava/lang/Throwable;Ljava/lang/String;)Lla;
      // b2: athrow
      // b3: return
   }

   final int c(int var1) {
      try {
         try {
            f++;
            if (var1 != -27153) {
               this.a(false);
            }
         } catch (RuntimeException var3) {
            throw var3;
         }

         return this.n;
      } catch (RuntimeException var4) {
         throw i.a(var4, A[21] + var1 + 41);
      }
   }

   final int b(boolean var1, int var2) {
      try {
         try {
            l++;
            if (!var1) {
               this.b(-33, (byte)91);
            }
         } catch (RuntimeException var4) {
            throw var4;
         }

         return this.b[var2].l;
      } catch (RuntimeException var5) {
         throw i.a(var5, A[19] + var1 + 44 + var2 + 41);
      }
   }

   final void a(String var1, String var2, String var3, int var4, String var5, byte var6) {
      try {
         int var13 = -26 % ((var6 - 15) / 33);
         this.a(0, var1, 0, 0, var2, 0, null, var4, 0, 125, var3, var5);
         B++;
      } catch (RuntimeException var12) {
         RuntimeException var7 = var12;

         RuntimeException var10000;
         StringBuilder var10001;
         String var10002;
         label57: {
            try {
               var10000 = var7;
               var10001 = new StringBuilder().append(A[2]);
               if (var1 != null) {
                  var10002 = A[0];
                  break label57;
               }
            } catch (RuntimeException var11) {
               throw var11;
            }

            var10002 = A[1];
         }

         label50: {
            try {
               var10001 = var10001.append(var10002).append(',');
               if (var2 != null) {
                  var10002 = A[0];
                  break label50;
               }
            } catch (RuntimeException var10) {
               throw var10;
            }

            var10002 = A[1];
         }

         label43: {
            try {
               var10001 = var10001.append(var10002).append(',');
               if (var3 != null) {
                  var10002 = A[0];
                  break label43;
               }
            } catch (RuntimeException var9) {
               throw var9;
            }

            var10002 = A[1];
         }

         try {
            var10001 = var10001.append(var10002).append(',').append(var4).append(',');
            if (var5 != null) {
               throw i.a(var10000, var10001.append(A[0]).append(',').append((int)var6).append(')').toString());
            }
         } catch (RuntimeException var8) {
            throw var8;
         }

         throw i.a(var10000, var10001.append(A[1]).append(',').append((int)var6).append(')').toString());
      }
   }

   final void a(int var1, int var2, boolean var3, String var4, String var5) {
      try {
         this.a(0, var4, 0, 0, var5, var1, null, var2, 0, 125, null, null);
         u++;
         if (var3) {
            this.a(61);
         }
      } catch (RuntimeException var9) {
         RuntimeException var6 = var9;

         RuntimeException var10000;
         StringBuilder var10001;
         String var10002;
         label36: {
            try {
               var10000 = var6;
               var10001 = new StringBuilder().append(A[3]).append(var1).append(',').append(var2).append(',').append(var3).append(',');
               if (var4 != null) {
                  var10002 = A[0];
                  break label36;
               }
            } catch (RuntimeException var8) {
               throw var8;
            }

            var10002 = A[1];
         }

         try {
            var10001 = var10001.append(var10002).append(',');
            if (var5 != null) {
               throw i.a(var10000, var10001.append(A[0]).append(')').toString());
            }
         } catch (RuntimeException var7) {
            throw var7;
         }

         throw i.a(var10000, var10001.append(A[1]).append(')').toString());
      }
   }

   final String c(int var1, int var2) {
      try {
         k++;
         return var2 != -4126 ? (String)null : this.b[var1].b;
      } catch (RuntimeException var4) {
         throw i.a(var4, A[23] + var1 + ',' + var2 + ')');
      }
   }

   final int a(int var1, int var2) {
      try {
         C++;
         return var1 >= -14 ? -114 : this.b[var2].d;
      } catch (RuntimeException var4) {
         throw i.a(var4, A[26] + var1 + 44 + var2 + 41);
      }
   }

   final int a(int var1, int var2, int var3, byte var4, int var5) {
      try {
         try {
            if (var4 != -12) {
               this.i = -77;
            }
         } catch (RuntimeException var7) {
            throw var7;
         }

         H++;
         return this.a(var3, var5, var1, var2, -66, true);
      } catch (RuntimeException var8) {
         throw i.a(var8, A[8] + var1 + 44 + var2 + 44 + var3 + 44 + var4 + 44 + var5 + 41);
      }
   }

   private final int a(int param1, int param2, int param3, int param4, int param5, boolean param6) {
      // $VF: Couldn't be decompiled
      // Please report this to the Vineflower issue tracker, at https://github.com/Vineflower/vineflower/issues with a copy of the class file (if you have the rights to distribute it!)
      // java.lang.RuntimeException: parsing failure!
      //   at org.jetbrains.java.decompiler.modules.decompiler.decompose.DomHelper.parseGraph(DomHelper.java:211)
      //   at org.jetbrains.java.decompiler.main.rels.MethodProcessor.codeToJava(MethodProcessor.java:166)
      //
      // Bytecode:
      // 000: getstatic client.vh Z
      // 003: istore 12
      // 005: getstatic wb.a I
      // 008: bipush 1
      // 009: iadd
      // 00a: putstatic wb.a I
      // 00d: bipush -1
      // 00e: aload 0
      // 00f: getfield wb.D I
      // 012: bipush -1
      // 013: ixor
      // 014: if_icmpeq 026
      // 017: aload 0
      // 018: getfield wb.I I
      // 01b: ifeq 026
      // 01e: goto 022
      // 021: athrow
      // 022: goto 028
      // 025: athrow
      // 026: bipush -1
      // 027: ireturn
      // 028: iload 6
      // 02a: ifne 031
      // 02d: goto 049
      // 030: athrow
      // 031: aload 0
      // 032: getfield wb.t Lba;
      // 035: sipush 160
      // 038: iload 4
      // 03a: aload 0
      // 03b: getfield wb.I I
      // 03e: bipush 0
      // 03f: iload 3
      // 040: aload 0
      // 041: getfield wb.D I
      // 044: ldc 13684944
      // 046: invokevirtual ba.c (IIIIIII)V
      // 049: bipush 1
      // 04a: aload 0
      // 04b: getfield wb.t Lba;
      // 04e: ldc 508305352
      // 050: aload 0
      // 051: getfield wb.i I
      // 054: invokevirtual ba.a (II)I
      // 057: iadd
      // 058: istore 7
      // 05a: bipush -3
      // 05c: iload 7
      // 05e: iload 3
      // 05f: iadd
      // 060: iadd
      // 061: istore 8
      // 063: bipush -1
      // 064: istore 9
      // 066: aconst_null
      // 067: aload 0
      // 068: getfield wb.m Ljava/lang/String;
      // 06b: if_acmpeq 0e0
      // 06e: iload 4
      // 070: iload 2
      // 071: if_icmpge 0b8
      // 074: goto 078
      // 077: athrow
      // 078: iload 1
      // 079: iload 8
      // 07b: bipush 3
      // 07c: iload 7
      // 07e: ineg
      // 07f: iadd
      // 080: iadd
      // 081: if_icmple 0b8
      // 084: goto 088
      // 087: athrow
      // 088: iload 1
      // 089: bipush -1
      // 08a: ixor
      // 08b: iload 8
      // 08d: bipush -3
      // 08f: isub
      // 090: bipush -1
      // 091: ixor
      // 092: if_icmple 0b8
      // 095: goto 099
      // 098: athrow
      // 099: iload 2
      // 09a: iload 4
      // 09c: aload 0
      // 09d: getfield wb.D I
      // 0a0: iadd
      // 0a1: if_icmpge 0b8
      // 0a4: goto 0a8
      // 0a7: athrow
      // 0a8: iload 6
      // 0aa: ifne 0b4
      // 0ad: goto 0b1
      // 0b0: athrow
      // 0b1: bipush -2
      // 0b3: ireturn
      // 0b4: bipush -2
      // 0b6: istore 9
      // 0b8: iload 6
      // 0ba: ifne 0c1
      // 0bd: goto 0d9
      // 0c0: athrow
      // 0c1: aload 0
      // 0c2: getfield wb.t Lba;
      // 0c5: aload 0
      // 0c6: getfield wb.m Ljava/lang/String;
      // 0c9: bipush 2
      // 0ca: iload 4
      // 0cc: iadd
      // 0cd: iload 8
      // 0cf: ldc 65535
      // 0d1: bipush 0
      // 0d2: aload 0
      // 0d3: getfield wb.i I
      // 0d6: invokevirtual ba.a (Ljava/lang/String;IIIZI)V
      // 0d9: iload 8
      // 0db: iload 7
      // 0dd: iadd
      // 0de: istore 8
      // 0e0: iload 5
      // 0e2: bipush -1
      // 0e3: if_icmplt 0f2
      // 0e6: aload 0
      // 0e7: aconst_null
      // 0e8: checkcast java/lang/String
      // 0eb: putfield wb.m Ljava/lang/String;
      // 0ee: goto 0f2
      // 0f1: athrow
      // 0f2: bipush 0
      // 0f3: istore 10
      // 0f5: iload 10
      // 0f7: aload 0
      // 0f8: getfield wb.n I
      // 0fb: if_icmpge 1b6
      // 0fe: ldc 16777215
      // 100: istore 11
      // 102: iload 2
      // 103: bipush -1
      // 104: ixor
      // 105: iload 12
      // 107: ifne 1b8
      // 10a: iload 4
      // 10c: bipush -1
      // 10d: ixor
      // 10e: if_icmpge 160
      // 111: goto 115
      // 114: athrow
      // 115: iload 7
      // 117: ineg
      // 118: bipush 3
      // 119: iload 8
      // 11b: iadd
      // 11c: iadd
      // 11d: bipush -1
      // 11e: ixor
      // 11f: iload 1
      // 120: bipush -1
      // 121: ixor
      // 122: if_icmple 160
      // 125: goto 129
      // 128: athrow
      // 129: bipush 3
      // 12a: iload 8
      // 12c: iadd
      // 12d: bipush -1
      // 12e: ixor
      // 12f: iload 1
      // 130: bipush -1
      // 131: ixor
      // 132: if_icmpge 160
      // 135: goto 139
      // 138: athrow
      // 139: iload 2
      // 13a: bipush -1
      // 13b: ixor
      // 13c: iload 4
      // 13e: aload 0
      // 13f: getfield wb.D I
      // 142: iadd
      // 143: bipush -1
      // 144: ixor
      // 145: if_icmpgt 150
      // 148: goto 14c
      // 14b: athrow
      // 14c: goto 160
      // 14f: athrow
      // 150: ldc 16776960
      // 152: istore 11
      // 154: iload 6
      // 156: ifne 15c
      // 159: iload 10
      // 15b: ireturn
      // 15c: iload 10
      // 15e: istore 9
      // 160: iload 6
      // 162: ifne 169
      // 165: goto 1a7
      // 168: athrow
      // 169: aload 0
      // 16a: getfield wb.t Lba;
      // 16d: new java/lang/StringBuilder
      // 170: dup
      // 171: invokespecial java/lang/StringBuilder.<init> ()V
      // 174: aload 0
      // 175: getfield wb.b [Lt;
      // 178: iload 10
      // 17a: aaload
      // 17b: getfield t.p Ljava/lang/String;
      // 17e: invokevirtual java/lang/StringBuilder.append (Ljava/lang/String;)Ljava/lang/StringBuilder;
      // 181: ldc " "
      // 183: invokevirtual java/lang/StringBuilder.append (Ljava/lang/String;)Ljava/lang/StringBuilder;
      // 186: aload 0
      // 187: getfield wb.b [Lt;
      // 18a: iload 10
      // 18c: aaload
      // 18d: getfield t.o Ljava/lang/String;
      // 190: invokevirtual java/lang/StringBuilder.append (Ljava/lang/String;)Ljava/lang/StringBuilder;
      // 193: invokevirtual java/lang/StringBuilder.toString ()Ljava/lang/String;
      // 196: iload 4
      // 198: bipush -2
      // 19a: isub
      // 19b: iload 8
      // 19d: iload 11
      // 19f: bipush 0
      // 1a0: aload 0
      // 1a1: getfield wb.i I
      // 1a4: invokevirtual ba.a (Ljava/lang/String;IIIZI)V
      // 1a7: iload 8
      // 1a9: iload 7
      // 1ab: iadd
      // 1ac: istore 8
      // 1ae: iinc 10 1
      // 1b1: iload 12
      // 1b3: ifeq 0f5
      // 1b6: iload 9
      // 1b8: ireturn
      // 1b9: astore 7
      // 1bb: aload 7
      // 1bd: new java/lang/StringBuilder
      // 1c0: dup
      // 1c1: invokespecial java/lang/StringBuilder.<init> ()V
      // 1c4: getstatic wb.A [Ljava/lang/String;
      // 1c7: bipush 29
      // 1c9: aaload
      // 1ca: invokevirtual java/lang/StringBuilder.append (Ljava/lang/String;)Ljava/lang/StringBuilder;
      // 1cd: iload 1
      // 1ce: invokevirtual java/lang/StringBuilder.append (I)Ljava/lang/StringBuilder;
      // 1d1: bipush 44
      // 1d3: invokevirtual java/lang/StringBuilder.append (C)Ljava/lang/StringBuilder;
      // 1d6: iload 2
      // 1d7: invokevirtual java/lang/StringBuilder.append (I)Ljava/lang/StringBuilder;
      // 1da: bipush 44
      // 1dc: invokevirtual java/lang/StringBuilder.append (C)Ljava/lang/StringBuilder;
      // 1df: iload 3
      // 1e0: invokevirtual java/lang/StringBuilder.append (I)Ljava/lang/StringBuilder;
      // 1e3: bipush 44
      // 1e5: invokevirtual java/lang/StringBuilder.append (C)Ljava/lang/StringBuilder;
      // 1e8: iload 4
      // 1ea: invokevirtual java/lang/StringBuilder.append (I)Ljava/lang/StringBuilder;
      // 1ed: bipush 44
      // 1ef: invokevirtual java/lang/StringBuilder.append (C)Ljava/lang/StringBuilder;
      // 1f2: iload 5
      // 1f4: invokevirtual java/lang/StringBuilder.append (I)Ljava/lang/StringBuilder;
      // 1f7: bipush 44
      // 1f9: invokevirtual java/lang/StringBuilder.append (C)Ljava/lang/StringBuilder;
      // 1fc: iload 6
      // 1fe: invokevirtual java/lang/StringBuilder.append (Z)Ljava/lang/StringBuilder;
      // 201: bipush 41
      // 203: invokevirtual java/lang/StringBuilder.append (C)Ljava/lang/StringBuilder;
      // 206: invokevirtual java/lang/StringBuilder.toString ()Ljava/lang/String;
      // 209: invokestatic i.a (Ljava/lang/Throwable;Ljava/lang/String;)Lla;
      // 20c: athrow
   }

   final void a(byte var1) {
      boolean var6 = client.vh;

      try {
         o++;
         if (this.n != 0) {
            int[] var2 = new int[this.n];
            Object[] var3 = new Object[this.n];
            int var4 = 0;

            while (true) {
               if (~var4 > ~this.n) {
                  t var5 = this.b[var4];

                  try {
                     var2[var4] = var5.d;
                     var3[var4] = var5;
                     var4++;
                     if (var6) {
                        break;
                     }

                     if (!var6) {
                        continue;
                     }
                  } catch (RuntimeException var9) {
                     throw var9;
                  }
               }

               cb.a((byte)-70, var3, var2);
               var4 = 0;
               break;
            }

            try {
               if (var1 != 16) {
                  this.I = -103;
               }
            } catch (RuntimeException var7) {
               throw var7;
            }

            while (~this.n < ~var4) {
               try {
                  this.b[var4] = (t)var3[var4];
                  var4++;
                  if (var6 || var6) {
                     break;
                  }
               } catch (RuntimeException var8) {
                  throw var8;
               }
            }
         }
      } catch (RuntimeException var10) {
         throw i.a(var10, A[22] + var1 + ')');
      }
   }

   final int a(int var1, byte var2) {
      try {
         try {
            d++;
            if (var2 != 22) {
               this.D = 4;
            }
         } catch (RuntimeException var4) {
            throw var4;
         }

         return this.b[var1].j;
      } catch (RuntimeException var5) {
         throw i.a(var5, A[16] + var1 + 44 + var2 + 41);
      }
   }

   final void a(int var1, String var2, String var3, int var4) {
      try {
         try {
            if (var4 != 30192) {
               this.a(true, 125);
            }
         } catch (RuntimeException var8) {
            throw var8;
         }

         e++;
         this.a(0, var3, 0, 0, var2, 0, null, var1, 0, var4 ^ 30093, null, null);
      } catch (RuntimeException var9) {
         RuntimeException var5 = var9;

         RuntimeException var10000;
         StringBuilder var10001;
         String var10002;
         label38: {
            try {
               var10000 = var5;
               var10001 = new StringBuilder().append(A[28]).append(var1).append(',');
               if (var2 != null) {
                  var10002 = A[0];
                  break label38;
               }
            } catch (RuntimeException var7) {
               throw var7;
            }

            var10002 = A[1];
         }

         try {
            var10001 = var10001.append(var10002).append(',');
            if (var3 != null) {
               throw i.a(var10000, var10001.append(A[0]).append(',').append(var4).append(')').toString());
            }
         } catch (RuntimeException var6) {
            throw var6;
         }

         throw i.a(var10000, var10001.append(A[1]).append(',').append(var4).append(')').toString());
      }
   }

   final String b(int var1, byte var2) {
      try {
         if (var2 != 53) {
            return (String)null;
         } else {
            J++;
            return this.b[var1].p;
         }
      } catch (RuntimeException var4) {
         throw i.a(var4, A[13] + var1 + ',' + var2 + ')');
      }
   }

   wb(ba var1, int var2) {
      this(var1, var2, null);
   }

   final void a(int var1, int var2, int var3, int var4, int var5, int var6, String var7, String var8) {
      try {
         if (var5 > 44) {
            G++;
            this.a(var2, var8, var3, 0, var7, var4, null, var1, var6, 125, null, null);
         }
      } catch (RuntimeException var12) {
         RuntimeException var9 = var12;

         RuntimeException var10000;
         StringBuilder var10001;
         String var10002;
         label38: {
            try {
               var10000 = var9;
               var10001 = new StringBuilder()
                  .append(A[10])
                  .append(var1)
                  .append(',')
                  .append(var2)
                  .append(',')
                  .append(var3)
                  .append(',')
                  .append(var4)
                  .append(',')
                  .append(var5)
                  .append(',')
                  .append(var6)
                  .append(',');
               if (var7 != null) {
                  var10002 = A[0];
                  break label38;
               }
            } catch (RuntimeException var11) {
               throw var11;
            }

            var10002 = A[1];
         }

         try {
            var10001 = var10001.append(var10002).append(',');
            if (var8 != null) {
               throw i.a(var10000, var10001.append(A[0]).append(')').toString());
            }
         } catch (RuntimeException var10) {
            throw var10;
         }

         throw i.a(var10000, var10001.append(A[1]).append(')').toString());
      }
   }

   final int a(byte var1, int var2) {
      try {
         y++;
         return var1 != 97 ? 2 : this.b[var2].m;
      } catch (RuntimeException var4) {
         throw i.a(var4, A[9] + var1 + 44 + var2 + 41);
      }
   }

   final void a(int var1, String var2, int var3, int var4, int var5, int var6, int var7, String var8, int var9) {
      try {
         r++;
         this.a(var1, var2, var7, var4, var8, var9, null, var6, var5, 126, null, null);
         int var14 = -66 / ((var3 - -42) / 41);
      } catch (RuntimeException var13) {
         RuntimeException var10 = var13;

         RuntimeException var10000;
         StringBuilder var10001;
         String var10002;
         label33: {
            try {
               var10000 = var10;
               var10001 = new StringBuilder().append(A[4]).append(var1).append(',');
               if (var2 != null) {
                  var10002 = A[0];
                  break label33;
               }
            } catch (RuntimeException var12) {
               throw var12;
            }

            var10002 = A[1];
         }

         try {
            var10001 = var10001.append(var10002)
               .append(',')
               .append(var3)
               .append(',')
               .append(var4)
               .append(',')
               .append(var5)
               .append(',')
               .append(var6)
               .append(',')
               .append(var7)
               .append(',');
            if (var8 != null) {
               throw i.a(var10000, var10001.append(A[0]).append(',').append(var9).append(')').toString());
            }
         } catch (RuntimeException var11) {
            throw var11;
         }

         throw i.a(var10000, var10001.append(A[1]).append(',').append(var9).append(')').toString());
      }
   }

   private final void a(boolean param1) {
      // $VF: Couldn't be decompiled
      // Please report this to the Vineflower issue tracker, at https://github.com/Vineflower/vineflower/issues with a copy of the class file (if you have the rights to distribute it!)
      // java.lang.RuntimeException: parsing failure!
      //   at org.jetbrains.java.decompiler.modules.decompiler.decompose.DomHelper.parseGraph(DomHelper.java:211)
      //   at org.jetbrains.java.decompiler.main.rels.MethodProcessor.codeToJava(MethodProcessor.java:166)
      //
      // Bytecode:
      // 00: getstatic client.vh Z
      // 03: istore 5
      // 05: getstatic wb.c I
      // 08: bipush 1
      // 09: iadd
      // 0a: putstatic wb.c I
      // 0d: aload 0
      // 0e: getfield wb.t Lba;
      // 11: ldc 508305352
      // 13: aload 0
      // 14: getfield wb.i I
      // 17: invokevirtual ba.a (II)I
      // 1a: bipush -1
      // 1b: isub
      // 1c: istore 2
      // 1d: aconst_null
      // 1e: aload 0
      // 1f: getfield wb.m Ljava/lang/String;
      // 22: if_acmpne 38
      // 25: aload 0
      // 26: bipush 0
      // 27: putfield wb.I I
      // 2a: aload 0
      // 2b: bipush 0
      // 2c: putfield wb.D I
      // 2f: iload 5
      // 31: ifeq 58
      // 34: goto 38
      // 37: athrow
      // 38: aload 0
      // 39: iload 2
      // 3a: putfield wb.I I
      // 3d: aload 0
      // 3e: bipush 5
      // 3f: aload 0
      // 40: getfield wb.t Lba;
      // 43: aload 0
      // 44: getfield wb.i I
      // 47: bipush 76
      // 49: aload 0
      // 4a: getfield wb.m Ljava/lang/String;
      // 4d: invokevirtual ba.a (IILjava/lang/String;)I
      // 50: iadd
      // 51: putfield wb.D I
      // 54: goto 58
      // 57: athrow
      // 58: iload 1
      // 59: bipush 1
      // 5a: if_icmpeq 69
      // 5d: aload 0
      // 5e: bipush 1
      // 5f: bipush 124
      // 61: invokevirtual wb.b (ZI)I
      // 64: pop
      // 65: goto 69
      // 68: athrow
      // 69: bipush 0
      // 6a: istore 3
      // 6b: aload 0
      // 6c: getfield wb.n I
      // 6f: iload 3
      // 70: if_icmple d9
      // 73: aload 0
      // 74: dup
      // 75: getfield wb.I I
      // 78: iload 2
      // 79: iadd
      // 7a: putfield wb.I I
      // 7d: bipush 5
      // 7e: aload 0
      // 7f: getfield wb.t Lba;
      // 82: aload 0
      // 83: getfield wb.i I
      // 86: bipush 105
      // 88: new java/lang/StringBuilder
      // 8b: dup
      // 8c: invokespecial java/lang/StringBuilder.<init> ()V
      // 8f: aload 0
      // 90: getfield wb.b [Lt;
      // 93: iload 3
      // 94: aaload
      // 95: getfield t.p Ljava/lang/String;
      // 98: invokevirtual java/lang/StringBuilder.append (Ljava/lang/String;)Ljava/lang/StringBuilder;
      // 9b: ldc " "
      // 9d: invokevirtual java/lang/StringBuilder.append (Ljava/lang/String;)Ljava/lang/StringBuilder;
      // a0: aload 0
      // a1: getfield wb.b [Lt;
      // a4: iload 3
      // a5: aaload
      // a6: getfield t.o Ljava/lang/String;
      // a9: invokevirtual java/lang/StringBuilder.append (Ljava/lang/String;)Ljava/lang/StringBuilder;
      // ac: invokevirtual java/lang/StringBuilder.toString ()Ljava/lang/String;
      // af: invokevirtual ba.a (IILjava/lang/String;)I
      // b2: iadd
      // b3: istore 4
      // b5: iload 5
      // b7: ifne fe
      // ba: iload 4
      // bc: aload 0
      // bd: getfield wb.D I
      // c0: if_icmpgt cb
      // c3: goto c7
      // c6: athrow
      // c7: goto d1
      // ca: athrow
      // cb: aload 0
      // cc: iload 4
      // ce: putfield wb.D I
      // d1: iinc 3 1
      // d4: iload 5
      // d6: ifeq 6b
      // d9: goto fe
      // dc: astore 2
      // dd: aload 2
      // de: new java/lang/StringBuilder
      // e1: dup
      // e2: invokespecial java/lang/StringBuilder.<init> ()V
      // e5: getstatic wb.A [Ljava/lang/String;
      // e8: bipush 27
      // ea: aaload
      // eb: invokevirtual java/lang/StringBuilder.append (Ljava/lang/String;)Ljava/lang/StringBuilder;
      // ee: iload 1
      // ef: invokevirtual java/lang/StringBuilder.append (Z)Ljava/lang/StringBuilder;
      // f2: bipush 41
      // f4: invokevirtual java/lang/StringBuilder.append (C)Ljava/lang/StringBuilder;
      // f7: invokevirtual java/lang/StringBuilder.toString ()Ljava/lang/String;
      // fa: invokestatic i.a (Ljava/lang/Throwable;Ljava/lang/String;)Lla;
      // fd: athrow
      // fe: return
   }

   // $VF: Handled exception range with multiple entry points by splitting it
   // $VF: Inserted dummy exception handlers to handle obfuscated exceptions
   static final void a(
      int var0,
      int var1,
      int var2,
      int var3,
      int[] var4,
      int var5,
      int var6,
      int var7,
      int var8,
      int var9,
      int var10,
      int var11,
      int var12,
      int var13,
      int[] var14,
      int var15
   ) {
      boolean var23 = client.vh;

      RuntimeException var10000;
      label314: {
         try {
            g++;
            if (var15 <= 0) {
               return;
            }
         } catch (RuntimeException var44) {
            var10000 = var44;
            boolean var10001 = false;
            break label314;
         }

         try {
            try {
               if (var1 != 10) {
                  a(-30, -28, 22, 0, (int[])null, -78, 109, 44, -120, 67, 27, 2, 107, -113, (int[])null, 56);
               }
            } catch (RuntimeException var42) {
               throw var42;
            }

            int var45 = 0;
            int var17 = 0;
            var11 <<= 2;

            label301: {
               try {
                  if (~var5 == -1) {
                     break label301;
                  }
               } catch (RuntimeException var41) {
                  throw var41;
               }

               var17 = var8 / var5 << 1419282055;
               var45 = var7 / var5 << 1665286983;
            }

            label333: {
               if (var45 < 0) {
                  var45 = 0;
                  boolean var50 = var23;

                  try {
                     if (!var50) {
                        break label333;
                     }
                  } catch (RuntimeException var40) {
                     boolean var65 = false;
                     throw var40;
                  }
               }

               try {
                  if (16256 >= var45) {
                     break label333;
                  }
               } catch (RuntimeException var39) {
                  boolean var66 = false;
                  throw var39;
               }

               var45 = 16256;
            }

            int var20 = var15;

            while (var20 > 0) {
               var7 += var13;
               var3 = var17;
               var5 += var10;
               var2 = var45;
               int var52 = var8;
               int var67 = var0;

               label279:
               while (true) {
                  var8 = var52 + var67;
                  if (var23) {
                     return;
                  }

                  if (var5 != 0) {
                     var45 = var7 / var5 << -47707001;
                     var17 = var8 / var5 << 856475559;
                  }

                  label276: {
                     label275: {
                        try {
                           if (var45 < 0) {
                              break label275;
                           }

                           if (-16257 <= ~var45) {
                              break label276;
                           }
                        } catch (RuntimeException var38) {
                           throw var38;
                        }

                        var45 = 16256;
                        if (!var23) {
                           break label276;
                        }
                     }

                     var45 = 0;
                  }

                  label321: {
                     int var18 = -var2 + var45 >> -716279868;
                     int var19 = -var3 + var17 >> 310733700;
                     int var21 = var6 >> -128834185;
                     var2 += 6291456 & var6;
                     var6 += var11;
                     if (var20 < 16) {
                        int var22 = 0;

                        while (var20 > var22) {
                           var52 = -1;
                           var67 = ~(var12 = var14[(var3 & 16256) + (var2 >> -557206009)] >>> var21);
                           if (var23) {
                              continue label279;
                           }

                           if (-1 != var67) {
                              var4[var9] = var12;
                           }

                           var9++;
                           var2 += var18;
                           var3 += var19;

                           label256: {
                              try {
                                 if (-4 != ~(var22 & 3)) {
                                    break label256;
                                 }
                              } catch (RuntimeException var37) {
                                 throw var37;
                              }

                              var2 = (var6 & 6291456) + (16383 & var2);
                              var21 = var6 >> 108767799;
                              var6 += var11;
                           }

                           var22++;
                           if (var23) {
                              break;
                           }
                        }

                        if (!var23) {
                           break label321;
                        }
                     }

                     byte var53 = -1;
                     var67 = var12 = var14[(var3 & 16256) + (var2 >> -1762053913)] >>> var21;
                     byte var78 = -1;

                     try {
                        if (var53 != (var67 ^ var78)) {
                           var4[var9] = var12;
                        }
                     } catch (RuntimeException var28) {
                        throw var28;
                     }

                     var2 += var18;
                     var9++;
                     var3 += var19;
                     if ((var12 = var14[(var2 >> 142914567) + (16256 & var3)] >>> var21) != 0) {
                        var4[var9] = var12;
                     }

                     var9++;
                     var3 += var19;
                     var2 += var18;
                     if ((var12 = var14[(var2 >> 702349191) + (16256 & var3)] >>> var21) != 0) {
                        var4[var9] = var12;
                     }

                     var9++;
                     var3 += var19;
                     var2 += var18;
                     if (0 != (var12 = var14[(var2 >> 84789639) + (var3 & 16256)] >>> var21)) {
                        var4[var9] = var12;
                     }

                     var2 += var18;
                     var3 += var19;
                     var9++;
                     var21 = var6 >> 84224663;
                     var2 = (var6 & 6291456) + (16383 & var2);
                     var6 += var11;
                     byte var54 = -1;
                     var67 = var12 = var14[(var3 & 16256) + (var2 >> -1461444889)] >>> var21;
                     var78 = -1;

                     try {
                        if (var54 != (var67 ^ var78)) {
                           var4[var9] = var12;
                        }
                     } catch (RuntimeException var36) {
                        throw var36;
                     }

                     var2 += var18;
                     var9++;
                     var3 += var19;
                     int var55 = var12 = var14[(16256 & var3) - -(var2 >> -497158425)] >>> var21;
                     int var70 = -1;

                     try {
                        if ((var55 ^ var70) != -1) {
                           var4[var9] = var12;
                        }
                     } catch (RuntimeException var27) {
                        throw var27;
                     }

                     var9++;
                     var2 += var18;
                     var3 += var19;
                     if ((var12 = var14[(var2 >> -319394553) + (16256 & var3)] >>> var21) != 0) {
                        try {
                           var4[var9] = var12;
                        } catch (RuntimeException var26) {
                           throw var26;
                        }
                     }

                     var2 += var18;
                     var3 += var19;
                     var9++;
                     byte var56 = -1;
                     var70 = var12 = var14[(var2 >> 1667252231) + (var3 & 16256)] >>> var21;
                     var78 = -1;

                     label226: {
                        try {
                           if (var56 == (var70 ^ var78)) {
                              break label226;
                           }
                        } catch (RuntimeException var35) {
                           throw var35;
                        }

                        var4[var9] = var12;
                     }

                     var3 += var19;
                     var9++;
                     var2 += var18;
                     var21 = var6 >> -348227017;
                     var2 = (var2 & 16383) - -(6291456 & var6);
                     int var57 = var12 = var14[(var2 >> 2085548263) + (var3 & 16256)] >>> var21;
                     int var72 = -1;

                     label220: {
                        try {
                           if ((var57 ^ var72) == -1) {
                              break label220;
                           }
                        } catch (RuntimeException var34) {
                           throw var34;
                        }

                        var4[var9] = var12;
                     }

                     var6 += var11;
                     var9++;
                     var2 += var18;
                     var3 += var19;
                     byte var58 = -1;
                     var72 = var12 = var14[(var2 >> -1433259769) + (var3 & 16256)] >>> var21;
                     var78 = -1;

                     label214: {
                        try {
                           if (var58 == (var72 ^ var78)) {
                              break label214;
                           }
                        } catch (RuntimeException var33) {
                           throw var33;
                        }

                        var4[var9] = var12;
                     }

                     var3 += var19;
                     var9++;
                     var2 += var18;
                     if ((var12 = var14[(16256 & var3) - -(var2 >> -728567193)] >>> var21) != 0) {
                        var4[var9] = var12;
                     }

                     var3 += var19;
                     var2 += var18;
                     var9++;
                     if ((var12 = var14[(var2 >> -532021593) + (var3 & 16256)] >>> var21) != 0) {
                        try {
                           var4[var9] = var12;
                        } catch (RuntimeException var25) {
                           throw var25;
                        }
                     }

                     var2 += var18;
                     var3 += var19;
                     var9++;
                     var2 = (var2 & 16383) - -(var6 & 6291456);
                     var21 = var6 >> 96919607;
                     int var59 = var12 = var14[(var3 & 16256) + (var2 >> 834075207)] >>> var21;
                     int var74 = -1;

                     label205: {
                        try {
                           if ((var59 ^ var74) == -1) {
                              break label205;
                           }
                        } catch (RuntimeException var32) {
                           throw var32;
                        }

                        var4[var9] = var12;
                     }

                     var6 += var11;
                     var3 += var19;
                     var9++;
                     var2 += var18;
                     byte var60 = -1;
                     var74 = var12 = var14[(var2 >> 2085930247) + (var3 & 16256)] >>> var21;
                     var78 = -1;

                     try {
                        if (var60 != (var74 ^ var78)) {
                           var4[var9] = var12;
                        }
                     } catch (RuntimeException var24) {
                        throw var24;
                     }

                     var9++;
                     var2 += var18;
                     var3 += var19;
                     if ((var12 = var14[(var2 >> -1394491673) + (var3 & 16256)] >>> var21) != 0) {
                        var4[var9] = var12;
                     }

                     var3 += var19;
                     var2 += var18;
                     var9++;
                     byte var61 = -1;
                     var74 = var12 = var14[(16256 & var3) - -(var2 >> -1327954841)] >>> var21;
                     var78 = -1;

                     try {
                        if (var61 != (var74 ^ var78)) {
                           var4[var9] = var12;
                        }
                     } catch (RuntimeException var31) {
                        throw var31;
                     }

                     var9++;
                  }

                  var20 -= 16;
                  if (var23) {
                     return;
                  }
                  break;
               }
            }

            return;
         } catch (RuntimeException var43) {
            var10000 = var43;
            boolean var62 = false;
         }
      }

      RuntimeException var16 = var10000;

      StringBuilder var63;
      String var10002;
      label184: {
         try {
            var10000 = var16;
            var63 = new StringBuilder().append(A[12]).append(var0).append(',').append(var1).append(',').append(var2).append(',').append(var3).append(',');
            if (var4 != null) {
               var10002 = A[0];
               break label184;
            }
         } catch (RuntimeException var30) {
            throw var30;
         }

         var10002 = A[1];
      }

      try {
         var63 = var63.append(var10002)
            .append(',')
            .append(var5)
            .append(',')
            .append(var6)
            .append(',')
            .append(var7)
            .append(',')
            .append(var8)
            .append(',')
            .append(var9)
            .append(',')
            .append(var10)
            .append(',')
            .append(var11)
            .append(',')
            .append(var12)
            .append(',')
            .append(var13)
            .append(',');
         if (var14 != null) {
            throw i.a(var10000, var63.append(A[0]).append(',').append(var15).append(')').toString());
         }
      } catch (RuntimeException var29) {
         throw var29;
      }

      throw i.a(var10000, var63.append(A[1]).append(',').append(var15).append(')').toString());
   }

   final void a(int var1, String var2, int var3, String var4, int var5, int var6) {
      try {
         try {
            if (var6 != 3296) {
               w = -93L;
            }
         } catch (RuntimeException var10) {
            throw var10;
         }

         v++;
         this.a(var5, var4, 0, 0, var2, var1, null, var3, 0, var6 + -3170, null, null);
      } catch (RuntimeException var11) {
         RuntimeException var7 = var11;

         RuntimeException var10000;
         StringBuilder var10001;
         String var10002;
         label38: {
            try {
               var10000 = var7;
               var10001 = new StringBuilder().append(A[15]).append(var1).append(',');
               if (var2 != null) {
                  var10002 = A[0];
                  break label38;
               }
            } catch (RuntimeException var9) {
               throw var9;
            }

            var10002 = A[1];
         }

         try {
            var10001 = var10001.append(var10002).append(',').append(var3).append(',');
            if (var4 != null) {
               throw i.a(var10000, var10001.append(A[0]).append(',').append(var5).append(',').append(var6).append(')').toString());
            }
         } catch (RuntimeException var8) {
            throw var8;
         }

         throw i.a(var10000, var10001.append(A[1]).append(',').append(var5).append(',').append(var6).append(')').toString());
      }
   }

   final void d(int var1) {
      try {
         K++;
         this.n = var1;
         this.a(true);
      } catch (RuntimeException var3) {
         throw i.a(var3, A[11] + var1 + ')');
      }
   }

   final int b(int var1, int var2, int var3, byte var4, int var5) {
      try {
         try {
            if (var4 != -40) {
               this.a((byte)-62);
            }
         } catch (RuntimeException var7) {
            throw var7;
         }

         M++;
         return this.a(var5, var1, var3, var2, -3, false);
      } catch (RuntimeException var8) {
         throw i.a(var8, A[18] + var1 + 44 + var2 + 44 + var3 + 44 + var4 + 44 + var5 + 41);
      }
   }

   final int a(int var1, boolean var2) {
      try {
         try {
            x++;
            if (var2) {
               this.i = 119;
            }
         } catch (RuntimeException var4) {
            throw var4;
         }

         return this.b[var1].i;
      } catch (RuntimeException var5) {
         throw i.a(var5, A[20] + var1 + 44 + var2 + 41);
      }
   }

   // $VF: Handled exception range with multiple entry points by splitting it
   // $VF: Inserted dummy exception handlers to handle obfuscated exceptions
   private final void a(
      int var1, String var2, int var3, int var4, String var5, int var6, String var7, int var8, int var9, int var10, String var11, String var12
   ) {
      boolean var15 = client.vh;

      RuntimeException var10000;
      label138: {
         try {
            int var32;
            label128: {
               label143: {
                  try {
                     if (~this.n != ~this.b.length) {
                        break label143;
                     }
                  } catch (RuntimeException var21) {
                     throw var21;
                  }

                  t[] var13 = this.b;
                  this.b = new t[10 + this.n];
                  int var14 = 0;

                  while (this.b.length > var14) {
                     label150: {
                        label121: {
                           try {
                              var29 = this.n;
                              var32 = var14;
                              if (var15) {
                                 break label128;
                              }

                              if (this.n <= var14) {
                                 break label121;
                              }
                           } catch (RuntimeException var25) {
                              throw var25;
                           }

                           try {
                              try {
                                 this.b[var14] = var13[var14];
                                 if (!var15) {
                                    break label150;
                                 }
                              } catch (RuntimeException var22) {
                                 throw var22;
                              }
                           } catch (RuntimeException var24) {
                              boolean var33 = false;
                              throw var24;
                           }
                        }

                        try {
                           this.b[var14] = new t();
                        } catch (RuntimeException var23) {
                           boolean var34 = false;
                           throw var23;
                        }
                     }

                     var14++;
                     if (var15) {
                        break;
                     }
                  }
               }

               var29 = var10;
               var32 = 124;
            }

            if (var29 <= var32) {
               return;
            }
         } catch (RuntimeException var27) {
            var10000 = var27;
            boolean var10001 = false;
            break label138;
         }

         try {
            L++;
            this.b[this.n++].a(var2, var4, var6, var1, var9, var7, 100, var8, var5, var11, var3, var12);
            this.a(true);
            return;
         } catch (RuntimeException var26) {
            var10000 = var26;
            boolean var35 = false;
         }
      }

      RuntimeException var28 = var10000;

      StringBuilder var36;
      String var10002;
      label98: {
         try {
            var10000 = var28;
            var36 = new StringBuilder().append(A[7]).append(var1).append(',');
            if (var2 != null) {
               var10002 = A[0];
               break label98;
            }
         } catch (RuntimeException var20) {
            throw var20;
         }

         var10002 = A[1];
      }

      label91: {
         try {
            var36 = var36.append(var10002).append(',').append(var3).append(',').append(var4).append(',');
            if (var5 != null) {
               var10002 = A[0];
               break label91;
            }
         } catch (RuntimeException var19) {
            throw var19;
         }

         var10002 = A[1];
      }

      label84: {
         try {
            var36 = var36.append(var10002).append(',').append(var6).append(',');
            if (var7 != null) {
               var10002 = A[0];
               break label84;
            }
         } catch (RuntimeException var18) {
            throw var18;
         }

         var10002 = A[1];
      }

      label77: {
         try {
            var36 = var36.append(var10002).append(',').append(var8).append(',').append(var9).append(',').append(var10).append(',');
            if (var11 != null) {
               var10002 = A[0];
               break label77;
            }
         } catch (RuntimeException var17) {
            throw var17;
         }

         var10002 = A[1];
      }

      try {
         var36 = var36.append(var10002).append(',');
         if (var12 != null) {
            throw i.a(var10000, var36.append(A[0]).append(')').toString());
         }
      } catch (RuntimeException var16) {
         throw var16;
      }

      throw i.a(var10000, var36.append(A[1]).append(')').toString());
   }

   final int b(int var1) {
      try {
         try {
            if (var1 != 16256) {
               this.a((byte)-39);
            }
         } catch (RuntimeException var3) {
            throw var3;
         }

         s++;
         return this.D;
      } catch (RuntimeException var4) {
         throw i.a(var4, A[6] + var1 + 41);
      }
   }

   final void a(int var1, byte var2, int var3, String var4, String var5, int var6, int var7) {
      try {
         try {
            z++;
            if (var2 != 22) {
               this.a(33, false);
            }
         } catch (RuntimeException var11) {
            throw var11;
         }

         this.a(var7, var4, var6, 0, var5, var1, null, var3, 0, 127, null, null);
      } catch (RuntimeException var12) {
         RuntimeException var8 = var12;

         RuntimeException var10000;
         StringBuilder var10001;
         String var10002;
         label38: {
            try {
               var10000 = var8;
               var10001 = new StringBuilder().append(A[30]).append(var1).append(',').append((int)var2).append(',').append(var3).append(',');
               if (var4 != null) {
                  var10002 = A[0];
                  break label38;
               }
            } catch (RuntimeException var10) {
               throw var10;
            }

            var10002 = A[1];
         }

         try {
            var10001 = var10001.append(var10002).append(',');
            if (var5 != null) {
               throw i.a(var10000, var10001.append(A[0]).append(',').append(var6).append(',').append(var7).append(')').toString());
            }
         } catch (RuntimeException var9) {
            throw var9;
         }

         throw i.a(var10000, var10001.append(A[1]).append(',').append(var6).append(',').append(var7).append(')').toString());
      }
   }

   wb(ba var1, int var2, String var3) {
      boolean var5 = client.vh;
      super();
      this.I = 0;
      this.n = 0;
      this.D = 0;

      try {
         this.i = var2;
         this.b = new t[10];
         this.t = var1;
         this.m = var3;
         int var10 = 0;

         while (true) {
            if (~var10 > -11) {
               try {
                  this.b[var10] = new t();
                  var10++;
                  if (var5) {
                     break;
                  }

                  if (!var5) {
                     continue;
                  }
               } catch (RuntimeException var8) {
                  throw var8;
               }
            }

            this.a(true);
            break;
         }
      } catch (RuntimeException var9) {
         RuntimeException var4 = var9;

         RuntimeException var10000;
         StringBuilder var10001;
         String var10002;
         label41: {
            try {
               var10000 = var4;
               var10001 = new StringBuilder().append(A[14]);
               if (var1 != null) {
                  var10002 = A[0];
                  break label41;
               }
            } catch (RuntimeException var7) {
               throw var7;
            }

            var10002 = A[1];
         }

         try {
            var10001 = var10001.append(var10002).append(',').append(var2).append(',');
            if (var3 != null) {
               throw i.a(var10000, var10001.append(A[0]).append(')').toString());
            }
         } catch (RuntimeException var6) {
            throw var6;
         }

         throw i.a(var10000, var10001.append(A[1]).append(')').toString());
      }
   }

   static {
      for (int var1 = 0; ~var1 > -257; var1++) {
         int var0 = var1;
         int var2 = 0;

         while (true) {
            label28: {
               label27: {
                  try {
                     if (var2 >= 8) {
                        break;
                     }

                     if (~(1 & var0) == -2) {
                        break label27;
                     }
                  } catch (RuntimeException var3) {
                     throw var3;
                  }

                  var0 >>>= 1;
                  break label28;
               }

               var0 = var0 >>> -1257587711 ^ -306674912;
            }

            var2++;
         }

         q[var1] = var0;
      }
   }

   private static char[] z(String var0) {
      char[] var10000 = var0.toCharArray();
      if (var10000.length < 2) {
         var10000[0] = (char)(var10000[0] ^ 'G');
      }

      return var10000;
   }

   private static String z(char[] var0) {
      int var10002 = var0.length;
      char[] var10001 = var0;
      int var10000 = var10002;

      for (int var1 = 0; var10000 > var1; var1++) {
         char var10004 = var10001[var1];
         byte var10005;
         switch (var1 % 5) {
            case 0:
               var10005 = 104;
               break;
            case 1:
               var10005 = 66;
               break;
            case 2:
               var10005 = 37;
               break;
            case 3:
               var10005 = 56;
               break;
            default:
               var10005 = 71;
         }

         var10001[var1] = (char)(var10004 ^ var10005);
      }

      return new String(var10001).intern();
   }
}
